Workbook
Name Amount_HRDGA: #REF!
Name Amount_Salary: #REF!
Name Entity_HRDGA: #REF!
Name Entity_Salary: #REF!
Name FSLI_HRDGA: #REF!
Name FSLI_Salary: #REF!
Name Grouping_HRDGA: #REF!
Name Grouping_Salary: #REF!

Sheet BMG Business Plan
A1: PT Boga Makmur Gracia
A2: Business Plan
A3: Oct 26 to Dec 27 | K3: 2026 | L3: =YEAR(L5) -> 2026 | M3: =YEAR(M5) -> 2026 | N3: =YEAR(N5) -> 2026 | O3: =YEAR(O5) -> 2026 | P3: =YEAR(P5) -> 2026 | Q3: =YEAR(Q5) -> 2026 | R3: =YEAR(R5) -> 2026 | S3: =YEAR(S5) -> 2026 | ... AI3: =YEAR(AI5) -> 2027
I4: Delta | K4: YTD | L4: Actual | M4: Actual | N4: Actual | O4: Actual | P4: Actual | Q4: Actual | R4: Actual | S4: Actual | T4: BP | U4: BP | V4: BP | W4: BP | X4: BP | Y4: BP | Z4: BP | AA4: BP | AB4: BP | AC4: BP | AD4: BP | AE4: BP | AF4: BP | AG4: BP | AH4: BP | AI4: BP | AJ4: Total
G5: Names | H5: Unit | I5: % | J5: =L5-31 -> 46022 | K5: Bud 2026 | L5: 46053 | M5: =EOMONTH(L5,1) -> 46081 | N5: =EOMONTH(M5,1) -> 46112 | O5: =EOMONTH(N5,1) -> 46142 | P5: =EOMONTH(O5,1) -> 46173 | Q5: =EOMONTH(P5,1) -> 46203 | R5: =EOMONTH(Q5,1) -> 46234 | S5: =EOMONTH(R5,1) -> 46265 | T5: =EOMONTH(S5,1) -> 46295 | ... AI5: =EOMONTH(AH5,1) -> 46752 | AJ5: Bud 2027
L6: =EOMONTH($L$5,11) -> 46387 | M6: =EOMONTH($L$5,11) -> 46387 | N6: =EOMONTH($L$5,11) -> 46387 | O6: =EOMONTH($L$5,11) -> 46387 | P6: =EOMONTH($L$5,11) -> 46387 | Q6: =EOMONTH($L$5,11) -> 46387 | R6: =EOMONTH($L$5,11) -> 46387 | S6: =EOMONTH($L$5,11) -> 46387 | ... AI6: =EOMONTH($L$5,11) -> 46387
B7: Financial statements
B8: 1.1 | C8: Income statement
C9: Revenue - Gross | H9: Rp m | I9: =IFERROR((K9-J9)/J9,0) -> 0 | K9: =SUM(L9:W9) -> 101135.45 | L9: =SUMIFS('PL Actual MTM - Aug 26'!D:D,'PL Actual MTM - Aug 26'!$R:$R,"Revenue")/10^6 -> 9369.4466 | M9: =SUMIFS('PL Actual MTM - Aug 26'!E:E,'PL Actual MTM - Aug 26'!$R:$R,"Revenue")/10^6 -> 8659.5707 | N9: =SUMIFS('PL Actual MTM - Aug 26'!F:F,'PL Actual MTM - Aug 26'!$R:$R,"Revenue")/10^6 -> 6547.2579 | O9: =SUMIFS('PL Actual MTM - Aug 26'!G:G,'PL Actual MTM - Aug 26'!$R:$R,"Revenue")/10^6 -> 6850.5287 | P9: =SUMIFS('PL Actual MTM - Aug 26'!H:H,'PL Actual MTM - Aug 26'!$R:$R,"Revenue")/10^6 -> 7705.4169 | Q9: =SUMIFS('PL Actual MTM - Aug 26'!I:I,'PL Actual MTM - Aug 26'!$R:$R,"Revenue")/10^6 -> 8295.2878 | R9: =SUMIFS('PL Actual MTM - Aug 26'!J:J,'PL Actual MTM - Aug 26'!$R:$R,"Revenue")/10^6 -> 8929.6805 | S9: =SUMIFS('PL Actual MTM - Aug 26'!K:K,'PL Actual MTM - Aug 26'!$R:$R,"Revenue")/10^6 -> 9793.1255 | T9: =SUM(T10:T13) -> 8746.2829 | U9: =SUM(U10:U13) -> 8746.2829 | V9: =SUM(V10:V13) -> 8746.2829 | W9: =SUM(W10:W13) -> 8746.2829 | X9: =SUM(X10:X13) -> 8746.2829 | Y9: =SUM(Y10:Y13) -> 8746.2829 | Z9: =SUM(Z10:Z13) -> 8746.2829 | AA9: =SUM(AA10:AA13) -> 8746.2829 | ... AI9: =SUM(AI10:AI13) -> 8746.2829 | AJ9: =SUM(X9:AI9) -> 104955.39
D10: FCC | H10: Rp m | I10: =IFERROR((K10-J10)/J10,0) -> 0 | K10: =SUM(L10:W10) -> 91932.686 | L10: =SUM('Data Aktual'!Q241:Q242)/10^6 -> 8944.5075 | M10: =SUM('Data Aktual'!R241:R242)/10^6 -> 8504.9933 | N10: =SUM('Data Aktual'!S241:S242)/10^6 -> 6061.6471 | O10: =SUM('Data Aktual'!T241:T242)/10^6 -> 6092.7878 | P10: =SUM('Data Aktual'!U241:U242)/10^6 -> 7072.8378 | Q10: =SUM('Data Aktual'!V241:V242)/10^6 -> 6880.534 | R10: =SUM('Data Aktual'!W241:W242)/10^6 -> 7823.6608 | S10: =SUM('Data Aktual'!X241:X242)/10^6 -> 8705.7869 | T10: =SUM('Business Plan - Model Details'!R76/10^6) -> 7961.4826 | U10: =SUM('Business Plan - Model Details'!S76/10^6) -> 7961.4826 | V10: =SUM('Business Plan - Model Details'!T76/10^6) -> 7961.4826 | W10: =SUM('Business Plan - Model Details'!U76/10^6) -> 7961.4826 | X10: =SUM('Business Plan - Model Details'!V76/10^6) -> 7961.4826 | Y10: =SUM('Business Plan - Model Details'!W76/10^6) -> 7961.4826 | Z10: =SUM('Business Plan - Model Details'!X76/10^6) -> 7961.4826 | AA10: =SUM('Business Plan - Model Details'!Y76/10^6) -> 7961.4826 | ... AI10: =SUM('Business Plan - Model Details'!AG76/10^6) -> 7961.4826 | AJ10: =SUM(X10:AI10) -> 95537.791
D11: Ubi Ungu | H11: Rp m | I11: =IFERROR((K11-J11)/J11,0) -> 0 | K11: =SUM(L11:W11) -> 3399.4832 | L11: ='Business Plan - Model Details'!J77/10^6 -> 30.560211 | M11: ='Business Plan - Model Details'!K77/10^6 -> 0.26675 | N11: ='Business Plan - Model Details'!L77/10^6 -> 150.97565 | O11: ='Business Plan - Model Details'!M77/10^6 -> 273.6855 | P11: ='Business Plan - Model Details'!N77/10^6 -> 241.821 | Q11: ='Business Plan - Model Details'!O77/10^6 -> 684.21375 | R11: ='Business Plan - Model Details'!P77/10^6 -> 430.26775 | S11: ='Business Plan - Model Details'!Q77/10^6 -> 349.70925 | ... AI11: ='Business Plan - Model Details'!AG77/10^6 -> 309.49583 | AJ11: =SUM(X11:AI11) -> 3713.9499
D12: Ubi Orange | H12: Rp m | I12: =IFERROR((K12-J12)/J12,0) -> 0 | K12: =SUM(L12:W12) -> 3177.5584 | L12: ='Business Plan - Model Details'!J78/10^6 -> 25.717483 | M12: ='Business Plan - Model Details'!K78/10^6 -> 0.49816 | N12: ='Business Plan - Model Details'!L78/10^6 -> 150.95685 | O12: ='Business Plan - Model Details'!M78/10^6 -> 264.00085 | P12: ='Business Plan - Model Details'!N78/10^6 -> 255.5465 | Q12: ='Business Plan - Model Details'!O78/10^6 -> 653.8829 | R12: ='Business Plan - Model Details'!P78/10^6 -> 404.6592 | S12: ='Business Plan - Model Details'!Q78/10^6 -> 354.6037 | ... AI12: ='Business Plan - Model Details'!AG78/10^6 -> 266.92318 | AJ12: =SUM(X12:AI12) -> 3203.0782
D13: Others (actual: retail & maklon per invoice; projection: model total operating revenue less the three products) | F13: Others (MBS, Nutrifood, Koperasi, Lembutan, maklon & merek) | H13: Rp m | I13: =IFERROR((K13-J13)/J13,0) -> 0 | K13: =SUM(L13:W13) -> 3073.3863 | L13: ='Business Plan - Model Details'!J83/10^6 -> 429.98577 | M13: ='Business Plan - Model Details'!K83/10^6 -> 216.98377 | N13: ='Business Plan - Model Details'!L83/10^6 -> 92.358781 | O13: ='Business Plan - Model Details'!M83/10^6 -> 283.67813 | P13: ='Business Plan - Model Details'!N83/10^6 -> 196.73241 | Q13: ='Business Plan - Model Details'!O83/10^6 -> 175.60696 | R13: ='Business Plan - Model Details'!P83/10^6 -> 353.60476 | S13: ='Business Plan - Model Details'!Q83/10^6 -> 490.91055 | ... AI13: ='Business Plan - Model Details'!AG83/10^6 -> 208.3813 | AJ13: =SUM(X13:AI13) -> 2500.5756
C14: Sales Discount and Return | K14: =SUM(L14:W14) -> -78.30075 | L14: =SUM(L15:L16) -> 0 | M14: =SUM(M15:M16) -> 0 | N14: =SUM(N15:N16) -> -62.7011 | O14: =SUM(O15:O16) -> 0 | P14: =SUM(P15:P16) -> 0 | Q14: =SUM(Q15:Q16) -> 0 | R14: =SUM(R15:R16) -> -15.59965 | S14: =SUM(S15:S16) -> 0 | ... AI14: =SUM(AI15:AI16) -> 0 | AJ14: =SUM(X14:AI14) -> 0
D15: Sales Discount | H15: Rp m | I15: =IFERROR((K15-J15)/J15,0) -> 0 | K15: =SUM(L15:W15) -> 0 | L15: =SUMIFS('PL Actual MTM - Aug 26'!D:D,'PL Actual MTM - Aug 26'!$R:$R,"Sales Return")/10^6 -> 0 | M15: =SUMIFS('PL Actual MTM - Aug 26'!E:E,'PL Actual MTM - Aug 26'!$R:$R,"Sales Return")/10^6 -> 0 | N15: 0 | O15: =SUMIFS('PL Actual MTM - Aug 26'!G:G,'PL Actual MTM - Aug 26'!$R:$R,"Sales Return")/10^6 -> 0 | P15: =SUMIFS('PL Actual MTM - Aug 26'!H:H,'PL Actual MTM - Aug 26'!$R:$R,"Sales Return")/10^6 -> 0 | Q15: =SUMIFS('PL Actual MTM - Aug 26'!I:I,'PL Actual MTM - Aug 26'!$R:$R,"Sales Return")/10^6 -> 0 | R15: 0 | S15: =SUMIFS('PL Actual MTM - Aug 26'!K:K,'PL Actual MTM - Aug 26'!$R:$R,"Sales Return")/10^6 -> 0 | T15: 0 | U15: 0 | V15: 0 | W15: 0 | X15: 0 | Y15: 0 | Z15: 0 | AA15: 0 | AB15: 0 | AC15: 0 | AD15: 0 | AE15: 0 | AF15: 0 | AG15: 0 | AH15: 0 | AI15: 0 | AJ15: =SUM(X15:AI15) -> 0
D16: Sales Return | H16: Rp m | I16: =IFERROR((K16-J16)/J16,0) -> 0 | K16: =SUM(L16:W16) -> -78.30075 | L16: =SUMIFS('PL Actual MTM - Aug 26'!D:D,'PL Actual MTM - Aug 26'!$R:$R,"Sales Return")/10^6 -> 0 | M16: =SUMIFS('PL Actual MTM - Aug 26'!E:E,'PL Actual MTM - Aug 26'!$R:$R,"Sales Return")/10^6 -> 0 | N16: =SUMIFS('PL Actual MTM - Aug 26'!F:F,'PL Actual MTM - Aug 26'!$R:$R,"Sales Return")/10^6 -> -62.7011 | O16: =SUMIFS('PL Actual MTM - Aug 26'!G:G,'PL Actual MTM - Aug 26'!$R:$R,"Sales Return")/10^6 -> 0 | P16: =SUMIFS('PL Actual MTM - Aug 26'!H:H,'PL Actual MTM - Aug 26'!$R:$R,"Sales Return")/10^6 -> 0 | Q16: =SUMIFS('PL Actual MTM - Aug 26'!I:I,'PL Actual MTM - Aug 26'!$R:$R,"Sales Return")/10^6 -> 0 | R16: =SUMIFS('PL Actual MTM - Aug 26'!J:J,'PL Actual MTM - Aug 26'!$R:$R,"Sales Return")/10^6 -> -15.59965 | S16: =SUMIFS('PL Actual MTM - Aug 26'!K:K,'PL Actual MTM - Aug 26'!$R:$R,"Sales Return")/10^6 -> 0 | T16: 0 | U16: 0 | V16: 0 | W16: 0 | X16: 0 | Y16: 0 | Z16: 0 | AA16: 0 | AB16: 0 | AC16: 0 | AD16: 0 | AE16: 0 | AF16: 0 | AG16: 0 | AH16: 0 | AI16: 0 | AJ16: =SUM(X16:AI16) -> 0
C17: Revenue | H17: Rp m | I17: =IFERROR((K17-J17)/J17,0) -> 0 | J17: =SUM(J9,J16) -> 0 | K17: =SUM(K9,K16) -> 101057.15 | L17: =SUM(L14,L9) -> 9369.4466 | M17: =SUM(M14,M9) -> 8659.5707 | N17: =SUM(N14,N9) -> 6484.5568 | O17: =SUM(O14,O9) -> 6850.5287 | P17: =SUM(P14,P9) -> 7705.4169 | Q17: =SUM(Q14,Q9) -> 8295.2878 | R17: =SUM(R14,R9) -> 8914.0809 | S17: =SUM(S14,S9) -> 9793.1255 | ... AI17: =SUM(AI14,AI9) -> 8746.2829 | AJ17: =SUM(AJ9,AJ16) -> 104955.39
C18: FCC | H18: Rp m | I18: =IFERROR((K18-J18)/J18,0) -> 0 | K18: =SUM(L18:W18) -> -79243.625 | L18: =SUM(L20:L26,L28:L32) -> -6689.2956 | M18: =SUM(M20:M26,M28:M32) -> -6206.1889 | N18: =SUM(N20:N26,N28:N32) -> -5128.5947 | O18: =SUM(O20:O26,O28:O32) -> -5575.0519 | P18: =SUM(P20:P26,P28:P32) -> -6145.3555 | Q18: =SUM(Q20:Q26,Q28:Q32) -> -6472.8107 | R18: =SUM(R20:R26,R28:R32) -> -6798.4327 | S18: =SUM(S20:S26,S28:S32) -> -7437.8719 | ... AI18: =SUM(AI20:AI26,AI28:AI32) -> -7236.8158
D19: Manufacturing Cost
E20: Raw Materials | H20: Rp m | I20: =IFERROR((K20-J20)/J20,0) -> 0 | K20: =SUM(L20:W20) -> -29186.661 | L20: =-'Business Plan - Model Details'!J546/10^6 -> -2152.6057 | M20: =-'Business Plan - Model Details'!K546/10^6 -> -1978.8554 | N20: =-'Business Plan - Model Details'!L546/10^6 -> -1593.9767 | O20: =-'Business Plan - Model Details'!M546/10^6 -> -1650.8016 | P20: =-'Business Plan - Model Details'!N546/10^6 -> -2023.7932 | Q20: =-'Business Plan - Model Details'!O546/10^6 -> -2337.955 | R20: =-'Business Plan - Model Details'!P546/10^6 -> -2576.5355 | S20: =-'Business Plan - Model Details'!Q546/10^6 -> -3103.9859 | ... AI20: =-'Business Plan - Model Details'!AG546/10^6 -> -2998.8255 | AJ20: =SUM(X20:AI20) -> -35986.163
E21: OIL | H21: Rp m | I21: =IFERROR((K21-J21)/J21,0) -> 0 | K21: =SUM(L21:W21) -> -16008.371 | L21: =-'Business Plan - Model Details'!J547/10^6 -> -1501.893 | M21: =-'Business Plan - Model Details'!K547/10^6 -> -1387.4366 | N21: =-'Business Plan - Model Details'!L547/10^6 -> -1076.0138 | O21: =-'Business Plan - Model Details'!M547/10^6 -> -1147.087 | P21: =-'Business Plan - Model Details'!N547/10^6 -> -1270.1684 | Q21: =-'Business Plan - Model Details'!O547/10^6 -> -1259.1326 | R21: =-'Business Plan - Model Details'!P547/10^6 -> -1334.6782 | S21: =-'Business Plan - Model Details'!Q547/10^6 -> -1362.1392 | ... AI21: =-'Business Plan - Model Details'!AG547/10^6 -> -1416.791
E22: CNG | H22: Rp m | I22: =IFERROR((K22-J22)/J22,0) -> 0 | K22: =SUM(L22:W22) -> -12201.974 | L22: =-'Business Plan - Model Details'!J548/10^6 -> -1107.9619 | M22: =-'Business Plan - Model Details'!K548/10^6 -> -1018.5149 | N22: =-'Business Plan - Model Details'!L548/10^6 -> -817.96911 | O22: =-'Business Plan - Model Details'!M548/10^6 -> -850.71281 | P22: =-'Business Plan - Model Details'!N548/10^6 -> -990.88117 | Q22: =-'Business Plan - Model Details'!O548/10^6 -> -1022.5894 | R22: =-'Business Plan - Model Details'!P548/10^6 -> -1055.0997 | S22: =-'Business Plan - Model Details'!Q548/10^6 -> -1156.699 | ... AI22: =-'Business Plan - Model Details'!AG548/10^6 -> -1045.3193 | AJ22: =SUM(X22:AI22) -> -12543.921
E23: Material - Others | H23: Rp m | I23: =IFERROR((K23-J23)/J23,0) -> 0 | K23: =SUM(L23:W23) -> -2748.1447 | L23: =-'Business Plan - Model Details'!J549/10^6 -> -245.82993 | M23: =-'Business Plan - Model Details'!K549/10^6 -> -186.81427 | N23: =-'Business Plan - Model Details'!L549/10^6 -> -143.26362 | O23: =-'Business Plan - Model Details'!M549/10^6 -> -169.81064 | P23: =-'Business Plan - Model Details'!N549/10^6 -> -250.9403 | Q23: =-'Business Plan - Model Details'!O549/10^6 -> -279.23552 | R23: =-'Business Plan - Model Details'!P549/10^6 -> -212.87493 | S23: =-'Business Plan - Model Details'!Q549/10^6 -> -286.68646 | ... AI23: =-'Business Plan - Model Details'!AG549/10^6 -> -237.45304 | AJ23: =SUM(X23:AI23) -> -2853.5178
E24: Upah Kupas | H24: Rp m | I24: =IFERROR((K24-J24)/J24,0) -> 0 | K24: =SUM(L24:W24) -> -1996.8395 | L24: =-'Business Plan - Model Details'!J550/10^6 -> -219.60534 | M24: =-'Business Plan - Model Details'!K550/10^6 -> -196.80334 | N24: =-'Business Plan - Model Details'!L550/10^6 -> -152.87413 | O24: =-'Business Plan - Model Details'!M550/10^6 -> -144.32887 | P24: =-'Business Plan - Model Details'!N550/10^6 -> -173.63913 | Q24: =-'Business Plan - Model Details'!O550/10^6 -> -174.7875 | R24: =-'Business Plan - Model Details'!P550/10^6 -> -155.36244 | S24: =-'Business Plan - Model Details'!Q550/10^6 -> -110.02163 | ... AI24: =-'Business Plan - Model Details'!AG550/10^6 -> -167.34267 | AJ24: =SUM(X24:AI24) -> -2008.1276
E25: Direct Labour | H25: Rp m | I25: =IFERROR((K25-J25)/J25,0) -> 0 | K25: =SUM(L25:W25) -> -9371.5494 | L25: =-'Business Plan - Model Details'!J551/10^6 -> -763.22929 | M25: =-'Business Plan - Model Details'!K551/10^6 -> -659.60587 | N25: =-'Business Plan - Model Details'!L551/10^6 -> -511.70588 | O25: =-'Business Plan - Model Details'!M551/10^6 -> -783.73635 | P25: =-'Business Plan - Model Details'!N551/10^6 -> -816.78222 | Q25: =-'Business Plan - Model Details'!O551/10^6 -> -799.59033 | R25: =-'Business Plan - Model Details'!P551/10^6 -> -838.00403 | S25: =-'Business Plan - Model Details'!Q551/10^6 -> -837.03787 | ... AI25: =-'Business Plan - Model Details'!AG551/10^6 -> -840.43914 | AJ25: =SUM(X25:AI25) -> -10085.254
E26: Factory overhead | H26: Rp m | I26: =IFERROR((K26-J26)/J26,0) -> 0 | K26: =SUM(L26:W26) -> -8196.9501 | L26: =-'Business Plan - Model Details'!J552/10^6 -> -698.17042 | M26: =-'Business Plan - Model Details'!K552/10^6 -> -778.1585 | N26: =-'Business Plan - Model Details'!L552/10^6 -> -832.79144 | O26: =-'Business Plan - Model Details'!M552/10^6 -> -828.57457 | P26: =-'Business Plan - Model Details'!N552/10^6 -> -619.15107 | Q26: =-'Business Plan - Model Details'!O552/10^6 -> -599.52042 | R26: =-'Business Plan - Model Details'!P552/10^6 -> -625.8779 | S26: =-'Business Plan - Model Details'!Q552/10^6 -> -581.30169 | ... AI26: =-'Business Plan - Model Details'!AG552/10^6 -> -642.52648 | AJ26: =SUM(X26:AI26) -> -7759.4607
D27: Inventory Movement
E28: KW 2 | H28: Rp m | I28: =IFERROR((K28-J28)/J28,0) -> 0 | K28: =SUM(L28:W28) -> 433.84386 | L28: =-'Business Plan - Model Details'!J555/10^6 -> 0 | M28: =-'Business Plan - Model Details'!K555/10^6 -> 0 | N28: =-'Business Plan - Model Details'!L555/10^6 -> 0 | O28: =-'Business Plan - Model Details'!M555/10^6 -> 0 | P28: =-'Business Plan - Model Details'!N555/10^6 -> 0 | Q28: =-'Business Plan - Model Details'!O555/10^6 -> 0 | R28: =-'Business Plan - Model Details'!P555/10^6 -> 0 | S28: =-'Business Plan - Model Details'!Q555/10^6 -> 0 | ... AI28: =-'Business Plan - Model Details'!AG555/10^6 -> 111.90126
E29: WIP - Beginnig Balance | H29: Rp m | I29: =IFERROR((K29-J29)/J29,0) -> 0 | K29: =SUM(L29:W29) -> -34.115454 | L29: =-'Business Plan - Model Details'!J558/10^6 -> 0 | M29: =-'Business Plan - Model Details'!K558/10^6 -> 0 | N29: =-'Business Plan - Model Details'!L558/10^6 -> 0 | O29: =-'Business Plan - Model Details'!M558/10^6 -> 0 | P29: =-'Business Plan - Model Details'!N558/10^6 -> 0 | Q29: =-'Business Plan - Model Details'!O558/10^6 -> 0 | R29: =-'Business Plan - Model Details'!P558/10^6 -> 0 | S29: =-'Business Plan - Model Details'!Q558/10^6 -> 0 | ... AI29: =-'Business Plan - Model Details'!AG558/10^6 -> -8.9797962
E30: WIP - Ending Balance | H30: Rp m | I30: =IFERROR((K30-J30)/J30,0) -> 0 | K30: =SUM(L30:W30) -> 35.713741 | L30: =-'Business Plan - Model Details'!J559/10^6 -> 0 | M30: =-'Business Plan - Model Details'!K559/10^6 -> 0 | N30: =-'Business Plan - Model Details'!L559/10^6 -> 0 | O30: =-'Business Plan - Model Details'!M559/10^6 -> 0 | P30: =-'Business Plan - Model Details'!N559/10^6 -> 0 | Q30: =-'Business Plan - Model Details'!O559/10^6 -> 0 | R30: =-'Business Plan - Model Details'!P559/10^6 -> 0 | S30: =-'Business Plan - Model Details'!Q559/10^6 -> 0 | ... AI30: =-'Business Plan - Model Details'!AG559/10^6 -> 8.9788181 | AJ30: =SUM(X30:AI30) -> 107.82017
E31: FG - Beginnig Balance | H31: Rp m | I31: =IFERROR((K31-J31)/J31,0) -> 0 | K31: =SUM(L31:W31) -> -669.97107 | L31: =-'Business Plan - Model Details'!J561/10^6 -> 0 | M31: =-'Business Plan - Model Details'!K561/10^6 -> 0 | N31: =-'Business Plan - Model Details'!L561/10^6 -> 0 | O31: =-'Business Plan - Model Details'!M561/10^6 -> 0 | P31: =-'Business Plan - Model Details'!N561/10^6 -> 0 | Q31: =-'Business Plan - Model Details'!O561/10^6 -> 0 | R31: =-'Business Plan - Model Details'!P561/10^6 -> 0 | S31: =-'Business Plan - Model Details'!Q561/10^6 -> 0 | ... AI31: =-'Business Plan - Model Details'!AG561/10^6 -> -176.55683 | AJ31: =SUM(X31:AI31) -> -2120.3507
E32: FG - Ending Balance | H32: Rp m | I32: =IFERROR((K32-J32)/J32,0) -> 0 | K32: =SUM(L32:W32) -> 701.39367 | L32: =-'Business Plan - Model Details'!J562/10^6 -> 0 | M32: =-'Business Plan - Model Details'!K562/10^6 -> 0 | N32: =-'Business Plan - Model Details'!L562/10^6 -> 0 | O32: =-'Business Plan - Model Details'!M562/10^6 -> 0 | P32: =-'Business Plan - Model Details'!N562/10^6 -> 0 | Q32: =-'Business Plan - Model Details'!O562/10^6 -> 0 | R32: =-'Business Plan - Model Details'!P562/10^6 -> 0 | S32: =-'Business Plan - Model Details'!Q562/10^6 -> 0 | ... AI32: =-'Business Plan - Model Details'!AG562/10^6 -> 176.53786 | AJ32: =SUM(X32:AI32) -> 2119.9213
C33: Ubi Ungu | H33: Rp m | I33: =IFERROR((K33-J33)/J33,0) -> 0 | K33: =SUM(L33:W33) -> -2951.3293 | L33: =SUM(L34:L41,L43:L47) -> -132.00802 | M33: =SUM(M34:M41,M43:M47) -> -88.08396 | N33: =SUM(N34:N41,N43:N47) -> -44.795944 | O33: =SUM(O34:O41,O43:O47) -> -253.58468 | P33: =SUM(P34:P41,P43:P47) -> -204.31368 | Q33: =SUM(Q34:Q41,Q43:Q47) -> -570.04226 | R33: =SUM(R34:R41,R43:R47) -> -325.14223 | S33: =SUM(S34:S41,S43:S47) -> -458.97133 | ... AI33: =SUM(AI34:AI41,AI43:AI47) -> -223.11707
D34: Manufacturing Cost
E35: Raw Materials | H35: Rp m | I35: =IFERROR((K35-J35)/J35,0) -> 0 | K35: =SUM(L35:W35) -> -1525.4028 | L35: =-'Business Plan - Model Details'!J702/10^6 -> -79.040705 | M35: =-'Business Plan - Model Details'!K702/10^6 -> -37.301 | N35: =-'Business Plan - Model Details'!L702/10^6 -> -23.689 | O35: =-'Business Plan - Model Details'!M702/10^6 -> -113.007 | P35: =-'Business Plan - Model Details'!N702/10^6 -> -102.14103 | Q35: =-'Business Plan - Model Details'!O702/10^6 -> -299.01619 | R35: =-'Business Plan - Model Details'!P702/10^6 -> -147.2659 | S35: =-'Business Plan - Model Details'!Q702/10^6 -> -246.3404 | ... AI35: =-'Business Plan - Model Details'!AG702/10^6 -> -119.4004 | AJ35: =SUM(X35:AI35) -> -1432.8048
E36: OIL | H36: Rp m | I36: =IFERROR((K36-J36)/J36,0) -> 0 | K36: =SUM(L36:W36) -> -521.24658 | L36: =-'Business Plan - Model Details'!J703/10^6 -> -5.9840709 | M36: =-'Business Plan - Model Details'!K703/10^6 -> -13.430525 | N36: =-'Business Plan - Model Details'!L703/10^6 -> -6.4167984 | O36: =-'Business Plan - Model Details'!M703/10^6 -> -46.75069 | P36: =-'Business Plan - Model Details'!N703/10^6 -> -35.684648 | Q36: =-'Business Plan - Model Details'!O703/10^6 -> -105.40289 | R36: =-'Business Plan - Model Details'!P703/10^6 -> -63.822502 | S36: =-'Business Plan - Model Details'!Q703/10^6 -> -71.810529 | ... AI36: =-'Business Plan - Model Details'!AG703/10^6 -> -42.968582
E37: CNG | H37: Rp m | I37: =IFERROR((K37-J37)/J37,0) -> 0 | K37: =SUM(L37:W37) -> -333.76307 | L37: =-'Business Plan - Model Details'!J704/10^6 -> 0 | M37: =-'Business Plan - Model Details'!K704/10^6 -> -10.624045 | N37: =-'Business Plan - Model Details'!L704/10^6 -> -4.2868911 | O37: =-'Business Plan - Model Details'!M704/10^6 -> -29.843052 | P37: =-'Business Plan - Model Details'!N704/10^6 -> -20.710968 | Q37: =-'Business Plan - Model Details'!O704/10^6 -> -62.27375 | R37: =-'Business Plan - Model Details'!P704/10^6 -> -41.031715 | S37: =-'Business Plan - Model Details'!Q704/10^6 -> -51.763471 | ... AI37: =-'Business Plan - Model Details'!AG704/10^6 -> -28.307295 | AJ37: =SUM(X37:AI37) -> -339.68754
E38: Material - Others | H38: Rp m | I38: =IFERROR((K38-J38)/J38,0) -> 0 | K38: =SUM(L38:W38) -> -54.996534 | L38: =-'Business Plan - Model Details'!J705/10^6 -> -0.37099799 | M38: =-'Business Plan - Model Details'!K705/10^6 -> -1.3249985 | N38: =-'Business Plan - Model Details'!L705/10^6 -> -0.6095 | O38: =-'Business Plan - Model Details'!M705/10^6 -> -3.0061594 | P38: =-'Business Plan - Model Details'!N705/10^6 -> -3.7565251 | Q38: =-'Business Plan - Model Details'!O705/10^6 -> -11.554204 | R38: =-'Business Plan - Model Details'!P705/10^6 -> -7.6002766 | S38: =-'Business Plan - Model Details'!Q705/10^6 -> -9.1148042 | ... AI38: =-'Business Plan - Model Details'!AG705/10^6 -> -4.360556 | AJ38: =SUM(X38:AI38) -> -52.340547
E39: Upah Kupas | H39: Rp m | I39: =IFERROR((K39-J39)/J39,0) -> 0 | K39: =SUM(L39:W39) -> 0 | L39: =-'Business Plan - Model Details'!J706/10^6 -> 0 | M39: =-'Business Plan - Model Details'!K706/10^6 -> 0 | N39: =-'Business Plan - Model Details'!L706/10^6 -> 0 | O39: =-'Business Plan - Model Details'!M706/10^6 -> 0 | P39: =-'Business Plan - Model Details'!N706/10^6 -> 0 | Q39: =-'Business Plan - Model Details'!O706/10^6 -> 0 | R39: =-'Business Plan - Model Details'!P706/10^6 -> 0 | S39: =-'Business Plan - Model Details'!Q706/10^6 -> 0 | ... AI39: =-'Business Plan - Model Details'!AG706/10^6 -> 0 | AJ39: =SUM(X39:AI39) -> 0
E40: Direct Labour | H40: Rp m | I40: =IFERROR((K40-J40)/J40,0) -> 0 | K40: =SUM(L40:W40) -> -322.78674 | L40: =-'Business Plan - Model Details'!J707/10^6 -> -21.68941 | M40: =-'Business Plan - Model Details'!K707/10^6 -> -11.358265 | N40: =-'Business Plan - Model Details'!L707/10^6 -> -4.5351858 | O40: =-'Business Plan - Model Details'!M707/10^6 -> -30.206963 | P40: =-'Business Plan - Model Details'!N707/10^6 -> -27.248602 | Q40: =-'Business Plan - Model Details'!O707/10^6 -> -61.897409 | R40: =-'Business Plan - Model Details'!P707/10^6 -> -39.027989 | S40: =-'Business Plan - Model Details'!Q707/10^6 -> -54.419153 | ... AI40: =-'Business Plan - Model Details'!AG707/10^6 -> -18.101547 | AJ40: =SUM(X40:AI40) -> -217.21667
E41: Factory overhead | H41: Rp m | I41: =IFERROR((K41-J41)/J41,0) -> 0 | K41: =SUM(L41:W41) -> -212.41633 | L41: =-'Business Plan - Model Details'!J708/10^6 -> -24.922835 | M41: =-'Business Plan - Model Details'!K708/10^6 -> -14.045127 | N41: =-'Business Plan - Model Details'!L708/10^6 -> -5.2585687 | O41: =-'Business Plan - Model Details'!M708/10^6 -> -30.770811 | P41: =-'Business Plan - Model Details'!N708/10^6 -> -14.771909 | Q41: =-'Business Plan - Model Details'!O708/10^6 -> -29.897811 | R41: =-'Business Plan - Model Details'!P708/10^6 -> -26.393849 | S41: =-'Business Plan - Model Details'!Q708/10^6 -> -25.522977 | ... AI41: =-'Business Plan - Model Details'!AG708/10^6 -> -9.965891 | AJ41: =SUM(X41:AI41) -> -120.35617
D42: Inventory Movement
E43: KW 2 | H43: Rp m | I43: =IFERROR((K43-J43)/J43,0) -> 0 | K43: =SUM(L43:W43) -> 0 | L43: =-'Business Plan - Model Details'!J711/10^6 -> 0 | M43: =-'Business Plan - Model Details'!K711/10^6 -> 0 | N43: =-'Business Plan - Model Details'!L711/10^6 -> 0 | O43: =-'Business Plan - Model Details'!M711/10^6 -> 0 | P43: =-'Business Plan - Model Details'!N711/10^6 -> 0 | Q43: =-'Business Plan - Model Details'!O711/10^6 -> 0 | R43: =-'Business Plan - Model Details'!P711/10^6 -> 0 | S43: =-'Business Plan - Model Details'!Q711/10^6 -> 0 | ... AI43: =-'Business Plan - Model Details'!AG711/10^6 -> 0
E44: WIP - Beginnig Balance | H44: Rp m | I44: =IFERROR((K44-J44)/J44,0) -> 0 | K44: =SUM(L44:W44) -> -537.36605 | L44: =-'Business Plan - Model Details'!J714/10^6 -> 0 | M44: =-'Business Plan - Model Details'!K714/10^6 -> 0 | N44: =-'Business Plan - Model Details'!L714/10^6 -> 0 | O44: =-'Business Plan - Model Details'!M714/10^6 -> 0 | P44: =-'Business Plan - Model Details'!N714/10^6 -> 0 | Q44: =-'Business Plan - Model Details'!O714/10^6 -> 0 | R44: =-'Business Plan - Model Details'!P714/10^6 -> 0 | S44: =-'Business Plan - Model Details'!Q714/10^6 -> 0 | ... AI44: =-'Business Plan - Model Details'!AG714/10^6 -> -139.78858
E45: WIP - Ending Balance | H45: Rp m | I45: =IFERROR((K45-J45)/J45,0) -> 0 | K45: =SUM(L45:W45) -> 551.21003 | L45: =-'Business Plan - Model Details'!J715/10^6 -> 0 | M45: =-'Business Plan - Model Details'!K715/10^6 -> 0 | N45: =-'Business Plan - Model Details'!L715/10^6 -> 0 | O45: =-'Business Plan - Model Details'!M715/10^6 -> 0 | P45: =-'Business Plan - Model Details'!N715/10^6 -> 0 | Q45: =-'Business Plan - Model Details'!O715/10^6 -> 0 | R45: =-'Business Plan - Model Details'!P715/10^6 -> 0 | S45: =-'Business Plan - Model Details'!Q715/10^6 -> 0 | ... AI45: =-'Business Plan - Model Details'!AG715/10^6 -> 139.77997 | AJ45: =SUM(X45:AI45) -> 1677.6648
E46: FG - Beginnig Balance | H46: Rp m | I46: =IFERROR((K46-J46)/J46,0) -> 0 | K46: =SUM(L46:W46) -> -282.23265 | L46: =-'Business Plan - Model Details'!J717/10^6 -> 0 | M46: =-'Business Plan - Model Details'!K717/10^6 -> 0 | N46: =-'Business Plan - Model Details'!L717/10^6 -> 0 | O46: =-'Business Plan - Model Details'!M717/10^6 -> 0 | P46: =-'Business Plan - Model Details'!N717/10^6 -> 0 | Q46: =-'Business Plan - Model Details'!O717/10^6 -> 0 | R46: =-'Business Plan - Model Details'!P717/10^6 -> 0 | S46: =-'Business Plan - Model Details'!Q717/10^6 -> 0 | ... AI46: =-'Business Plan - Model Details'!AG717/10^6 -> -73.413849 | AJ46: =SUM(X46:AI46) -> -880.74089
E47: FG - Ending Balance | H47: Rp m | I47: =IFERROR((K47-J47)/J47,0) -> 0 | K47: =SUM(L47:W47) -> 287.67146 | L47: =-'Business Plan - Model Details'!J718/10^6 -> 0 | M47: =-'Business Plan - Model Details'!K718/10^6 -> 0 | N47: =-'Business Plan - Model Details'!L718/10^6 -> 0 | O47: =-'Business Plan - Model Details'!M718/10^6 -> 0 | P47: =-'Business Plan - Model Details'!N718/10^6 -> 0 | Q47: =-'Business Plan - Model Details'!O718/10^6 -> 0 | R47: =-'Business Plan - Model Details'!P718/10^6 -> 0 | S47: =-'Business Plan - Model Details'!Q718/10^6 -> 0 | ... AI47: =-'Business Plan - Model Details'!AG718/10^6 -> 73.409653 | AJ47: =SUM(X47:AI47) -> 880.97989
C48: Ubi Orange | H48: Rp m | I48: =IFERROR((K48-J48)/J48,0) -> 0 | K48: =SUM(L48:W48) -> -2374.1797 | L48: =SUM(L49:L56,L58:L62) -> 0 | M48: =SUM(M49:M56,M58:M62) -> -153.98799 | N48: =SUM(N49:N56,N58:N62) -> 0 | O48: =SUM(O49:O56,O58:O62) -> -230.39068 | P48: =SUM(P49:P56,P58:P62) -> -194.76969 | Q48: =SUM(Q49:Q56,Q58:Q62) -> -485.12358 | R48: =SUM(R49:R56,R58:R62) -> -315.92519 | S48: =SUM(S49:S56,S58:S62) -> -235.48818 | ... AI48: =SUM(AI49:AI56,AI58:AI62) -> -190.33707
D49: Manufacturing Cost
E50: Raw Materials | H50: Rp m | I50: =IFERROR((K50-J50)/J50,0) -> 0 | K50: =SUM(L50:W50) -> -1139.1326 | L50: =-'Business Plan - Model Details'!J866/10^6 -> 0 | M50: =-'Business Plan - Model Details'!K866/10^6 -> -66.744 | N50: =-'Business Plan - Model Details'!L866/10^6 -> 0 | O50: =-'Business Plan - Model Details'!M866/10^6 -> -100.7685 | P50: =-'Business Plan - Model Details'!N866/10^6 -> -86.8005 | Q50: =-'Business Plan - Model Details'!O866/10^6 -> -237.5235 | R50: =-'Business Plan - Model Details'!P866/10^6 -> -142.5186 | S50: =-'Business Plan - Model Details'!Q866/10^6 -> -122.5183 | ... AI50: =-'Business Plan - Model Details'!AG866/10^6 -> -95.564799 | AJ50: =SUM(X50:AI50) -> -1146.7776
E51: OIL | H51: Rp m | I51: =IFERROR((K51-J51)/J51,0) -> 0 | K51: =SUM(L51:W51) -> -487.97612 | L51: =-'Business Plan - Model Details'!J867/10^6 -> 0 | M51: =-'Business Plan - Model Details'!K867/10^6 -> -35.56572 | N51: =-'Business Plan - Model Details'!L867/10^6 -> 0 | O51: =-'Business Plan - Model Details'!M867/10^6 -> -52.200789 | P51: =-'Business Plan - Model Details'!N867/10^6 -> -43.888815 | Q51: =-'Business Plan - Model Details'!O867/10^6 -> -98.64574 | R51: =-'Business Plan - Model Details'!P867/10^6 -> -60.943421 | S51: =-'Business Plan - Model Details'!Q867/10^6 -> -35.620507 | ... AI51: =-'Business Plan - Model Details'!AG867/10^6 -> -40.261478
E52: CNG | H52: Rp m | I52: =IFERROR((K52-J52)/J52,0) -> 0 | K52: =SUM(L52:W52) -> -283.32857 | L52: =-'Business Plan - Model Details'!J868/10^6 -> 0 | M52: =-'Business Plan - Model Details'!K868/10^6 -> -13.913755 | N52: =-'Business Plan - Model Details'!L868/10^6 -> 0 | O52: =-'Business Plan - Model Details'!M868/10^6 -> -25.443646 | P52: =-'Business Plan - Model Details'!N868/10^6 -> -22.073862 | Q52: =-'Business Plan - Model Details'!O868/10^6 -> -58.277347 | R52: =-'Business Plan - Model Details'!P868/10^6 -> -37.845113 | S52: =-'Business Plan - Model Details'!Q868/10^6 -> -29.661172 | ... AI52: =-'Business Plan - Model Details'!AG868/10^6 -> -24.028418 | AJ52: =SUM(X52:AI52) -> -288.34101
E53: Material - Others | H53: Rp m | I53: =IFERROR((K53-J53)/J53,0) -> 0 | K53: =SUM(L53:W53) -> -48.086396 | L53: =-'Business Plan - Model Details'!J869/10^6 -> 0 | M53: =-'Business Plan - Model Details'!K869/10^6 -> -1.8404249 | N53: =-'Business Plan - Model Details'!L869/10^6 -> 0 | O53: =-'Business Plan - Model Details'!M869/10^6 -> -3.021 | P53: =-'Business Plan - Model Details'!N869/10^6 -> -4.0174467 | Q53: =-'Business Plan - Model Details'!O869/10^6 -> -11.148489 | R53: =-'Business Plan - Model Details'!P869/10^6 -> -6.8299775 | S53: =-'Business Plan - Model Details'!Q869/10^6 -> -5.0530768 | ... AI53: =-'Business Plan - Model Details'!AG869/10^6 -> -4.0001846 | AJ53: =SUM(X53:AI53) -> -48.010171
E54: Upah Kupas | H54: Rp m | I54: =IFERROR((K54-J54)/J54,0) -> 0 | K54: =SUM(L54:W54) -> 0 | L54: =-'Business Plan - Model Details'!J870/10^6 -> 0 | M54: =-'Business Plan - Model Details'!K870/10^6 -> 0 | N54: =-'Business Plan - Model Details'!L870/10^6 -> 0 | O54: =-'Business Plan - Model Details'!M870/10^6 -> 0 | P54: =-'Business Plan - Model Details'!N870/10^6 -> 0 | Q54: =-'Business Plan - Model Details'!O870/10^6 -> 0 | R54: =-'Business Plan - Model Details'!P870/10^6 -> 0 | S54: =-'Business Plan - Model Details'!Q870/10^6 -> 0 | ... AI54: =-'Business Plan - Model Details'!AG870/10^6 -> 0 | AJ54: =SUM(X54:AI54) -> 0
E55: Direct Labour | H55: Rp m | I55: =IFERROR((K55-J55)/J55,0) -> 0 | K55: =SUM(L55:W55) -> -261.97346 | L55: =-'Business Plan - Model Details'!J871/10^6 -> 0 | M55: =-'Business Plan - Model Details'!K871/10^6 -> -19.842986 | N55: =-'Business Plan - Model Details'!L871/10^6 -> 0 | O55: =-'Business Plan - Model Details'!M871/10^6 -> -27.820037 | P55: =-'Business Plan - Model Details'!N871/10^6 -> -25.045635 | Q55: =-'Business Plan - Model Details'!O871/10^6 -> -51.630449 | R55: =-'Business Plan - Model Details'!P871/10^6 -> -45.640745 | S55: =-'Business Plan - Model Details'!Q871/10^6 -> -28.924522 | ... AI55: =-'Business Plan - Model Details'!AG871/10^6 -> -15.767799 | AJ55: =SUM(X55:AI55) -> -189.21194
E56: Factory overhead | H56: Rp m | I56: =IFERROR((K56-J56)/J56,0) -> 0 | K56: =SUM(L56:W56) -> -157.90534 | L56: =-'Business Plan - Model Details'!J872/10^6 -> 0 | M56: =-'Business Plan - Model Details'!K872/10^6 -> -16.081106 | N56: =-'Business Plan - Model Details'!L872/10^6 -> 0 | O56: =-'Business Plan - Model Details'!M872/10^6 -> -21.136711 | P56: =-'Business Plan - Model Details'!N872/10^6 -> -12.94343 | Q56: =-'Business Plan - Model Details'!O872/10^6 -> -27.898054 | R56: =-'Business Plan - Model Details'!P872/10^6 -> -22.14733 | S56: =-'Business Plan - Model Details'!Q872/10^6 -> -13.710597 | ... AI56: =-'Business Plan - Model Details'!AG872/10^6 -> -10.709839 | AJ56: =SUM(X56:AI56) -> -129.38185
D57: Inventory Movement
E58: KW 2 | I58: =IFERROR((K58-J58)/J58,0) -> 0 | K58: =SUM(L58:W58) -> 0 | L58: =-'Business Plan - Model Details'!J875/10^6 -> 0 | M58: =-'Business Plan - Model Details'!K875/10^6 -> 0 | N58: =-'Business Plan - Model Details'!L875/10^6 -> 0 | O58: =-'Business Plan - Model Details'!M875/10^6 -> 0 | P58: =-'Business Plan - Model Details'!N875/10^6 -> 0 | Q58: =-'Business Plan - Model Details'!O875/10^6 -> 0 | R58: =-'Business Plan - Model Details'!P875/10^6 -> 0 | S58: =-'Business Plan - Model Details'!Q875/10^6 -> 0 | ... AI58: =-'Business Plan - Model Details'!AG875/10^6 -> 0
E59: WIP - Beginnig Balance | I59: =IFERROR((K59-J59)/J59,0) -> 0 | K59: =SUM(L59:W59) -> -3.2130629e-14 | L59: =-'Business Plan - Model Details'!J878/10^6 -> 0 | M59: =-'Business Plan - Model Details'!K878/10^6 -> 0 | N59: =-'Business Plan - Model Details'!L878/10^6 -> 0 | O59: =-'Business Plan - Model Details'!M878/10^6 -> 0 | P59: =-'Business Plan - Model Details'!N878/10^6 -> 0 | Q59: =-'Business Plan - Model Details'!O878/10^6 -> 0 | R59: =-'Business Plan - Model Details'!P878/10^6 -> 0 | S59: =-'Business Plan - Model Details'!Q878/10^6 -> 0 | ... AI59: =-'Business Plan - Model Details'!AG878/10^6 -> -1.2572855e-14
E60: WIP - Ending Balance | I60: =IFERROR((K60-J60)/J60,0) -> 0 | K60: =SUM(L60:W60) -> 4.5634806e-14 | L60: =-'Business Plan - Model Details'!J879/10^6 -> 0 | M60: =-'Business Plan - Model Details'!K879/10^6 -> 0 | N60: =-'Business Plan - Model Details'!L879/10^6 -> 0 | O60: =-'Business Plan - Model Details'!M879/10^6 -> 0 | P60: =-'Business Plan - Model Details'!N879/10^6 -> 0 | Q60: =-'Business Plan - Model Details'!O879/10^6 -> 0 | R60: =-'Business Plan - Model Details'!P879/10^6 -> 0 | S60: =-'Business Plan - Model Details'!Q879/10^6 -> 0 | ... AI60: =-'Business Plan - Model Details'!AG879/10^6 -> 2.0954758e-14 | AJ60: =SUM(X60:AI60) -> 1.4877878e-13
E61: FG - Beginnig Balance | I61: =IFERROR((K61-J61)/J61,0) -> 0 | K61: =SUM(L61:W61) -> -282.25629 | L61: =-'Business Plan - Model Details'!J881/10^6 -> 0 | M61: =-'Business Plan - Model Details'!K881/10^6 -> 0 | N61: =-'Business Plan - Model Details'!L881/10^6 -> 0 | O61: =-'Business Plan - Model Details'!M881/10^6 -> 0 | P61: =-'Business Plan - Model Details'!N881/10^6 -> 0 | Q61: =-'Business Plan - Model Details'!O881/10^6 -> 0 | R61: =-'Business Plan - Model Details'!P881/10^6 -> 0 | S61: =-'Business Plan - Model Details'!Q881/10^6 -> 0 | ... AI61: =-'Business Plan - Model Details'!AG881/10^6 -> -71.897844 | AJ61: =SUM(X61:AI61) -> -863.11202
E62: FG - Ending Balance | I62: =IFERROR((K62-J62)/J62,0) -> 0 | K62: =SUM(L62:W62) -> 286.47904 | L62: =-'Business Plan - Model Details'!J882/10^6 -> 0 | M62: =-'Business Plan - Model Details'!K882/10^6 -> 0 | N62: =-'Business Plan - Model Details'!L882/10^6 -> 0 | O62: =-'Business Plan - Model Details'!M882/10^6 -> 0 | P62: =-'Business Plan - Model Details'!N882/10^6 -> 0 | Q62: =-'Business Plan - Model Details'!O882/10^6 -> 0 | R62: =-'Business Plan - Model Details'!P882/10^6 -> 0 | S62: =-'Business Plan - Model Details'!Q882/10^6 -> 0 | ... AI62: =-'Business Plan - Model Details'!AG882/10^6 -> 71.893293 | AJ62: =SUM(X62:AI62) -> 863.05072
C63: COGS - Others | H63: Rp m | I63: =IFERROR((K63-J63)/J63,0) -> 0 | K63: =SUM(L63:W63) -> -661.9438 | L63: =-'Business Plan - Model Details'!J955/10^6 -> -83.818101 | M63: =-'Business Plan - Model Details'!K955/10^6 -> -70.947392 | N63: =-'Business Plan - Model Details'!L955/10^6 -> -29.180852 | O63: =-'Business Plan - Model Details'!M955/10^6 -> -42.436041 | P63: =-'Business Plan - Model Details'!N955/10^6 -> -57.906749 | Q63: =-'Business Plan - Model Details'!O955/10^6 -> -23.87986 | R63: =-'Business Plan - Model Details'!P955/10^6 -> -109.06666 | S63: =-'Business Plan - Model Details'!Q955/10^6 -> -76.725653 | ... AI63: =-'Business Plan - Model Details'!AG955/10^6 -> -41.534915
C64: Cost of revenue - Product Level | H64: Rp m | I64: =IFERROR((K64-J64)/J64,0) -> 0 | K64: =SUM(K18,K33,K48) -> -84569.134 | L64: =SUM(L18,L33,L48,L63)+L83 -> -6667.182 | M64: =SUM(M18,M33,M48,M63)+M83 -> -6591.9515 | N64: =SUM(N18,N33,N48,N63)+N83 -> -5211.7545 | O64: =SUM(O18,O33,O48,O63)+O83 -> -5876.8618 | P64: =SUM(P18,P33,P48,P63)+P83 -> -6624.8784 | Q64: =SUM(Q18,Q33,Q48,Q63)+Q83 -> -7152.2142 | R64: =SUM(R18,R33,R48,R63)+R83 -> -7596.8221 | S64: =SUM(S18,S33,S48,S63)+S83 -> -7842.1457 | ... AI64: =SUM(AI18,AI33,AI48,AI63)+AI83 -> -7691.8048 | AJ64: =SUM(X64:AI64) -> -92353.85
C65: Direct Materials
D66: COGM Bahan Jadi | H66: Rp m | I66: =IFERROR((K66-J66)/J66,0) -> 0 | K66: =SUM(L66:W66) -> -65981.637 | L66: =-('Business Plan - Model Details'!J251)/10^6 -> -5494.6915 | M66: =-('Business Plan - Model Details'!K251)/10^6 -> -4882.7691 | N66: =-('Business Plan - Model Details'!L251)/10^6 -> -3454.2392 | O66: =-('Business Plan - Model Details'!M251)/10^6 -> -4329.8412 | P66: =-('Business Plan - Model Details'!N251)/10^6 -> -5087.8175 | Q66: =-('Business Plan - Model Details'!O251)/10^6 -> -5559.3339 | R66: =-('Business Plan - Model Details'!P251)/10^6 -> -5655.7373 | S66: =-('Business Plan - Model Details'!Q251)/10^6 -> -6713.5239 | ... AI66: =-('Business Plan - Model Details'!AG251)/10^6 -> -6251.235
C67: Direct Labour
C68: DL - Basic Salary (termasuk upah harian pabrik) | D68: DL - Basic Salary | H68: Rp m | I68: =IFERROR((K68-J68)/J68,0) -> 0 | K68: =SUM(L68:W68) -> -8310.6412 | L68: =-('Business Plan - Model Details'!J102+'Business Plan - Model Details'!J117)/10^6 -> -637.79389 | M68: =-('Business Plan - Model Details'!K102+'Business Plan - Model Details'!K117)/10^6 -> -538.38272 | N68: =-('Business Plan - Model Details'!L102+'Business Plan - Model Details'!L117)/10^6 -> -411.66934 | O68: =-('Business Plan - Model Details'!M102+'Business Plan - Model Details'!M117)/10^6 -> -668.93095 | P68: =-('Business Plan - Model Details'!N102+'Business Plan - Model Details'!N117)/10^6 -> -728.97079 | Q68: =-('Business Plan - Model Details'!O102+'Business Plan - Model Details'!O117)/10^6 -> -767.7483 | R68: =-('Business Plan - Model Details'!P102+'Business Plan - Model Details'!P117)/10^6 -> -799.1756 | S68: =-('Business Plan - Model Details'!Q102+'Business Plan - Model Details'!Q117)/10^6 -> -795.94609 | ... AI68: =-('Business Plan - Model Details'!AG102+'Business Plan - Model Details'!AG117)/10^6 -> -740.50589
D69: DL - THR And Bonus | H69: Rp m | I69: =IFERROR((K69-J69)/J69,0) -> 0 | K69: =SUM(L69:W69) -> -771.67228 | L69: =-('Business Plan - Model Details'!J137)/10^6 -> -90.489591 | M69: =-('Business Plan - Model Details'!K137)/10^6 -> -86.690751 | N69: =-('Business Plan - Model Details'!L137)/10^6 -> -40.430224 | O69: =-('Business Plan - Model Details'!M137)/10^6 -> -89.501467 | P69: =-('Business Plan - Model Details'!N137)/10^6 -> -65.51817 | Q69: =-('Business Plan - Model Details'!O137)/10^6 -> -49.66038 | R69: =-('Business Plan - Model Details'!P137)/10^6 -> -50.294529 | S69: =-('Business Plan - Model Details'!Q137)/10^6 -> -52.251872 | ... AI69: =-('Business Plan - Model Details'!AG137)/10^6 -> -61.708824
D70: DL - BPJS | H70: Rp m | I70: =IFERROR((K70-J70)/J70,0) -> 0 | K70: =SUM(L70:W70) -> -1018.4456 | L70: =-('Business Plan - Model Details'!J142)/10^6 -> -73.623014 | M70: =-('Business Plan - Model Details'!K142)/10^6 -> -80.02685 | N70: =-('Business Plan - Model Details'!L142)/10^6 -> -70.946437 | O70: =-('Business Plan - Model Details'!M142)/10^6 -> -93.30288 | P70: =-('Business Plan - Model Details'!N142)/10^6 -> -95.901507 | Q70: =-('Business Plan - Model Details'!O142)/10^6 -> -104.25297 | R70: =-('Business Plan - Model Details'!P142)/10^6 -> -105.51454 | S70: =-('Business Plan - Model Details'!Q142)/10^6 -> -106.40588 | ... AI70: =-('Business Plan - Model Details'!AG142)/10^6 -> -72.093772
D71: DL - Others | H71: Rp m | I71: =IFERROR((K71-J71)/J71,0) -> 0 | K71: =SUM(L71:W71) -> 0 | L71: 0 | M71: 0 | N71: 0 | O71: 0 | P71: 0 | Q71: 0 | R71: 0 | S71: 0 | T71: 0 | U71: 0 | V71: 0 | W71: 0 | X71: 0 | Y71: 0 | Z71: 0 | AA71: 0 | AB71: 0 | AC71: 0 | AD71: 0 | AE71: 0 | AF71: 0 | AG71: 0 | AH71: 0 | AI71: 0
C72: FOH
C73: IDL - Basic Salary (bulanan) | D73: IDL - Basic Salary | H73: Rp m | I73: =IFERROR((K73-J73)/J73,0) -> 0 | K73: =SUM(L73:W73) -> -2150.396 | L73: =-('Business Plan - Model Details'!J134)/10^6 -> -198.45956 | M73: =-('Business Plan - Model Details'!K134)/10^6 -> -198.45956 | N73: =-('Business Plan - Model Details'!L134)/10^6 -> -198.45956 | O73: =-('Business Plan - Model Details'!M134)/10^6 -> -205.81304 | P73: =-('Business Plan - Model Details'!N134)/10^6 -> -208.25308 | Q73: =-('Business Plan - Model Details'!O134)/10^6 -> -208.35021 | R73: =-('Business Plan - Model Details'!P134)/10^6 -> -204.06777 | S73: =-('Business Plan - Model Details'!Q134)/10^6 -> -165.81371 | ... AI73: =-('Business Plan - Model Details'!AG134)/10^6 -> -140.67989
D74: IDL - THR and Bonus | H74: Rp m | I74: =IFERROR((K74-J74)/J74,0) -> 0 | K74: =SUM(L74:W74) -> -209.95666 | L74: =-('Business Plan - Model Details'!J138)/10^6 -> -28.157254 | M74: =-('Business Plan - Model Details'!K138)/10^6 -> -31.956093 | N74: =-('Business Plan - Model Details'!L138)/10^6 -> -19.490799 | O74: =-('Business Plan - Model Details'!M138)/10^6 -> -27.537324 | P74: =-('Business Plan - Model Details'!N138)/10^6 -> -18.717294 | Q74: =-('Business Plan - Model Details'!O138)/10^6 -> -13.476748 | R74: =-('Business Plan - Model Details'!P138)/10^6 -> -12.8426 | S74: =-('Business Plan - Model Details'!Q138)/10^6 -> -10.885256 | ... AI74: =-('Business Plan - Model Details'!AG138)/10^6 -> -11.723324
D75: IDL - BPJS | H75: Rp m | I75: =IFERROR((K75-J75)/J75,0) -> 0 | K75: =SUM(L75:W75) -> -402.29858 | L75: =-('Business Plan - Model Details'!J143)/10^6 -> -22.908954 | M75: =-('Business Plan - Model Details'!K143)/10^6 -> -29.499634 | N75: =-('Business Plan - Model Details'!L143)/10^6 -> -34.202205 | O75: =-('Business Plan - Model Details'!M143)/10^6 -> -28.706923 | P75: =-('Business Plan - Model Details'!N143)/10^6 -> -27.397236 | Q75: =-('Business Plan - Model Details'!O143)/10^6 -> -28.291992 | R75: =-('Business Plan - Model Details'!P143)/10^6 -> -26.942911 | S75: =-('Business Plan - Model Details'!Q143)/10^6 -> -22.166769 | ... AI75: =-('Business Plan - Model Details'!AG143)/10^6 -> -45.530264
D76: Electricity | H76: Rp m | I76: =IFERROR((K76-J76)/J76,0) -> 0 | K76: =SUM(L76:W76) -> -646.41827 | L76: =-('Business Plan - Model Details'!J150)/10^6 -> -63.184268 | M76: =-('Business Plan - Model Details'!K150)/10^6 -> -53.698233 | N76: =-('Business Plan - Model Details'!L150)/10^6 -> -42.036498 | O76: =-('Business Plan - Model Details'!M150)/10^6 -> -50.567237 | P76: =-('Business Plan - Model Details'!N150)/10^6 -> -54.443107 | Q76: =-('Business Plan - Model Details'!O150)/10^6 -> -56.260859 | R76: =-('Business Plan - Model Details'!P150)/10^6 -> -58.622228 | S76: =-('Business Plan - Model Details'!Q150)/10^6 -> -56.566114 | ... AI76: =-('Business Plan - Model Details'!AG150)/10^6 -> -52.484432
D77: Water | H77: Rp m | I77: =IFERROR((K77-J77)/J77,0) -> 0 | K77: =SUM(L77:W77) -> -0.9463 | L77: =-('Business Plan - Model Details'!J152+'Business Plan - Model Details'!J153)/10^6 -> -0.0769 | M77: =-('Business Plan - Model Details'!K152+'Business Plan - Model Details'!K153)/10^6 -> -0.0794 | N77: =-('Business Plan - Model Details'!L152+'Business Plan - Model Details'!L153)/10^6 -> -0.079 | O77: =-('Business Plan - Model Details'!M152+'Business Plan - Model Details'!M153)/10^6 -> -0.079 | P77: =-('Business Plan - Model Details'!N152+'Business Plan - Model Details'!N153)/10^6 -> -0.079 | Q77: =-('Business Plan - Model Details'!O152+'Business Plan - Model Details'!O153)/10^6 -> -0.079 | R77: =-('Business Plan - Model Details'!P152+'Business Plan - Model Details'!P153)/10^6 -> -0.079 | S77: =-('Business Plan - Model Details'!Q152+'Business Plan - Model Details'!Q153)/10^6 -> -0.079 | ... AI77: =-('Business Plan - Model Details'!AG152+'Business Plan - Model Details'!AG153)/10^6 -> -0.079
D78: Biaya Rumah Tangga Pabrik | H78: Rp m | I78: =IFERROR((K78-J78)/J78,0) -> 0 | K78: =SUM(L78:W78) -> -310.91486 | L78: =-('Business Plan - Model Details'!J156)/10^6 -> -19.782842 | M78: =-('Business Plan - Model Details'!K156)/10^6 -> -20.47204 | N78: =-('Business Plan - Model Details'!L156)/10^6 -> -49.527426 | O78: =-('Business Plan - Model Details'!M156)/10^6 -> -26.756279 | P78: =-('Business Plan - Model Details'!N156)/10^6 -> -17.482207 | Q78: =-('Business Plan - Model Details'!O156)/10^6 -> -21.592538 | R78: =-('Business Plan - Model Details'!P156)/10^6 -> -33.93573 | S78: =-('Business Plan - Model Details'!Q156)/10^6 -> -24.213641 | ... AI78: =-('Business Plan - Model Details'!AG156)/10^6 -> -24.277476
D79: Maintenance - Machinery | H79: Rp m | I79: =IFERROR((K79-J79)/J79,0) -> 0 | K79: =SUM(L79:W79) -> -1630.905 | L79: =-('Business Plan - Model Details'!J158)/10^6 -> -144.38894 | M79: =-('Business Plan - Model Details'!K158)/10^6 -> -77.736043 | N79: =-('Business Plan - Model Details'!L158)/10^6 -> -156.87543 | O79: =-('Business Plan - Model Details'!M158)/10^6 -> -254.43778 | P79: =-('Business Plan - Model Details'!N158)/10^6 -> -122.61569 | Q79: =-('Business Plan - Model Details'!O158)/10^6 -> -111.86396 | R79: =-('Business Plan - Model Details'!P158)/10^6 -> -115.69685 | S79: =-('Business Plan - Model Details'!Q158)/10^6 -> -103.65535 | ... AI79: =-('Business Plan - Model Details'!AG158)/10^6 -> -135.90875
D80: Maintenance - Factory | H80: Rp m | I80: =IFERROR((K80-J80)/J80,0) -> 0 | K80: =SUM(L80:W80) -> -765.6369 | L80: =-('Business Plan - Model Details'!J159)/10^6 -> -50.19835 | M80: =-('Business Plan - Model Details'!K159)/10^6 -> -186.4807 | N80: =-('Business Plan - Model Details'!L159)/10^6 -> -133.94955 | O80: =-('Business Plan - Model Details'!M159)/10^6 -> -73.955 | P80: =-('Business Plan - Model Details'!N159)/10^6 -> -6.5375 | Q80: =-('Business Plan - Model Details'!O159)/10^6 -> -0.612 | R80: =-('Business Plan - Model Details'!P159)/10^6 -> -17.1 | S80: =-('Business Plan - Model Details'!Q159)/10^6 -> -41.591502 | ... AI80: =-('Business Plan - Model Details'!AG159)/10^6 -> -63.803075
D81: Maintenance - Factory Equipments | H81: Rp m | I81: =IFERROR((K81-J81)/J81,0) -> 0 | K81: =SUM(L81:W81) -> -89.387797 | L81: =-('Business Plan - Model Details'!J160)/10^6 -> -3.7 | M81: =-('Business Plan - Model Details'!K160)/10^6 -> -1.344631 | N81: =-('Business Plan - Model Details'!L160)/10^6 -> -2.075 | O81: =-('Business Plan - Model Details'!M160)/10^6 -> -17.203 | P81: =-('Business Plan - Model Details'!N160)/10^6 -> -4.85 | Q81: =-('Business Plan - Model Details'!O160)/10^6 -> -8.118919 | R81: =-('Business Plan - Model Details'!P160)/10^6 -> -17.59718 | S81: =-('Business Plan - Model Details'!Q160)/10^6 -> -4.703135 | ... AI81: =-('Business Plan - Model Details'!AG160)/10^6 -> -7.4489831
D82: Depreciation - Machinery | H82: Rp m | I82: projection = model plant-cost pool, which reads Register FA (machinery + factory equipment) | K82: =SUM(L82:W82) -> -2515.7022 | L82: =-('Business Plan - Model Details'!J162+'Business Plan - Model Details'!J163+'Business Plan - Model Details'!J167+'Business Plan - Model Details'!J168+'Business Plan - Model Details'!J164+'Business Plan - Model Details'!J165+'Business Plan - Model Details'!J166)/10^6 -> -211.608 | M82: =-('Business Plan - Model Details'!K162+'Business Plan - Model Details'!K163+'Business Plan - Model Details'!K167+'Business Plan - Model Details'!K168+'Business Plan - Model Details'!K164+'Business Plan - Model Details'!K165+'Business Plan - Model Details'!K166)/10^6 -> -215.80755 | N82: =-('Business Plan - Model Details'!L162+'Business Plan - Model Details'!L163+'Business Plan - Model Details'!L167+'Business Plan - Model Details'!L168+'Business Plan - Model Details'!L164+'Business Plan - Model Details'!L165+'Business Plan - Model Details'!L166)/10^6 -> -211.3048 | O82: =-('Business Plan - Model Details'!M162+'Business Plan - Model Details'!M163+'Business Plan - Model Details'!M167+'Business Plan - Model Details'!M168+'Business Plan - Model Details'!M164+'Business Plan - Model Details'!M165+'Business Plan - Model Details'!M166)/10^6 -> -208.42034 | P82: =-('Business Plan - Model Details'!N162+'Business Plan - Model Details'!N163+'Business Plan - Model Details'!N167+'Business Plan - Model Details'!N168+'Business Plan - Model Details'!N164+'Business Plan - Model Details'!N165+'Business Plan - Model Details'!N166)/10^6 -> -209.42117 | Q82: =-('Business Plan - Model Details'!O162+'Business Plan - Model Details'!O163+'Business Plan - Model Details'!O167+'Business Plan - Model Details'!O168+'Business Plan - Model Details'!O164+'Business Plan - Model Details'!O165+'Business Plan - Model Details'!O166)/10^6 -> -209.45093 | R82: =-('Business Plan - Model Details'!P162+'Business Plan - Model Details'!P163+'Business Plan - Model Details'!P167+'Business Plan - Model Details'!P168+'Business Plan - Model Details'!P164+'Business Plan - Model Details'!P165+'Business Plan - Model Details'!P166)/10^6 -> -209.41295 | S82: =-('Business Plan - Model Details'!Q162+'Business Plan - Model Details'!Q163+'Business Plan - Model Details'!Q167+'Business Plan - Model Details'!Q168+'Business Plan - Model Details'!Q164+'Business Plan - Model Details'!Q165+'Business Plan - Model Details'!Q166)/10^6 -> -209.86909 | ... AI82: =-('Business Plan - Model Details'!AG162+'Business Plan - Model Details'!AG163+'Business Plan - Model Details'!AG167+'Business Plan - Model Details'!AG168+'Business Plan - Model Details'!AG164+'Business Plan - Model Details'!AG165+'Business Plan - Model Details'!AG166)/10^6 -> -190.96783
C83: Selisih kartu CoGM vs GL (variance produksi) | D83: Vairance Productions | F83: Variance Produksi (5101-015) - nihil di GL Jan-Agu; masuk matriks bila muncul | H83: Rp m | I83: =IFERROR((K83-J83)/J83,0) -> 0 | K83: =SUM(L83:W83) -> 1076.3805 | L83: =-('Business Plan - Model Details'!J252+'Business Plan - Model Details'!J253)/10^6 -> 237.93972 | M83: =-('Business Plan - Model Details'!K252+'Business Plan - Model Details'!K253)/10^6 -> -72.743234 | N83: =-('Business Plan - Model Details'!L252+'Business Plan - Model Details'!L253)/10^6 -> -9.1829294 | O83: =-('Business Plan - Model Details'!M252+'Business Plan - Model Details'!M253)/10^6 -> 224.60147 | P83: =-('Business Plan - Model Details'!N252+'Business Plan - Model Details'!N253)/10^6 -> -22.53274 | Q83: =-('Business Plan - Model Details'!O252+'Business Plan - Model Details'!O253)/10^6 -> 399.64219 | R83: =-('Business Plan - Model Details'!P252+'Business Plan - Model Details'!P253)/10^6 -> -48.255281 | S83: =-('Business Plan - Model Details'!Q252+'Business Plan - Model Details'!Q253)/10^6 -> 366.91131 | ... AI83: =-('Business Plan - Model Details'!AG252+'Business Plan - Model Details'!AG253)/10^6 -> 0
D84: Delivery Expenses | H84: Rp m | I84: =IFERROR((K84-J84)/J84,0) -> 0 | K84: =SUM(L84:W84) -> -63.199946 | L84: =-('Business Plan - Model Details'!J171)/10^6 -> -1.8652 | M84: =-('Business Plan - Model Details'!K171)/10^6 -> -10.639288 | N84: =-('Business Plan - Model Details'!L171)/10^6 -> -0.5048 | O84: =-('Business Plan - Model Details'!M171)/10^6 -> -1.221625 | P84: =-('Business Plan - Model Details'!N171)/10^6 -> -0.558499 | Q84: =-('Business Plan - Model Details'!O171)/10^6 -> -3.901714 | R84: =-('Business Plan - Model Details'!P171)/10^6 -> -11.113022 | S84: =-('Business Plan - Model Details'!Q171)/10^6 -> -12.505355 | ... AI84: =-('Business Plan - Model Details'!AG171)/10^6 -> -5.2222815
C85: Inventory Reconciliation to COGM | F85: Inventory Reconciliation to COGM (KW 2, mutasi WIP & FG, penyesuaian ke GL) | H85: Rp m | L85: =-('Business Plan - Model Details'!J555+'Business Plan - Model Details'!J711+'Business Plan - Model Details'!J875+'Business Plan - Model Details'!J558+'Business Plan - Model Details'!J714+'Business Plan - Model Details'!J878+'Business Plan - Model Details'!J950+'Business Plan - Model Details'!J559+'Business Plan - Model Details'!J715+'Business Plan - Model Details'!J879+'Business Plan - Model Details'!J951+'Business Plan - Model Details'!J561+'Business Plan - Model Details'!J717+'Business Plan - Model Details'!J881+'Business Plan - Model Details'!J953+'Business Plan - Model Details'!J562+'Business Plan - Model Details'!J718+'Business Plan - Model Details'!J882+'Business Plan - Model Details'!J954+'Business Plan - Model Details'!J253)/10^6 -> 373.74629 | M85: =-('Business Plan - Model Details'!K555+'Business Plan - Model Details'!K711+'Business Plan - Model Details'!K875+'Business Plan - Model Details'!K558+'Business Plan - Model Details'!K714+'Business Plan - Model Details'!K878+'Business Plan - Model Details'!K950+'Business Plan - Model Details'!K559+'Business Plan - Model Details'!K715+'Business Plan - Model Details'!K879+'Business Plan - Model Details'!K951+'Business Plan - Model Details'!K561+'Business Plan - Model Details'!K717+'Business Plan - Model Details'!K881+'Business Plan - Model Details'!K953+'Business Plan - Model Details'!K562+'Business Plan - Model Details'!K718+'Business Plan - Model Details'!K882+'Business Plan - Model Details'!K954+'Business Plan - Model Details'!K253)/10^6 -> -177.90882 | N85: =-('Business Plan - Model Details'!L555+'Business Plan - Model Details'!L711+'Business Plan - Model Details'!L875+'Business Plan - Model Details'!L558+'Business Plan - Model Details'!L714+'Business Plan - Model Details'!L878+'Business Plan - Model Details'!L950+'Business Plan - Model Details'!L559+'Business Plan - Model Details'!L715+'Business Plan - Model Details'!L879+'Business Plan - Model Details'!L951+'Business Plan - Model Details'!L561+'Business Plan - Model Details'!L717+'Business Plan - Model Details'!L881+'Business Plan - Model Details'!L953+'Business Plan - Model Details'!L562+'Business Plan - Model Details'!L718+'Business Plan - Model Details'!L882+'Business Plan - Model Details'!L954+'Business Plan - Model Details'!L253)/10^6 -> -385.96418 | O85: =-('Business Plan - Model Details'!M555+'Business Plan - Model Details'!M711+'Business Plan - Model Details'!M875+'Business Plan - Model Details'!M558+'Business Plan - Model Details'!M714+'Business Plan - Model Details'!M878+'Business Plan - Model Details'!M950+'Business Plan - Model Details'!M559+'Business Plan - Model Details'!M715+'Business Plan - Model Details'!M879+'Business Plan - Model Details'!M951+'Business Plan - Model Details'!M561+'Business Plan - Model Details'!M717+'Business Plan - Model Details'!M881+'Business Plan - Model Details'!M953+'Business Plan - Model Details'!M562+'Business Plan - Model Details'!M718+'Business Plan - Model Details'!M882+'Business Plan - Model Details'!M954+'Business Plan - Model Details'!M253)/10^6 -> 199.41221 | P85: =-('Business Plan - Model Details'!N555+'Business Plan - Model Details'!N711+'Business Plan - Model Details'!N875+'Business Plan - Model Details'!N558+'Business Plan - Model Details'!N714+'Business Plan - Model Details'!N878+'Business Plan - Model Details'!N950+'Business Plan - Model Details'!N559+'Business Plan - Model Details'!N715+'Business Plan - Model Details'!N879+'Business Plan - Model Details'!N951+'Business Plan - Model Details'!N561+'Business Plan - Model Details'!N717+'Business Plan - Model Details'!N881+'Business Plan - Model Details'!N953+'Business Plan - Model Details'!N562+'Business Plan - Model Details'!N718+'Business Plan - Model Details'!N882+'Business Plan - Model Details'!N954+'Business Plan - Model Details'!N253)/10^6 -> 23.684381 | Q85: =-('Business Plan - Model Details'!O555+'Business Plan - Model Details'!O711+'Business Plan - Model Details'!O875+'Business Plan - Model Details'!O558+'Business Plan - Model Details'!O714+'Business Plan - Model Details'!O878+'Business Plan - Model Details'!O950+'Business Plan - Model Details'!O559+'Business Plan - Model Details'!O715+'Business Plan - Model Details'!O879+'Business Plan - Model Details'!O951+'Business Plan - Model Details'!O561+'Business Plan - Model Details'!O717+'Business Plan - Model Details'!O881+'Business Plan - Model Details'!O953+'Business Plan - Model Details'!O562+'Business Plan - Model Details'!O718+'Business Plan - Model Details'!O882+'Business Plan - Model Details'!O954+'Business Plan - Model Details'!O253)/10^6 -> -9.2197551 | R85: =-('Business Plan - Model Details'!P555+'Business Plan - Model Details'!P711+'Business Plan - Model Details'!P875+'Business Plan - Model Details'!P558+'Business Plan - Model Details'!P714+'Business Plan - Model Details'!P878+'Business Plan - Model Details'!P950+'Business Plan - Model Details'!P559+'Business Plan - Model Details'!P715+'Business Plan - Model Details'!P879+'Business Plan - Model Details'!P951+'Business Plan - Model Details'!P561+'Business Plan - Model Details'!P717+'Business Plan - Model Details'!P881+'Business Plan - Model Details'!P953+'Business Plan - Model Details'!P562+'Business Plan - Model Details'!P718+'Business Plan - Model Details'!P882+'Business Plan - Model Details'!P954+'Business Plan - Model Details'!P253)/10^6 -> -278.68993 | S85: =-('Business Plan - Model Details'!Q555+'Business Plan - Model Details'!Q711+'Business Plan - Model Details'!Q875+'Business Plan - Model Details'!Q558+'Business Plan - Model Details'!Q714+'Business Plan - Model Details'!Q878+'Business Plan - Model Details'!Q950+'Business Plan - Model Details'!Q559+'Business Plan - Model Details'!Q715+'Business Plan - Model Details'!Q879+'Business Plan - Model Details'!Q951+'Business Plan - Model Details'!Q561+'Business Plan - Model Details'!Q717+'Business Plan - Model Details'!Q881+'Business Plan - Model Details'!Q953+'Business Plan - Model Details'!Q562+'Business Plan - Model Details'!Q718+'Business Plan - Model Details'!Q882+'Business Plan - Model Details'!Q954+'Business Plan - Model Details'!Q253)/10^6 -> 478.03093 | ... AI85: =-('Business Plan - Model Details'!AG555+'Business Plan - Model Details'!AG711+'Business Plan - Model Details'!AG875+'Business Plan - Model Details'!AG558+'Business Plan - Model Details'!AG714+'Business Plan - Model Details'!AG878+'Business Plan - Model Details'!AG950+'Business Plan - Model Details'!AG559+'Business Plan - Model Details'!AG715+'Business Plan - Model Details'!AG879+'Business Plan - Model Details'!AG951+'Business Plan - Model Details'!AG561+'Business Plan - Model Details'!AG717+'Business Plan - Model Details'!AG881+'Business Plan - Model Details'!AG953+'Business Plan - Model Details'!AG562+'Business Plan - Model Details'!AG718+'Business Plan - Model Details'!AG882+'Business Plan - Model Details'!AG954+'Business Plan - Model Details'!AG253)/10^6 -> 111.86396
C86: COGS - Others | F86: COGS - Others (sudah termasuk di baris jenis biaya di atas) | L86: 0 | M86: 0 | N86: 0 | O86: 0 | P86: 0 | Q86: 0 | R86: 0 | S86: 0 | T86: 0 | U86: 0 | V86: 0 | W86: 0 | X86: 0 | Y86: 0 | Z86: 0 | AA86: 0 | AB86: 0 | AC86: 0 | AD86: 0 | AE86: 0 | AF86: 0 | AG86: 0 | AH86: 0 | AI86: 0
C87: Cost of revenue - blended | H87: Rp m | I87: =IFERROR((K87-J87)/J87,0) -> 0 | K87: =SUM(L87:W87) -> -84154.697 | L87: =SUM(L66,L68:L71,L73:L82,L84:L86) -> -6667.182 | M87: =SUM(M66,M68:M71,M73:M82,M84:M86) -> -6591.9515 | N87: =SUM(N66,N68:N71,N73:N82,N84:N86) -> -5211.7545 | O87: =SUM(O66,O68:O71,O73:O82,O84:O86) -> -5876.8618 | P87: =SUM(P66,P68:P71,P73:P82,P84:P86) -> -6624.8784 | Q87: =SUM(Q66,Q68:Q71,Q73:Q82,Q84:Q86) -> -7152.2142 | R87: =SUM(R66,R68:R71,R73:R82,R84:R86) -> -7596.8221 | S87: =SUM(S66,S68:S71,S73:S82,S84:S86) -> -7842.1457 | ... AI87: =SUM(AI66,AI68:AI71,AI73:AI82,AI84:AI86) -> -7691.8048
F88: Cek: cost of revenue blended - product level (harus nol) | L88: =L87-L64 -> 0 | M88: =M87-M64 -> 0 | N88: =N87-N64 -> 0 | O88: =O87-O64 -> 0 | P88: =P87-P64 -> 0 | Q88: =Q87-Q64 -> 0 | R88: =R87-R64 -> 0 | S88: =S87-S64 -> 0 | ... AI88: =AI87-AI64 -> 0
C89: Gross profit | H89: Rp m | I89: =IFERROR((K89-J89)/J89,0) -> 0 | K89: =SUM(L89:W89) -> 16902.448 | L89: =L17+L64 -> 2702.2645 | M89: =M17+M64 -> 2067.6192 | N89: =N17+N64 -> 1272.8023 | O89: =O17+O64 -> 973.66688 | P89: =P17+P64 -> 1080.5385 | Q89: =Q17+Q64 -> 1143.0735 | R89: =R17+R64 -> 1317.2588 | S89: =S17+S64 -> 1950.9797 | ... AI89: =AI17+AI64 -> 1054.4781 | AJ89: =SUM(X89:AI89) -> 12601.544
D90: GP Margin | I90: =IFERROR((K90-J90)/J90,0) -> 0 | K90: =K89/K17 -> 0.16725634 | L90: =L89/L17 -> 0.2884124 | M90: =M89/M17 -> 0.23876694 | N90: =N89/N17 -> 0.19628209 | O90: =O89/O17 -> 0.14213018 | P90: =P89/P17 -> 0.14023103 | Q90: =Q89/Q17 -> 0.13779794 | R90: =R89/R17 -> 0.14777281 | ... AI90: =AI89/AI17 -> 0.12056299 | AJ90: =IF(AJ17=0,0,AJ89/AJ17) -> 0.12006571
D91: GP Margin - FCC | I91: =IFERROR((K91-J91)/J91,0) -> 0 | K91: =K90/K18 -> -2.1106598e-06 | L91: =(L10+L18)/L10 -> 0.25213371 | M91: =(M10+M18)/M10 -> 0.2702888 | N91: =(N10+N18)/N10 -> 0.1539272 | O91: =(O10+O18)/O10 -> 0.084975205 | P91: =(P10+P18)/P10 -> 0.13113298 | Q91: =(Q10+Q18)/Q10 -> 0.059257505 | R91: =(R10+R18)/R10 -> 0.13104199 | S91: =(S10+S18)/S10 -> 0.14564048 | ... AI91: =(AI10+AI18)/AI10 -> 0.09102159
D92: GP Margin - UbI Ungu | I92: =IFERROR((K92-J92)/J92,0) -> 0 | K92: =K91/K19 -> #DIV/0! | L92: =(L33+L11)/L11 -> -3.3196043 | M92: =(M33+M11)/M11 -> -329.21166 | N92: =(N33+N11)/N11 -> 0.70329027 | O92: =(O33+O11)/O11 -> 0.073444973 | P92: =(P33+P11)/P11 -> 0.15510365 | Q92: =(Q33+Q11)/Q11 -> 0.16686524 | R92: =(R33+R11)/R11 -> 0.24432581 | S92: =(S33+S11)/S11 -> -0.31243693 | ... AI92: =(AI33+AI11)/AI11 -> 0.27909505
D93: GP Margin | I93: =IFERROR((K93-J93)/J93,0) -> 0 | K93: =K92/K20 -> #DIV/0! | L93: =L92/L20 -> 0.001542133 | M93: =M92/M20 -> 0.16636469 | N93: =N92/N20 -> -0.0004412174 | O93: =O92/O20 -> -4.449049e-05 | P93: =P92/P20 -> -7.6640068e-05 | Q93: =Q92/Q20 -> -7.1372304e-05 | R93: =R92/R20 -> -9.4827264e-05 | ... AI93: =AI92/AI20 -> -9.306812e-05
C94: Selling Expense
D95: Delivery Expenses - SE | H95: Rp m | I95: =IFERROR((K95-J95)/J95,0) -> 0 | K95: =SUM(L95:W95) -> -2130.5376 | L95: =-SUMIFS('PL Actual MTM - Aug 26'!D:D,'PL Actual MTM - Aug 26'!$R:$R,$D95)/10^6 -> -166.6262 | M95: =-SUMIFS('PL Actual MTM - Aug 26'!E:E,'PL Actual MTM - Aug 26'!$R:$R,$D95)/10^6 -> -161.6678 | N95: =-SUMIFS('PL Actual MTM - Aug 26'!F:F,'PL Actual MTM - Aug 26'!$R:$R,$D95)/10^6 -> -131.47968 | O95: =-SUMIFS('PL Actual MTM - Aug 26'!G:G,'PL Actual MTM - Aug 26'!$R:$R,$D95)/10^6 -> -137.7508 | P95: =-SUMIFS('PL Actual MTM - Aug 26'!H:H,'PL Actual MTM - Aug 26'!$R:$R,$D95)/10^6 -> -186.57222 | Q95: =-SUMIFS('PL Actual MTM - Aug 26'!I:I,'PL Actual MTM - Aug 26'!$R:$R,$D95)/10^6 -> -184.9956 | R95: =-SUMIFS('PL Actual MTM - Aug 26'!J:J,'PL Actual MTM - Aug 26'!$R:$R,$D95)/10^6 -> -243.58797 | S95: =-SUMIFS('PL Actual MTM - Aug 26'!K:K,'PL Actual MTM - Aug 26'!$R:$R,$D95)/10^6 -> -220.56534 | T95: =-SUM('Business Plan - Model Details'!R1252,'Business Plan - Model Details'!R1267)/10^6 -> -174.323 | U95: =-SUM('Business Plan - Model Details'!S1252,'Business Plan - Model Details'!S1267)/10^6 -> -174.323 | V95: =-SUM('Business Plan - Model Details'!T1252,'Business Plan - Model Details'!T1267)/10^6 -> -174.323 | W95: =-SUM('Business Plan - Model Details'!U1252,'Business Plan - Model Details'!U1267)/10^6 -> -174.323 | X95: =-SUM('Business Plan - Model Details'!V1252,'Business Plan - Model Details'!V1267)/10^6 -> -174.323 | Y95: =-SUM('Business Plan - Model Details'!W1252,'Business Plan - Model Details'!W1267)/10^6 -> -174.323 | Z95: =-SUM('Business Plan - Model Details'!X1252,'Business Plan - Model Details'!X1267)/10^6 -> -174.323 | AA95: =-SUM('Business Plan - Model Details'!Y1252,'Business Plan - Model Details'!Y1267)/10^6 -> -174.323 | ... AI95: =-SUM('Business Plan - Model Details'!AG1252,'Business Plan - Model Details'!AG1267)/10^6 -> -174.323 | AJ95: =SUM(X95:AI95) -> -2091.876
D96: Commission Expenses | H96: Rp m | I96: =IFERROR((K96-J96)/J96,0) -> 0 | K96: =SUM(L96:W96) -> -101 | L96: =-SUMIFS('PL Actual MTM - Aug 26'!D:D,'PL Actual MTM - Aug 26'!$R:$R,$D96)/10^6 -> -1 | M96: =-SUMIFS('PL Actual MTM - Aug 26'!E:E,'PL Actual MTM - Aug 26'!$R:$R,$D96)/10^6 -> 0 | N96: =-SUMIFS('PL Actual MTM - Aug 26'!F:F,'PL Actual MTM - Aug 26'!$R:$R,$D96)/10^6 -> 0 | O96: =-SUMIFS('PL Actual MTM - Aug 26'!G:G,'PL Actual MTM - Aug 26'!$R:$R,$D96)/10^6 -> 0 | P96: =-SUMIFS('PL Actual MTM - Aug 26'!H:H,'PL Actual MTM - Aug 26'!$R:$R,$D96)/10^6 -> -100 | Q96: =-SUMIFS('PL Actual MTM - Aug 26'!I:I,'PL Actual MTM - Aug 26'!$R:$R,$D96)/10^6 -> 0 | R96: =-SUMIFS('PL Actual MTM - Aug 26'!J:J,'PL Actual MTM - Aug 26'!$R:$R,$D96)/10^6 -> 0 | S96: =-SUMIFS('PL Actual MTM - Aug 26'!K:K,'PL Actual MTM - Aug 26'!$R:$R,$D96)/10^6 -> 0 | T96: 0 | U96: 0 | V96: 0 | W96: 0 | X96: 0 | Y96: 0 | Z96: 0 | AA96: 0 | AB96: 0 | AC96: 0 | AD96: 0 | AE96: 0 | AF96: 0 | AG96: 0 | AH96: 0 | AI96: 0 | AJ96: =SUM(X96:AI96) -> 0
D97: Other selling Expense | H97: Rp m | I97: =IFERROR((K97-J97)/J97,0) -> 0 | K97: =SUM(L97:W97) -> -5.4303134 | L97: =-SUMIFS('PL Actual MTM - Aug 26'!D:D,'PL Actual MTM - Aug 26'!$R:$R,$D97)/10^6 -> -1.3701444 | M97: =-SUMIFS('PL Actual MTM - Aug 26'!E:E,'PL Actual MTM - Aug 26'!$R:$R,$D97)/10^6 -> 0 | N97: =-SUMIFS('PL Actual MTM - Aug 26'!F:F,'PL Actual MTM - Aug 26'!$R:$R,$D97)/10^6 -> 0 | O97: =-SUMIFS('PL Actual MTM - Aug 26'!G:G,'PL Actual MTM - Aug 26'!$R:$R,$D97)/10^6 -> 0 | P97: =-SUMIFS('PL Actual MTM - Aug 26'!H:H,'PL Actual MTM - Aug 26'!$R:$R,$D97)/10^6 -> 0 | Q97: =-SUMIFS('PL Actual MTM - Aug 26'!I:I,'PL Actual MTM - Aug 26'!$R:$R,$D97)/10^6 -> -1.25419 | R97: =-SUMIFS('PL Actual MTM - Aug 26'!J:J,'PL Actual MTM - Aug 26'!$R:$R,$D97)/10^6 -> 0 | S97: =-SUMIFS('PL Actual MTM - Aug 26'!K:K,'PL Actual MTM - Aug 26'!$R:$R,$D97)/10^6 -> -1.001459 | T97: -0.45113 | U97: -0.45113 | V97: -0.45113 | W97: -0.45113 | X97: -0.45113 | Y97: -0.45113 | Z97: -0.45113 | AA97: -0.45113 | AB97: -0.45113 | AC97: -0.45113 | AD97: -0.45113 | AE97: -0.45113 | AF97: -0.45113 | AG97: -0.45113 | AH97: -0.45113 | AI97: -0.45113 | AJ97: =SUM(X97:AI97) -> -5.41356
C98: General and Administrative Expenses | T98: 0 | U98: 0 | V98: 0 | W98: 0 | X98: 0 | Y98: 0 | Z98: 0 | AA98: 0 | AB98: 0 | AC98: 0 | AD98: 0 | AE98: 0 | AF98: 0 | AG98: 0 | AH98: 0 | AI98: 0
D99: Salaries and allowance | H99: Rp m | I99: =IFERROR((K99-J99)/J99,0) -> 0 | K99: =SUM(L99:W99) -> -3903.8727 | L99: =-SUMIFS('PL Actual MTM - Aug 26'!D:D,'PL Actual MTM - Aug 26'!$R:$R,$D99)/10^6 -> -429.984 | M99: =-SUMIFS('PL Actual MTM - Aug 26'!E:E,'PL Actual MTM - Aug 26'!$R:$R,$D99)/10^6 -> -471.07126 | N99: =-SUMIFS('PL Actual MTM - Aug 26'!F:F,'PL Actual MTM - Aug 26'!$R:$R,$D99)/10^6 -> -1265.0359 | O99: =-SUMIFS('PL Actual MTM - Aug 26'!G:G,'PL Actual MTM - Aug 26'!$R:$R,$D99)/10^6 -> -189.15595 | P99: =-SUMIFS('PL Actual MTM - Aug 26'!H:H,'PL Actual MTM - Aug 26'!$R:$R,$D99)/10^6 -> -230.13584 | Q99: =-SUMIFS('PL Actual MTM - Aug 26'!I:I,'PL Actual MTM - Aug 26'!$R:$R,$D99)/10^6 -> -171.35061 | R99: =-SUMIFS('PL Actual MTM - Aug 26'!J:J,'PL Actual MTM - Aug 26'!$R:$R,$D99)/10^6 -> -167.72026 | S99: =-SUMIFS('PL Actual MTM - Aug 26'!K:K,'PL Actual MTM - Aug 26'!$R:$R,$D99)/10^6 -> -296.68144 | T99: =-'Business Plan - Model Details'!R1279/10^6 -> -170.68436 | U99: =-'Business Plan - Model Details'!S1279/10^6 -> -170.68436 | V99: =-'Business Plan - Model Details'!T1279/10^6 -> -170.68436 | W99: =-'Business Plan - Model Details'!U1279/10^6 -> -170.68436 | X99: =-'Business Plan - Model Details'!V1279/10^6 -> -170.68436 | Y99: =-'Business Plan - Model Details'!W1279/10^6 -> -170.68436 | Z99: =-'Business Plan - Model Details'!X1279/10^6 -> -170.68436 | AA99: =-'Business Plan - Model Details'!Y1279/10^6 -> -170.68436 | ... AI99: =-'Business Plan - Model Details'!AG1279/10^6 -> -170.68436 | AJ99: =SUM(X99:AI99) -> -2048.2123
D100: Delivery Expenses | H100: Rp m | I100: =IFERROR((K100-J100)/J100,0) -> 0 | K100: =SUM(L100:W100) -> -613.03875 | L100: =-SUMIFS('PL Actual MTM - Aug 26'!D:D,'PL Actual MTM - Aug 26'!$R:$R,$D100)/10^6 -> -43.526 | M100: =-SUMIFS('PL Actual MTM - Aug 26'!E:E,'PL Actual MTM - Aug 26'!$R:$R,$D100)/10^6 -> -51.066222 | N100: =-SUMIFS('PL Actual MTM - Aug 26'!F:F,'PL Actual MTM - Aug 26'!$R:$R,$D100)/10^6 -> -44.159822 | O100: =-SUMIFS('PL Actual MTM - Aug 26'!G:G,'PL Actual MTM - Aug 26'!$R:$R,$D100)/10^6 -> -50.5954 | P100: =-SUMIFS('PL Actual MTM - Aug 26'!H:H,'PL Actual MTM - Aug 26'!$R:$R,$D100)/10^6 -> -54.418356 | Q100: =-SUMIFS('PL Actual MTM - Aug 26'!I:I,'PL Actual MTM - Aug 26'!$R:$R,$D100)/10^6 -> -56.9376 | R100: =-SUMIFS('PL Actual MTM - Aug 26'!J:J,'PL Actual MTM - Aug 26'!$R:$R,$D100)/10^6 -> -46.875 | S100: =-SUMIFS('PL Actual MTM - Aug 26'!K:K,'PL Actual MTM - Aug 26'!$R:$R,$D100)/10^6 -> -55.058 | T100: =AVERAGE(Q100:S100) -> -52.956867 | U100: =AVERAGE(R100:T100) -> -51.629956 | V100: =AVERAGE(S100:U100) -> -53.214941 | W100: =AVERAGE(T100:V100) -> -52.600588 | X100: =AVERAGE(U100:W100) -> -52.481828 | Y100: =AVERAGE(V100:X100) -> -52.765785 | Z100: =AVERAGE(W100:Y100) -> -52.616067 | AA100: =AVERAGE(X100:Z100) -> -52.621227 | ... AI100: =AVERAGE(AF100:AH100) -> -52.643116 | AJ100: =SUM(X100:AI100) -> -631.64936
...

Sheet Business Plan - Model Details
A1: PT Boga Makmur Gracia
A2: Business Plan
A3: Oct 2026 to Dec 2027 | J3: Actual | K3: Actual | L3: Actual | M3: Actual | N3: Actual | O3: Actual | P3: Actual | Q3: Actual
I4: Unit | J4: 46053 | K4: =EOMONTH(J4,1) -> 46081 | L4: =EOMONTH(K4,1) -> 46112 | M4: =EOMONTH(L4,1) -> 46142 | N4: =EOMONTH(M4,1) -> 46173 | O4: =EOMONTH(N4,1) -> 46203 | P4: =EOMONTH(O4,1) -> 46234 | Q4: =EOMONTH(P4,1) -> 46265 | R4: =EOMONTH(Q4,1) -> 46295 | ... AG4: =EOMONTH(AF4,1) -> 46752
A6: 1 | B6: General assumptions
B8: 1.1 | C8: Macroeconomics
C9: Inflation rate | I9: % yoy | R9: 0 | S9: 0 | T9: 0 | U9: 0 | V9: 0 | W9: 0 | X9: 0 | Y9: 0 | Z9: 0 | AA9: 0 | AB9: 0 | AC9: 0 | AD9: 0 | AE9: 0 | AF9: 0 | AG9: 0
C10: Index | I10: x | R10: =(1+R9)^(1/12) -> 1 | S10: =R10*(1+S9)^(1/12) -> 1 | T10: =S10*(1+T9)^(1/12) -> 1 | U10: =T10*(1+U9)^(1/12) -> 1 | V10: =U10*(1+V9)^(1/12) -> 1 | W10: =V10*(1+W9)^(1/12) -> 1 | X10: =W10*(1+X9)^(1/12) -> 1 | Y10: =X10*(1+Y9)^(1/12) -> 1 | Z10: =Y10*(1+Z9)^(1/12) -> 1 | ... AG10: =AF10*(1+AG9)^(1/12) -> 1
C11: Minimum Wage adjustment | I11: % yoy | R11: 0 | S11: 0 | T11: 0 | U11: 0 | V11: 0 | W11: 0 | X11: 0 | Y11: 0 | Z11: 0 | AA11: 0 | AB11: 0 | AC11: 0 | AD11: 0 | AE11: 0 | AF11: 0 | AG11: 0
C12: Combined wage adjustment | D12: Indeks upah (kumulatif dari Minimum Wage adjustment, basis Agu-26 = 1) | I12: x | R12: =(1+R11)^(1/12) -> 1 | S12: =R12*(1+S11)^(1/12) -> 1 | T12: =S12*(1+T11)^(1/12) -> 1 | U12: =T12*(1+U11)^(1/12) -> 1 | V12: =U12*(1+V11)^(1/12) -> 1 | W12: =V12*(1+W11)^(1/12) -> 1 | X12: =W12*(1+X11)^(1/12) -> 1 | Y12: =X12*(1+Y11)^(1/12) -> 1 | Z12: =Y12*(1+Z11)^(1/12) -> 1 | ... AG12: =AF12*(1+AG11)^(1/12) -> 1
C13: IDR to USD | I13: IDR | J13: 16786 | K13: 16758 | L13: 16993 | M13: 17324 | N13: 17789 | O13: 17856 | P13: 18078 | Q13: 17703 | R13: ='Input Operasional'!Q156 -> 18000 | S13: ='Input Operasional'!R156 -> 18000 | T13: ='Input Operasional'!S156 -> 18000 | U13: ='Input Operasional'!T156 -> 18000 | V13: ='Input Operasional'!U156 -> 18000 | W13: ='Input Operasional'!V156 -> 18000 | X13: ='Input Operasional'!W156 -> 18000 | Y13: ='Input Operasional'!X156 -> 18000 | ... AG13: ='Input Operasional'!AF156 -> 18000
B15: 1.2 | C15: Growth Assumption
C16: Revenue growth target | I16: % yoy | AC16: 0.045 | AD16: 0.045 | AE16: 0.045 | AF16: 0.045 | AG16: 0.045
C17: Period x | I17: x year | AC17: 1 | AD17: 1 | AE17: 1 | AF17: 1 | AG17: 1
C18: Period cashflow (half period) | I18: x year | AC18: 2.5 | AD18: 3.5 | AE18: 4.5 | AF18: 5.5 | AG18: 6.5
C19: Month in period | I19: x month | AC19: 12 | AD19: 12 | AE19: 12 | AF19: 12 | AG19: 12
A21: 2 | B21: Operational assumptions
B23: 2.1 | C23: Operational Days
C24: Total Days | I24: Days | J24: =DAY(J4) -> 31 | K24: =DAY(K4) -> 28 | L24: =DAY(L4) -> 31 | M24: =DAY(M4) -> 30 | N24: =DAY(N4) -> 31 | O24: =DAY(O4) -> 30 | P24: =DAY(P4) -> 31 | Q24: =DAY(Q4) -> 31 | ... AG24: =DAY(AG4) -> 31
C25: Holidays | I25: Days | J25: 4 | K25: 4 | L25: 4 | M25: 4 | N25: 4 | O25: 4 | P25: 4 | Q25: 4 | R25: ='Input Operasional'!Q157 -> 4 | S25: ='Input Operasional'!R157 -> 4 | T25: ='Input Operasional'!S157 -> 4 | U25: ='Input Operasional'!T157 -> 4 | V25: ='Input Operasional'!U157 -> 4 | W25: ='Input Operasional'!V157 -> 4 | X25: ='Input Operasional'!W157 -> 4 | Y25: ='Input Operasional'!X157 -> 4 | ... AG25: ='Input Operasional'!AF157 -> 4
C26: Production Days | I26: Days | J26: =J24-J25 -> 27 | K26: =K24-K25 -> 24 | L26: =L24-L25 -> 27 | M26: =M24-M25 -> 26 | N26: =N24-N25 -> 27 | O26: =O24-O25 -> 26 | P26: =P24-P25 -> 27 | Q26: =Q24-Q25 -> 27 | ... AG26: =AG24-AG25 -> 27
B28: 2.2 | C28: Production Capacity/Days
C29: Washing | I29: KG - Wet | J29: 48000 | K29: 48000 | L29: 48000 | M29: 48000 | N29: 48000 | O29: 48000 | P29: 48000 | Q29: 48000 | R29: ='Input Operasional'!Q158 -> 48000 | S29: ='Input Operasional'!R158 -> 48000 | T29: ='Input Operasional'!S158 -> 48000 | U29: ='Input Operasional'!T158 -> 48000 | V29: ='Input Operasional'!U158 -> 48000 | W29: ='Input Operasional'!V158 -> 48000 | X29: ='Input Operasional'!W158 -> 48000 | Y29: ='Input Operasional'!X158 -> 48000 | ... AG29: ='Input Operasional'!AF158 -> 48000
C30: Slicing | I30: KG - Wet | J30: =J29 -> 48000 | K30: =K29 -> 48000 | L30: =L29 -> 48000 | M30: =M29 -> 48000 | N30: =N29 -> 48000 | O30: =O29 -> 48000 | P30: =P29 -> 48000 | Q30: =Q29 -> 48000 | ... AG30: =AG29 -> 48000
C31: Fyring | I31: KG - Dry | J31: =J30/3.33 -> 14414.414 | K31: =K30/3.33 -> 14414.414 | L31: =L30/3.33 -> 14414.414 | M31: =M30/3.33 -> 14414.414 | N31: =N30/3.33 -> 14414.414 | O31: =O30/3.33 -> 14414.414 | P31: =P30/3.33 -> 14414.414 | Q31: =Q30/3.33 -> 14414.414 | ... AG31: =AG30/3.33 -> 14414.414
B33: 2.4 | C33: Production Capacity/Month
C34: Washing | I34: Ton - Wet | J34: =J26*J29/10^3 -> 1296 | K34: =K36*3.3 -> 1141.6216 | L34: =L36*3.3 -> 1284.3243 | M34: =M36*3.3 -> 1236.7568 | N34: =N36*3.3 -> 1284.3243 | O34: =O36*3.3 -> 1236.7568 | P34: =P36*3.3 -> 1284.3243 | Q34: =Q36*3.3 -> 1284.3243 | R34: =R36*3.3 -> 1236.7568 | ... AG34: =AG36*3.3 -> 1284.3243
C35: Slicing | I35: Ton - Wet | J35: =J26*J30/10^3 -> 1296 | K35: =K34 -> 1141.6216 | L35: =L34 -> 1284.3243 | M35: =M34 -> 1236.7568 | N35: =N34 -> 1284.3243 | O35: =O34 -> 1236.7568 | P35: =P34 -> 1284.3243 | Q35: =Q34 -> 1284.3243 | R35: =R34 -> 1236.7568 | ... AG35: =AG34 -> 1284.3243
C36: Fyring | I36: Ton - Dry | J36: =J26*J31/10^3 -> 389.18919 | K36: =K26*K31/10^3 -> 345.94595 | L36: =L26*L31/10^3 -> 389.18919 | M36: =M26*M31/10^3 -> 374.77477 | N36: =N26*N31/10^3 -> 389.18919 | O36: =O26*O31/10^3 -> 374.77477 | P36: =P26*P31/10^3 -> 389.18919 | Q36: =Q26*Q31/10^3 -> 389.18919 | ... AG36: =AG26*AG31/10^3 -> 389.18919
B38: 2.4 | C38: Personal
C39: Washing | I39: People
C40: Slicing | I40: People
C41: Fyring | I41: People
B42: 2.5 | C42: Working Hours Mesin & Kapasitas dari Jam Operasi
C43: Jam operasi - Washing | I43: jam | J43: ='Data Aktual'!K43 -> 680 | K43: ='Data Aktual'!L43 -> 656 | L43: ='Data Aktual'!M43 -> 512 | M43: ='Data Aktual'!N43 -> 512 | N43: ='Data Aktual'!O43 -> 688 | O43: ='Data Aktual'!P43 -> 688 | P43: ='Data Aktual'!Q43 -> 688 | Q43: ='Data Aktual'!R43 -> 696 | R43: 632.5 | S43: 632.5 | T43: 632.5 | U43: 632.5 | V43: 632.5 | W43: 632.5 | X43: 632.5 | Y43: 632.5 | Z43: 632.5 | AA43: 632.5 | AB43: 632.5 | AC43: 632.5 | AD43: 632.5 | AE43: 632.5 | AF43: 632.5 | AG43: 632.5
C44: Jam operasi - Slicing | I44: jam | J44: ='Data Aktual'!K43 -> 680 | K44: ='Data Aktual'!L43 -> 656 | L44: ='Data Aktual'!M43 -> 512 | M44: ='Data Aktual'!N43 -> 512 | N44: ='Data Aktual'!O43 -> 688 | O44: ='Data Aktual'!P43 -> 688 | P44: ='Data Aktual'!Q43 -> 688 | Q44: ='Data Aktual'!R43 -> 696 | R44: 632.5 | S44: 632.5 | T44: 632.5 | U44: 632.5 | V44: 632.5 | W44: 632.5 | X44: 632.5 | Y44: 632.5 | Z44: 632.5 | AA44: 632.5 | AB44: 632.5 | AC44: 632.5 | AD44: 632.5 | AE44: 632.5 | AF44: 632.5 | AG44: 632.5
C45: Jam operasi - Frying (tahap penentu) | I45: jam | J45: ='Data Aktual'!K43 -> 680 | K45: ='Data Aktual'!L43 -> 656 | L45: ='Data Aktual'!M43 -> 512 | M45: ='Data Aktual'!N43 -> 512 | N45: ='Data Aktual'!O43 -> 688 | O45: ='Data Aktual'!P43 -> 688 | P45: ='Data Aktual'!Q43 -> 688 | Q45: ='Data Aktual'!R43 -> 696 | R45: 632.5 | S45: 632.5 | T45: 632.5 | U45: 632.5 | V45: 632.5 | W45: 632.5 | X45: 632.5 | Y45: 632.5 | Z45: 632.5 | AA45: 632.5 | AB45: 632.5 | AC45: 632.5 | AD45: 632.5 | AE45: 632.5 | AF45: 632.5 | AG45: 632.5
C46: Kapasitas per jam - Frying (kapasitas/hari baris 31 / jam operasi per hari) | I46: KG - Dry/jam | J46: 600.6006 | K46: 600.6006 | L46: 600.6006 | M46: 600.6006 | N46: 600.6006 | O46: 600.6006 | P46: 600.6006 | Q46: 600.6006 | R46: 600.6006 | S46: 600.6006 | T46: 600.6006 | U46: 600.6006 | V46: 600.6006 | W46: 600.6006 | X46: 600.6006 | Y46: 600.6006 | Z46: 600.6006 | AA46: 600.6006 | AB46: 600.6006 | AC46: 600.6006 | AD46: 600.6006 | AE46: 600.6006 | AF46: 600.6006 | AG46: 600.6006
C47: Kapasitas dari working hours - Frying (jam x kapasitas/jam) | I47: KG - Dry | J47: =J45*J46 -> 408408.41 | K47: =K45*K46 -> 393993.99 | L47: =L45*L46 -> 307507.51 | M47: =M45*M46 -> 307507.51 | N47: =N45*N46 -> 413213.21 | O47: =O45*O46 -> 413213.21 | P47: =P45*P46 -> 413213.21 | Q47: =Q45*Q46 -> 418018.02 | ... AG47: =AG45*AG46 -> 379879.88
C48: Total target volume produksi - 4 blok produk | I48: KG | J48: =J421+J582+J741+J892 -> 350705.13 | K48: =K421+K582+K741+K892 -> 343801.8 | L48: =L421+L582+L741+L892 -> 249392.6 | M48: =M421+M582+M741+M892 -> 259914.75 | N48: =N421+N582+N741+N892 -> 286092.5 | O48: =O421+O582+O741+O892 -> 309896.6 | P48: =P421+P582+P741+P892 -> 310829 | Q48: =Q421+Q582+Q741+Q892 -> 361606.5 | R48: =R421+R581+R741+R892 -> 305038.94 | S48: =S421+S581+S741+S892 -> 305544.12 | T48: =T421+T581+T741+T892 -> 304923.59 | U48: =U421+U581+U741+U892 -> 305168.64 | V48: =V421+V581+V741+V892 -> 305211.9 | W48: =W421+W581+W741+W892 -> 305101.32 | X48: =X421+X581+X741+X892 -> 305160.61 | Y48: =Y421+Y581+Y741+Y892 -> 305157.94 | ... AG48: =AG421+AG581+AG741+AG892 -> 305149.58
C49: Utilisasi working hours (target / kapasitas dari jam) | I49: % | J49: =IF(J47=0,0,J48/J47) -> 0.85871183 | K49: =IF(K47=0,0,K48/K47) -> 0.8726067 | L49: =IF(L47=0,0,L48/L47) -> 0.81101304 | M49: =IF(M47=0,0,M48/M47) -> 0.84523058 | N49: =IF(N47=0,0,N48/N47) -> 0.69236048 | O49: =IF(O47=0,0,O48/O47) -> 0.74996779 | P49: =IF(P47=0,0,P48/P47) -> 0.75222425 | Q49: =IF(Q47=0,0,Q48/Q47) -> 0.86505003 | ... AG49: =IF(AG47=0,0,AG48/AG47) -> 0.80327914
C50: Cek kapasitas: kapasitas - target (negatif = target melebihi kapasitas jam) | I50: KG - Dry | J50: =J47-J48 -> 57703.278 | K50: =K47-K48 -> 50192.194 | L50: =L47-L48 -> 58114.908 | M50: =M47-M48 -> 47592.758 | N50: =N47-N48 -> 127120.71 | O50: =O47-O48 -> 103316.61 | P50: =P47-P48 -> 102384.21 | Q50: =Q47-Q48 -> 56411.518 | ... AG50: =AG47-AG48 -> 74730.295
A52: 3 | B52: Revenue
C54: 3.1 Volume Penjualan | I54: KG
D55: IFM - FCC | I55: KG | J55: ='Input Operasional'!I9 -> 337068.5 | K55: ='Input Operasional'!J9 -> 319330 | L55: ='Input Operasional'!K9 -> 227535.88 | M55: ='Input Operasional'!L9 -> 226963 | N55: ='Input Operasional'!M9 -> 263224.5 | O55: ='Input Operasional'!N9 -> 255491.5 | P55: ='Input Operasional'!O9 -> 277436.5 | Q55: ='Input Operasional'!P9 -> 301075.5 | ... AG55: ='Input Operasional'!AF9 -> 278373.52
D56: IFM - Ubi Ungu | I56: KG | J56: ='Input Operasional'!I10 -> 676.5 | K56: ='Input Operasional'!J10 -> 5.5 | L56: ='Input Operasional'!K10 -> 3112.9 | M56: ='Input Operasional'!L10 -> 5643 | N56: ='Input Operasional'!M10 -> 4986 | O56: ='Input Operasional'!N10 -> 14107.5 | P56: ='Input Operasional'!O10 -> 8871.5 | Q56: ='Input Operasional'!P10 -> 7210.5 | ... AG56: ='Input Operasional'!AF10 -> 6388
D57: IFM - Ubi Orange | I57: KG | J57: ='Input Operasional'!I11 -> 473 | K57: ='Input Operasional'!J11 -> 10.4 | L57: ='Input Operasional'!K11 -> 3151.5 | M57: ='Input Operasional'!L11 -> 5511.5 | N57: ='Input Operasional'!M11 -> 5335 | O57: ='Input Operasional'!N11 -> 13651 | P57: ='Input Operasional'!O11 -> 8448 | Q57: ='Input Operasional'!P11 -> 7403 | ... AG57: ='Input Operasional'!AF11 -> 5564.425
D58: IFM - total | I58: KG | J58: =SUM(J55:J57) -> 338218 | K58: =SUM(K55:K57) -> 319345.9 | L58: =SUM(L55:L57) -> 233800.28 | M58: =SUM(M55:M57) -> 238117.5 | N58: =SUM(N55:N57) -> 273545.5 | O58: =SUM(O55:O57) -> 283250 | P58: =SUM(P55:P57) -> 294756 | Q58: =SUM(Q55:Q57) -> 315689 | ... AG58: =SUM(AG55:AG57) -> 290325.94
D59: Ekspor & Singkong Fresh | I59: KG
D60: Other (MBS, Nutrifood, Koperasi, Lembutan) | I60: KG | M60: 459.9 | N60: 0 | O60: 0 | P60: 571.5 | Q60: 0 | R60: 0 | S60: 0 | T60: 0 | U60: 0 | V60: 0 | W60: 0 | X60: 0 | Y60: 0 | Z60: 0 | AA60: 0 | AB60: 0 | AC60: 0 | AD60: 0 | AE60: 0 | AF60: 0 | AG60: 0
D61: Total volume penjualan | I61: KG | J61: =J58+J59+J60 -> 338218 | K61: =K58+K59+K60 -> 319345.9 | L61: =L58+L59+L60 -> 233800.28 | M61: =M58+M59+M60 -> 238577.4 | N61: =N58+N59+N60 -> 273545.5 | O61: =O58+O59+O60 -> 283250 | P61: =P58+P59+P60 -> 295327.5 | Q61: =Q58+Q59+Q60 -> 315689 | ... AG61: =AG58+AG59+AG60 -> 290325.94
D62: IFM Semarang - Volume Proportion | I62: % | J62: 0.70371 | K62: 0.651636 | L62: 0.595357 | M62: 0.52479 | N62: 0.463737 | O62: 0.545476 | P62: 0.45255 | Q62: 0.541642 | R62: ='Input Operasional'!Q14 -> 0.5 | S62: ='Input Operasional'!R14 -> 0.5 | T62: ='Input Operasional'!S14 -> 0.5 | U62: ='Input Operasional'!T14 -> 0.5 | V62: ='Input Operasional'!U14 -> 0.5 | W62: ='Input Operasional'!V14 -> 0.5 | X62: ='Input Operasional'!W14 -> 0.5 | Y62: ='Input Operasional'!X14 -> 0.5 | ... AG62: ='Input Operasional'!AF14 -> 0.5
D63: IFM Tanggerang - Volume Proportion | I63: % | J63: 0.296271 | K63: 0.348364 | L63: 0.404591 | M63: 0.475161 | N63: 0.536263 | O63: 0.454524 | P63: 0.54745 | Q63: 0.458322 | R63: ='Input Operasional'!Q15 -> 0.5 | S63: ='Input Operasional'!R15 -> 0.5 | T63: ='Input Operasional'!S15 -> 0.5 | U63: ='Input Operasional'!T15 -> 0.5 | V63: ='Input Operasional'!U15 -> 0.5 | W63: ='Input Operasional'!V15 -> 0.5 | X63: ='Input Operasional'!W15 -> 0.5 | Y63: ='Input Operasional'!X15 -> 0.5 | ... AG63: ='Input Operasional'!AF15 -> 0.5
C64: 3.2 Harga Rata-rata
D65: IFM Semarang - FCC | I65: IDR/KG | R65: ='Input Operasional'!Q17 -> 28100 | S65: ='Input Operasional'!R17 -> 28100 | T65: ='Input Operasional'!S17 -> 28100 | U65: ='Input Operasional'!T17 -> 28100 | V65: ='Input Operasional'!U17 -> 28100 | W65: ='Input Operasional'!V17 -> 28100 | X65: ='Input Operasional'!W17 -> 28100 | Y65: ='Input Operasional'!X17 -> 28100 | ... AG65: ='Input Operasional'!AF17 -> 28100
D66: IFM Tanggerang - FCC | I66: IDR/KG | R66: ='Input Operasional'!Q18 -> 29100 | S66: ='Input Operasional'!R18 -> 29100 | T66: ='Input Operasional'!S18 -> 29100 | U66: ='Input Operasional'!T18 -> 29100 | V66: ='Input Operasional'!U18 -> 29100 | W66: ='Input Operasional'!V18 -> 29100 | X66: ='Input Operasional'!W18 -> 29100 | Y66: ='Input Operasional'!X18 -> 29100 | ... AG66: ='Input Operasional'!AF18 -> 29100
D67: IFM Blended - FCC | I67: IDR/KG | J67: =IF(J55=0,0,J76/J55) -> 26363.333 | K67: =IF(K55=0,0,K76/K55) -> 26448.364 | L67: =IF(L55=0,0,L76/L55) -> 26504.734 | M67: =IF(M55=0,0,M76/M55) -> 26575.293 | N67: =IF(N55=0,0,N76/N55) -> 26636.263 | O67: =IF(O55=0,0,O76/O55) -> 26554.524 | P67: =IF(P55=0,0,P76/P55) -> 27846.189 | Q67: =IF(Q55=0,0,Q76/Q55) -> 28558.391 | R67: =SUM(R65*R62*R61,R66*R61*R63)/R61 -> 28600 | S67: =SUM(S65*S62*S61,S66*S61*S63)/S61 -> 28600 | T67: =SUM(T65*T62*T61,T66*T61*T63)/T61 -> 28600 | U67: =SUM(U65*U62*U61,U66*U61*U63)/U61 -> 28600 | V67: =SUM(V65*V62*V61,V66*V61*V63)/V61 -> 28600 | W67: =SUM(W65*W62*W61,W66*W61*W63)/W61 -> 28600 | X67: =SUM(X65*X62*X61,X66*X61*X63)/X61 -> 28600 | Y67: =SUM(Y65*Y62*Y61,Y66*Y61*Y63)/Y61 -> 28600 | ... AG67: =SUM(AG65*AG62*AG61,AG66*AG61*AG63)/AG61 -> 28600
D68: IFM - Ubi Ungu | I68: IDR/KG | J68: ='Input Operasional'!I19 -> 25039.27 | K68: ='Input Operasional'!J19 -> 25738.158 | L68: ='Input Operasional'!K19 -> 26986.193 | M68: ='Input Operasional'!L19 -> 26799.014 | N68: ='Input Operasional'!M19 -> 27733.316 | O68: ='Input Operasional'!N19 -> 27716.847 | P68: ='Input Operasional'!O19 -> 29478.02 | Q68: ='Input Operasional'!P19 -> 27452.39 | ... AG68: ='Input Operasional'!AF19 -> 48449.566
D69: IFM - Ubi Orange | I69: IDR/KG | J69: ='Input Operasional'!I20 -> 25039.27 | K69: ='Input Operasional'!J20 -> 25738.158 | L69: ='Input Operasional'!K20 -> 26986.193 | M69: ='Input Operasional'!L20 -> 26799.014 | N69: ='Input Operasional'!M20 -> 27733.316 | O69: ='Input Operasional'!N20 -> 27716.847 | P69: ='Input Operasional'!O20 -> 29478.02 | Q69: ='Input Operasional'!P20 -> 27452.39 | ... AG69: ='Input Operasional'!AF20 -> 47969.59
D70: IFM - rata-rata | I70: IDR/KG | J70: =IF(J58=0,0,J80/J58) -> 26431.062 | K70: =IF(K58=0,0,K80/K58) -> 26437.123 | L70: =IF(L58=0,0,L80/L58) -> 27340.421 | M70: =IF(M58=0,0,M80/M58) -> 27578.194 | N70: =IF(N58=0,0,N80/N58) -> 27449.49 | O70: =IF(O58=0,0,O80/O58) -> 28666.128 | P70: =IF(P58=0,0,P80/P58) -> 29042.585 | Q70: =IF(Q58=0,0,Q80/Q58) -> 29466.389 | ... AG70: =IF(AG58=0,0,AG80/AG58) -> 29407.987
D71: Ekspor & Singkong Fresh | I71: IDR/KG | J71: =IF(J59=0,0,J81/J59) -> 0 | K71: =IF(K59=0,0,K81/K59) -> 0 | L71: =IF(L59=0,0,L81/L59) -> 0 | M71: =IF(M59=0,0,M81/M59) -> 0 | N71: =IF(N59=0,0,N81/N59) -> 0 | O71: =IF(O59=0,0,O81/O59) -> 0 | P71: =IF(P59=0,0,P81/P59) -> 0 | Q71: =IF(Q59=0,0,Q81/Q59) -> 0 | ... AG71: =IF(AG59=0,0,AG81/AG59) -> 0
D72: Other | I72: IDR/KG | J72: =IF(J60=0,0,J83/J60) -> 0 | K72: =IF(K60=0,0,K83/K60) -> 0 | L72: =IF(L60=0,0,L83/L60) -> 0 | M72: =IF(M60=0,0,M83/M60) -> 616825.67 | N72: =IF(N60=0,0,N83/N60) -> 0 | O72: =IF(O60=0,0,O83/O60) -> 0 | P72: =IF(P60=0,0,P83/P60) -> 618730.98 | Q72: =IF(Q60=0,0,Q83/Q60) -> 0 | ... AG72: =IF(AG60=0,0,AG83/AG60) -> 0
C73: 3.3 Revenue
D74: IFM Semarang - FCC | I74: IDR Mil | R74: =R55*R62*R65 -> 3.9111479e+09 | S74: =S55*S62*S65 -> 3.9111479e+09 | T74: =T55*T62*T65 -> 3.9111479e+09 | U74: =U55*U62*U65 -> 3.9111479e+09 | V74: =V55*V62*V65 -> 3.9111479e+09 | W74: =W55*W62*W65 -> 3.9111479e+09 | X74: =X55*X62*X65 -> 3.9111479e+09 | Y74: =Y55*Y62*Y65 -> 3.9111479e+09 | ... AG74: =AG55*AG62*AG65 -> 3.9111479e+09
D75: IFM Tanggerang - FCC | I75: IDR Mil | R75: =R55*R63*R66 -> 4.0503347e+09 | S75: =S55*S63*S66 -> 4.0503347e+09 | T75: =T55*T63*T66 -> 4.0503347e+09 | U75: =U55*U63*U66 -> 4.0503347e+09 | V75: =V55*V63*V66 -> 4.0503347e+09 | W75: =W55*W63*W66 -> 4.0503347e+09 | X75: =X55*X63*X66 -> 4.0503347e+09 | Y75: =Y55*Y63*Y66 -> 4.0503347e+09 | ... AG75: =AG55*AG63*AG66 -> 4.0503347e+09
D76: IFM - FCC | I76: IDR Mil | J76: ='Data Aktual'!I63 -> 8886249100 | K76: ='Data Aktual'!J63 -> 8445756000 | L76: ='Data Aktual'!K63 -> 6.0307779e+09 | M76: ='Data Aktual'!L63 -> 6.0316083e+09 | N76: ='Data Aktual'!M63 -> 7011316950 | O76: ='Data Aktual'!N63 -> 6784455150 | P76: ='Data Aktual'!O63 -> 7725549150 | Q76: ='Data Aktual'!P63 -> 8598231950 | R76: =SUM(R74:R75) -> 7.9614826e+09 | S76: =SUM(S74:S75) -> 7.9614826e+09 | T76: =SUM(T74:T75) -> 7.9614826e+09 | U76: =SUM(U74:U75) -> 7.9614826e+09 | V76: =SUM(V74:V75) -> 7.9614826e+09 | W76: =SUM(W74:W75) -> 7.9614826e+09 | X76: =SUM(X74:X75) -> 7.9614826e+09 | Y76: =SUM(Y74:Y75) -> 7.9614826e+09 | ... AG76: =SUM(AG74:AG75) -> 7.9614826e+09
D77: IFM - Ubi Ungu | I77: IDR Mil | J77: ='Data Aktual'!I66 -> 30560211 | K77: ='Data Aktual'!J66 -> 266750 | L77: ='Data Aktual'!K66 -> 150975650 | M77: ='Data Aktual'!L66 -> 273685500 | N77: ='Data Aktual'!M66 -> 241821000 | O77: ='Data Aktual'!N66 -> 684213750 | P77: ='Data Aktual'!O66 -> 430267750 | Q77: ='Data Aktual'!P66 -> 349709250 | R77: =R56*R68 -> 3.0949583e+08 | S77: =S56*S68 -> 3.0949583e+08 | T77: =T56*T68 -> 3.0949583e+08 | U77: =U56*U68 -> 3.0949583e+08 | V77: =V56*V68 -> 3.0949583e+08 | W77: =W56*W68 -> 3.0949583e+08 | X77: =X56*X68 -> 3.0949583e+08 | Y77: =Y56*Y68 -> 3.0949583e+08 | ... AG77: =AG56*AG68 -> 3.0949583e+08
D78: IFM - Ubi Orange | I78: IDR Mil | J78: ='Data Aktual'!I67 -> 25717483 | K78: ='Data Aktual'!J67 -> 498160 | L78: ='Data Aktual'!K67 -> 150956850 | M78: ='Data Aktual'!L67 -> 264000850 | N78: ='Data Aktual'!M67 -> 255546500 | O78: ='Data Aktual'!N67 -> 653882900 | P78: ='Data Aktual'!O67 -> 404659200 | Q78: ='Data Aktual'!P67 -> 354603700 | R78: =R57*R69 -> 2.6692318e+08 | S78: =S57*S69 -> 2.6692318e+08 | T78: =T57*T69 -> 2.6692318e+08 | U78: =U57*U69 -> 2.6692318e+08 | V78: =V57*V69 -> 2.6692318e+08 | W78: =W57*W69 -> 2.6692318e+08 | X78: =X57*X69 -> 2.6692318e+08 | Y78: =Y57*Y69 -> 2.6692318e+08 | ... AG78: =AG57*AG69 -> 2.6692318e+08
D79: IFM - Others | I79: IDR Mil | J79: -3066000 | K79: -3934010 | L79: 59487613 | M79: -2444097 | N79: 0 | O79: -2871000 | P79: 0 | Q79: -330000
D80: IFM - total per Laba Rugi | I80: IDR Mil | J80: =SUM(J76:J79) -> 8.9394608e+09 | K80: =SUM(K76:K79) -> 8442586900 | L80: =SUM(L76:L79) -> 6.392198e+09 | M80: =SUM(M76:M79) -> 6566850570 | N80: =SUM(N76:N79) -> 7508684450 | O80: =SUM(O76:O79) -> 8119680800 | P80: =SUM(P76:P79) -> 8560476100 | Q80: =SUM(Q76:Q79) -> 9302214900 | ... AG80: =SUM(AG76:AG79) -> 8.5379016e+09
D81: Ekspor & Singkong Fresh | I81: IDR Mil | J81: ='DATA - GL Aktual 2026'!C10 -> 0 | K81: ='DATA - GL Aktual 2026'!D10 -> 0 | L81: ='DATA - GL Aktual 2026'!E10 -> 0 | M81: ='DATA - GL Aktual 2026'!F10 -> 0 | N81: ='DATA - GL Aktual 2026'!G10 -> 0 | O81: ='DATA - GL Aktual 2026'!H10 -> 0 | P81: ='DATA - GL Aktual 2026'!I10 -> 0 | Q81: ='DATA - GL Aktual 2026'!J10 -> 0 | R81: 0 | S81: 0 | T81: 0 | U81: 0 | V81: 0 | W81: 0 | X81: 0 | Y81: 0 | Z81: 0 | AA81: 0 | AB81: 0 | AC81: 0 | AD81: 0 | AE81: 0 | AF81: 0 | AG81: 0
D82: KBF
D83: Other (MBS, Nutrifood, Koperasi, Lembutan) | I83: IDR Mil | J83: ='DATA - GL Aktual 2026'!C11 -> 4.2998577e+08 | K83: ='DATA - GL Aktual 2026'!D11 -> 2.1698377e+08 | L83: ='DATA - GL Aktual 2026'!E11 -> 92358781 | M83: ='DATA - GL Aktual 2026'!F11 -> 2.8367813e+08 | N83: ='DATA - GL Aktual 2026'!G11 -> 1.9673241e+08 | O83: ='DATA - GL Aktual 2026'!H11 -> 1.7560696e+08 | P83: ='DATA - GL Aktual 2026'!I11 -> 3.5360476e+08 | Q83: ='DATA - GL Aktual 2026'!J11 -> 4.9091055e+08 | R83: 2.083813e+08 | S83: 2.083813e+08 | T83: 2.083813e+08 | U83: 2.083813e+08 | V83: 2.083813e+08 | W83: 2.083813e+08 | X83: 2.083813e+08 | Y83: 2.083813e+08 | Z83: 2.083813e+08 | AA83: 2.083813e+08 | AB83: 2.083813e+08 | AC83: 2.083813e+08 | AD83: 2.083813e+08 | AE83: 2.083813e+08 | AF83: 2.083813e+08 | AG83: 2.083813e+08
C84: Total Operating Revenue - hitungan | I84: IDR Mil | J84: =SUM(J80:J83) -> 9.3694466e+09 | K84: =SUM(K80:K83) -> 8.6595707e+09 | L84: =SUM(L80:L83) -> 6.4845568e+09 | M84: =SUM(M80:M83) -> 6.8505287e+09 | N84: =SUM(N80:N83) -> 7.7054169e+09 | O84: =SUM(O80:O83) -> 8.2952878e+09 | P84: =SUM(P80:P83) -> 8.9140809e+09 | Q84: =SUM(Q80:Q83) -> 9.7931255e+09 | ... AG84: =SUM(AG80:AG83) -> 8.7462829e+09
D85: Total Operating Revenue per Laba Rugi (baris 12) | I85: IDR Mil | J85: ='DATA - GL Aktual 2026'!C12 -> 9.3694466e+09 | K85: ='DATA - GL Aktual 2026'!D12 -> 8.6595707e+09 | L85: ='DATA - GL Aktual 2026'!E12 -> 6.4845568e+09 | M85: ='DATA - GL Aktual 2026'!F12 -> 6.8505287e+09 | N85: ='DATA - GL Aktual 2026'!G12 -> 7.7054169e+09 | O85: ='DATA - GL Aktual 2026'!H12 -> 8.2952878e+09 | P85: ='DATA - GL Aktual 2026'!I12 -> 8.9140809e+09 | Q85: ='DATA - GL Aktual 2026'!J12 -> 9.7931255e+09
D86: ctrl | I86: IDR Mil | J86: =J84-J85 -> 0 | K86: =K84-K85 -> 0 | L86: =L84-L85 -> 0 | M86: =M84-M85 -> 0 | N86: =N84-N85 -> 0 | O86: =O84-O85 -> 0 | P86: =P84-P85 -> 0 | Q86: =Q84-Q85 -> 0
C87: 3.4 Claim & Discount | I87: IDR Mil | J87: {=-J86:Q86} -> 0 | K87: 0 | L87: 0 | M87: 0 | N87: 0 | O87: 0 | P87: 0 | Q87: 0
D88: Claim & discount | I88: IDR Mil | R88: 0 | S88: 0 | T88: 0 | U88: 0 | V88: 0 | W88: 0 | X88: 0 | Y88: 0 | Z88: 0 | AA88: 0 | AB88: 0 | AC88: 0 | AD88: 0 | AE88: 0 | AF88: 0 | AG88: 0
C89: Revenue neto | I89: IDR Mil | J89: =J84+J88 -> 9.3694466e+09 | K89: =K84+K88 -> 8.6595707e+09 | L89: =L84+L88 -> 6.4845568e+09 | M89: =M84+M88 -> 6.8505287e+09 | N89: =N84+N88 -> 7.7054169e+09 | O89: =O84+O88 -> 8.2952878e+09 | P89: =P84+P88 -> 8.9140809e+09 | Q89: =Q84+Q88 -> 9.7931255e+09 | ... AG89: =AG84+AG88 -> 8.7462829e+09
A91: 4 | B91: Pool Biaya Pabrik & Alokasi
C92: 4.1 Pool biaya pabrik per Laba Rugi - akun | I92: IDR Mil
D93: 4.1.1 | E93: Manpower Cost | G93: Basic Salary | H93: Grup A | I93: IDR Mil | J93: ='DATA - GL Aktual 2026'!C15 -> 836253454 | K93: ='DATA - GL Aktual 2026'!D15 -> 736842285 | L93: ='DATA - GL Aktual 2026'!E15 -> 610128896 | M93: ='DATA - GL Aktual 2026'!F15 -> 874743990 | N93: ='DATA - GL Aktual 2026'!G15 -> 937223872 | O93: ='DATA - GL Aktual 2026'!H15 -> 976098507 | P93: ='DATA - GL Aktual 2026'!I15 -> 1003243362 | Q93: ='DATA - GL Aktual 2026'!J15 -> 961759797 | R93: =R102+R117+R134 -> 8.8118577e+08 | S93: =S102+S117+S134 -> 8.8118577e+08 | T93: =T102+T117+T134 -> 8.8118577e+08 | U93: =U102+U117+U134 -> 8.8118577e+08 | V93: =V102+V117+V134 -> 8.8118577e+08 | W93: =W102+W117+W134 -> 8.8118577e+08 | X93: =X102+X117+X134 -> 8.8118577e+08 | Y93: =Y102+Y117+Y134 -> 8.8118577e+08 | ... AG93: =AG102+AG117+AG134 -> 8.8118577e+08
E94: 4.1.1.1 Direct Labour - Basic Salary
E95: Detail Headcount
F96: Departement | G96: Function | H96: Status | I96: Mapping Cost
F97: Production | G97: Unit 1 | H97: Daily Worker | I97: Direct Labour | R97: 100 | S97: 100 | T97: 100 | U97: 100 | V97: 100 | W97: 100 | X97: 100 | Y97: 100 | Z97: 100 | AA97: 100 | AB97: 100 | AC97: 100 | AD97: 100 | AE97: 100 | AF97: 100 | AG97: 100
F98: Production | G98: Unit 2 | H98: Daily Worker | I98: Direct Labour | R98: 43 | S98: 43 | T98: 43 | U98: 43 | V98: 43 | W98: 43 | X98: 43 | Y98: 43 | Z98: 43 | AA98: 43 | AB98: 43 | AC98: 43 | AD98: 43 | AE98: 43 | AF98: 43 | AG98: 43
F99: Production | G99: Unit 3 | H99: Daily Worker | I99: Direct Labour | R99: 16 | S99: 16 | T99: 16 | U99: 16 | V99: 16 | W99: 16 | X99: 16 | Y99: 16 | Z99: 16 | AA99: 16 | AB99: 16 | AC99: 16 | AD99: 16 | AE99: 16 | AF99: 16 | AG99: 16
E100: Daily Rate | I100: IDR | R100: 141534 | S100: 141534 | T100: 141534 | U100: 141534 | V100: 141534 | W100: 141534 | X100: 141534 | Y100: 141534 | Z100: 141534 | AA100: 141534 | AB100: 141534 | AC100: 141534 | AD100: 141534 | AE100: 141534 | AF100: 141534 | AG100: 141534
E101: Working Days | I101: Days | R101: 24 | S101: 24 | T101: 24 | U101: 24 | V101: 24 | W101: 24 | X101: 24 | Y101: 24 | Z101: 24 | AA101: 24 | AB101: 24 | AC101: 24 | AD101: 24 | AE101: 24 | AF101: 24 | AG101: 24
E102: Monthly - Coast | I102: IDR Mil | J102: =(J93-J134)*0.7366071429 -> 4.6980354e+08 | K102: =(K93-K134)*0.7366071429 -> 3.9657656e+08 | L102: =(L93-L134)*0.7366071429 -> 3.0323857e+08 | M102: =(M93-M134)*0.7366071429 -> 4.9273932e+08 | N102: =(N93-N134)*0.7366071429 -> 5.3696509e+08 | O102: =(O93-O134)*0.7366071429 -> 5.6552888e+08 | P102: =(P93-P134)*0.7366071429 -> 5.8867845e+08 | Q102: =(Q93-Q134)*0.7366071429 -> 5.8629957e+08 | R102: =R101*R100*SUM(R97:R99) -> 540093744 | S102: =S101*S100*SUM(S97:S99) -> 540093744 | T102: =T101*T100*SUM(T97:T99) -> 540093744 | U102: =U101*U100*SUM(U97:U99) -> 540093744 | V102: =V101*V100*SUM(V97:V99) -> 540093744 | W102: =W101*W100*SUM(W97:W99) -> 540093744 | X102: =X101*X100*SUM(X97:X99) -> 540093744 | Y102: =Y101*Y100*SUM(Y97:Y99) -> 540093744 | ... AG102: =AG101*AG100*SUM(AG97:AG99) -> 540093744
E103: 4.1.1.2 FOH - Basic Salary - Daily Worker
E104: Detail Headcount
F105: Departement | G105: Function | H105: Status | I105: Mapping Cost
F106: Production | G106: Unit 1 | H106: Daily Worker | I106: COGS - Manufacturing Overhead | R106: ='Input Operasional'!Q110 -> 14 | S106: ='Input Operasional'!R110 -> 14 | T106: ='Input Operasional'!S110 -> 14 | U106: ='Input Operasional'!T110 -> 14 | V106: ='Input Operasional'!U110 -> 14 | W106: ='Input Operasional'!V110 -> 14 | X106: ='Input Operasional'!W110 -> 14 | Y106: ='Input Operasional'!X110 -> 14 | ... AG106: ='Input Operasional'!AF110 -> 14
F107: Production | G107: Unit 2 | H107: Daily Worker | I107: COGS - Manufacturing Overhead | R107: ='Input Operasional'!Q111 -> 2 | S107: ='Input Operasional'!R111 -> 2 | T107: ='Input Operasional'!S111 -> 2 | U107: ='Input Operasional'!T111 -> 2 | V107: ='Input Operasional'!U111 -> 2 | W107: ='Input Operasional'!V111 -> 2 | X107: ='Input Operasional'!W111 -> 2 | Y107: ='Input Operasional'!X111 -> 2 | ... AG107: ='Input Operasional'!AF111 -> 2
F108: Production | G108: Unit 3 | H108: Daily Worker | I108: COGS - Manufacturing Overhead | R108: ='Input Operasional'!Q112 -> 8 | S108: ='Input Operasional'!R112 -> 8 | T108: ='Input Operasional'!S112 -> 8 | U108: ='Input Operasional'!T112 -> 8 | V108: ='Input Operasional'!U112 -> 8 | W108: ='Input Operasional'!V112 -> 8 | X108: ='Input Operasional'!W112 -> 8 | Y108: ='Input Operasional'!X112 -> 8 | ... AG108: ='Input Operasional'!AF112 -> 8
F109: Engineering | G109: Engineering | H109: Daily Worker | I109: COGS - Manufacturing Overhead | R109: ='Input Operasional'!Q113 -> 8 | S109: ='Input Operasional'!R113 -> 8 | T109: ='Input Operasional'!S113 -> 8 | U109: ='Input Operasional'!T113 -> 8 | V109: ='Input Operasional'!U113 -> 8 | W109: ='Input Operasional'!V113 -> 8 | X109: ='Input Operasional'!W113 -> 8 | Y109: ='Input Operasional'!X113 -> 8 | ... AG109: ='Input Operasional'!AF113 -> 8
F110: HSE | G110: HSE | H110: Daily Worker | I110: COGS - Manufacturing Overhead | R110: ='Input Operasional'!Q114 -> 3 | S110: ='Input Operasional'!R114 -> 3 | T110: ='Input Operasional'!S114 -> 3 | U110: ='Input Operasional'!T114 -> 3 | V110: ='Input Operasional'!U114 -> 3 | W110: ='Input Operasional'!V114 -> 3 | X110: ='Input Operasional'!W114 -> 3 | Y110: ='Input Operasional'!X114 -> 3 | ... AG110: ='Input Operasional'!AF114 -> 3
F111: PPIC | G111: PPIC | H111: Daily Worker | I111: COGS - Manufacturing Overhead | R111: ='Input Operasional'!Q115 -> 1 | S111: ='Input Operasional'!R115 -> 1 | T111: ='Input Operasional'!S115 -> 1 | U111: ='Input Operasional'!T115 -> 1 | V111: ='Input Operasional'!U115 -> 1 | W111: ='Input Operasional'!V115 -> 1 | X111: ='Input Operasional'!W115 -> 1 | Y111: ='Input Operasional'!X115 -> 1 | ... AG111: ='Input Operasional'!AF115 -> 1
...

Sheet Register FA
A1: PT Boga Makmur Gracia
A2: Fixed Assets List
U5: 46053 | V5: 46081 | W5: 46112 | X5: 46142 | Y5: 46173 | Z5: 46203 | AA5: 46234 | AB5: 46265 | AG5: 46295 | AH5: 46326 | AI5: 46356 | AJ5: 46387 | AK5: 46418 | AL5: 46446 | AM5: 46477 | AN5: 46507 | AO5: 46538 | AP5: 46568 | AQ5: 46599 | AR5: 46630 | AS5: 46660 | AT5: 46691 | AU5: 46721 | AV5: 46752
A6: No | B6: Sheet sumber | C6: Baris sumber | D6: Kelas (mapping BS) | E6: Golongan | F6: Akun GL aset | G6: Akun GL akum. penyusutan | H6: Akun GL beban penyusutan | I6: Baris P&L Business Plan | J6: Kode | K6: Kode Accurate | L6: Tanggal perolehan | M6: Nama aset | N6: Keterangan | O6: Status | P6: Qty | Q6: Nilai perolehan (Rp) | R6: Umur (bulan) | S6: Depr/bulan register (Rp) | T6: Akum. penyusutan 31 Des 2025 (Rp) | U6: Aktual Jan-26 | V6: Aktual Feb-26 | W6: Aktual Mar-26 | X6: Aktual Apr-26 | Y6: Aktual May-26 | Z6: Aktual Jun-26 | AA6: Aktual Jul-26 | AB6: Aktual Aug-26 | AC6: Akum. penyusutan 31 Agu 2026 | AD6: Nilai buku 31 Agu 2026 | AE6: Depr/bulan berjalan (= Agu-26) | AF6: Sisa umur (bulan) | AG6: Proyeksi Sep-26 | AH6: Proyeksi Oct-26 | AI6: Proyeksi Nov-26 | AJ6: Proyeksi Dec-26 | AK6: Proyeksi Jan-27 | AL6: Proyeksi Feb-27 | AM6: Proyeksi Mar-27 | AN6: Proyeksi Apr-27 | AO6: Proyeksi May-27 | AP6: Proyeksi Jun-27 | AQ6: Proyeksi Jul-27 | AR6: Proyeksi Aug-27 | AS6: Proyeksi Sep-27 | AT6: Proyeksi Oct-27 | AU6: Proyeksi Nov-27 | AV6: Proyeksi Dec-27 | AW6: Total proyeksi Sep-26 s/d Des-27 | AX6: Nilai buku 31 Des 2027
A7: 1 | B7: FA Bangunan | C7: 8 | D7: Buildings | E7: Bangunan | F7: 1201-001 | G7: 1202-001 | H7: 6500-001 | I7: Depreciation Expenses | J7: BP.01/12 | K7: GD.0001 | L7: 41090 | M7: Pembangunan Parik Boja | N7: Bangun pabrik di Boja, Semarang | O7: Aktif | P7: 1 | Q7: 3175850457 | R7: 240 | S7: 13232710 | T7: 2.1569318e+09 | U7: 13232710 | V7: 13232710 | W7: 13232710 | X7: 13232710 | Y7: 13232710 | Z7: 13232710 | AA7: 13232710 | AB7: 13232710 | AC7: =T7+SUM(U7:AB7) -> 2.2627935e+09 | AD7: =Q7-AC7 -> 9.1305701e+08 | AE7: =IF(O7="Aktif",AB7,0) -> 13232710 | AF7: =IF(AE7>0,MAX(0,AD7)/AE7,0) -> 69 | AG7: =IF($O7="Aktif",MAX(0,MIN($AE7,$AD7-0)),0) -> 13232710 | AH7: =IF($O7="Aktif",MAX(0,MIN($AE7,$AD7-SUM($AG7:AG7))),0) -> 13232710 | AI7: =IF($O7="Aktif",MAX(0,MIN($AE7,$AD7-SUM($AG7:AH7))),0) -> 13232710 | AJ7: =IF($O7="Aktif",MAX(0,MIN($AE7,$AD7-SUM($AG7:AI7))),0) -> 13232710 | AK7: =IF($O7="Aktif",MAX(0,MIN($AE7,$AD7-SUM($AG7:AJ7))),0) -> 13232710 | AL7: =IF($O7="Aktif",MAX(0,MIN($AE7,$AD7-SUM($AG7:AK7))),0) -> 13232710 | AM7: =IF($O7="Aktif",MAX(0,MIN($AE7,$AD7-SUM($AG7:AL7))),0) -> 13232710 | AN7: =IF($O7="Aktif",MAX(0,MIN($AE7,$AD7-SUM($AG7:AM7))),0) -> 13232710 | AO7: =IF($O7="Aktif",MAX(0,MIN($AE7,$AD7-SUM($AG7:AN7))),0) -> 13232710 | ... AV7: =IF($O7="Aktif",MAX(0,MIN($AE7,$AD7-SUM($AG7:AU7))),0) -> 13232710 | AW7: =SUM(AG7:AV7) -> 2.1172336e+08 | AX7: =AD7-AW7 -> 7.0133364e+08
A8: 2 | B8: FA Bangunan | C8: 9 | D8: Buildings | E8: Bangunan | F8: 1201-001 | G8: 1202-001 | H8: 6500-001 | I8: Depreciation Expenses | J8: BP.01/14 | K8: GD.0002 | L8: 41820 | M8: Pembangunan Gedung Pabrik Semarang | N8: Pembangunan gedung pabrik SMG (termasuk pagar dan jalan baru) | O8: Aktif | P8: 1 | Q8: 2649000000 | R8: 240 | S8: 11037500 | T8: 1534212500 | U8: 11037500 | V8: 11037500 | W8: 11037500 | X8: 11037500 | Y8: 11037500 | Z8: 11037500 | AA8: 11037500 | AB8: 11037500 | AC8: =T8+SUM(U8:AB8) -> 1622512500 | AD8: =Q8-AC8 -> 1026487500 | AE8: =IF(O8="Aktif",AB8,0) -> 11037500 | AF8: =IF(AE8>0,MAX(0,AD8)/AE8,0) -> 93 | AG8: =IF($O8="Aktif",MAX(0,MIN($AE8,$AD8-0)),0) -> 11037500 | AH8: =IF($O8="Aktif",MAX(0,MIN($AE8,$AD8-SUM($AG8:AG8))),0) -> 11037500 | AI8: =IF($O8="Aktif",MAX(0,MIN($AE8,$AD8-SUM($AG8:AH8))),0) -> 11037500 | AJ8: =IF($O8="Aktif",MAX(0,MIN($AE8,$AD8-SUM($AG8:AI8))),0) -> 11037500 | AK8: =IF($O8="Aktif",MAX(0,MIN($AE8,$AD8-SUM($AG8:AJ8))),0) -> 11037500 | AL8: =IF($O8="Aktif",MAX(0,MIN($AE8,$AD8-SUM($AG8:AK8))),0) -> 11037500 | AM8: =IF($O8="Aktif",MAX(0,MIN($AE8,$AD8-SUM($AG8:AL8))),0) -> 11037500 | AN8: =IF($O8="Aktif",MAX(0,MIN($AE8,$AD8-SUM($AG8:AM8))),0) -> 11037500 | AO8: =IF($O8="Aktif",MAX(0,MIN($AE8,$AD8-SUM($AG8:AN8))),0) -> 11037500 | ... AV8: =IF($O8="Aktif",MAX(0,MIN($AE8,$AD8-SUM($AG8:AU8))),0) -> 11037500 | AW8: =SUM(AG8:AV8) -> 176600000 | AX8: =AD8-AW8 -> 849887500
A9: 3 | B9: FA Bangunan | C9: 10 | D9: Buildings | E9: Bangunan | F9: 1201-001 | G9: 1202-001 | H9: 6500-001 | I9: Depreciation Expenses | J9: BP.01/16 | K9: GD.0003 | L9: 42582 | M9: Pembangunan Gudang Boja Tahap 3 | N9: Pembangunan Perluasan Gudang Boja Tahap III | O9: Aktif | P9: 1 | Q9: 5353400000 | R9: 240 | S9: 22305833 | T9: 2.542865e+09 | U9: 22305833 | V9: 22305833 | W9: 22305833 | X9: 22305833 | Y9: 22305833 | Z9: 22305833 | AA9: 22305833 | AB9: 22305833 | AC9: =T9+SUM(U9:AB9) -> 2.7213117e+09 | AD9: =Q9-AC9 -> 2.6320883e+09 | AE9: =IF(O9="Aktif",AB9,0) -> 22305833 | AF9: =IF(AE9>0,MAX(0,AD9)/AE9,0) -> 118 | AG9: =IF($O9="Aktif",MAX(0,MIN($AE9,$AD9-0)),0) -> 22305833 | AH9: =IF($O9="Aktif",MAX(0,MIN($AE9,$AD9-SUM($AG9:AG9))),0) -> 22305833 | AI9: =IF($O9="Aktif",MAX(0,MIN($AE9,$AD9-SUM($AG9:AH9))),0) -> 22305833 | AJ9: =IF($O9="Aktif",MAX(0,MIN($AE9,$AD9-SUM($AG9:AI9))),0) -> 22305833 | AK9: =IF($O9="Aktif",MAX(0,MIN($AE9,$AD9-SUM($AG9:AJ9))),0) -> 22305833 | AL9: =IF($O9="Aktif",MAX(0,MIN($AE9,$AD9-SUM($AG9:AK9))),0) -> 22305833 | AM9: =IF($O9="Aktif",MAX(0,MIN($AE9,$AD9-SUM($AG9:AL9))),0) -> 22305833 | AN9: =IF($O9="Aktif",MAX(0,MIN($AE9,$AD9-SUM($AG9:AM9))),0) -> 22305833 | AO9: =IF($O9="Aktif",MAX(0,MIN($AE9,$AD9-SUM($AG9:AN9))),0) -> 22305833 | ... AV9: =IF($O9="Aktif",MAX(0,MIN($AE9,$AD9-SUM($AG9:AU9))),0) -> 22305833 | AW9: =SUM(AG9:AV9) -> 3.5689333e+08 | AX9: =AD9-AW9 -> 2.275195e+09
A10: 4 | B10: FA Bangunan | C10: 11 | D10: Buildings | E10: Bangunan | F10: 1201-001 | G10: 1202-001 | H10: 6500-001 | I10: Depreciation Expenses | J10: BP.01/18 | K10: GD.0004 | L10: 43131 | M10: Instalansi Gas, Minyak, Dan Air | N10: Instalansi gas, minyak, dan air,menunjang produksi Singkong serut di unit 4 | O10: Aktif | P10: 1 | Q10: 85470000 | R10: 240 | S10: 356125 | T10: 34188000 | U10: 356125 | V10: 356125 | W10: 356125 | X10: 356125 | Y10: 356125 | Z10: 356125 | AA10: 356125 | AB10: 356125 | AC10: =T10+SUM(U10:AB10) -> 37037000 | AD10: =Q10-AC10 -> 48433000 | AE10: =IF(O10="Aktif",AB10,0) -> 356125 | AF10: =IF(AE10>0,MAX(0,AD10)/AE10,0) -> 136 | AG10: =IF($O10="Aktif",MAX(0,MIN($AE10,$AD10-0)),0) -> 356125 | AH10: =IF($O10="Aktif",MAX(0,MIN($AE10,$AD10-SUM($AG10:AG10))),0) -> 356125 | AI10: =IF($O10="Aktif",MAX(0,MIN($AE10,$AD10-SUM($AG10:AH10))),0) -> 356125 | AJ10: =IF($O10="Aktif",MAX(0,MIN($AE10,$AD10-SUM($AG10:AI10))),0) -> 356125 | AK10: =IF($O10="Aktif",MAX(0,MIN($AE10,$AD10-SUM($AG10:AJ10))),0) -> 356125 | AL10: =IF($O10="Aktif",MAX(0,MIN($AE10,$AD10-SUM($AG10:AK10))),0) -> 356125 | AM10: =IF($O10="Aktif",MAX(0,MIN($AE10,$AD10-SUM($AG10:AL10))),0) -> 356125 | AN10: =IF($O10="Aktif",MAX(0,MIN($AE10,$AD10-SUM($AG10:AM10))),0) -> 356125 | AO10: =IF($O10="Aktif",MAX(0,MIN($AE10,$AD10-SUM($AG10:AN10))),0) -> 356125 | ... AV10: =IF($O10="Aktif",MAX(0,MIN($AE10,$AD10-SUM($AG10:AU10))),0) -> 356125 | AW10: =SUM(AG10:AV10) -> 5698000 | AX10: =AD10-AW10 -> 42735000
A11: 5 | B11: FA Bangunan | C11: 12 | D11: Buildings | E11: Bangunan | F11: 1201-001 | G11: 1202-001 | H11: 6500-001 | I11: Depreciation Expenses | J11: BP.02/18 | K11: GD.0005 | L11: 43131 | M11: Atap Area Hois & Area Rendam | N11: Atap area Hois & area rendam | O11: Aktif | P11: 1 | Q11: 230000000 | R11: 240 | S11: 958333.33 | T11: 92000000 | U11: 958333.33 | V11: 958333.33 | W11: 958333.33 | X11: 958333.33 | Y11: 958333.33 | Z11: 958333.33 | AA11: 958333.33 | AB11: 958333.33 | AC11: =T11+SUM(U11:AB11) -> 99666667 | AD11: =Q11-AC11 -> 1.3033333e+08 | AE11: =IF(O11="Aktif",AB11,0) -> 958333.33 | AF11: =IF(AE11>0,MAX(0,AD11)/AE11,0) -> 136 | AG11: =IF($O11="Aktif",MAX(0,MIN($AE11,$AD11-0)),0) -> 958333.33 | AH11: =IF($O11="Aktif",MAX(0,MIN($AE11,$AD11-SUM($AG11:AG11))),0) -> 958333.33 | AI11: =IF($O11="Aktif",MAX(0,MIN($AE11,$AD11-SUM($AG11:AH11))),0) -> 958333.33 | AJ11: =IF($O11="Aktif",MAX(0,MIN($AE11,$AD11-SUM($AG11:AI11))),0) -> 958333.33 | AK11: =IF($O11="Aktif",MAX(0,MIN($AE11,$AD11-SUM($AG11:AJ11))),0) -> 958333.33 | AL11: =IF($O11="Aktif",MAX(0,MIN($AE11,$AD11-SUM($AG11:AK11))),0) -> 958333.33 | AM11: =IF($O11="Aktif",MAX(0,MIN($AE11,$AD11-SUM($AG11:AL11))),0) -> 958333.33 | AN11: =IF($O11="Aktif",MAX(0,MIN($AE11,$AD11-SUM($AG11:AM11))),0) -> 958333.33 | AO11: =IF($O11="Aktif",MAX(0,MIN($AE11,$AD11-SUM($AG11:AN11))),0) -> 958333.33 | ... AV11: =IF($O11="Aktif",MAX(0,MIN($AE11,$AD11-SUM($AG11:AU11))),0) -> 958333.33 | AW11: =SUM(AG11:AV11) -> 15333333 | AX11: =AD11-AW11 -> 1.15e+08
A12: 6 | B12: FA Bangunan | C12: 13 | D12: Buildings | E12: Bangunan | F12: 1201-001 | G12: 1202-001 | H12: 6500-001 | I12: Depreciation Expenses | J12: BP.03/18 | K12: GD.0006 | L12: 43131 | M12: Pekerjaan Atap Dan Pagar Area Kupas | N12: Pekerjaan Atap dan pagar area kupas | O12: Aktif | P12: 1 | Q12: 96000000 | R12: 240 | S12: 400000 | T12: 38400000 | U12: 400000 | V12: 400000 | W12: 400000 | X12: 400000 | Y12: 400000 | Z12: 400000 | AA12: 400000 | AB12: 400000 | AC12: =T12+SUM(U12:AB12) -> 41600000 | AD12: =Q12-AC12 -> 54400000 | AE12: =IF(O12="Aktif",AB12,0) -> 400000 | AF12: =IF(AE12>0,MAX(0,AD12)/AE12,0) -> 136 | AG12: =IF($O12="Aktif",MAX(0,MIN($AE12,$AD12-0)),0) -> 400000 | AH12: =IF($O12="Aktif",MAX(0,MIN($AE12,$AD12-SUM($AG12:AG12))),0) -> 400000 | AI12: =IF($O12="Aktif",MAX(0,MIN($AE12,$AD12-SUM($AG12:AH12))),0) -> 400000 | AJ12: =IF($O12="Aktif",MAX(0,MIN($AE12,$AD12-SUM($AG12:AI12))),0) -> 400000 | AK12: =IF($O12="Aktif",MAX(0,MIN($AE12,$AD12-SUM($AG12:AJ12))),0) -> 400000 | AL12: =IF($O12="Aktif",MAX(0,MIN($AE12,$AD12-SUM($AG12:AK12))),0) -> 400000 | AM12: =IF($O12="Aktif",MAX(0,MIN($AE12,$AD12-SUM($AG12:AL12))),0) -> 400000 | AN12: =IF($O12="Aktif",MAX(0,MIN($AE12,$AD12-SUM($AG12:AM12))),0) -> 400000 | AO12: =IF($O12="Aktif",MAX(0,MIN($AE12,$AD12-SUM($AG12:AN12))),0) -> 400000 | ... AV12: =IF($O12="Aktif",MAX(0,MIN($AE12,$AD12-SUM($AG12:AU12))),0) -> 400000 | AW12: =SUM(AG12:AV12) -> 6400000 | AX12: =AD12-AW12 -> 48000000
A13: 7 | B13: FA Bangunan | C13: 14 | D13: Buildings | E13: Bangunan | F13: 1201-001 | G13: 1202-001 | H13: 6500-001 | I13: Depreciation Expenses | J13: BP.04/18 | K13: GD.0007 | L13: 43109 | M13: Pekerjaan Perbaikan Lantai | N13: pekerjaan pengecoran lantai unit 1 goreng ( bongkar lantai cor u.1,beton cor k 300 6,dl),29/12/17 | O13: Aktif | P13: 1 | Q13: 34000000 | R13: 240 | S13: 141666.67 | T13: 13600000 | U13: 141666.67 | V13: 141666.67 | W13: 141666.67 | X13: 141666.67 | Y13: 141666.67 | Z13: 141666.67 | AA13: 141666.67 | AB13: 141666.67 | AC13: =T13+SUM(U13:AB13) -> 14733333 | AD13: =Q13-AC13 -> 19266667 | AE13: =IF(O13="Aktif",AB13,0) -> 141666.67 | AF13: =IF(AE13>0,MAX(0,AD13)/AE13,0) -> 136 | AG13: =IF($O13="Aktif",MAX(0,MIN($AE13,$AD13-0)),0) -> 141666.67 | AH13: =IF($O13="Aktif",MAX(0,MIN($AE13,$AD13-SUM($AG13:AG13))),0) -> 141666.67 | AI13: =IF($O13="Aktif",MAX(0,MIN($AE13,$AD13-SUM($AG13:AH13))),0) -> 141666.67 | AJ13: =IF($O13="Aktif",MAX(0,MIN($AE13,$AD13-SUM($AG13:AI13))),0) -> 141666.67 | AK13: =IF($O13="Aktif",MAX(0,MIN($AE13,$AD13-SUM($AG13:AJ13))),0) -> 141666.67 | AL13: =IF($O13="Aktif",MAX(0,MIN($AE13,$AD13-SUM($AG13:AK13))),0) -> 141666.67 | AM13: =IF($O13="Aktif",MAX(0,MIN($AE13,$AD13-SUM($AG13:AL13))),0) -> 141666.67 | AN13: =IF($O13="Aktif",MAX(0,MIN($AE13,$AD13-SUM($AG13:AM13))),0) -> 141666.67 | AO13: =IF($O13="Aktif",MAX(0,MIN($AE13,$AD13-SUM($AG13:AN13))),0) -> 141666.67 | ... AV13: =IF($O13="Aktif",MAX(0,MIN($AE13,$AD13-SUM($AG13:AU13))),0) -> 141666.67 | AW13: =SUM(AG13:AV13) -> 2266666.7 | AX13: =AD13-AW13 -> 17000000
A14: 8 | B14: FA Bangunan | C14: 15 | D14: Buildings | E14: Bangunan | F14: 1201-001 | G14: 1202-001 | H14: 6500-001 | I14: Depreciation Expenses | J14: BP.05/18 | K14: GD.0008 | L14: 43144 | M14: Pekerjaan Instalasi Listrik R. Angin, R. Bumbu | N14: pekerjaan listrik ( instalansi ), R.aging, R. Bumbu,dll di karya mandiri (pph 23) | O14: Aktif | P14: 1 | Q14: 8340000 | R14: 240 | S14: 34750 | T14: 3301250 | U14: 34750 | V14: 34750 | W14: 34750 | X14: 34750 | Y14: 34750 | Z14: 34750 | AA14: 34750 | AB14: 34750 | AC14: =T14+SUM(U14:AB14) -> 3579250 | AD14: =Q14-AC14 -> 4760750 | AE14: =IF(O14="Aktif",AB14,0) -> 34750 | AF14: =IF(AE14>0,MAX(0,AD14)/AE14,0) -> 137 | AG14: =IF($O14="Aktif",MAX(0,MIN($AE14,$AD14-0)),0) -> 34750 | AH14: =IF($O14="Aktif",MAX(0,MIN($AE14,$AD14-SUM($AG14:AG14))),0) -> 34750 | AI14: =IF($O14="Aktif",MAX(0,MIN($AE14,$AD14-SUM($AG14:AH14))),0) -> 34750 | AJ14: =IF($O14="Aktif",MAX(0,MIN($AE14,$AD14-SUM($AG14:AI14))),0) -> 34750 | AK14: =IF($O14="Aktif",MAX(0,MIN($AE14,$AD14-SUM($AG14:AJ14))),0) -> 34750 | AL14: =IF($O14="Aktif",MAX(0,MIN($AE14,$AD14-SUM($AG14:AK14))),0) -> 34750 | AM14: =IF($O14="Aktif",MAX(0,MIN($AE14,$AD14-SUM($AG14:AL14))),0) -> 34750 | AN14: =IF($O14="Aktif",MAX(0,MIN($AE14,$AD14-SUM($AG14:AM14))),0) -> 34750 | AO14: =IF($O14="Aktif",MAX(0,MIN($AE14,$AD14-SUM($AG14:AN14))),0) -> 34750 | ... AV14: =IF($O14="Aktif",MAX(0,MIN($AE14,$AD14-SUM($AG14:AU14))),0) -> 34750 | AW14: =SUM(AG14:AV14) -> 556000 | AX14: =AD14-AW14 -> 4204750
A15: 9 | B15: FA Bangunan | C15: 16 | D15: Buildings | E15: Bangunan | F15: 1201-001 | G15: 1202-001 | H15: 6500-001 | I15: Depreciation Expenses | J15: BP.06/18 | K15: GD.0009 | L15: 43144 | M15: Pemasangan Pintu Emergency R. Angin & Perbaikan Pipa Aur | N15: pemasangan pintu emergency,R. Anging, Pindah Pipa Aur bersih,dll di karya mandiri (pph 23) | O15: Aktif | P15: 1 | Q15: 51500000 | R15: 240 | S15: 214583.33 | T15: 20385417 | U15: 214583.33 | V15: 214583.33 | W15: 214583.33 | X15: 214583.33 | Y15: 214583.33 | Z15: 214583.33 | AA15: 214583.33 | AB15: 214583.33 | AC15: =T15+SUM(U15:AB15) -> 22102083 | AD15: =Q15-AC15 -> 29397917 | AE15: =IF(O15="Aktif",AB15,0) -> 214583.33 | AF15: =IF(AE15>0,MAX(0,AD15)/AE15,0) -> 137 | AG15: =IF($O15="Aktif",MAX(0,MIN($AE15,$AD15-0)),0) -> 214583.33 | AH15: =IF($O15="Aktif",MAX(0,MIN($AE15,$AD15-SUM($AG15:AG15))),0) -> 214583.33 | AI15: =IF($O15="Aktif",MAX(0,MIN($AE15,$AD15-SUM($AG15:AH15))),0) -> 214583.33 | AJ15: =IF($O15="Aktif",MAX(0,MIN($AE15,$AD15-SUM($AG15:AI15))),0) -> 214583.33 | AK15: =IF($O15="Aktif",MAX(0,MIN($AE15,$AD15-SUM($AG15:AJ15))),0) -> 214583.33 | AL15: =IF($O15="Aktif",MAX(0,MIN($AE15,$AD15-SUM($AG15:AK15))),0) -> 214583.33 | AM15: =IF($O15="Aktif",MAX(0,MIN($AE15,$AD15-SUM($AG15:AL15))),0) -> 214583.33 | AN15: =IF($O15="Aktif",MAX(0,MIN($AE15,$AD15-SUM($AG15:AM15))),0) -> 214583.33 | AO15: =IF($O15="Aktif",MAX(0,MIN($AE15,$AD15-SUM($AG15:AN15))),0) -> 214583.33 | ... AV15: =IF($O15="Aktif",MAX(0,MIN($AE15,$AD15-SUM($AG15:AU15))),0) -> 214583.33 | AW15: =SUM(AG15:AV15) -> 3433333.3 | AX15: =AD15-AW15 -> 25964583
A16: 10 | B16: FA Bangunan | C16: 17 | D16: Buildings | E16: Bangunan | F16: 1201-001 | G16: 1202-001 | H16: 6500-001 | I16: Depreciation Expenses | J16: BP.07/18 | K16: GD.0010 | L16: 43158 | M16: Pekerjaan Ruang & Rak Bumbu | N16: Pekerjaan ruang dan rak bumbu baru unit 1 (gudang bumbu ) di karya mandiri, 19/2/18 ( pph 23 4%) | O16: Aktif | P16: 1 | Q16: 40000000 | R16: 240 | S16: 166666.67 | T16: 15833333 | U16: 166666.67 | V16: 166666.67 | W16: 166666.67 | X16: 166666.67 | Y16: 166666.67 | Z16: 166666.67 | AA16: 166666.67 | AB16: 166666.67 | AC16: =T16+SUM(U16:AB16) -> 17166667 | AD16: =Q16-AC16 -> 22833333 | AE16: =IF(O16="Aktif",AB16,0) -> 166666.67 | AF16: =IF(AE16>0,MAX(0,AD16)/AE16,0) -> 137 | AG16: =IF($O16="Aktif",MAX(0,MIN($AE16,$AD16-0)),0) -> 166666.67 | AH16: =IF($O16="Aktif",MAX(0,MIN($AE16,$AD16-SUM($AG16:AG16))),0) -> 166666.67 | AI16: =IF($O16="Aktif",MAX(0,MIN($AE16,$AD16-SUM($AG16:AH16))),0) -> 166666.67 | AJ16: =IF($O16="Aktif",MAX(0,MIN($AE16,$AD16-SUM($AG16:AI16))),0) -> 166666.67 | AK16: =IF($O16="Aktif",MAX(0,MIN($AE16,$AD16-SUM($AG16:AJ16))),0) -> 166666.67 | AL16: =IF($O16="Aktif",MAX(0,MIN($AE16,$AD16-SUM($AG16:AK16))),0) -> 166666.67 | AM16: =IF($O16="Aktif",MAX(0,MIN($AE16,$AD16-SUM($AG16:AL16))),0) -> 166666.67 | AN16: =IF($O16="Aktif",MAX(0,MIN($AE16,$AD16-SUM($AG16:AM16))),0) -> 166666.67 | AO16: =IF($O16="Aktif",MAX(0,MIN($AE16,$AD16-SUM($AG16:AN16))),0) -> 166666.67 | ... AV16: =IF($O16="Aktif",MAX(0,MIN($AE16,$AD16-SUM($AG16:AU16))),0) -> 166666.67 | AW16: =SUM(AG16:AV16) -> 2666666.7 | AX16: =AD16-AW16 -> 20166667
A17: 11 | B17: FA Bangunan | C17: 18 | D17: Buildings | E17: Bangunan | F17: 1201-001 | G17: 1202-001 | H17: 6500-001 | I17: Depreciation Expenses | J17: BP.08/18 | K17: GD.0011 | L17: 43140 | M17: Radiator, Pipa Steam Gas, Steam Floatin | N17: PT Beta Pramesti Radiator,pipa steam gas,steam floatin,dll(dipotong pph 23) | O17: Aktif | P17: 1 | Q17: 38565000 | R17: 240 | S17: 160687.5 | T17: 15265312 | U17: 160687.5 | V17: 160687.5 | W17: 160687.5 | X17: 160687.5 | Y17: 160687.5 | Z17: 160687.5 | AA17: 160687.5 | AB17: 160687.5 | AC17: =T17+SUM(U17:AB17) -> 16550812 | AD17: =Q17-AC17 -> 22014188 | AE17: =IF(O17="Aktif",AB17,0) -> 160687.5 | AF17: =IF(AE17>0,MAX(0,AD17)/AE17,0) -> 137 | AG17: =IF($O17="Aktif",MAX(0,MIN($AE17,$AD17-0)),0) -> 160687.5 | AH17: =IF($O17="Aktif",MAX(0,MIN($AE17,$AD17-SUM($AG17:AG17))),0) -> 160687.5 | AI17: =IF($O17="Aktif",MAX(0,MIN($AE17,$AD17-SUM($AG17:AH17))),0) -> 160687.5 | AJ17: =IF($O17="Aktif",MAX(0,MIN($AE17,$AD17-SUM($AG17:AI17))),0) -> 160687.5 | AK17: =IF($O17="Aktif",MAX(0,MIN($AE17,$AD17-SUM($AG17:AJ17))),0) -> 160687.5 | AL17: =IF($O17="Aktif",MAX(0,MIN($AE17,$AD17-SUM($AG17:AK17))),0) -> 160687.5 | AM17: =IF($O17="Aktif",MAX(0,MIN($AE17,$AD17-SUM($AG17:AL17))),0) -> 160687.5 | AN17: =IF($O17="Aktif",MAX(0,MIN($AE17,$AD17-SUM($AG17:AM17))),0) -> 160687.5 | AO17: =IF($O17="Aktif",MAX(0,MIN($AE17,$AD17-SUM($AG17:AN17))),0) -> 160687.5 | ... AV17: =IF($O17="Aktif",MAX(0,MIN($AE17,$AD17-SUM($AG17:AU17))),0) -> 160687.5 | AW17: =SUM(AG17:AV17) -> 2571000 | AX17: =AD17-AW17 -> 19443188
A18: 12 | B18: FA Bangunan | C18: 19 | D18: Buildings | E18: Bangunan | F18: 1201-001 | G18: 1202-001 | H18: 6500-001 | I18: Depreciation Expenses | J18: BP.09/18 | K18: GD.0012 | L18: 43186 | M18: Pekerjaan Ruangan QC & Mushola | N18: Pekerjaan ruang qc dan mushola (pph 23 4%)di karya mandiri, 12/3/18 | O18: Aktif | P18: 1 | Q18: 25100000 | R18: 240 | S18: 104583.33 | T18: 9830833.3 | U18: 104583.33 | V18: 104583.33 | W18: 104583.33 | X18: 104583.33 | Y18: 104583.33 | Z18: 104583.33 | AA18: 104583.33 | AB18: 104583.33 | AC18: =T18+SUM(U18:AB18) -> 10667500 | AD18: =Q18-AC18 -> 14432500 | AE18: =IF(O18="Aktif",AB18,0) -> 104583.33 | AF18: =IF(AE18>0,MAX(0,AD18)/AE18,0) -> 138 | AG18: =IF($O18="Aktif",MAX(0,MIN($AE18,$AD18-0)),0) -> 104583.33 | AH18: =IF($O18="Aktif",MAX(0,MIN($AE18,$AD18-SUM($AG18:AG18))),0) -> 104583.33 | AI18: =IF($O18="Aktif",MAX(0,MIN($AE18,$AD18-SUM($AG18:AH18))),0) -> 104583.33 | AJ18: =IF($O18="Aktif",MAX(0,MIN($AE18,$AD18-SUM($AG18:AI18))),0) -> 104583.33 | AK18: =IF($O18="Aktif",MAX(0,MIN($AE18,$AD18-SUM($AG18:AJ18))),0) -> 104583.33 | AL18: =IF($O18="Aktif",MAX(0,MIN($AE18,$AD18-SUM($AG18:AK18))),0) -> 104583.33 | AM18: =IF($O18="Aktif",MAX(0,MIN($AE18,$AD18-SUM($AG18:AL18))),0) -> 104583.33 | AN18: =IF($O18="Aktif",MAX(0,MIN($AE18,$AD18-SUM($AG18:AM18))),0) -> 104583.33 | AO18: =IF($O18="Aktif",MAX(0,MIN($AE18,$AD18-SUM($AG18:AN18))),0) -> 104583.33 | ... AV18: =IF($O18="Aktif",MAX(0,MIN($AE18,$AD18-SUM($AG18:AU18))),0) -> 104583.33 | AW18: =SUM(AG18:AV18) -> 1673333.3 | AX18: =AD18-AW18 -> 12759167
... A24: 18 | B24: FA Bangunan | C24: 25 | D24: Buildings | E24: Bangunan | F24: 1201-001 | G24: 1202-001 | H24: 6500-001 | I24: Depreciation Expenses | J24: BP.15/18 | K24: GD.0018 | L24: 43465 | M24: Perbaikan Bangunan | N24: Karya Mandiri, Pekerjaan Pengecoran lantai R N D Bangunan Unit 4, 4/10/17 | O24: Aktif | P24: 1 | Q24: 24000000 | R24: 240 | S24: 100000 | T24: 8500000 | U24: 100000 | V24: 100000 | W24: 100000 | X24: 100000 | Y24: 100000 | Z24: 100000 | AA24: 100000 | AB24: 100000 | AC24: =T24+SUM(U24:AB24) -> 9300000 | AD24: =Q24-AC24 -> 14700000 | AE24: =IF(O24="Aktif",AB24,0) -> 100000 | AF24: =IF(AE24>0,MAX(0,AD24)/AE24,0) -> 147 | AG24: =IF($O24="Aktif",MAX(0,MIN($AE24,$AD24-0)),0) -> 100000 | AH24: =IF($O24="Aktif",MAX(0,MIN($AE24,$AD24-SUM($AG24:AG24))),0) -> 100000 | AI24: =IF($O24="Aktif",MAX(0,MIN($AE24,$AD24-SUM($AG24:AH24))),0) -> 100000 | AJ24: =IF($O24="Aktif",MAX(0,MIN($AE24,$AD24-SUM($AG24:AI24))),0) -> 100000 | AK24: =IF($O24="Aktif",MAX(0,MIN($AE24,$AD24-SUM($AG24:AJ24))),0) -> 100000 | AL24: =IF($O24="Aktif",MAX(0,MIN($AE24,$AD24-SUM($AG24:AK24))),0) -> 100000 | AM24: =IF($O24="Aktif",MAX(0,MIN($AE24,$AD24-SUM($AG24:AL24))),0) -> 100000 | AN24: =IF($O24="Aktif",MAX(0,MIN($AE24,$AD24-SUM($AG24:AM24))),0) -> 100000 | AO24: =IF($O24="Aktif",MAX(0,MIN($AE24,$AD24-SUM($AG24:AN24))),0) -> 100000 | ... AV24: =IF($O24="Aktif",MAX(0,MIN($AE24,$AD24-SUM($AG24:AU24))),0) -> 100000 | AW24: =SUM(AG24:AV24) -> 1600000 | AX24: =AD24-AW24 -> 13100000
A25: 19 | B25: FA Bangunan | C25: 26 | D25: Buildings | E25: Bangunan | F25: 1201-001 | G25: 1202-001 | H25: 6500-001 | I25: Depreciation Expenses | K25: GD.0019 | L25: 44114 | M25: Material Time line 1 dan 3 | N25: Reimbursement pembelian material time line 1 dan 3 utk area kompressor project Nabati | O25: Aktif | P25: 1 | Q25: 11913500 | R25: 240 | S25: 49639.583 | T25: 3127293.8 | U25: 49639.583 | V25: 49639.583 | W25: 49639.583 | X25: 49639.583 | Y25: 49639.583 | Z25: 49639.583 | AA25: 49639.583 | AB25: 49639.583 | AC25: =T25+SUM(U25:AB25) -> 3524410.4 | AD25: =Q25-AC25 -> 8389089.6 | AE25: =IF(O25="Aktif",AB25,0) -> 49639.583 | AF25: =IF(AE25>0,MAX(0,AD25)/AE25,0) -> 169 | AG25: =IF($O25="Aktif",MAX(0,MIN($AE25,$AD25-0)),0) -> 49639.583 | AH25: =IF($O25="Aktif",MAX(0,MIN($AE25,$AD25-SUM($AG25:AG25))),0) -> 49639.583 | AI25: =IF($O25="Aktif",MAX(0,MIN($AE25,$AD25-SUM($AG25:AH25))),0) -> 49639.583 | AJ25: =IF($O25="Aktif",MAX(0,MIN($AE25,$AD25-SUM($AG25:AI25))),0) -> 49639.583 | AK25: =IF($O25="Aktif",MAX(0,MIN($AE25,$AD25-SUM($AG25:AJ25))),0) -> 49639.583 | AL25: =IF($O25="Aktif",MAX(0,MIN($AE25,$AD25-SUM($AG25:AK25))),0) -> 49639.583 | AM25: =IF($O25="Aktif",MAX(0,MIN($AE25,$AD25-SUM($AG25:AL25))),0) -> 49639.583 | AN25: =IF($O25="Aktif",MAX(0,MIN($AE25,$AD25-SUM($AG25:AM25))),0) -> 49639.583 | AO25: =IF($O25="Aktif",MAX(0,MIN($AE25,$AD25-SUM($AG25:AN25))),0) -> 49639.583 | ... AV25: =IF($O25="Aktif",MAX(0,MIN($AE25,$AD25-SUM($AG25:AU25))),0) -> 49639.583 | AW25: =SUM(AG25:AV25) -> 794233.33 | AX25: =AD25-AW25 -> 7594856.3
A26: 20 | B26: FA Bangunan | C26: 27 | D26: Buildings | E26: Bangunan | F26: 1201-001 | G26: 1202-001 | H26: 6500-001 | I26: Depreciation Expenses | K26: GD.0020 | L26: 44165 | M26: Pembangunan Ruangan Panel | N26: CV Koronka Nusantara, Pembuatan Ruang Panel Project Nabati 23/11/20 | O26: Aktif | P26: 1 | Q26: 99680000 | R26: 240 | S26: 415333.33 | T26: 25750667 | U26: 415333.33 | V26: 415333.33 | W26: 415333.33 | X26: 415333.33 | Y26: 415333.33 | Z26: 415333.33 | AA26: 415333.33 | AB26: 415333.33 | AC26: =T26+SUM(U26:AB26) -> 29073333 | AD26: =Q26-AC26 -> 70606667 | AE26: =IF(O26="Aktif",AB26,0) -> 415333.33 | AF26: =IF(AE26>0,MAX(0,AD26)/AE26,0) -> 170 | AG26: =IF($O26="Aktif",MAX(0,MIN($AE26,$AD26-0)),0) -> 415333.33 | AH26: =IF($O26="Aktif",MAX(0,MIN($AE26,$AD26-SUM($AG26:AG26))),0) -> 415333.33 | AI26: =IF($O26="Aktif",MAX(0,MIN($AE26,$AD26-SUM($AG26:AH26))),0) -> 415333.33 | AJ26: =IF($O26="Aktif",MAX(0,MIN($AE26,$AD26-SUM($AG26:AI26))),0) -> 415333.33 | AK26: =IF($O26="Aktif",MAX(0,MIN($AE26,$AD26-SUM($AG26:AJ26))),0) -> 415333.33 | AL26: =IF($O26="Aktif",MAX(0,MIN($AE26,$AD26-SUM($AG26:AK26))),0) -> 415333.33 | AM26: =IF($O26="Aktif",MAX(0,MIN($AE26,$AD26-SUM($AG26:AL26))),0) -> 415333.33 | AN26: =IF($O26="Aktif",MAX(0,MIN($AE26,$AD26-SUM($AG26:AM26))),0) -> 415333.33 | AO26: =IF($O26="Aktif",MAX(0,MIN($AE26,$AD26-SUM($AG26:AN26))),0) -> 415333.33 | ... AV26: =IF($O26="Aktif",MAX(0,MIN($AE26,$AD26-SUM($AG26:AU26))),0) -> 415333.33 | AW26: =SUM(AG26:AV26) -> 6645333.3 | AX26: =AD26-AW26 -> 63961333
A27: 21 | B27: FA Bangunan | C27: 28 | D27: Buildings | E27: Bangunan | F27: 1201-001 | G27: 1202-001 | H27: 6500-001 | I27: Depreciation Expenses | K27: GD.0021 | L27: 44613 | M27: Pekerjaan pembuatan ruang Decanter | N27: Karya Mandiri, Pekerjaan pembuatan ruang Decanter, 21/2/22 Material | O27: Aktif | P27: 1 | Q27: 12311500 | R27: 240 | S27: 51297.917 | T27: 2411002.1 | U27: 51297.917 | V27: 51297.917 | W27: 51297.917 | X27: 51297.917 | Y27: 51297.917 | Z27: 51297.917 | AA27: 51297.917 | AB27: 51297.917 | AC27: =T27+SUM(U27:AB27) -> 2821385.4 | AD27: =Q27-AC27 -> 9490114.6 | AE27: =IF(O27="Aktif",AB27,0) -> 51297.917 | AF27: =IF(AE27>0,MAX(0,AD27)/AE27,0) -> 185 | AG27: =IF($O27="Aktif",MAX(0,MIN($AE27,$AD27-0)),0) -> 51297.917 | AH27: =IF($O27="Aktif",MAX(0,MIN($AE27,$AD27-SUM($AG27:AG27))),0) -> 51297.917 | AI27: =IF($O27="Aktif",MAX(0,MIN($AE27,$AD27-SUM($AG27:AH27))),0) -> 51297.917 | AJ27: =IF($O27="Aktif",MAX(0,MIN($AE27,$AD27-SUM($AG27:AI27))),0) -> 51297.917 | AK27: =IF($O27="Aktif",MAX(0,MIN($AE27,$AD27-SUM($AG27:AJ27))),0) -> 51297.917 | AL27: =IF($O27="Aktif",MAX(0,MIN($AE27,$AD27-SUM($AG27:AK27))),0) -> 51297.917 | AM27: =IF($O27="Aktif",MAX(0,MIN($AE27,$AD27-SUM($AG27:AL27))),0) -> 51297.917 | AN27: =IF($O27="Aktif",MAX(0,MIN($AE27,$AD27-SUM($AG27:AM27))),0) -> 51297.917 | AO27: =IF($O27="Aktif",MAX(0,MIN($AE27,$AD27-SUM($AG27:AN27))),0) -> 51297.917 | ... AV27: =IF($O27="Aktif",MAX(0,MIN($AE27,$AD27-SUM($AG27:AU27))),0) -> 51297.917 | AW27: =SUM(AG27:AV27) -> 820766.67 | AX27: =AD27-AW27 -> 8669347.9
A28: 22 | B28: FA Bangunan | C28: 29 | D28: Buildings | E28: Bangunan | F28: 1201-001 | G28: 1202-001 | H28: 6500-001 | I28: Depreciation Expenses | K28: GD.0022 | L28: 44623 | M28: Ducting Line CF 1 | N28: Cipta Mandiri,Pembuatan Ducting Line CF 1, -PPh 21 2,5%, 03/03/22 - Material | O28: Aktif | P28: 1 | Q28: 28200000 | R28: 240 | S28: 117500 | T28: 5405000 | U28: 117500 | V28: 117500 | W28: 117500 | X28: 117500 | Y28: 117500 | Z28: 117500 | AA28: 117500 | AB28: 117500 | AC28: =T28+SUM(U28:AB28) -> 6345000 | AD28: =Q28-AC28 -> 21855000 | AE28: =IF(O28="Aktif",AB28,0) -> 117500 | AF28: =IF(AE28>0,MAX(0,AD28)/AE28,0) -> 186 | AG28: =IF($O28="Aktif",MAX(0,MIN($AE28,$AD28-0)),0) -> 117500 | AH28: =IF($O28="Aktif",MAX(0,MIN($AE28,$AD28-SUM($AG28:AG28))),0) -> 117500 | AI28: =IF($O28="Aktif",MAX(0,MIN($AE28,$AD28-SUM($AG28:AH28))),0) -> 117500 | AJ28: =IF($O28="Aktif",MAX(0,MIN($AE28,$AD28-SUM($AG28:AI28))),0) -> 117500 | AK28: =IF($O28="Aktif",MAX(0,MIN($AE28,$AD28-SUM($AG28:AJ28))),0) -> 117500 | AL28: =IF($O28="Aktif",MAX(0,MIN($AE28,$AD28-SUM($AG28:AK28))),0) -> 117500 | AM28: =IF($O28="Aktif",MAX(0,MIN($AE28,$AD28-SUM($AG28:AL28))),0) -> 117500 | AN28: =IF($O28="Aktif",MAX(0,MIN($AE28,$AD28-SUM($AG28:AM28))),0) -> 117500 | AO28: =IF($O28="Aktif",MAX(0,MIN($AE28,$AD28-SUM($AG28:AN28))),0) -> 117500 | ... AV28: =IF($O28="Aktif",MAX(0,MIN($AE28,$AD28-SUM($AG28:AU28))),0) -> 117500 | AW28: =SUM(AG28:AV28) -> 1880000 | AX28: =AD28-AW28 -> 19975000
A29: 23 | B29: FA Bangunan | C29: 30 | D29: Buildings | E29: Bangunan | F29: 1201-001 | G29: 1202-001 | H29: 6500-001 | I29: Depreciation Expenses | K29: GD.0023 | L29: 44671 | M29: Tempat Kerja & Ducting | N29: Karya Mandiri, Pembuatan Tempat Kerja dan Ducting, -PPh 21 3%, 19/01/22 Jasa | O29: Aktif | P29: 1 | Q29: 30441800 | R29: 240 | S29: 126840.83 | T29: 5707837.5 | U29: 126840.83 | V29: 126840.83 | W29: 126840.83 | X29: 126840.83 | Y29: 126840.83 | Z29: 126840.83 | AA29: 126840.83 | AB29: 126840.83 | AC29: =T29+SUM(U29:AB29) -> 6722564.2 | AD29: =Q29-AC29 -> 23719236 | AE29: =IF(O29="Aktif",AB29,0) -> 126840.83 | AF29: =IF(AE29>0,MAX(0,AD29)/AE29,0) -> 187 | AG29: =IF($O29="Aktif",MAX(0,MIN($AE29,$AD29-0)),0) -> 126840.83 | AH29: =IF($O29="Aktif",MAX(0,MIN($AE29,$AD29-SUM($AG29:AG29))),0) -> 126840.83 | AI29: =IF($O29="Aktif",MAX(0,MIN($AE29,$AD29-SUM($AG29:AH29))),0) -> 126840.83 | AJ29: =IF($O29="Aktif",MAX(0,MIN($AE29,$AD29-SUM($AG29:AI29))),0) -> 126840.83 | AK29: =IF($O29="Aktif",MAX(0,MIN($AE29,$AD29-SUM($AG29:AJ29))),0) -> 126840.83 | AL29: =IF($O29="Aktif",MAX(0,MIN($AE29,$AD29-SUM($AG29:AK29))),0) -> 126840.83 | AM29: =IF($O29="Aktif",MAX(0,MIN($AE29,$AD29-SUM($AG29:AL29))),0) -> 126840.83 | AN29: =IF($O29="Aktif",MAX(0,MIN($AE29,$AD29-SUM($AG29:AM29))),0) -> 126840.83 | AO29: =IF($O29="Aktif",MAX(0,MIN($AE29,$AD29-SUM($AG29:AN29))),0) -> 126840.83 | ... AV29: =IF($O29="Aktif",MAX(0,MIN($AE29,$AD29-SUM($AG29:AU29))),0) -> 126840.83 | AW29: =SUM(AG29:AV29) -> 2029453.3 | AX29: =AD29-AW29 -> 21689783
A30: 24 | B30: FA Bangunan | C30: 31 | D30: Buildings | E30: Bangunan | F30: 1201-001 | G30: 1202-001 | H30: 6500-001 | I30: Depreciation Expenses | K30: GD.0024 | L30: 44994 | M30: Pekerjaan Pembangunan Pabrik Kendal-Semarang | N30: PT Adidi Citra Estetika, Pekerjaan Pembangunan Pabrik Kendal-Semarang, +PPN 11%, 09/03/23 | O30: Aktif | P30: 1 | Q30: 2018391185 | R30: 240 | S30: 8409963.3 | T30: 2.8593875e+08 | U30: 8409963.3 | V30: 8409963.3 | W30: 8409963.3 | X30: 8409963.3 | Y30: 8409963.3 | Z30: 8409963.3 | AA30: 8409963.3 | AB30: 8409963.3 | AC30: =T30+SUM(U30:AB30) -> 3.5321846e+08 | AD30: =Q30-AC30 -> 1.6651727e+09 | AE30: =IF(O30="Aktif",AB30,0) -> 8409963.3 | AF30: =IF(AE30>0,MAX(0,AD30)/AE30,0) -> 198 | AG30: =IF($O30="Aktif",MAX(0,MIN($AE30,$AD30-0)),0) -> 8409963.3 | AH30: =IF($O30="Aktif",MAX(0,MIN($AE30,$AD30-SUM($AG30:AG30))),0) -> 8409963.3 | AI30: =IF($O30="Aktif",MAX(0,MIN($AE30,$AD30-SUM($AG30:AH30))),0) -> 8409963.3 | AJ30: =IF($O30="Aktif",MAX(0,MIN($AE30,$AD30-SUM($AG30:AI30))),0) -> 8409963.3 | AK30: =IF($O30="Aktif",MAX(0,MIN($AE30,$AD30-SUM($AG30:AJ30))),0) -> 8409963.3 | AL30: =IF($O30="Aktif",MAX(0,MIN($AE30,$AD30-SUM($AG30:AK30))),0) -> 8409963.3 | AM30: =IF($O30="Aktif",MAX(0,MIN($AE30,$AD30-SUM($AG30:AL30))),0) -> 8409963.3 | AN30: =IF($O30="Aktif",MAX(0,MIN($AE30,$AD30-SUM($AG30:AM30))),0) -> 8409963.3 | AO30: =IF($O30="Aktif",MAX(0,MIN($AE30,$AD30-SUM($AG30:AN30))),0) -> 8409963.3 | ... AV30: =IF($O30="Aktif",MAX(0,MIN($AE30,$AD30-SUM($AG30:AU30))),0) -> 8409963.3 | AW30: =SUM(AG30:AV30) -> 1.3455941e+08 | AX30: =AD30-AW30 -> 1.5306133e+09
A31: 25 | B31: FA Bangunan | C31: 32 | D31: Buildings | E31: Bangunan | F31: 1201-001 | G31: 1202-001 | H31: 6500-001 | I31: Depreciation Expenses | K31: GD.0025 | L31: 45216 | M31: Material Cor | N31: CV Mandiri Jaya Sejahtera, Material Cor Rp 42.500.000+ PPn 11% 17/10/23 | O31: Aktif | P31: 1 | Q31: 85000000 | R31: 240 | S31: 354166.67 | T31: 9562500 | U31: 354166.67 | V31: 354166.67 | W31: 354166.67 | X31: 354166.67 | Y31: 354166.67 | Z31: 354166.67 | AA31: 354166.67 | AB31: 354166.67 | AC31: =T31+SUM(U31:AB31) -> 12395833 | AD31: =Q31-AC31 -> 72604167 | AE31: =IF(O31="Aktif",AB31,0) -> 354166.67 | AF31: =IF(AE31>0,MAX(0,AD31)/AE31,0) -> 205 | AG31: =IF($O31="Aktif",MAX(0,MIN($AE31,$AD31-0)),0) -> 354166.67 | AH31: =IF($O31="Aktif",MAX(0,MIN($AE31,$AD31-SUM($AG31:AG31))),0) -> 354166.67 | AI31: =IF($O31="Aktif",MAX(0,MIN($AE31,$AD31-SUM($AG31:AH31))),0) -> 354166.67 | AJ31: =IF($O31="Aktif",MAX(0,MIN($AE31,$AD31-SUM($AG31:AI31))),0) -> 354166.67 | AK31: =IF($O31="Aktif",MAX(0,MIN($AE31,$AD31-SUM($AG31:AJ31))),0) -> 354166.67 | AL31: =IF($O31="Aktif",MAX(0,MIN($AE31,$AD31-SUM($AG31:AK31))),0) -> 354166.67 | AM31: =IF($O31="Aktif",MAX(0,MIN($AE31,$AD31-SUM($AG31:AL31))),0) -> 354166.67 | AN31: =IF($O31="Aktif",MAX(0,MIN($AE31,$AD31-SUM($AG31:AM31))),0) -> 354166.67 | AO31: =IF($O31="Aktif",MAX(0,MIN($AE31,$AD31-SUM($AG31:AN31))),0) -> 354166.67 | ... AV31: =IF($O31="Aktif",MAX(0,MIN($AE31,$AD31-SUM($AG31:AU31))),0) -> 354166.67 | AW31: =SUM(AG31:AV31) -> 5666666.7 | AX31: =AD31-AW31 -> 66937500
A32: 26 | B32: FA Bangunan | C32: 33 | D32: Buildings | E32: Bangunan | F32: 1201-001 | G32: 1202-001 | H32: 6500-001 | I32: Depreciation Expenses | K32: GD.0026 | L32: 15 Jun 2024 | M32: Material Cor 227M | O32: Aktif | P32: 1 | Q32: 80000000 | R32: 240 | S32: 333333.33 | T32: 6333333.3 | U32: 333333.33 | V32: 333333.33 | W32: 333333.33 | X32: 333333.33 | Y32: 333333.33 | Z32: 333333.33 | AA32: 333333.33 | AB32: 333333.33 | AC32: =T32+SUM(U32:AB32) -> 9000000 | AD32: =Q32-AC32 -> 71000000 | AE32: =IF(O32="Aktif",AB32,0) -> 333333.33 | AF32: =IF(AE32>0,MAX(0,AD32)/AE32,0) -> 213 | AG32: =IF($O32="Aktif",MAX(0,MIN($AE32,$AD32-0)),0) -> 333333.33 | AH32: =IF($O32="Aktif",MAX(0,MIN($AE32,$AD32-SUM($AG32:AG32))),0) -> 333333.33 | AI32: =IF($O32="Aktif",MAX(0,MIN($AE32,$AD32-SUM($AG32:AH32))),0) -> 333333.33 | AJ32: =IF($O32="Aktif",MAX(0,MIN($AE32,$AD32-SUM($AG32:AI32))),0) -> 333333.33 | AK32: =IF($O32="Aktif",MAX(0,MIN($AE32,$AD32-SUM($AG32:AJ32))),0) -> 333333.33 | AL32: =IF($O32="Aktif",MAX(0,MIN($AE32,$AD32-SUM($AG32:AK32))),0) -> 333333.33 | AM32: =IF($O32="Aktif",MAX(0,MIN($AE32,$AD32-SUM($AG32:AL32))),0) -> 333333.33 | AN32: =IF($O32="Aktif",MAX(0,MIN($AE32,$AD32-SUM($AG32:AM32))),0) -> 333333.33 | AO32: =IF($O32="Aktif",MAX(0,MIN($AE32,$AD32-SUM($AG32:AN32))),0) -> 333333.33 | ... AV32: =IF($O32="Aktif",MAX(0,MIN($AE32,$AD32-SUM($AG32:AU32))),0) -> 333333.33 | AW32: =SUM(AG32:AV32) -> 5333333.3 | AX32: =AD32-AW32 -> 65666667
A33: 27 | B33: FA Bangunan | C33: 34 | D33: Buildings | E33: Bangunan | F33: 1201-001 | G33: 1202-001 | H33: 6500-001 | I33: Depreciation Expenses | K33: GD.0027 | L33: 45883 | M33: Material Ducting dan Hood Mesin BF Spiral | O33: Aktif | P33: 1 | Q33: 155350000 | R33: 240 | S33: 647291.67 | T33: 3236458.3 | U33: 647291.67 | V33: 647291.67 | W33: 647291.67 | X33: 647291.67 | Y33: 647291.67 | Z33: 647291.67 | AA33: 647291.67 | AB33: 647291.67 | AC33: =T33+SUM(U33:AB33) -> 8414791.7 | AD33: =Q33-AC33 -> 1.4693521e+08 | AE33: =IF(O33="Aktif",AB33,0) -> 647291.67 | AF33: =IF(AE33>0,MAX(0,AD33)/AE33,0) -> 227 | AG33: =IF($O33="Aktif",MAX(0,MIN($AE33,$AD33-0)),0) -> 647291.67 | AH33: =IF($O33="Aktif",MAX(0,MIN($AE33,$AD33-SUM($AG33:AG33))),0) -> 647291.67 | AI33: =IF($O33="Aktif",MAX(0,MIN($AE33,$AD33-SUM($AG33:AH33))),0) -> 647291.67 | AJ33: =IF($O33="Aktif",MAX(0,MIN($AE33,$AD33-SUM($AG33:AI33))),0) -> 647291.67 | AK33: =IF($O33="Aktif",MAX(0,MIN($AE33,$AD33-SUM($AG33:AJ33))),0) -> 647291.67 | AL33: =IF($O33="Aktif",MAX(0,MIN($AE33,$AD33-SUM($AG33:AK33))),0) -> 647291.67 | AM33: =IF($O33="Aktif",MAX(0,MIN($AE33,$AD33-SUM($AG33:AL33))),0) -> 647291.67 | AN33: =IF($O33="Aktif",MAX(0,MIN($AE33,$AD33-SUM($AG33:AM33))),0) -> 647291.67 | AO33: =IF($O33="Aktif",MAX(0,MIN($AE33,$AD33-SUM($AG33:AN33))),0) -> 647291.67 | ... AV33: =IF($O33="Aktif",MAX(0,MIN($AE33,$AD33-SUM($AG33:AU33))),0) -> 647291.67 | AW33: =SUM(AG33:AV33) -> 10356667 | AX33: =AD33-AW33 -> 1.3657854e+08
A34: 28 | B34: FA Bangunan | C34: 35 | D34: Buildings | E34: Bangunan | F34: 1201-001 | G34: 1202-001 | H34: 6500-001 | I34: Depreciation Expenses | K34: GD.0028 | L34: 46249 | M34: Ducting dan Hood Unit 1B | N34: Ducting dan Hood Unit 1B | O34: Aktif | P34: 1 | Q34: 89800000 | R34: 240 | S34: 374166.67 | T34: 0 | U34: 0 | V34: 0 | W34: 0 | X34: 0 | Y34: 0 | Z34: 0 | AA34: 0 | AB34: 374166.67 | AC34: =T34+SUM(U34:AB34) -> 374166.67 | AD34: =Q34-AC34 -> 89425833 | AE34: =IF(O34="Aktif",AB34,0) -> 374166.67 | AF34: =IF(AE34>0,MAX(0,AD34)/AE34,0) -> 239 | AG34: =IF($O34="Aktif",MAX(0,MIN($AE34,$AD34-0)),0) -> 374166.67 | AH34: =IF($O34="Aktif",MAX(0,MIN($AE34,$AD34-SUM($AG34:AG34))),0) -> 374166.67 | AI34: =IF($O34="Aktif",MAX(0,MIN($AE34,$AD34-SUM($AG34:AH34))),0) -> 374166.67 | AJ34: =IF($O34="Aktif",MAX(0,MIN($AE34,$AD34-SUM($AG34:AI34))),0) -> 374166.67 | AK34: =IF($O34="Aktif",MAX(0,MIN($AE34,$AD34-SUM($AG34:AJ34))),0) -> 374166.67 | AL34: =IF($O34="Aktif",MAX(0,MIN($AE34,$AD34-SUM($AG34:AK34))),0) -> 374166.67 | AM34: =IF($O34="Aktif",MAX(0,MIN($AE34,$AD34-SUM($AG34:AL34))),0) -> 374166.67 | AN34: =IF($O34="Aktif",MAX(0,MIN($AE34,$AD34-SUM($AG34:AM34))),0) -> 374166.67 | AO34: =IF($O34="Aktif",MAX(0,MIN($AE34,$AD34-SUM($AG34:AN34))),0) -> 374166.67 | ... AV34: =IF($O34="Aktif",MAX(0,MIN($AE34,$AD34-SUM($AG34:AU34))),0) -> 374166.67 | AW34: =SUM(AG34:AV34) -> 5986666.7 | AX34: =AD34-AW34 -> 83439167
A35: 29 | B35: FA Kendaraan | C35: 8 | D35: Vehicles | E35: Gol 1 | F35: 1201-003 | G35: 1202-003 | H35: 6500-003 | I35: Depreciation Expenses | L35: 09-11-2010 | M35: Honda Supra Fit Thn 2003 H 3642 Ja | N35: Honda Supra Fit Thn 2003 H 3642 JA | O35: Aktif | P35: 1 | Q35: 5700000 | R35: 48 | S35: 0 | T35: 5700000 | U35: 0 | V35: 0 | W35: 0 | X35: 0 | Y35: 0 | Z35: 0 | AA35: 0 | AB35: 0 | AC35: =T35+SUM(U35:AB35) -> 5700000 | AD35: =Q35-AC35 -> 0 | AE35: =IF(O35="Aktif",AB35,0) -> 0 | AF35: =IF(AE35>0,MAX(0,AD35)/AE35,0) -> 0 | AG35: =IF($O35="Aktif",MAX(0,MIN($AE35,$AD35-0)),0) -> 0 | AH35: =IF($O35="Aktif",MAX(0,MIN($AE35,$AD35-SUM($AG35:AG35))),0) -> 0 | AI35: =IF($O35="Aktif",MAX(0,MIN($AE35,$AD35-SUM($AG35:AH35))),0) -> 0 | AJ35: =IF($O35="Aktif",MAX(0,MIN($AE35,$AD35-SUM($AG35:AI35))),0) -> 0 | AK35: =IF($O35="Aktif",MAX(0,MIN($AE35,$AD35-SUM($AG35:AJ35))),0) -> 0 | AL35: =IF($O35="Aktif",MAX(0,MIN($AE35,$AD35-SUM($AG35:AK35))),0) -> 0 | AM35: =IF($O35="Aktif",MAX(0,MIN($AE35,$AD35-SUM($AG35:AL35))),0) -> 0 | AN35: =IF($O35="Aktif",MAX(0,MIN($AE35,$AD35-SUM($AG35:AM35))),0) -> 0 | AO35: =IF($O35="Aktif",MAX(0,MIN($AE35,$AD35-SUM($AG35:AN35))),0) -> 0 | ... AV35: =IF($O35="Aktif",MAX(0,MIN($AE35,$AD35-SUM($AG35:AU35))),0) -> 0 | AW35: =SUM(AG35:AV35) -> 0 | AX35: =AD35-AW35 -> 0
A36: 30 | B36: FA Kendaraan | C36: 9 | D36: Vehicles | E36: Gol 1 | F36: 1201-003 | G36: 1202-003 | H36: 6500-003 | I36: Depreciation Expenses | L36: 42035 | M36: Honda Supra Fit Thn 2003 H 3642 Ja | N36: Penjualan Motor Inventaris H 3642 JA 04 Desember 2014 | O36: Dijual | P36: 1 | Q36: -5700000 | R36: 48 | S36: 0 | T36: -5700000 | U36: 0 | V36: 0 | W36: 0 | X36: 0 | Y36: 0 | Z36: 0 | AA36: 0 | AB36: 0 | AC36: =T36+SUM(U36:AB36) -> -5700000 | AD36: =Q36-AC36 -> 0 | AE36: =IF(O36="Aktif",AB36,0) -> 0 | AF36: =IF(AE36>0,MAX(0,AD36)/AE36,0) -> 0 | AG36: =IF($O36="Aktif",MAX(0,MIN($AE36,$AD36-0)),0) -> 0 | AH36: =IF($O36="Aktif",MAX(0,MIN($AE36,$AD36-SUM($AG36:AG36))),0) -> 0 | AI36: =IF($O36="Aktif",MAX(0,MIN($AE36,$AD36-SUM($AG36:AH36))),0) -> 0 | AJ36: =IF($O36="Aktif",MAX(0,MIN($AE36,$AD36-SUM($AG36:AI36))),0) -> 0 | AK36: =IF($O36="Aktif",MAX(0,MIN($AE36,$AD36-SUM($AG36:AJ36))),0) -> 0 | AL36: =IF($O36="Aktif",MAX(0,MIN($AE36,$AD36-SUM($AG36:AK36))),0) -> 0 | AM36: =IF($O36="Aktif",MAX(0,MIN($AE36,$AD36-SUM($AG36:AL36))),0) -> 0 | AN36: =IF($O36="Aktif",MAX(0,MIN($AE36,$AD36-SUM($AG36:AM36))),0) -> 0 | AO36: =IF($O36="Aktif",MAX(0,MIN($AE36,$AD36-SUM($AG36:AN36))),0) -> 0 | ... AV36: =IF($O36="Aktif",MAX(0,MIN($AE36,$AD36-SUM($AG36:AU36))),0) -> 0 | AW36: =SUM(AG36:AV36) -> 0 | AX36: =AD36-AW36 -> 0
A37: 31 | B37: FA Kendaraan | C37: 10 | D37: Vehicles | E37: Gol 1 | F37: 1201-003 | G37: 1202-003 | H37: 6500-003 | I37: Depreciation Expenses | L37: 26-03-2010 | M37: Daihatsu Xenia B 1213 TKB | N37: Daihatsu Xenia B1213TKB | O37: Aktif | P37: 1 | Q37: 120500000 | R37: 48 | S37: 0 | T37: 120500000 | U37: 0 | V37: 0 | W37: 0 | X37: 0 | Y37: 0 | Z37: 0 | AA37: 0 | AB37: 0 | AC37: =T37+SUM(U37:AB37) -> 120500000 | AD37: =Q37-AC37 -> 0 | AE37: =IF(O37="Aktif",AB37,0) -> 0 | AF37: =IF(AE37>0,MAX(0,AD37)/AE37,0) -> 0 | AG37: =IF($O37="Aktif",MAX(0,MIN($AE37,$AD37-0)),0) -> 0 | AH37: =IF($O37="Aktif",MAX(0,MIN($AE37,$AD37-SUM($AG37:AG37))),0) -> 0 | AI37: =IF($O37="Aktif",MAX(0,MIN($AE37,$AD37-SUM($AG37:AH37))),0) -> 0 | AJ37: =IF($O37="Aktif",MAX(0,MIN($AE37,$AD37-SUM($AG37:AI37))),0) -> 0 | AK37: =IF($O37="Aktif",MAX(0,MIN($AE37,$AD37-SUM($AG37:AJ37))),0) -> 0 | AL37: =IF($O37="Aktif",MAX(0,MIN($AE37,$AD37-SUM($AG37:AK37))),0) -> 0 | AM37: =IF($O37="Aktif",MAX(0,MIN($AE37,$AD37-SUM($AG37:AL37))),0) -> 0 | AN37: =IF($O37="Aktif",MAX(0,MIN($AE37,$AD37-SUM($AG37:AM37))),0) -> 0 | AO37: =IF($O37="Aktif",MAX(0,MIN($AE37,$AD37-SUM($AG37:AN37))),0) -> 0 | ... AV37: =IF($O37="Aktif",MAX(0,MIN($AE37,$AD37-SUM($AG37:AU37))),0) -> 0 | AW37: =SUM(AG37:AV37) -> 0 | AX37: =AD37-AW37 -> 0
A38: 32 | B38: FA Kendaraan | C38: 11 | D38: Vehicles | E38: Gol 1 | F38: 1201-003 | G38: 1202-003 | H38: 6500-003 | I38: Depreciation Expenses | L38: 42064 | M38: Daihatsu Xenia B 1213 TKB | N38: Penjualan Inventaris Mobil Xenia B 1213 TKB Dijual Maret 2015 Rp 80 Jt | O38: Dijual | P38: 1 | Q38: -120500000 | R38: 48 | S38: 0 | T38: -120500000 | U38: 0 | V38: 0 | W38: 0 | X38: 0 | Y38: 0 | Z38: 0 | AA38: 0 | AB38: 0 | AC38: =T38+SUM(U38:AB38) -> -120500000 | AD38: =Q38-AC38 -> 0 | AE38: =IF(O38="Aktif",AB38,0) -> 0 | AF38: =IF(AE38>0,MAX(0,AD38)/AE38,0) -> 0 | AG38: =IF($O38="Aktif",MAX(0,MIN($AE38,$AD38-0)),0) -> 0 | AH38: =IF($O38="Aktif",MAX(0,MIN($AE38,$AD38-SUM($AG38:AG38))),0) -> 0 | AI38: =IF($O38="Aktif",MAX(0,MIN($AE38,$AD38-SUM($AG38:AH38))),0) -> 0 | AJ38: =IF($O38="Aktif",MAX(0,MIN($AE38,$AD38-SUM($AG38:AI38))),0) -> 0 | AK38: =IF($O38="Aktif",MAX(0,MIN($AE38,$AD38-SUM($AG38:AJ38))),0) -> 0 | AL38: =IF($O38="Aktif",MAX(0,MIN($AE38,$AD38-SUM($AG38:AK38))),0) -> 0 | AM38: =IF($O38="Aktif",MAX(0,MIN($AE38,$AD38-SUM($AG38:AL38))),0) -> 0 | AN38: =IF($O38="Aktif",MAX(0,MIN($AE38,$AD38-SUM($AG38:AM38))),0) -> 0 | AO38: =IF($O38="Aktif",MAX(0,MIN($AE38,$AD38-SUM($AG38:AN38))),0) -> 0 | ... AV38: =IF($O38="Aktif",MAX(0,MIN($AE38,$AD38-SUM($AG38:AU38))),0) -> 0 | AW38: =SUM(AG38:AV38) -> 0 | AX38: =AD38-AW38 -> 0
A39: 33 | B39: FA Kendaraan | C39: 12 | D39: Vehicles | E39: Gol 1 | F39: 1201-003 | G39: 1202-003 | H39: 6500-003 | I39: Depreciation Expenses | L39: 41353 | M39: Kijang Innova G/Manual | N39: Pembelian 1 unit Kijang Innova G/manual | O39: Aktif | P39: 1 | Q39: 232400000 | R39: 48 | S39: 0 | T39: 232400000 | U39: 0 | V39: 0 | W39: 0 | X39: 0 | Y39: 0 | Z39: 0 | AA39: 0 | AB39: 0 | AC39: =T39+SUM(U39:AB39) -> 232400000 | AD39: =Q39-AC39 -> 0 | AE39: =IF(O39="Aktif",AB39,0) -> 0 | AF39: =IF(AE39>0,MAX(0,AD39)/AE39,0) -> 0 | AG39: =IF($O39="Aktif",MAX(0,MIN($AE39,$AD39-0)),0) -> 0 | AH39: =IF($O39="Aktif",MAX(0,MIN($AE39,$AD39-SUM($AG39:AG39))),0) -> 0 | AI39: =IF($O39="Aktif",MAX(0,MIN($AE39,$AD39-SUM($AG39:AH39))),0) -> 0 | AJ39: =IF($O39="Aktif",MAX(0,MIN($AE39,$AD39-SUM($AG39:AI39))),0) -> 0 | AK39: =IF($O39="Aktif",MAX(0,MIN($AE39,$AD39-SUM($AG39:AJ39))),0) -> 0 | AL39: =IF($O39="Aktif",MAX(0,MIN($AE39,$AD39-SUM($AG39:AK39))),0) -> 0 | AM39: =IF($O39="Aktif",MAX(0,MIN($AE39,$AD39-SUM($AG39:AL39))),0) -> 0 | AN39: =IF($O39="Aktif",MAX(0,MIN($AE39,$AD39-SUM($AG39:AM39))),0) -> 0 | AO39: =IF($O39="Aktif",MAX(0,MIN($AE39,$AD39-SUM($AG39:AN39))),0) -> 0 | ... AV39: =IF($O39="Aktif",MAX(0,MIN($AE39,$AD39-SUM($AG39:AU39))),0) -> 0 | AW39: =SUM(AG39:AV39) -> 0 | AX39: =AD39-AW39 -> 0
A40: 34 | B40: FA Kendaraan | C40: 13 | D40: Vehicles | E40: Gol 1 | F40: 1201-003 | G40: 1202-003 | H40: 6500-003 | I40: Depreciation Expenses | L40: 43434 | M40: Kijang Innova G/Manual | N40: Penjualan mobil Kijang Innova G/manual B1907TZZ | O40: Dijual | P40: 1 | Q40: -232400000 | R40: 48 | S40: 0 | T40: -232400000 | U40: 0 | V40: 0 | W40: 0 | X40: 0 | Y40: 0 | Z40: 0 | AA40: 0 | AB40: 0 | AC40: =T40+SUM(U40:AB40) -> -232400000 | AD40: =Q40-AC40 -> 0 | AE40: =IF(O40="Aktif",AB40,0) -> 0 | AF40: =IF(AE40>0,MAX(0,AD40)/AE40,0) -> 0 | AG40: =IF($O40="Aktif",MAX(0,MIN($AE40,$AD40-0)),0) -> 0 | AH40: =IF($O40="Aktif",MAX(0,MIN($AE40,$AD40-SUM($AG40:AG40))),0) -> 0 | AI40: =IF($O40="Aktif",MAX(0,MIN($AE40,$AD40-SUM($AG40:AH40))),0) -> 0 | AJ40: =IF($O40="Aktif",MAX(0,MIN($AE40,$AD40-SUM($AG40:AI40))),0) -> 0 | AK40: =IF($O40="Aktif",MAX(0,MIN($AE40,$AD40-SUM($AG40:AJ40))),0) -> 0 | AL40: =IF($O40="Aktif",MAX(0,MIN($AE40,$AD40-SUM($AG40:AK40))),0) -> 0 | AM40: =IF($O40="Aktif",MAX(0,MIN($AE40,$AD40-SUM($AG40:AL40))),0) -> 0 | AN40: =IF($O40="Aktif",MAX(0,MIN($AE40,$AD40-SUM($AG40:AM40))),0) -> 0 | AO40: =IF($O40="Aktif",MAX(0,MIN($AE40,$AD40-SUM($AG40:AN40))),0) -> 0 | ... AV40: =IF($O40="Aktif",MAX(0,MIN($AE40,$AD40-SUM($AG40:AU40))),0) -> 0 | AW40: =SUM(AG40:AV40) -> 0 | AX40: =AD40-AW40 -> 0
A41: 35 | B41: FA Kendaraan | C41: 14 | D41: Vehicles | E41: Gol 1 | F41: 1201-003 | G41: 1202-003 | H41: 6500-003 | I41: Depreciation Expenses | J41: KND.01/09 | L41: 02-01-2009 | M41: Truk 9822 Ar - 9729 Aq- 9199 Ai | N41: Truk 9822AR - 9729AQ- 9199 AI | O41: Aktif | P41: 1 | Q41: 49046357 | R41: 48 | S41: 0 | T41: 49046357 | U41: 0 | V41: 0 | W41: 0 | X41: 0 | Y41: 0 | Z41: 0 | AA41: 0 | AB41: 0 | AC41: =T41+SUM(U41:AB41) -> 49046357 | AD41: =Q41-AC41 -> 0 | AE41: =IF(O41="Aktif",AB41,0) -> 0 | AF41: =IF(AE41>0,MAX(0,AD41)/AE41,0) -> 0 | AG41: =IF($O41="Aktif",MAX(0,MIN($AE41,$AD41-0)),0) -> 0 | AH41: =IF($O41="Aktif",MAX(0,MIN($AE41,$AD41-SUM($AG41:AG41))),0) -> 0 | AI41: =IF($O41="Aktif",MAX(0,MIN($AE41,$AD41-SUM($AG41:AH41))),0) -> 0 | AJ41: =IF($O41="Aktif",MAX(0,MIN($AE41,$AD41-SUM($AG41:AI41))),0) -> 0 | AK41: =IF($O41="Aktif",MAX(0,MIN($AE41,$AD41-SUM($AG41:AJ41))),0) -> 0 | AL41: =IF($O41="Aktif",MAX(0,MIN($AE41,$AD41-SUM($AG41:AK41))),0) -> 0 | AM41: =IF($O41="Aktif",MAX(0,MIN($AE41,$AD41-SUM($AG41:AL41))),0) -> 0 | AN41: =IF($O41="Aktif",MAX(0,MIN($AE41,$AD41-SUM($AG41:AM41))),0) -> 0 | AO41: =IF($O41="Aktif",MAX(0,MIN($AE41,$AD41-SUM($AG41:AN41))),0) -> 0 | ... AV41: =IF($O41="Aktif",MAX(0,MIN($AE41,$AD41-SUM($AG41:AU41))),0) -> 0 | AW41: =SUM(AG41:AV41) -> 0 | AX41: =AD41-AW41 -> 0
A42: 36 | B42: FA Kendaraan | C42: 15 | D42: Vehicles | E42: Gol 1 | F42: 1201-003 | G42: 1202-003 | H42: 6500-003 | I42: Depreciation Expenses | J42: KND.01/10 | L42: 29-03-2010 | M42: Daihatsu Granmax B 1450 TKB | N42: Daihatsu Granmax B1450TKB | O42: Aktif | P42: 1 | Q42: 105100000 | R42: 48 | S42: 0 | T42: 105100000 | U42: 0 | V42: 0 | W42: 0 | X42: 0 | Y42: 0 | Z42: 0 | AA42: 0 | AB42: 0 | AC42: =T42+SUM(U42:AB42) -> 105100000 | AD42: =Q42-AC42 -> 0 | AE42: =IF(O42="Aktif",AB42,0) -> 0 | AF42: =IF(AE42>0,MAX(0,AD42)/AE42,0) -> 0 | AG42: =IF($O42="Aktif",MAX(0,MIN($AE42,$AD42-0)),0) -> 0 | AH42: =IF($O42="Aktif",MAX(0,MIN($AE42,$AD42-SUM($AG42:AG42))),0) -> 0 | AI42: =IF($O42="Aktif",MAX(0,MIN($AE42,$AD42-SUM($AG42:AH42))),0) -> 0 | AJ42: =IF($O42="Aktif",MAX(0,MIN($AE42,$AD42-SUM($AG42:AI42))),0) -> 0 | AK42: =IF($O42="Aktif",MAX(0,MIN($AE42,$AD42-SUM($AG42:AJ42))),0) -> 0 | AL42: =IF($O42="Aktif",MAX(0,MIN($AE42,$AD42-SUM($AG42:AK42))),0) -> 0 | AM42: =IF($O42="Aktif",MAX(0,MIN($AE42,$AD42-SUM($AG42:AL42))),0) -> 0 | AN42: =IF($O42="Aktif",MAX(0,MIN($AE42,$AD42-SUM($AG42:AM42))),0) -> 0 | AO42: =IF($O42="Aktif",MAX(0,MIN($AE42,$AD42-SUM($AG42:AN42))),0) -> 0 | ... AV42: =IF($O42="Aktif",MAX(0,MIN($AE42,$AD42-SUM($AG42:AU42))),0) -> 0 | AW42: =SUM(AG42:AV42) -> 0 | AX42: =AD42-AW42 -> 0
A43: 37 | B43: FA Kendaraan | C43: 16 | D43: Vehicles | E43: Gol 1 | F43: 1201-003 | G43: 1202-003 | H43: 6500-003 | I43: Depreciation Expenses | J43: KND.01/11 | L43: 40544 | M43: Daihatsu Granmax Pick-Up B 9862 TAA | N43: Daihatsu Granmax pick-up B9862TAA | O43: Aktif | P43: 1 | Q43: 85400000 | R43: 48 | S43: 0 | T43: 85400000 | U43: 0 | V43: 0 | W43: 0 | X43: 0 | Y43: 0 | Z43: 0 | AA43: 0 | AB43: 0 | AC43: =T43+SUM(U43:AB43) -> 85400000 | AD43: =Q43-AC43 -> 0 | AE43: =IF(O43="Aktif",AB43,0) -> 0 | AF43: =IF(AE43>0,MAX(0,AD43)/AE43,0) -> 0 | AG43: =IF($O43="Aktif",MAX(0,MIN($AE43,$AD43-0)),0) -> 0 | AH43: =IF($O43="Aktif",MAX(0,MIN($AE43,$AD43-SUM($AG43:AG43))),0) -> 0 | AI43: =IF($O43="Aktif",MAX(0,MIN($AE43,$AD43-SUM($AG43:AH43))),0) -> 0 | AJ43: =IF($O43="Aktif",MAX(0,MIN($AE43,$AD43-SUM($AG43:AI43))),0) -> 0 | AK43: =IF($O43="Aktif",MAX(0,MIN($AE43,$AD43-SUM($AG43:AJ43))),0) -> 0 | AL43: =IF($O43="Aktif",MAX(0,MIN($AE43,$AD43-SUM($AG43:AK43))),0) -> 0 | AM43: =IF($O43="Aktif",MAX(0,MIN($AE43,$AD43-SUM($AG43:AL43))),0) -> 0 | AN43: =IF($O43="Aktif",MAX(0,MIN($AE43,$AD43-SUM($AG43:AM43))),0) -> 0 | AO43: =IF($O43="Aktif",MAX(0,MIN($AE43,$AD43-SUM($AG43:AN43))),0) -> 0 | ... AV43: =IF($O43="Aktif",MAX(0,MIN($AE43,$AD43-SUM($AG43:AU43))),0) -> 0 | AW43: =SUM(AG43:AV43) -> 0 | AX43: =AD43-AW43 -> 0
A44: 38 | B44: FA Kendaraan | C44: 17 | D44: Vehicles | E44: Gol 1 | F44: 1201-003 | G44: 1202-003 | H44: 6500-003 | I44: Depreciation Expenses | J44: KND.01/13 | L44: 41275 | M44: Mitsubshi Colt L300 Diesel E-2 Pu Std 2012 | N44: Pembelian Mitsubshi Colt L300 Diesel E-2 PU STD 2012 | O44: Aktif | P44: 1 | Q44: 146000000 | R44: 48 | S44: 0 | T44: 146000000 | U44: 0 | V44: 0 | W44: 0 | X44: 0 | Y44: 0 | Z44: 0 | AA44: 0 | AB44: 0 | AC44: =T44+SUM(U44:AB44) -> 146000000 | AD44: =Q44-AC44 -> 0 | AE44: =IF(O44="Aktif",AB44,0) -> 0 | AF44: =IF(AE44>0,MAX(0,AD44)/AE44,0) -> 0 | AG44: =IF($O44="Aktif",MAX(0,MIN($AE44,$AD44-0)),0) -> 0 | AH44: =IF($O44="Aktif",MAX(0,MIN($AE44,$AD44-SUM($AG44:AG44))),0) -> 0 | AI44: =IF($O44="Aktif",MAX(0,MIN($AE44,$AD44-SUM($AG44:AH44))),0) -> 0 | AJ44: =IF($O44="Aktif",MAX(0,MIN($AE44,$AD44-SUM($AG44:AI44))),0) -> 0 | AK44: =IF($O44="Aktif",MAX(0,MIN($AE44,$AD44-SUM($AG44:AJ44))),0) -> 0 | AL44: =IF($O44="Aktif",MAX(0,MIN($AE44,$AD44-SUM($AG44:AK44))),0) -> 0 | AM44: =IF($O44="Aktif",MAX(0,MIN($AE44,$AD44-SUM($AG44:AL44))),0) -> 0 | AN44: =IF($O44="Aktif",MAX(0,MIN($AE44,$AD44-SUM($AG44:AM44))),0) -> 0 | AO44: =IF($O44="Aktif",MAX(0,MIN($AE44,$AD44-SUM($AG44:AN44))),0) -> 0 | ... AV44: =IF($O44="Aktif",MAX(0,MIN($AE44,$AD44-SUM($AG44:AU44))),0) -> 0 | AW44: =SUM(AG44:AV44) -> 0 | AX44: =AD44-AW44 -> 0
A45: 39 | B45: FA Kendaraan | C45: 18 | D45: Vehicles | E45: Gol 1 | F45: 1201-003 | G45: 1202-003 | H45: 6500-003 | I45: Depreciation Expenses | J45: KND.02/13 | L45: 41295 | M45: Bak Terbuka Utk Mitsubishi L300 | N45: Bak terbuka utk Mitsubishi L300 (angkut ibu kupas), H 1761 NM | O45: Aktif | P45: 1 | Q45: 16090909 | R45: 48 | S45: 0 | T45: 16090909 | U45: 0 | V45: 0 | W45: 0 | X45: 0 | Y45: 0 | Z45: 0 | AA45: 0 | AB45: 0 | AC45: =T45+SUM(U45:AB45) -> 16090909 | AD45: =Q45-AC45 -> 0 | AE45: =IF(O45="Aktif",AB45,0) -> 0 | AF45: =IF(AE45>0,MAX(0,AD45)/AE45,0) -> 0 | AG45: =IF($O45="Aktif",MAX(0,MIN($AE45,$AD45-0)),0) -> 0 | AH45: =IF($O45="Aktif",MAX(0,MIN($AE45,$AD45-SUM($AG45:AG45))),0) -> 0 | AI45: =IF($O45="Aktif",MAX(0,MIN($AE45,$AD45-SUM($AG45:AH45))),0) -> 0 | AJ45: =IF($O45="Aktif",MAX(0,MIN($AE45,$AD45-SUM($AG45:AI45))),0) -> 0 | AK45: =IF($O45="Aktif",MAX(0,MIN($AE45,$AD45-SUM($AG45:AJ45))),0) -> 0 | AL45: =IF($O45="Aktif",MAX(0,MIN($AE45,$AD45-SUM($AG45:AK45))),0) -> 0 | AM45: =IF($O45="Aktif",MAX(0,MIN($AE45,$AD45-SUM($AG45:AL45))),0) -> 0 | AN45: =IF($O45="Aktif",MAX(0,MIN($AE45,$AD45-SUM($AG45:AM45))),0) -> 0 | AO45: =IF($O45="Aktif",MAX(0,MIN($AE45,$AD45-SUM($AG45:AN45))),0) -> 0 | ... AV45: =IF($O45="Aktif",MAX(0,MIN($AE45,$AD45-SUM($AG45:AU45))),0) -> 0 | AW45: =SUM(AG45:AV45) -> 0 | AX45: =AD45-AW45 -> 0
A46: 40 | B46: FA Kendaraan | C46: 19 | D46: Vehicles | E46: Gol 1 | F46: 1201-003 | G46: 1202-003 | H46: 6500-003 | I46: Depreciation Expenses | J46: KND.03/13 | L46: 41334 | M46: Mobil B 9861 JH | N46: Mobil B9861JH (mobil 292jt + box 42,5jt) | O46: Aktif | P46: 1 | Q46: 334500000 | R46: 48 | S46: 0 | T46: 334500000 | U46: 0 | V46: 0 | W46: 0 | X46: 0 | Y46: 0 | Z46: 0 | AA46: 0 | AB46: 0 | AC46: =T46+SUM(U46:AB46) -> 334500000 | AD46: =Q46-AC46 -> 0 | AE46: =IF(O46="Aktif",AB46,0) -> 0 | AF46: =IF(AE46>0,MAX(0,AD46)/AE46,0) -> 0 | AG46: =IF($O46="Aktif",MAX(0,MIN($AE46,$AD46-0)),0) -> 0 | AH46: =IF($O46="Aktif",MAX(0,MIN($AE46,$AD46-SUM($AG46:AG46))),0) -> 0 | AI46: =IF($O46="Aktif",MAX(0,MIN($AE46,$AD46-SUM($AG46:AH46))),0) -> 0 | AJ46: =IF($O46="Aktif",MAX(0,MIN($AE46,$AD46-SUM($AG46:AI46))),0) -> 0 | AK46: =IF($O46="Aktif",MAX(0,MIN($AE46,$AD46-SUM($AG46:AJ46))),0) -> 0 | AL46: =IF($O46="Aktif",MAX(0,MIN($AE46,$AD46-SUM($AG46:AK46))),0) -> 0 | AM46: =IF($O46="Aktif",MAX(0,MIN($AE46,$AD46-SUM($AG46:AL46))),0) -> 0 | AN46: =IF($O46="Aktif",MAX(0,MIN($AE46,$AD46-SUM($AG46:AM46))),0) -> 0 | AO46: =IF($O46="Aktif",MAX(0,MIN($AE46,$AD46-SUM($AG46:AN46))),0) -> 0 | ... AV46: =IF($O46="Aktif",MAX(0,MIN($AE46,$AD46-SUM($AG46:AU46))),0) -> 0 | AW46: =SUM(AG46:AV46) -> 0 | AX46: =AD46-AW46 -> 0
A47: 41 | B47: FA Kendaraan | C47: 20 | D47: Vehicles | E47: - | F47: 1201-003 | G47: 1202-003 | H47: 6500-003 | I47: Depreciation Expenses | L47: 44260 | M47: Mobil B 9861 JH | N47: Penjualan Mobil B9861JH (mobil 292jt + box 42,5jt) | O47: Dijual | P47: 1 | Q47: -334500000 | S47: 0 | T47: -334500000 | U47: 0 | V47: 0 | W47: 0 | X47: 0 | Y47: 0 | Z47: 0 | AA47: 0 | AB47: 0 | AC47: =T47+SUM(U47:AB47) -> -334500000 | AD47: =Q47-AC47 -> 0 | AE47: =IF(O47="Aktif",AB47,0) -> 0 | AF47: =IF(AE47>0,MAX(0,AD47)/AE47,0) -> 0 | AG47: =IF($O47="Aktif",MAX(0,MIN($AE47,$AD47-0)),0) -> 0 | AH47: =IF($O47="Aktif",MAX(0,MIN($AE47,$AD47-SUM($AG47:AG47))),0) -> 0 | AI47: =IF($O47="Aktif",MAX(0,MIN($AE47,$AD47-SUM($AG47:AH47))),0) -> 0 | AJ47: =IF($O47="Aktif",MAX(0,MIN($AE47,$AD47-SUM($AG47:AI47))),0) -> 0 | AK47: =IF($O47="Aktif",MAX(0,MIN($AE47,$AD47-SUM($AG47:AJ47))),0) -> 0 | AL47: =IF($O47="Aktif",MAX(0,MIN($AE47,$AD47-SUM($AG47:AK47))),0) -> 0 | AM47: =IF($O47="Aktif",MAX(0,MIN($AE47,$AD47-SUM($AG47:AL47))),0) -> 0 | AN47: =IF($O47="Aktif",MAX(0,MIN($AE47,$AD47-SUM($AG47:AM47))),0) -> 0 | AO47: =IF($O47="Aktif",MAX(0,MIN($AE47,$AD47-SUM($AG47:AN47))),0) -> 0 | ... AV47: =IF($O47="Aktif",MAX(0,MIN($AE47,$AD47-SUM($AG47:AU47))),0) -> 0 | AW47: =SUM(AG47:AV47) -> 0 | AX47: =AD47-AW47 -> 0
A48: 42 | B48: FA Kendaraan | C48: 21 | D48: Vehicles | E48: Gol 1 | F48: 1201-003 | G48: 1202-003 | H48: 6500-003 | I48: Depreciation Expenses | J48: KND.01/15 | L48: 42038 | M48: Honda Blade B 6420 TXR | N48: Pembelian Motor Honda Blade No Pol B 6420 TXR | O48: Aktif | P48: 1 | Q48: 4600000 | R48: 48 | S48: 0 | T48: 4600000 | U48: 0 | V48: 0 | W48: 0 | X48: 0 | Y48: 0 | Z48: 0 | AA48: 0 | AB48: 0 | AC48: =T48+SUM(U48:AB48) -> 4600000 | AD48: =Q48-AC48 -> 0 | AE48: =IF(O48="Aktif",AB48,0) -> 0 | AF48: =IF(AE48>0,MAX(0,AD48)/AE48,0) -> 0 | AG48: =IF($O48="Aktif",MAX(0,MIN($AE48,$AD48-0)),0) -> 0 | AH48: =IF($O48="Aktif",MAX(0,MIN($AE48,$AD48-SUM($AG48:AG48))),0) -> 0 | AI48: =IF($O48="Aktif",MAX(0,MIN($AE48,$AD48-SUM($AG48:AH48))),0) -> 0 | AJ48: =IF($O48="Aktif",MAX(0,MIN($AE48,$AD48-SUM($AG48:AI48))),0) -> 0 | AK48: =IF($O48="Aktif",MAX(0,MIN($AE48,$AD48-SUM($AG48:AJ48))),0) -> 0 | AL48: =IF($O48="Aktif",MAX(0,MIN($AE48,$AD48-SUM($AG48:AK48))),0) -> 0 | AM48: =IF($O48="Aktif",MAX(0,MIN($AE48,$AD48-SUM($AG48:AL48))),0) -> 0 | AN48: =IF($O48="Aktif",MAX(0,MIN($AE48,$AD48-SUM($AG48:AM48))),0) -> 0 | AO48: =IF($O48="Aktif",MAX(0,MIN($AE48,$AD48-SUM($AG48:AN48))),0) -> 0 | ... AV48: =IF($O48="Aktif",MAX(0,MIN($AE48,$AD48-SUM($AG48:AU48))),0) -> 0 | AW48: =SUM(AG48:AV48) -> 0 | AX48: =AD48-AW48 -> 0
A49: 43 | B49: FA Kendaraan | C49: 22 | D49: Vehicles | E49: Gol 1 | F49: 1201-003 | G49: 1202-003 | H49: 6500-003 | I49: Depreciation Expenses | J49: KND.01/16 | L49: 42671 | M49: Granmax B 9174 UXT | N49: PEMBELIAN MOBIL GRANMAX NOPOL B 9174 UXT | O49: Aktif | P49: 1 | Q49: 70000000 | R49: 48 | S49: 0 | T49: 70000000 | U49: 0 | V49: 0 | W49: 0 | X49: 0 | Y49: 0 | Z49: 0 | AA49: 0 | AB49: 0 | AC49: =T49+SUM(U49:AB49) -> 70000000 | AD49: =Q49-AC49 -> 0 | AE49: =IF(O49="Aktif",AB49,0) -> 0 | AF49: =IF(AE49>0,MAX(0,AD49)/AE49,0) -> 0 | AG49: =IF($O49="Aktif",MAX(0,MIN($AE49,$AD49-0)),0) -> 0 | AH49: =IF($O49="Aktif",MAX(0,MIN($AE49,$AD49-SUM($AG49:AG49))),0) -> 0 | AI49: =IF($O49="Aktif",MAX(0,MIN($AE49,$AD49-SUM($AG49:AH49))),0) -> 0 | AJ49: =IF($O49="Aktif",MAX(0,MIN($AE49,$AD49-SUM($AG49:AI49))),0) -> 0 | AK49: =IF($O49="Aktif",MAX(0,MIN($AE49,$AD49-SUM($AG49:AJ49))),0) -> 0 | AL49: =IF($O49="Aktif",MAX(0,MIN($AE49,$AD49-SUM($AG49:AK49))),0) -> 0 | AM49: =IF($O49="Aktif",MAX(0,MIN($AE49,$AD49-SUM($AG49:AL49))),0) -> 0 | AN49: =IF($O49="Aktif",MAX(0,MIN($AE49,$AD49-SUM($AG49:AM49))),0) -> 0 | AO49: =IF($O49="Aktif",MAX(0,MIN($AE49,$AD49-SUM($AG49:AN49))),0) -> 0 | ... AV49: =IF($O49="Aktif",MAX(0,MIN($AE49,$AD49-SUM($AG49:AU49))),0) -> 0 | AW49: =SUM(AG49:AV49) -> 0 | AX49: =AD49-AW49 -> 0
A50: 44 | B50: FA Kendaraan | C50: 23 | D50: Vehicles | E50: Gol 1 | F50: 1201-003 | G50: 1202-003 | H50: 6500-003 | I50: Depreciation Expenses | L50: 39783 | M50: Daihatsu Xenia B 8791 KP | N50: Daihatsu Xenia B8791KP | O50: Aktif | P50: 1 | Q50: 72179250 | R50: 48 | S50: 0 | T50: 72179250 | U50: 0 | V50: 0 | W50: 0 | X50: 0 | Y50: 0 | Z50: 0 | AA50: 0 | AB50: 0 | AC50: =T50+SUM(U50:AB50) -> 72179250 | AD50: =Q50-AC50 -> 0 | AE50: =IF(O50="Aktif",AB50,0) -> 0 | AF50: =IF(AE50>0,MAX(0,AD50)/AE50,0) -> 0 | AG50: =IF($O50="Aktif",MAX(0,MIN($AE50,$AD50-0)),0) -> 0 | AH50: =IF($O50="Aktif",MAX(0,MIN($AE50,$AD50-SUM($AG50:AG50))),0) -> 0 | AI50: =IF($O50="Aktif",MAX(0,MIN($AE50,$AD50-SUM($AG50:AH50))),0) -> 0 | AJ50: =IF($O50="Aktif",MAX(0,MIN($AE50,$AD50-SUM($AG50:AI50))),0) -> 0 | AK50: =IF($O50="Aktif",MAX(0,MIN($AE50,$AD50-SUM($AG50:AJ50))),0) -> 0 | AL50: =IF($O50="Aktif",MAX(0,MIN($AE50,$AD50-SUM($AG50:AK50))),0) -> 0 | AM50: =IF($O50="Aktif",MAX(0,MIN($AE50,$AD50-SUM($AG50:AL50))),0) -> 0 | AN50: =IF($O50="Aktif",MAX(0,MIN($AE50,$AD50-SUM($AG50:AM50))),0) -> 0 | AO50: =IF($O50="Aktif",MAX(0,MIN($AE50,$AD50-SUM($AG50:AN50))),0) -> 0 | ... AV50: =IF($O50="Aktif",MAX(0,MIN($AE50,$AD50-SUM($AG50:AU50))),0) -> 0 | AW50: =SUM(AG50:AV50) -> 0 | AX50: =AD50-AW50 -> 0
A51: 45 | B51: FA Kendaraan | C51: 24 | D51: Vehicles | E51: Gol 1 | F51: 1201-003 | G51: 1202-003 | H51: 6500-003 | I51: Depreciation Expenses | J51: KND.01/17 | L51: 42783 | M51: Mitsubishi Fuso B 9328 PRU | N51: Pembelian mobil mitsubishi Fuso B 9328 PRU | O51: Aktif | P51: 1 | Q51: 100000000 | R51: 48 | S51: 2083333.3 | T51: 100000000 | U51: 0 | V51: 0 | W51: 0 | X51: 0 | Y51: 0 | Z51: 0 | AA51: 0 | AB51: 0 | AC51: =T51+SUM(U51:AB51) -> 100000000 | AD51: =Q51-AC51 -> 0 | AE51: =IF(O51="Aktif",AB51,0) -> 0 | AF51: =IF(AE51>0,MAX(0,AD51)/AE51,0) -> 0 | AG51: =IF($O51="Aktif",MAX(0,MIN($AE51,$AD51-0)),0) -> 0 | AH51: =IF($O51="Aktif",MAX(0,MIN($AE51,$AD51-SUM($AG51:AG51))),0) -> 0 | AI51: =IF($O51="Aktif",MAX(0,MIN($AE51,$AD51-SUM($AG51:AH51))),0) -> 0 | AJ51: =IF($O51="Aktif",MAX(0,MIN($AE51,$AD51-SUM($AG51:AI51))),0) -> 0 | AK51: =IF($O51="Aktif",MAX(0,MIN($AE51,$AD51-SUM($AG51:AJ51))),0) -> 0 | AL51: =IF($O51="Aktif",MAX(0,MIN($AE51,$AD51-SUM($AG51:AK51))),0) -> 0 | AM51: =IF($O51="Aktif",MAX(0,MIN($AE51,$AD51-SUM($AG51:AL51))),0) -> 0 | AN51: =IF($O51="Aktif",MAX(0,MIN($AE51,$AD51-SUM($AG51:AM51))),0) -> 0 | AO51: =IF($O51="Aktif",MAX(0,MIN($AE51,$AD51-SUM($AG51:AN51))),0) -> 0 | ... AV51: =IF($O51="Aktif",MAX(0,MIN($AE51,$AD51-SUM($AG51:AU51))),0) -> 0 | AW51: =SUM(AG51:AV51) -> 0 | AX51: =AD51-AW51 -> 0
A52: 46 | B52: FA Kendaraan | C52: 25 | D52: Vehicles | E52: Gol 1 | F52: 1201-003 | G52: 1202-003 | H52: 6500-003 | I52: Depreciation Expenses | J52: KND.02/17 | L52: 42978 | M52: Fortuner G/Manual B 1875 TJM | N52: 1 unit Fortuner G/manual | O52: Aktif | P52: 1 | Q52: 426800000 | R52: 48 | S52: 8891666.7 | T52: 4.1790833e+08 | U52: 0 | V52: 0 | W52: 0 | X52: 0 | Y52: 0 | Z52: 0 | AA52: 0 | AB52: 0 | AC52: =T52+SUM(U52:AB52) -> 4.1790833e+08 | AD52: =Q52-AC52 -> 8891666.7 | AE52: =IF(O52="Aktif",AB52,0) -> 0 | AF52: =IF(AE52>0,MAX(0,AD52)/AE52,0) -> 0 | AG52: =IF($O52="Aktif",MAX(0,MIN($AE52,$AD52-0)),0) -> 0 | AH52: =IF($O52="Aktif",MAX(0,MIN($AE52,$AD52-SUM($AG52:AG52))),0) -> 0 | AI52: =IF($O52="Aktif",MAX(0,MIN($AE52,$AD52-SUM($AG52:AH52))),0) -> 0 | AJ52: =IF($O52="Aktif",MAX(0,MIN($AE52,$AD52-SUM($AG52:AI52))),0) -> 0 | AK52: =IF($O52="Aktif",MAX(0,MIN($AE52,$AD52-SUM($AG52:AJ52))),0) -> 0 | AL52: =IF($O52="Aktif",MAX(0,MIN($AE52,$AD52-SUM($AG52:AK52))),0) -> 0 | AM52: =IF($O52="Aktif",MAX(0,MIN($AE52,$AD52-SUM($AG52:AL52))),0) -> 0 | AN52: =IF($O52="Aktif",MAX(0,MIN($AE52,$AD52-SUM($AG52:AM52))),0) -> 0 | AO52: =IF($O52="Aktif",MAX(0,MIN($AE52,$AD52-SUM($AG52:AN52))),0) -> 0 | ... AV52: =IF($O52="Aktif",MAX(0,MIN($AE52,$AD52-SUM($AG52:AU52))),0) -> 0 | AW52: =SUM(AG52:AV52) -> 0 | AX52: =AD52-AW52 -> 8891666.7
A53: 47 | B53: FA Kendaraan | C53: 26 | D53: Vehicles | E53: - | F53: 1201-003 | G53: 1202-003 | H53: 6500-003 | I53: Depreciation Expenses | J53: MJ21060007 | L53: 44349 | M53: Fortuner G/Manual B 1875 TJM | N53: Penjualan 1 unit Fortuner G/manual B 1875 TJM | O53: Dijual | P53: 1 | Q53: -426800000 | S53: 0 | T53: -4.1790833e+08 | U53: 0 | V53: 0 | W53: 0 | X53: 0 | Y53: 0 | Z53: 0 | AA53: 0 | AB53: 0 | AC53: =T53+SUM(U53:AB53) -> -4.1790833e+08 | AD53: =Q53-AC53 -> -8891666.7 | AE53: =IF(O53="Aktif",AB53,0) -> 0 | AF53: =IF(AE53>0,MAX(0,AD53)/AE53,0) -> 0 | AG53: =IF($O53="Aktif",MAX(0,MIN($AE53,$AD53-0)),0) -> 0 | AH53: =IF($O53="Aktif",MAX(0,MIN($AE53,$AD53-SUM($AG53:AG53))),0) -> 0 | AI53: =IF($O53="Aktif",MAX(0,MIN($AE53,$AD53-SUM($AG53:AH53))),0) -> 0 | AJ53: =IF($O53="Aktif",MAX(0,MIN($AE53,$AD53-SUM($AG53:AI53))),0) -> 0 | AK53: =IF($O53="Aktif",MAX(0,MIN($AE53,$AD53-SUM($AG53:AJ53))),0) -> 0 | AL53: =IF($O53="Aktif",MAX(0,MIN($AE53,$AD53-SUM($AG53:AK53))),0) -> 0 | AM53: =IF($O53="Aktif",MAX(0,MIN($AE53,$AD53-SUM($AG53:AL53))),0) -> 0 | AN53: =IF($O53="Aktif",MAX(0,MIN($AE53,$AD53-SUM($AG53:AM53))),0) -> 0 | AO53: =IF($O53="Aktif",MAX(0,MIN($AE53,$AD53-SUM($AG53:AN53))),0) -> 0 | ... AV53: =IF($O53="Aktif",MAX(0,MIN($AE53,$AD53-SUM($AG53:AU53))),0) -> 0 | AW53: =SUM(AG53:AV53) -> 0 | AX53: =AD53-AW53 -> -8891666.7
A54: 48 | B54: FA Kendaraan | C54: 27 | D54: Vehicles | E54: Gol 1 | F54: 1201-003 | G54: 1202-003 | H54: 6500-003 | I54: Depreciation Expenses | J54: KND.03/17 | L54: 43039 | M54: BMW 740 LI | N54: 1 unit BMW 740 Li | O54: Aktif | P54: 1 | Q54: 1900000000 | R54: 48 | S54: 39583333 | T54: 1.8208333e+09 | U54: 0 | V54: 0 | W54: 0 | X54: 0 | Y54: 0 | Z54: 0 | AA54: 0 | AB54: 0 | AC54: =T54+SUM(U54:AB54) -> 1.8208333e+09 | AD54: =Q54-AC54 -> 79166667 | AE54: =IF(O54="Aktif",AB54,0) -> 0 | AF54: =IF(AE54>0,MAX(0,AD54)/AE54,0) -> 0 | AG54: =IF($O54="Aktif",MAX(0,MIN($AE54,$AD54-0)),0) -> 0 | AH54: =IF($O54="Aktif",MAX(0,MIN($AE54,$AD54-SUM($AG54:AG54))),0) -> 0 | AI54: =IF($O54="Aktif",MAX(0,MIN($AE54,$AD54-SUM($AG54:AH54))),0) -> 0 | AJ54: =IF($O54="Aktif",MAX(0,MIN($AE54,$AD54-SUM($AG54:AI54))),0) -> 0 | AK54: =IF($O54="Aktif",MAX(0,MIN($AE54,$AD54-SUM($AG54:AJ54))),0) -> 0 | AL54: =IF($O54="Aktif",MAX(0,MIN($AE54,$AD54-SUM($AG54:AK54))),0) -> 0 | AM54: =IF($O54="Aktif",MAX(0,MIN($AE54,$AD54-SUM($AG54:AL54))),0) -> 0 | AN54: =IF($O54="Aktif",MAX(0,MIN($AE54,$AD54-SUM($AG54:AM54))),0) -> 0 | AO54: =IF($O54="Aktif",MAX(0,MIN($AE54,$AD54-SUM($AG54:AN54))),0) -> 0 | ... AV54: =IF($O54="Aktif",MAX(0,MIN($AE54,$AD54-SUM($AG54:AU54))),0) -> 0 | AW54: =SUM(AG54:AV54) -> 0 | AX54: =AD54-AW54 -> 79166667
A55: 49 | B55: FA Kendaraan | C55: 28 | D55: Vehicles | E55: - | F55: 1201-003 | G55: 1202-003 | H55: 6500-003 | I55: Depreciation Expenses | M55: BMW 740 LI | N55: Christopher Brian H Toha, Inv 979 BMW 74OLI 7E22 AT, Hitam Metalik Tahun 2016 1 Unit 25/05/22 | O55: Dijual | P55: 1 | Q55: -1900000000 | S55: 0 | T55: -1.8208333e+09 | U55: 0 | V55: 0 | W55: 0 | X55: 0 | Y55: 0 | Z55: 0 | AA55: 0 | AB55: 0 | AC55: =T55+SUM(U55:AB55) -> -1.8208333e+09 | AD55: =Q55-AC55 -> -79166667 | AE55: =IF(O55="Aktif",AB55,0) -> 0 | AF55: =IF(AE55>0,MAX(0,AD55)/AE55,0) -> 0 | AG55: =IF($O55="Aktif",MAX(0,MIN($AE55,$AD55-0)),0) -> 0 | AH55: =IF($O55="Aktif",MAX(0,MIN($AE55,$AD55-SUM($AG55:AG55))),0) -> 0 | AI55: =IF($O55="Aktif",MAX(0,MIN($AE55,$AD55-SUM($AG55:AH55))),0) -> 0 | AJ55: =IF($O55="Aktif",MAX(0,MIN($AE55,$AD55-SUM($AG55:AI55))),0) -> 0 | AK55: =IF($O55="Aktif",MAX(0,MIN($AE55,$AD55-SUM($AG55:AJ55))),0) -> 0 | AL55: =IF($O55="Aktif",MAX(0,MIN($AE55,$AD55-SUM($AG55:AK55))),0) -> 0 | AM55: =IF($O55="Aktif",MAX(0,MIN($AE55,$AD55-SUM($AG55:AL55))),0) -> 0 | AN55: =IF($O55="Aktif",MAX(0,MIN($AE55,$AD55-SUM($AG55:AM55))),0) -> 0 | AO55: =IF($O55="Aktif",MAX(0,MIN($AE55,$AD55-SUM($AG55:AN55))),0) -> 0 | ... AV55: =IF($O55="Aktif",MAX(0,MIN($AE55,$AD55-SUM($AG55:AU55))),0) -> 0 | AW55: =SUM(AG55:AV55) -> 0 | AX55: =AD55-AW55 -> -79166667
A56: 50 | B56: FA Kendaraan | C56: 29 | D56: Vehicles | E56: Gol 1 | F56: 1201-003 | G56: 1202-003 | H56: 6500-003 | I56: Depreciation Expenses | J56: KND.01/18 | L56: 43409 | M56: Mitsubishi Pajero Sport B 1841 BJJ | N56: Pembelian mobil Pajero | O56: Aktif | P56: 1 | Q56: 250834000 | R56: 48 | S56: 5225708.3 | T56: 1.5677125e+08 | U56: 0 | V56: 0 | W56: 0 | X56: 0 | Y56: 0 | Z56: 0 | AA56: 0 | AB56: 0 | AC56: =T56+SUM(U56:AB56) -> 1.5677125e+08 | AD56: =Q56-AC56 -> 94062750 | AE56: =IF(O56="Aktif",AB56,0) -> 0 | AF56: =IF(AE56>0,MAX(0,AD56)/AE56,0) -> 0 | AG56: =IF($O56="Aktif",MAX(0,MIN($AE56,$AD56-0)),0) -> 0 | AH56: =IF($O56="Aktif",MAX(0,MIN($AE56,$AD56-SUM($AG56:AG56))),0) -> 0 | AI56: =IF($O56="Aktif",MAX(0,MIN($AE56,$AD56-SUM($AG56:AH56))),0) -> 0 | AJ56: =IF($O56="Aktif",MAX(0,MIN($AE56,$AD56-SUM($AG56:AI56))),0) -> 0 | AK56: =IF($O56="Aktif",MAX(0,MIN($AE56,$AD56-SUM($AG56:AJ56))),0) -> 0 | AL56: =IF($O56="Aktif",MAX(0,MIN($AE56,$AD56-SUM($AG56:AK56))),0) -> 0 | AM56: =IF($O56="Aktif",MAX(0,MIN($AE56,$AD56-SUM($AG56:AL56))),0) -> 0 | AN56: =IF($O56="Aktif",MAX(0,MIN($AE56,$AD56-SUM($AG56:AM56))),0) -> 0 | AO56: =IF($O56="Aktif",MAX(0,MIN($AE56,$AD56-SUM($AG56:AN56))),0) -> 0 | ... AV56: =IF($O56="Aktif",MAX(0,MIN($AE56,$AD56-SUM($AG56:AU56))),0) -> 0 | AW56: =SUM(AG56:AV56) -> 0 | AX56: =AD56-AW56 -> 94062750
A57: 51 | B57: FA Kendaraan | C57: 30 | D57: Vehicles | E57: - | F57: 1201-003 | G57: 1202-003 | H57: 6500-003 | I57: Depreciation Expenses | L57: 44294 | M57: Mitsubishi Pajero Sport B 1841 BJJ | N57: Penjualan Mitsubishi Pajero Sport B 1841 BJJ 08/04/21 - PPN | O57: Dijual | P57: 1 | Q57: -250834000 | S57: 0 | T57: -156771250 | U57: 0 | V57: 0 | W57: 0 | X57: 0 | Y57: 0 | Z57: 0 | AA57: 0 | AB57: 0 | AC57: =T57+SUM(U57:AB57) -> -156771250 | AD57: =Q57-AC57 -> -94062750 | AE57: =IF(O57="Aktif",AB57,0) -> 0 | AF57: =IF(AE57>0,MAX(0,AD57)/AE57,0) -> 0 | AG57: =IF($O57="Aktif",MAX(0,MIN($AE57,$AD57-0)),0) -> 0 | AH57: =IF($O57="Aktif",MAX(0,MIN($AE57,$AD57-SUM($AG57:AG57))),0) -> 0 | AI57: =IF($O57="Aktif",MAX(0,MIN($AE57,$AD57-SUM($AG57:AH57))),0) -> 0 | AJ57: =IF($O57="Aktif",MAX(0,MIN($AE57,$AD57-SUM($AG57:AI57))),0) -> 0 | AK57: =IF($O57="Aktif",MAX(0,MIN($AE57,$AD57-SUM($AG57:AJ57))),0) -> 0 | AL57: =IF($O57="Aktif",MAX(0,MIN($AE57,$AD57-SUM($AG57:AK57))),0) -> 0 | AM57: =IF($O57="Aktif",MAX(0,MIN($AE57,$AD57-SUM($AG57:AL57))),0) -> 0 | AN57: =IF($O57="Aktif",MAX(0,MIN($AE57,$AD57-SUM($AG57:AM57))),0) -> 0 | AO57: =IF($O57="Aktif",MAX(0,MIN($AE57,$AD57-SUM($AG57:AN57))),0) -> 0 | ... AV57: =IF($O57="Aktif",MAX(0,MIN($AE57,$AD57-SUM($AG57:AU57))),0) -> 0 | AW57: =SUM(AG57:AV57) -> 0 | AX57: =AD57-AW57 -> -94062750
A58: 52 | B58: FA Kendaraan | C58: 31 | D58: Vehicles | E58: Gol 2 | F58: 1201-003 | G58: 1202-003 | H58: 6500-003 | I58: Depreciation Expenses | K58: KD2.0001 | L58: 31/03/2021 | M58: Wuling Confero 1.5 Db Black B 2336 TRH | N58: PT Arista Jaya Lestari, Mobil Wuling Confero 1.5 DB BLACK 31/03/21 + Bea Balik Nama + Admin B 2336 TRH | O58: Aktif | P58: 1 | Q58: 128447432 | R58: 96 | S58: 1337994.1 | T58: 77603657 | U58: 1337994.1 | V58: 1337994.1 | W58: 1337994.1 | X58: 1337994.1 | Y58: 1337994.1 | Z58: 1337994.1 | AA58: 1337994.1 | AB58: 1337994.1 | AC58: =T58+SUM(U58:AB58) -> 88307609 | AD58: =Q58-AC58 -> 40139823 | AE58: =IF(O58="Aktif",AB58,0) -> 1337994.1 | AF58: =IF(AE58>0,MAX(0,AD58)/AE58,0) -> 30 | AG58: =IF($O58="Aktif",MAX(0,MIN($AE58,$AD58-0)),0) -> 1337994.1 | AH58: =IF($O58="Aktif",MAX(0,MIN($AE58,$AD58-SUM($AG58:AG58))),0) -> 1337994.1 | AI58: =IF($O58="Aktif",MAX(0,MIN($AE58,$AD58-SUM($AG58:AH58))),0) -> 1337994.1 | AJ58: =IF($O58="Aktif",MAX(0,MIN($AE58,$AD58-SUM($AG58:AI58))),0) -> 1337994.1 | AK58: =IF($O58="Aktif",MAX(0,MIN($AE58,$AD58-SUM($AG58:AJ58))),0) -> 1337994.1 | AL58: =IF($O58="Aktif",MAX(0,MIN($AE58,$AD58-SUM($AG58:AK58))),0) -> 1337994.1 | AM58: =IF($O58="Aktif",MAX(0,MIN($AE58,$AD58-SUM($AG58:AL58))),0) -> 1337994.1 | AN58: =IF($O58="Aktif",MAX(0,MIN($AE58,$AD58-SUM($AG58:AM58))),0) -> 1337994.1 | AO58: =IF($O58="Aktif",MAX(0,MIN($AE58,$AD58-SUM($AG58:AN58))),0) -> 1337994.1 | ... AV58: =IF($O58="Aktif",MAX(0,MIN($AE58,$AD58-SUM($AG58:AU58))),0) -> 1337994.1 | AW58: =SUM(AG58:AV58) -> 21407905 | AX58: =AD58-AW58 -> 18731917
A59: 53 | B59: FA Kendaraan | C59: 32 | D59: Vehicles | E59: Gol 2 | F59: 1201-003 | G59: 1202-003 | H59: 6500-003 | I59: Depreciation Expenses | L59: 31/03/2021 | M59: Wuling Cortez 1.5S Starry Black B 2330 TRH | N59: PT Arista Jaya Lestari, Mobil Wuling Cortez 1.5S Starry Black Inv 0103 31/03/21 + Bea Balik Nama + Admin B 2330 TRH | O59: Aktif | P59: 1 | Q59: 193840386 | R59: 96 | S59: 2019170.7 | T59: 42402584 | U59: 0 | V59: 0 | W59: 0 | X59: 0 | Y59: 0 | Z59: 0 | AA59: 0 | AB59: 0 | AC59: =T59+SUM(U59:AB59) -> 42402584 | AD59: =Q59-AC59 -> 1.514378e+08 | AE59: =IF(O59="Aktif",AB59,0) -> 0 | AF59: =IF(AE59>0,MAX(0,AD59)/AE59,0) -> 0 | AG59: =IF($O59="Aktif",MAX(0,MIN($AE59,$AD59-0)),0) -> 0 | AH59: =IF($O59="Aktif",MAX(0,MIN($AE59,$AD59-SUM($AG59:AG59))),0) -> 0 | AI59: =IF($O59="Aktif",MAX(0,MIN($AE59,$AD59-SUM($AG59:AH59))),0) -> 0 | AJ59: =IF($O59="Aktif",MAX(0,MIN($AE59,$AD59-SUM($AG59:AI59))),0) -> 0 | AK59: =IF($O59="Aktif",MAX(0,MIN($AE59,$AD59-SUM($AG59:AJ59))),0) -> 0 | AL59: =IF($O59="Aktif",MAX(0,MIN($AE59,$AD59-SUM($AG59:AK59))),0) -> 0 | AM59: =IF($O59="Aktif",MAX(0,MIN($AE59,$AD59-SUM($AG59:AL59))),0) -> 0 | AN59: =IF($O59="Aktif",MAX(0,MIN($AE59,$AD59-SUM($AG59:AM59))),0) -> 0 | AO59: =IF($O59="Aktif",MAX(0,MIN($AE59,$AD59-SUM($AG59:AN59))),0) -> 0 | ... AV59: =IF($O59="Aktif",MAX(0,MIN($AE59,$AD59-SUM($AG59:AU59))),0) -> 0 | AW59: =SUM(AG59:AV59) -> 0 | AX59: =AD59-AW59 -> 1.514378e+08
A60: 54 | B60: FA Kendaraan | C60: 33 | D60: Vehicles | E60: - | F60: 1201-003 | G60: 1202-003 | H60: 6500-003 | I60: Depreciation Expenses | L60: 44896 | M60: Mobil Wuling B 2330 TRH | N60: PT Niaga Makmur Globalindo, Penjualan Mobil Wuling B 2330 TRH 01/12/22 | O60: Dijual | P60: 1 | Q60: -193840386 | S60: 0 | T60: -42402584 | U60: 0 | V60: 0 | W60: 0 | X60: 0 | Y60: 0 | Z60: 0 | AA60: 0 | AB60: 0 | AC60: =T60+SUM(U60:AB60) -> -42402584 | AD60: =Q60-AC60 -> -1.514378e+08 | AE60: =IF(O60="Aktif",AB60,0) -> 0 | AF60: =IF(AE60>0,MAX(0,AD60)/AE60,0) -> 0 | AG60: =IF($O60="Aktif",MAX(0,MIN($AE60,$AD60-0)),0) -> 0 | AH60: =IF($O60="Aktif",MAX(0,MIN($AE60,$AD60-SUM($AG60:AG60))),0) -> 0 | AI60: =IF($O60="Aktif",MAX(0,MIN($AE60,$AD60-SUM($AG60:AH60))),0) -> 0 | AJ60: =IF($O60="Aktif",MAX(0,MIN($AE60,$AD60-SUM($AG60:AI60))),0) -> 0 | AK60: =IF($O60="Aktif",MAX(0,MIN($AE60,$AD60-SUM($AG60:AJ60))),0) -> 0 | AL60: =IF($O60="Aktif",MAX(0,MIN($AE60,$AD60-SUM($AG60:AK60))),0) -> 0 | AM60: =IF($O60="Aktif",MAX(0,MIN($AE60,$AD60-SUM($AG60:AL60))),0) -> 0 | AN60: =IF($O60="Aktif",MAX(0,MIN($AE60,$AD60-SUM($AG60:AM60))),0) -> 0 | AO60: =IF($O60="Aktif",MAX(0,MIN($AE60,$AD60-SUM($AG60:AN60))),0) -> 0 | ... AV60: =IF($O60="Aktif",MAX(0,MIN($AE60,$AD60-SUM($AG60:AU60))),0) -> 0 | AW60: =SUM(AG60:AV60) -> 0 | AX60: =AD60-AW60 -> -1.514378e+08
A61: 55 | B61: FA Kendaraan | C61: 34 | D61: Vehicles | E61: Gol 2 | F61: 1201-003 | G61: 1202-003 | H61: 6500-003 | I61: Depreciation Expenses | K61: KD2.0002 | L61: 31/03/2021 | M61: Wuling Cortez 1.5S Starry Black B 2619 TRH | N61: PT Arista Jaya Lestari, Mobil Wuling Cortez 1.5S Starry Black Inv 0103 31/03/21 + Bea Balik Nama + Admin B 2619 TRH | O61: Aktif | P61: 1 | Q61: 193840386 | R61: 96 | S61: 2019170.7 | T61: 92881852 | U61: 0 | V61: 0 | W61: 0 | X61: 0 | Y61: 0 | Z61: 0 | AA61: 0 | AB61: 0 | AC61: =T61+SUM(U61:AB61) -> 92881852 | AD61: =Q61-AC61 -> 1.0095853e+08 | AE61: =IF(O61="Aktif",AB61,0) -> 0 | AF61: =IF(AE61>0,MAX(0,AD61)/AE61,0) -> 0 | AG61: =IF($O61="Aktif",MAX(0,MIN($AE61,$AD61-0)),0) -> 0 | AH61: =IF($O61="Aktif",MAX(0,MIN($AE61,$AD61-SUM($AG61:AG61))),0) -> 0 | AI61: =IF($O61="Aktif",MAX(0,MIN($AE61,$AD61-SUM($AG61:AH61))),0) -> 0 | AJ61: =IF($O61="Aktif",MAX(0,MIN($AE61,$AD61-SUM($AG61:AI61))),0) -> 0 | AK61: =IF($O61="Aktif",MAX(0,MIN($AE61,$AD61-SUM($AG61:AJ61))),0) -> 0 | AL61: =IF($O61="Aktif",MAX(0,MIN($AE61,$AD61-SUM($AG61:AK61))),0) -> 0 | AM61: =IF($O61="Aktif",MAX(0,MIN($AE61,$AD61-SUM($AG61:AL61))),0) -> 0 | AN61: =IF($O61="Aktif",MAX(0,MIN($AE61,$AD61-SUM($AG61:AM61))),0) -> 0 | AO61: =IF($O61="Aktif",MAX(0,MIN($AE61,$AD61-SUM($AG61:AN61))),0) -> 0 | ... AV61: =IF($O61="Aktif",MAX(0,MIN($AE61,$AD61-SUM($AG61:AU61))),0) -> 0 | AW61: =SUM(AG61:AV61) -> 0 | AX61: =AD61-AW61 -> 1.0095853e+08
A62: 56 | B62: FA Kendaraan | C62: 35 | D62: Vehicles | E62: - | F62: 1201-003 | G62: 1202-003 | H62: 6500-003 | I62: Depreciation Expenses | L62: 17/12/2024 | M62: Wuling Cortez 1.5S Starry Black B 2619 TRH | N62: PT Arista Jaya Lestari, Mobil Wuling Cortez 1.5S Starry Black Inv 0103 31/03/21 + Bea Balik Nama + Admin B 2619 TRH | O62: Dijual | P62: 1 | Q62: -193840386 | S62: 0 | T62: -92881852 | U62: 0 | V62: 0 | W62: 0 | X62: 0 | Y62: 0 | Z62: 0 | AA62: 0 | AB62: 0 | AC62: =T62+SUM(U62:AB62) -> -92881852 | AD62: =Q62-AC62 -> -1.0095853e+08 | AE62: =IF(O62="Aktif",AB62,0) -> 0 | AF62: =IF(AE62>0,MAX(0,AD62)/AE62,0) -> 0 | AG62: =IF($O62="Aktif",MAX(0,MIN($AE62,$AD62-0)),0) -> 0 | AH62: =IF($O62="Aktif",MAX(0,MIN($AE62,$AD62-SUM($AG62:AG62))),0) -> 0 | AI62: =IF($O62="Aktif",MAX(0,MIN($AE62,$AD62-SUM($AG62:AH62))),0) -> 0 | AJ62: =IF($O62="Aktif",MAX(0,MIN($AE62,$AD62-SUM($AG62:AI62))),0) -> 0 | AK62: =IF($O62="Aktif",MAX(0,MIN($AE62,$AD62-SUM($AG62:AJ62))),0) -> 0 | AL62: =IF($O62="Aktif",MAX(0,MIN($AE62,$AD62-SUM($AG62:AK62))),0) -> 0 | AM62: =IF($O62="Aktif",MAX(0,MIN($AE62,$AD62-SUM($AG62:AL62))),0) -> 0 | AN62: =IF($O62="Aktif",MAX(0,MIN($AE62,$AD62-SUM($AG62:AM62))),0) -> 0 | AO62: =IF($O62="Aktif",MAX(0,MIN($AE62,$AD62-SUM($AG62:AN62))),0) -> 0 | ... AV62: =IF($O62="Aktif",MAX(0,MIN($AE62,$AD62-SUM($AG62:AU62))),0) -> 0 | AW62: =SUM(AG62:AV62) -> 0 | AX62: =AD62-AW62 -> -1.0095853e+08
A63: 57 | B63: FA Kendaraan | C63: 36 | D63: Vehicles | E63: Gol 2 | F63: 1201-003 | G63: 1202-003 | H63: 6500-003 | I63: Depreciation Expenses | K63: KD2.0003 | L63: 23/06/2021 | M63: Kijang Innova 2.4 G A/T | N63: PT Tunas Ridean Tbk, Kijang Innova 2.4 G A/T 1 Unit 23/06/21+Accesoris B 2483 TRL | O63: Aktif | P63: 1 | Q63: 338157091 | R63: 96 | S63: 3522469.7 | T63: 1.9373583e+08 | U63: 3522469.7 | V63: 3522469.7 | W63: 3522469.7 | X63: 3522469.7 | Y63: 3522469.7 | Z63: 3522469.7 | AA63: 3522469.7 | AB63: 3522469.7 | AC63: =T63+SUM(U63:AB63) -> 2.2191559e+08 | AD63: =Q63-AC63 -> 1.162415e+08 | AE63: =IF(O63="Aktif",AB63,0) -> 3522469.7 | AF63: =IF(AE63>0,MAX(0,AD63)/AE63,0) -> 33 | AG63: =IF($O63="Aktif",MAX(0,MIN($AE63,$AD63-0)),0) -> 3522469.7 | AH63: =IF($O63="Aktif",MAX(0,MIN($AE63,$AD63-SUM($AG63:AG63))),0) -> 3522469.7 | AI63: =IF($O63="Aktif",MAX(0,MIN($AE63,$AD63-SUM($AG63:AH63))),0) -> 3522469.7 | AJ63: =IF($O63="Aktif",MAX(0,MIN($AE63,$AD63-SUM($AG63:AI63))),0) -> 3522469.7 | AK63: =IF($O63="Aktif",MAX(0,MIN($AE63,$AD63-SUM($AG63:AJ63))),0) -> 3522469.7 | AL63: =IF($O63="Aktif",MAX(0,MIN($AE63,$AD63-SUM($AG63:AK63))),0) -> 3522469.7 | AM63: =IF($O63="Aktif",MAX(0,MIN($AE63,$AD63-SUM($AG63:AL63))),0) -> 3522469.7 | AN63: =IF($O63="Aktif",MAX(0,MIN($AE63,$AD63-SUM($AG63:AM63))),0) -> 3522469.7 | AO63: =IF($O63="Aktif",MAX(0,MIN($AE63,$AD63-SUM($AG63:AN63))),0) -> 3522469.7 | ... AV63: =IF($O63="Aktif",MAX(0,MIN($AE63,$AD63-SUM($AG63:AU63))),0) -> 3522469.7 | AW63: =SUM(AG63:AV63) -> 56359515 | AX63: =AD63-AW63 -> 59881985
A64: 58 | B64: FA Kendaraan | C64: 37 | D64: Vehicles | E64: Gol 1 | F64: 1201-003 | G64: 1202-003 | H64: 6500-003 | I64: Depreciation Expenses | K64: KD1.0009 | L64: 44494 | M64: Sepeda Motor Beat Sporty CBSSPION Plus H 6692 OD | N64: CV Cendana Sukorejo, Sepeda Motor Beat Sporty CBSSPION Plus 1unit x Rp 16.700.000/unit 25/10/21 BBN | O64: Aktif | P64: 1 | Q64: 15448091 | R64: 48 | S64: 321835.23 | T64: 15448091 | U64: 0 | V64: 0 | W64: 0 | X64: 0 | Y64: 0 | Z64: 0 | AA64: 0 | AB64: 0 | AC64: =T64+SUM(U64:AB64) -> 15448091 | AD64: =Q64-AC64 -> 0 | AE64: =IF(O64="Aktif",AB64,0) -> 0 | AF64: =IF(AE64>0,MAX(0,AD64)/AE64,0) -> 0 | AG64: =IF($O64="Aktif",MAX(0,MIN($AE64,$AD64-0)),0) -> 0 | AH64: =IF($O64="Aktif",MAX(0,MIN($AE64,$AD64-SUM($AG64:AG64))),0) -> 0 | AI64: =IF($O64="Aktif",MAX(0,MIN($AE64,$AD64-SUM($AG64:AH64))),0) -> 0 | AJ64: =IF($O64="Aktif",MAX(0,MIN($AE64,$AD64-SUM($AG64:AI64))),0) -> 0 | AK64: =IF($O64="Aktif",MAX(0,MIN($AE64,$AD64-SUM($AG64:AJ64))),0) -> 0 | AL64: =IF($O64="Aktif",MAX(0,MIN($AE64,$AD64-SUM($AG64:AK64))),0) -> 0 | AM64: =IF($O64="Aktif",MAX(0,MIN($AE64,$AD64-SUM($AG64:AL64))),0) -> 0 | AN64: =IF($O64="Aktif",MAX(0,MIN($AE64,$AD64-SUM($AG64:AM64))),0) -> 0 | AO64: =IF($O64="Aktif",MAX(0,MIN($AE64,$AD64-SUM($AG64:AN64))),0) -> 0 | ... AV64: =IF($O64="Aktif",MAX(0,MIN($AE64,$AD64-SUM($AG64:AU64))),0) -> 0 | AW64: =SUM(AG64:AV64) -> 0 | AX64: =AD64-AW64 -> 0
A65: 59 | B65: FA Kendaraan | C65: 38 | D65: Vehicles | E65: Gol 2 | F65: 1201-003 | G65: 1202-003 | H65: 6500-003 | I65: Depreciation Expenses | L65: 44621 | M65: BMW X5 xDrive 40i xLine - G05 Alpine White | N65: PT Artha Motor Lestari, BMW X5 xDrive 40i xLine - G05 Alpine White 1 Unit, +PPn 10% 01/03/22 | O65: Aktif | P65: 1 | Q65: 1575340909 | R65: 96 | S65: 16409801 | T65: 16409801 | U65: 0 | V65: 0 | W65: 0 | X65: 0 | Y65: 0 | Z65: 0 | AA65: 0 | AB65: 0 | AC65: =T65+SUM(U65:AB65) -> 16409801 | AD65: =Q65-AC65 -> 1.5589311e+09 | AE65: =IF(O65="Aktif",AB65,0) -> 0 | AF65: =IF(AE65>0,MAX(0,AD65)/AE65,0) -> 0 | AG65: =IF($O65="Aktif",MAX(0,MIN($AE65,$AD65-0)),0) -> 0 | AH65: =IF($O65="Aktif",MAX(0,MIN($AE65,$AD65-SUM($AG65:AG65))),0) -> 0 | AI65: =IF($O65="Aktif",MAX(0,MIN($AE65,$AD65-SUM($AG65:AH65))),0) -> 0 | AJ65: =IF($O65="Aktif",MAX(0,MIN($AE65,$AD65-SUM($AG65:AI65))),0) -> 0 | AK65: =IF($O65="Aktif",MAX(0,MIN($AE65,$AD65-SUM($AG65:AJ65))),0) -> 0 | AL65: =IF($O65="Aktif",MAX(0,MIN($AE65,$AD65-SUM($AG65:AK65))),0) -> 0 | AM65: =IF($O65="Aktif",MAX(0,MIN($AE65,$AD65-SUM($AG65:AL65))),0) -> 0 | AN65: =IF($O65="Aktif",MAX(0,MIN($AE65,$AD65-SUM($AG65:AM65))),0) -> 0 | AO65: =IF($O65="Aktif",MAX(0,MIN($AE65,$AD65-SUM($AG65:AN65))),0) -> 0 | ... AV65: =IF($O65="Aktif",MAX(0,MIN($AE65,$AD65-SUM($AG65:AU65))),0) -> 0 | AW65: =SUM(AG65:AV65) -> 0 | AX65: =AD65-AW65 -> 1.5589311e+09
A66: 60 | B66: FA Kendaraan | C66: 39 | D66: Vehicles | E66: - | F66: 1201-003 | G66: 1202-003 | H66: 6500-003 | I66: Depreciation Expenses | L66: 44674 | M66: BMW X5 xDrive 40i xLine - G05 Alpine White | N66: MATRIX AUTO, Inv 816 BMW X5 XDRIVE 40l, Jeep Putih Metalik Tahun 2022 1 Unit 23/04/2022 | O66: Dijual | P66: 1 | Q66: -1575340909 | S66: 0 | T66: -16409801 | U66: 0 | V66: 0 | W66: 0 | X66: 0 | Y66: 0 | Z66: 0 | AA66: 0 | AB66: 0 | AC66: =T66+SUM(U66:AB66) -> -16409801 | AD66: =Q66-AC66 -> -1.5589311e+09 | AE66: =IF(O66="Aktif",AB66,0) -> 0 | AF66: =IF(AE66>0,MAX(0,AD66)/AE66,0) -> 0 | AG66: =IF($O66="Aktif",MAX(0,MIN($AE66,$AD66-0)),0) -> 0 | AH66: =IF($O66="Aktif",MAX(0,MIN($AE66,$AD66-SUM($AG66:AG66))),0) -> 0 | AI66: =IF($O66="Aktif",MAX(0,MIN($AE66,$AD66-SUM($AG66:AH66))),0) -> 0 | AJ66: =IF($O66="Aktif",MAX(0,MIN($AE66,$AD66-SUM($AG66:AI66))),0) -> 0 | AK66: =IF($O66="Aktif",MAX(0,MIN($AE66,$AD66-SUM($AG66:AJ66))),0) -> 0 | AL66: =IF($O66="Aktif",MAX(0,MIN($AE66,$AD66-SUM($AG66:AK66))),0) -> 0 | AM66: =IF($O66="Aktif",MAX(0,MIN($AE66,$AD66-SUM($AG66:AL66))),0) -> 0 | AN66: =IF($O66="Aktif",MAX(0,MIN($AE66,$AD66-SUM($AG66:AM66))),0) -> 0 | AO66: =IF($O66="Aktif",MAX(0,MIN($AE66,$AD66-SUM($AG66:AN66))),0) -> 0 | ... AV66: =IF($O66="Aktif",MAX(0,MIN($AE66,$AD66-SUM($AG66:AU66))),0) -> 0 | AW66: =SUM(AG66:AV66) -> 0 | AX66: =AD66-AW66 -> -1.5589311e+09
A67: 61 | B67: FA Kendaraan | C67: 40 | D67: Vehicles | E67: Gol 2 | F67: 1201-003 | G67: 1202-003 | H67: 6500-003 | I67: Depreciation Expenses | K67: KD2.0004 | L67: 31/08/2022 | M67: Mits. Fuso Fighter FN61FL (6x2) M/T | N67: PT Bumen Redja Abadi, Mits. Fuso Fighter FN61FL M/T 1unit 25/08/22 + karoseri + BBN + Admin H 8595 SM | O67: Aktif | P67: 1 | Q67: 990910811 | R67: 96 | S67: 10321988 | T67: 4.2320149e+08 | U67: 10321988 | V67: 10321988 | W67: 10321988 | X67: 10321988 | Y67: 10321988 | Z67: 10321988 | AA67: 10321988 | AB67: 10321988 | AC67: =T67+SUM(U67:AB67) -> 5.0577739e+08 | AD67: =Q67-AC67 -> 4.8513342e+08 | AE67: =IF(O67="Aktif",AB67,0) -> 10321988 | AF67: =IF(AE67>0,MAX(0,AD67)/AE67,0) -> 47 | AG67: =IF($O67="Aktif",MAX(0,MIN($AE67,$AD67-0)),0) -> 10321988 | AH67: =IF($O67="Aktif",MAX(0,MIN($AE67,$AD67-SUM($AG67:AG67))),0) -> 10321988 | AI67: =IF($O67="Aktif",MAX(0,MIN($AE67,$AD67-SUM($AG67:AH67))),0) -> 10321988 | AJ67: =IF($O67="Aktif",MAX(0,MIN($AE67,$AD67-SUM($AG67:AI67))),0) -> 10321988 | AK67: =IF($O67="Aktif",MAX(0,MIN($AE67,$AD67-SUM($AG67:AJ67))),0) -> 10321988 | AL67: =IF($O67="Aktif",MAX(0,MIN($AE67,$AD67-SUM($AG67:AK67))),0) -> 10321988 | AM67: =IF($O67="Aktif",MAX(0,MIN($AE67,$AD67-SUM($AG67:AL67))),0) -> 10321988 | AN67: =IF($O67="Aktif",MAX(0,MIN($AE67,$AD67-SUM($AG67:AM67))),0) -> 10321988 | AO67: =IF($O67="Aktif",MAX(0,MIN($AE67,$AD67-SUM($AG67:AN67))),0) -> 10321988 | ... AV67: =IF($O67="Aktif",MAX(0,MIN($AE67,$AD67-SUM($AG67:AU67))),0) -> 10321988 | AW67: =SUM(AG67:AV67) -> 1.651518e+08 | AX67: =AD67-AW67 -> 3.1998162e+08
A68: 62 | B68: FA Kendaraan | C68: 41 | D68: Vehicles | E68: Gol 2 | F68: 1201-003 | G68: 1202-003 | H68: 6500-003 | I68: Depreciation Expenses | L68: 44917 | M68: Mobil Mercedez Benz V260 AVG-XLAX B 800 ZNC | N68: Matrix Auto, Mobil Mercedez Benz V260 AVG-XLAX Thn 2020, B 800 ZNC | O68: Aktif | P68: 1 | Q68: 1825000000 | R68: 96 | S68: 19010417 | T68: 1.5208333e+08 | U68: 0 | V68: 0 | W68: 0 | X68: 0 | Y68: 0 | Z68: 0 | AA68: 0 | AB68: 0 | AC68: =T68+SUM(U68:AB68) -> 1.5208333e+08 | AD68: =Q68-AC68 -> 1.6729167e+09 | AE68: =IF(O68="Aktif",AB68,0) -> 0 | AF68: =IF(AE68>0,MAX(0,AD68)/AE68,0) -> 0 | AG68: =IF($O68="Aktif",MAX(0,MIN($AE68,$AD68-0)),0) -> 0 | AH68: =IF($O68="Aktif",MAX(0,MIN($AE68,$AD68-SUM($AG68:AG68))),0) -> 0 | AI68: =IF($O68="Aktif",MAX(0,MIN($AE68,$AD68-SUM($AG68:AH68))),0) -> 0 | AJ68: =IF($O68="Aktif",MAX(0,MIN($AE68,$AD68-SUM($AG68:AI68))),0) -> 0 | AK68: =IF($O68="Aktif",MAX(0,MIN($AE68,$AD68-SUM($AG68:AJ68))),0) -> 0 | AL68: =IF($O68="Aktif",MAX(0,MIN($AE68,$AD68-SUM($AG68:AK68))),0) -> 0 | AM68: =IF($O68="Aktif",MAX(0,MIN($AE68,$AD68-SUM($AG68:AL68))),0) -> 0 | AN68: =IF($O68="Aktif",MAX(0,MIN($AE68,$AD68-SUM($AG68:AM68))),0) -> 0 | AO68: =IF($O68="Aktif",MAX(0,MIN($AE68,$AD68-SUM($AG68:AN68))),0) -> 0 | ... AV68: =IF($O68="Aktif",MAX(0,MIN($AE68,$AD68-SUM($AG68:AU68))),0) -> 0 | AW68: =SUM(AG68:AV68) -> 0 | AX68: =AD68-AW68 -> 1.6729167e+09
A69: 63 | B69: FA Kendaraan | C69: 42 | D69: Vehicles | E69: - | F69: 1201-003 | G69: 1202-003 | H69: 6500-003 | I69: Depreciation Expenses | L69: 45124 | M69: Mobil Mercedez Benz V260 AVG-XLAX Thn 2020, B 800 ZNC | N69: Mobil Mercedez Benz V260 AVG-XLAX Thn 2020, B 800 ZNC | O69: Dihapus | P69: 1 | Q69: -1825000000 | S69: 0 | T69: -1.5208333e+08 | U69: 0 | V69: 0 | W69: 0 | X69: 0 | Y69: 0 | Z69: 0 | AA69: 0 | AB69: 0 | AC69: =T69+SUM(U69:AB69) -> -1.5208333e+08 | AD69: =Q69-AC69 -> -1.6729167e+09 | AE69: =IF(O69="Aktif",AB69,0) -> 0 | AF69: =IF(AE69>0,MAX(0,AD69)/AE69,0) -> 0 | AG69: =IF($O69="Aktif",MAX(0,MIN($AE69,$AD69-0)),0) -> 0 | AH69: =IF($O69="Aktif",MAX(0,MIN($AE69,$AD69-SUM($AG69:AG69))),0) -> 0 | AI69: =IF($O69="Aktif",MAX(0,MIN($AE69,$AD69-SUM($AG69:AH69))),0) -> 0 | AJ69: =IF($O69="Aktif",MAX(0,MIN($AE69,$AD69-SUM($AG69:AI69))),0) -> 0 | AK69: =IF($O69="Aktif",MAX(0,MIN($AE69,$AD69-SUM($AG69:AJ69))),0) -> 0 | AL69: =IF($O69="Aktif",MAX(0,MIN($AE69,$AD69-SUM($AG69:AK69))),0) -> 0 | AM69: =IF($O69="Aktif",MAX(0,MIN($AE69,$AD69-SUM($AG69:AL69))),0) -> 0 | AN69: =IF($O69="Aktif",MAX(0,MIN($AE69,$AD69-SUM($AG69:AM69))),0) -> 0 | AO69: =IF($O69="Aktif",MAX(0,MIN($AE69,$AD69-SUM($AG69:AN69))),0) -> 0 | ... AV69: =IF($O69="Aktif",MAX(0,MIN($AE69,$AD69-SUM($AG69:AU69))),0) -> 0 | AW69: =SUM(AG69:AV69) -> 0 | AX69: =AD69-AW69 -> -1.6729167e+09
A70: 64 | B70: FA Kendaraan | C70: 43 | D70: Vehicles | E70: Gol 2 | F70: 1201-003 | G70: 1202-003 | H70: 6500-003 | I70: Depreciation Expenses | K70: KD2.0004 | L70: 44977 | M70: Kendaraan Roda Tiga | N70: PT Kencana Laju Mandiri, Kendaraan Roda Tiga utk Kirim Daging Singkong, +PPN 11%, 20/02/23 | O70: Aktif | P70: 1 | Q70: 32441441 | R70: 96 | S70: 337931.68 | T70: 11827609 | U70: 337931.68 | V70: 337931.68 | W70: 337931.68 | X70: 337931.68 | Y70: 337931.68 | Z70: 337931.68 | AA70: 337931.68 | AB70: 337931.68 | AC70: =T70+SUM(U70:AB70) -> 14531062 | AD70: =Q70-AC70 -> 17910379 | AE70: =IF(O70="Aktif",AB70,0) -> 337931.68 | AF70: =IF(AE70>0,MAX(0,AD70)/AE70,0) -> 53 | AG70: =IF($O70="Aktif",MAX(0,MIN($AE70,$AD70-0)),0) -> 337931.68 | AH70: =IF($O70="Aktif",MAX(0,MIN($AE70,$AD70-SUM($AG70:AG70))),0) -> 337931.68 | AI70: =IF($O70="Aktif",MAX(0,MIN($AE70,$AD70-SUM($AG70:AH70))),0) -> 337931.68 | AJ70: =IF($O70="Aktif",MAX(0,MIN($AE70,$AD70-SUM($AG70:AI70))),0) -> 337931.68 | AK70: =IF($O70="Aktif",MAX(0,MIN($AE70,$AD70-SUM($AG70:AJ70))),0) -> 337931.68 | AL70: =IF($O70="Aktif",MAX(0,MIN($AE70,$AD70-SUM($AG70:AK70))),0) -> 337931.68 | AM70: =IF($O70="Aktif",MAX(0,MIN($AE70,$AD70-SUM($AG70:AL70))),0) -> 337931.68 | AN70: =IF($O70="Aktif",MAX(0,MIN($AE70,$AD70-SUM($AG70:AM70))),0) -> 337931.68 | AO70: =IF($O70="Aktif",MAX(0,MIN($AE70,$AD70-SUM($AG70:AN70))),0) -> 337931.68 | ... AV70: =IF($O70="Aktif",MAX(0,MIN($AE70,$AD70-SUM($AG70:AU70))),0) -> 337931.68 | AW70: =SUM(AG70:AV70) -> 5406906.8 | AX70: =AD70-AW70 -> 12503472
A71: 65 | B71: FA Kendaraan | C71: 44 | D71: Vehicles | E71: Gol 1 | F71: 1201-003 | G71: 1202-003 | H71: 6500-003 | I71: Depreciation Expenses | K71: KD1.0010 | L71: 45550 | M71: Daihatsu Terios B 2328 UKM | O71: Aktif | P71: 1 | Q71: 170000000 | R71: 96 | S71: 1770833.3 | T71: 28333333 | U71: 1770833.3 | V71: 1770833.3 | W71: 1770833.3 | X71: 1770833.3 | Y71: 1770833.3 | Z71: 1770833.3 | AA71: 1770833.3 | AB71: 1770833.3 | AC71: =T71+SUM(U71:AB71) -> 42500000 | AD71: =Q71-AC71 -> 1.275e+08 | AE71: =IF(O71="Aktif",AB71,0) -> 1770833.3 | AF71: =IF(AE71>0,MAX(0,AD71)/AE71,0) -> 72 | AG71: =IF($O71="Aktif",MAX(0,MIN($AE71,$AD71-0)),0) -> 1770833.3 | AH71: =IF($O71="Aktif",MAX(0,MIN($AE71,$AD71-SUM($AG71:AG71))),0) -> 1770833.3 | AI71: =IF($O71="Aktif",MAX(0,MIN($AE71,$AD71-SUM($AG71:AH71))),0) -> 1770833.3 | AJ71: =IF($O71="Aktif",MAX(0,MIN($AE71,$AD71-SUM($AG71:AI71))),0) -> 1770833.3 | AK71: =IF($O71="Aktif",MAX(0,MIN($AE71,$AD71-SUM($AG71:AJ71))),0) -> 1770833.3 | AL71: =IF($O71="Aktif",MAX(0,MIN($AE71,$AD71-SUM($AG71:AK71))),0) -> 1770833.3 | AM71: =IF($O71="Aktif",MAX(0,MIN($AE71,$AD71-SUM($AG71:AL71))),0) -> 1770833.3 | AN71: =IF($O71="Aktif",MAX(0,MIN($AE71,$AD71-SUM($AG71:AM71))),0) -> 1770833.3 | AO71: =IF($O71="Aktif",MAX(0,MIN($AE71,$AD71-SUM($AG71:AN71))),0) -> 1770833.3 | ... AV71: =IF($O71="Aktif",MAX(0,MIN($AE71,$AD71-SUM($AG71:AU71))),0) -> 1770833.3 | AW71: =SUM(AG71:AV71) -> 28333333 | AX71: =AD71-AW71 -> 99166667
A72: 66 | B72: FA Kendaraan | C72: 45 | D72: Vehicles | E72: Gol 2 | F72: 1201-003 | G72: 1202-003 | H72: 6500-003 | I72: Depreciation Expenses | K72: KD2.0006 | L72: 45884 | M72: Stargazer Essential IVT 6 Seat Midnight Black Pearl, B1710 RZX | O72: Aktif | P72: 1 | Q72: 236329821 | R72: 96 | S72: 2461769 | T72: 12308845 | U72: 2461769 | V72: 2461769 | W72: 2461769 | X72: 2461769 | Y72: 2461769 | Z72: 2461769 | AA72: 2461769 | AB72: 2461769 | AC72: =T72+SUM(U72:AB72) -> 32002997 | AD72: =Q72-AC72 -> 2.0432682e+08 | AE72: =IF(O72="Aktif",AB72,0) -> 2461769 | AF72: =IF(AE72>0,MAX(0,AD72)/AE72,0) -> 83 | AG72: =IF($O72="Aktif",MAX(0,MIN($AE72,$AD72-0)),0) -> 2461769 | AH72: =IF($O72="Aktif",MAX(0,MIN($AE72,$AD72-SUM($AG72:AG72))),0) -> 2461769 | AI72: =IF($O72="Aktif",MAX(0,MIN($AE72,$AD72-SUM($AG72:AH72))),0) -> 2461769 | AJ72: =IF($O72="Aktif",MAX(0,MIN($AE72,$AD72-SUM($AG72:AI72))),0) -> 2461769 | AK72: =IF($O72="Aktif",MAX(0,MIN($AE72,$AD72-SUM($AG72:AJ72))),0) -> 2461769 | AL72: =IF($O72="Aktif",MAX(0,MIN($AE72,$AD72-SUM($AG72:AK72))),0) -> 2461769 | AM72: =IF($O72="Aktif",MAX(0,MIN($AE72,$AD72-SUM($AG72:AL72))),0) -> 2461769 | AN72: =IF($O72="Aktif",MAX(0,MIN($AE72,$AD72-SUM($AG72:AM72))),0) -> 2461769 | AO72: =IF($O72="Aktif",MAX(0,MIN($AE72,$AD72-SUM($AG72:AN72))),0) -> 2461769 | ... AV72: =IF($O72="Aktif",MAX(0,MIN($AE72,$AD72-SUM($AG72:AU72))),0) -> 2461769 | AW72: =SUM(AG72:AV72) -> 39388304 | AX72: =AD72-AW72 -> 1.6493852e+08
A73: 67 | B73: FA Kendaraan | C73: 46 | D73: Vehicles | E73: Gol 2 | F73: 1201-003 | G73: 1202-003 | H73: 6500-003 | I73: Depreciation Expenses | K73: KD2.0007 | L73: 45976 | M73: Mobil Daihatsu Luxio, B 1935 RYE | N73: Mobil Daihatsu Luxio, B 1935 RYE | O73: Aktif | P73: 1 | Q73: 246578010 | R73: 96 | S73: 2568520.9 | T73: 5137041.9 | U73: 2568520.9 | V73: 2568520.9 | W73: 2568520.9 | X73: 2568520.9 | Y73: 2568520.9 | Z73: 2568520.9 | AA73: 2568520.9 | AB73: 2568520.9 | AC73: =T73+SUM(U73:AB73) -> 25685209 | AD73: =Q73-AC73 -> 2.208928e+08 | AE73: =IF(O73="Aktif",AB73,0) -> 2568520.9 | AF73: =IF(AE73>0,MAX(0,AD73)/AE73,0) -> 86 | AG73: =IF($O73="Aktif",MAX(0,MIN($AE73,$AD73-0)),0) -> 2568520.9 | AH73: =IF($O73="Aktif",MAX(0,MIN($AE73,$AD73-SUM($AG73:AG73))),0) -> 2568520.9 | AI73: =IF($O73="Aktif",MAX(0,MIN($AE73,$AD73-SUM($AG73:AH73))),0) -> 2568520.9 | AJ73: =IF($O73="Aktif",MAX(0,MIN($AE73,$AD73-SUM($AG73:AI73))),0) -> 2568520.9 | AK73: =IF($O73="Aktif",MAX(0,MIN($AE73,$AD73-SUM($AG73:AJ73))),0) -> 2568520.9 | AL73: =IF($O73="Aktif",MAX(0,MIN($AE73,$AD73-SUM($AG73:AK73))),0) -> 2568520.9 | AM73: =IF($O73="Aktif",MAX(0,MIN($AE73,$AD73-SUM($AG73:AL73))),0) -> 2568520.9 | AN73: =IF($O73="Aktif",MAX(0,MIN($AE73,$AD73-SUM($AG73:AM73))),0) -> 2568520.9 | AO73: =IF($O73="Aktif",MAX(0,MIN($AE73,$AD73-SUM($AG73:AN73))),0) -> 2568520.9 | ... AV73: =IF($O73="Aktif",MAX(0,MIN($AE73,$AD73-SUM($AG73:AU73))),0) -> 2568520.9 | AW73: =SUM(AG73:AV73) -> 41096335 | AX73: =AD73-AW73 -> 1.7979647e+08
A74: 68 | B74: FA Kendaraan | C74: 47 | D74: Vehicles | E74: Gol 2 | F74: 1201-003 | G74: 1202-003 | H74: 6500-003 | I74: Depreciation Expenses | K74: KD2.0008 | L74: 45995 | M74: Daihatsu Grand Max Bv 1.3 AC FH E4 | N74: Daihatsu Grand Max Bv 1.3 AC FH E4, B 9925 TCT | O74: Aktif | P74: 1 | Q74: 143422719 | R74: 96 | S74: 1493986.7 | T74: 1493986.7 | U74: 1493986.7 | V74: 1493986.7 | W74: 1493986.7 | X74: 1493986.7 | Y74: 1493986.7 | Z74: 1493986.7 | AA74: 1493986.7 | AB74: 1493986.7 | AC74: =T74+SUM(U74:AB74) -> 13445880 | AD74: =Q74-AC74 -> 1.2997684e+08 | AE74: =IF(O74="Aktif",AB74,0) -> 1493986.7 | AF74: =IF(AE74>0,MAX(0,AD74)/AE74,0) -> 87 | AG74: =IF($O74="Aktif",MAX(0,MIN($AE74,$AD74-0)),0) -> 1493986.7 | AH74: =IF($O74="Aktif",MAX(0,MIN($AE74,$AD74-SUM($AG74:AG74))),0) -> 1493986.7 | AI74: =IF($O74="Aktif",MAX(0,MIN($AE74,$AD74-SUM($AG74:AH74))),0) -> 1493986.7 | AJ74: =IF($O74="Aktif",MAX(0,MIN($AE74,$AD74-SUM($AG74:AI74))),0) -> 1493986.7 | AK74: =IF($O74="Aktif",MAX(0,MIN($AE74,$AD74-SUM($AG74:AJ74))),0) -> 1493986.7 | AL74: =IF($O74="Aktif",MAX(0,MIN($AE74,$AD74-SUM($AG74:AK74))),0) -> 1493986.7 | AM74: =IF($O74="Aktif",MAX(0,MIN($AE74,$AD74-SUM($AG74:AL74))),0) -> 1493986.7 | AN74: =IF($O74="Aktif",MAX(0,MIN($AE74,$AD74-SUM($AG74:AM74))),0) -> 1493986.7 | AO74: =IF($O74="Aktif",MAX(0,MIN($AE74,$AD74-SUM($AG74:AN74))),0) -> 1493986.7 | ... AV74: =IF($O74="Aktif",MAX(0,MIN($AE74,$AD74-SUM($AG74:AU74))),0) -> 1493986.7 | AW74: =SUM(AG74:AV74) -> 23903786 | AX74: =AD74-AW74 -> 1.0607305e+08
A75: 69 | B75: FA Kendaraan | C75: 48 | D75: Vehicles | E75: Gol 2 | F75: 1201-003 | G75: 1202-003 | H75: 6500-003 | I75: Depreciation Expenses | K75: KD2.0009 | L75: 46006 | M75: Sepeda Motor Roda Tiga VIAR | N75: Sepeda Motor Roda Tiga VIAR | O75: Aktif | P75: 1 | Q75: 32546847 | R75: 96 | S75: 339029.66 | T75: 339029.66 | U75: 339029.66 | V75: 339029.66 | W75: 339029.66 | X75: 339029.66 | Y75: 339029.66 | Z75: 339029.66 | AA75: 339029.66 | AB75: 339029.66 | AC75: =T75+SUM(U75:AB75) -> 3051266.9 | AD75: =Q75-AC75 -> 29495580 | AE75: =IF(O75="Aktif",AB75,0) -> 339029.66 | AF75: =IF(AE75>0,MAX(0,AD75)/AE75,0) -> 87 | AG75: =IF($O75="Aktif",MAX(0,MIN($AE75,$AD75-0)),0) -> 339029.66 | AH75: =IF($O75="Aktif",MAX(0,MIN($AE75,$AD75-SUM($AG75:AG75))),0) -> 339029.66 | AI75: =IF($O75="Aktif",MAX(0,MIN($AE75,$AD75-SUM($AG75:AH75))),0) -> 339029.66 | AJ75: =IF($O75="Aktif",MAX(0,MIN($AE75,$AD75-SUM($AG75:AI75))),0) -> 339029.66 | AK75: =IF($O75="Aktif",MAX(0,MIN($AE75,$AD75-SUM($AG75:AJ75))),0) -> 339029.66 | AL75: =IF($O75="Aktif",MAX(0,MIN($AE75,$AD75-SUM($AG75:AK75))),0) -> 339029.66 | AM75: =IF($O75="Aktif",MAX(0,MIN($AE75,$AD75-SUM($AG75:AL75))),0) -> 339029.66 | AN75: =IF($O75="Aktif",MAX(0,MIN($AE75,$AD75-SUM($AG75:AM75))),0) -> 339029.66 | AO75: =IF($O75="Aktif",MAX(0,MIN($AE75,$AD75-SUM($AG75:AN75))),0) -> 339029.66 | ... AV75: =IF($O75="Aktif",MAX(0,MIN($AE75,$AD75-SUM($AG75:AU75))),0) -> 339029.66 | AW75: =SUM(AG75:AV75) -> 5424474.5 | AX75: =AD75-AW75 -> 24071106
A76: 70 | B76: FA Kendaraan | C76: 49 | D76: Vehicles | E76: Gol 2 | F76: 1201-003 | G76: 1202-003 | H76: 6500-003 | I76: Depreciation Expenses | K76: KD2.0011 | L76: 46143 | M76: Tesla Model Y A/T B 1125 SNR | N76: Tesla Model Y A/T B 1125 SNR | O76: Aktif | P76: 1 | Q76: 600000000 | R76: 96 | S76: 6250000 | T76: 0 | U76: 0 | V76: 0 | W76: 0 | X76: 0 | Y76: 6250000 | Z76: 6250000 | AA76: 6250000 | AB76: 6250000 | AC76: =T76+SUM(U76:AB76) -> 25000000 | AD76: =Q76-AC76 -> 575000000 | AE76: =IF(O76="Aktif",AB76,0) -> 6250000 | AF76: =IF(AE76>0,MAX(0,AD76)/AE76,0) -> 92 | AG76: =IF($O76="Aktif",MAX(0,MIN($AE76,$AD76-0)),0) -> 6250000 | AH76: =IF($O76="Aktif",MAX(0,MIN($AE76,$AD76-SUM($AG76:AG76))),0) -> 6250000 | AI76: =IF($O76="Aktif",MAX(0,MIN($AE76,$AD76-SUM($AG76:AH76))),0) -> 6250000 | AJ76: =IF($O76="Aktif",MAX(0,MIN($AE76,$AD76-SUM($AG76:AI76))),0) -> 6250000 | AK76: =IF($O76="Aktif",MAX(0,MIN($AE76,$AD76-SUM($AG76:AJ76))),0) -> 6250000 | AL76: =IF($O76="Aktif",MAX(0,MIN($AE76,$AD76-SUM($AG76:AK76))),0) -> 6250000 | AM76: =IF($O76="Aktif",MAX(0,MIN($AE76,$AD76-SUM($AG76:AL76))),0) -> 6250000 | AN76: =IF($O76="Aktif",MAX(0,MIN($AE76,$AD76-SUM($AG76:AM76))),0) -> 6250000 | AO76: =IF($O76="Aktif",MAX(0,MIN($AE76,$AD76-SUM($AG76:AN76))),0) -> 6250000 | ... AV76: =IF($O76="Aktif",MAX(0,MIN($AE76,$AD76-SUM($AG76:AU76))),0) -> 6250000 | AW76: =SUM(AG76:AV76) -> 100000000 | AX76: =AD76-AW76 -> 475000000
A77: 71 | B77: FA Inventaris Kantor | C77: 9 | D77: Office Furniture and Equipment | E77: Value Gol 1 | F77: 1201-011 | G77: 1202-011 | H77: 6500-009 | I77: Depreciation Expenses | K77: Asset Cost Value 1 | L77: 2007 | M77: Software | N77: Pembelian Software | O77: Aktif | P77: 1 | Q77: 11200000 | R77: 48 | S77: 0 | T77: 11200000 | U77: 0 | V77: 0 | W77: 0 | X77: 0 | Y77: 0 | Z77: 0 | AA77: 0 | AB77: 0 | AC77: =T77+SUM(U77:AB77) -> 11200000 | AD77: =Q77-AC77 -> 0 | AE77: =IF(O77="Aktif",AB77,0) -> 0 | AF77: =IF(AE77>0,MAX(0,AD77)/AE77,0) -> 0 | AG77: =IF($O77="Aktif",MAX(0,MIN($AE77,$AD77-0)),0) -> 0 | AH77: =IF($O77="Aktif",MAX(0,MIN($AE77,$AD77-SUM($AG77:AG77))),0) -> 0 | AI77: =IF($O77="Aktif",MAX(0,MIN($AE77,$AD77-SUM($AG77:AH77))),0) -> 0 | AJ77: =IF($O77="Aktif",MAX(0,MIN($AE77,$AD77-SUM($AG77:AI77))),0) -> 0 | AK77: =IF($O77="Aktif",MAX(0,MIN($AE77,$AD77-SUM($AG77:AJ77))),0) -> 0 | AL77: =IF($O77="Aktif",MAX(0,MIN($AE77,$AD77-SUM($AG77:AK77))),0) -> 0 | AM77: =IF($O77="Aktif",MAX(0,MIN($AE77,$AD77-SUM($AG77:AL77))),0) -> 0 | AN77: =IF($O77="Aktif",MAX(0,MIN($AE77,$AD77-SUM($AG77:AM77))),0) -> 0 | AO77: =IF($O77="Aktif",MAX(0,MIN($AE77,$AD77-SUM($AG77:AN77))),0) -> 0 | ... AV77: =IF($O77="Aktif",MAX(0,MIN($AE77,$AD77-SUM($AG77:AU77))),0) -> 0 | AW77: =SUM(AG77:AV77) -> 0 | AX77: =AD77-AW77 -> 0
A78: 72 | B78: FA Inventaris Kantor | C78: 10 | D78: Office Furniture and Equipment | E78: Value Gol 1 | F78: 1201-011 | G78: 1202-011 | H78: 6500-009 | I78: Depreciation Expenses | K78: Asset Cost Value 1 | L78: 03-01-2008 | M78: Walkie Talkie | N78: 3 BH Walkie Talkie | O78: Aktif | P78: 1 | Q78: 1545000 | R78: 48 | S78: 0 | T78: 1545000 | U78: 0 | V78: 0 | W78: 0 | X78: 0 | Y78: 0 | Z78: 0 | AA78: 0 | AB78: 0 | AC78: =T78+SUM(U78:AB78) -> 1545000 | AD78: =Q78-AC78 -> 0 | AE78: =IF(O78="Aktif",AB78,0) -> 0 | AF78: =IF(AE78>0,MAX(0,AD78)/AE78,0) -> 0 | AG78: =IF($O78="Aktif",MAX(0,MIN($AE78,$AD78-0)),0) -> 0 | AH78: =IF($O78="Aktif",MAX(0,MIN($AE78,$AD78-SUM($AG78:AG78))),0) -> 0 | AI78: =IF($O78="Aktif",MAX(0,MIN($AE78,$AD78-SUM($AG78:AH78))),0) -> 0 | AJ78: =IF($O78="Aktif",MAX(0,MIN($AE78,$AD78-SUM($AG78:AI78))),0) -> 0 | AK78: =IF($O78="Aktif",MAX(0,MIN($AE78,$AD78-SUM($AG78:AJ78))),0) -> 0 | AL78: =IF($O78="Aktif",MAX(0,MIN($AE78,$AD78-SUM($AG78:AK78))),0) -> 0 | AM78: =IF($O78="Aktif",MAX(0,MIN($AE78,$AD78-SUM($AG78:AL78))),0) -> 0 | AN78: =IF($O78="Aktif",MAX(0,MIN($AE78,$AD78-SUM($AG78:AM78))),0) -> 0 | AO78: =IF($O78="Aktif",MAX(0,MIN($AE78,$AD78-SUM($AG78:AN78))),0) -> 0 | ... AV78: =IF($O78="Aktif",MAX(0,MIN($AE78,$AD78-SUM($AG78:AU78))),0) -> 0 | AW78: =SUM(AG78:AV78) -> 0 | AX78: =AD78-AW78 -> 0
A79: 73 | B79: FA Inventaris Kantor | C79: 11 | D79: Office Furniture and Equipment | E79: Value Gol 1 | F79: 1201-011 | G79: 1202-011 | H79: 6500-009 | I79: Depreciation Expenses | K79: Asset Cost Value 1 | L79: 28-01-2008 | M79: Komputer + Monitor | N79: 2 Unit Komputer + Monitor | O79: Aktif | P79: 1 | Q79: 12425000 | R79: 48 | S79: 0 | T79: 12425000 | U79: 0 | V79: 0 | W79: 0 | X79: 0 | Y79: 0 | Z79: 0 | AA79: 0 | AB79: 0 | AC79: =T79+SUM(U79:AB79) -> 12425000 | AD79: =Q79-AC79 -> 0 | AE79: =IF(O79="Aktif",AB79,0) -> 0 | AF79: =IF(AE79>0,MAX(0,AD79)/AE79,0) -> 0 | AG79: =IF($O79="Aktif",MAX(0,MIN($AE79,$AD79-0)),0) -> 0 | AH79: =IF($O79="Aktif",MAX(0,MIN($AE79,$AD79-SUM($AG79:AG79))),0) -> 0 | AI79: =IF($O79="Aktif",MAX(0,MIN($AE79,$AD79-SUM($AG79:AH79))),0) -> 0 | AJ79: =IF($O79="Aktif",MAX(0,MIN($AE79,$AD79-SUM($AG79:AI79))),0) -> 0 | AK79: =IF($O79="Aktif",MAX(0,MIN($AE79,$AD79-SUM($AG79:AJ79))),0) -> 0 | AL79: =IF($O79="Aktif",MAX(0,MIN($AE79,$AD79-SUM($AG79:AK79))),0) -> 0 | AM79: =IF($O79="Aktif",MAX(0,MIN($AE79,$AD79-SUM($AG79:AL79))),0) -> 0 | AN79: =IF($O79="Aktif",MAX(0,MIN($AE79,$AD79-SUM($AG79:AM79))),0) -> 0 | AO79: =IF($O79="Aktif",MAX(0,MIN($AE79,$AD79-SUM($AG79:AN79))),0) -> 0 | ... AV79: =IF($O79="Aktif",MAX(0,MIN($AE79,$AD79-SUM($AG79:AU79))),0) -> 0 | AW79: =SUM(AG79:AV79) -> 0 | AX79: =AD79-AW79 -> 0
A80: 74 | B80: FA Inventaris Kantor | C80: 12 | D80: Office Furniture and Equipment | E80: Value Gol 1 | F80: 1201-011 | G80: 1202-011 | H80: 6500-009 | I80: Depreciation Expenses | K80: Asset Cost Value 1 | L80: 28-01-2008 | M80: Notebook | N80: 1 Unit Notebook | O80: Aktif | P80: 1 | Q80: 9125000 | R80: 48 | S80: 0 | T80: 9125000 | U80: 0 | V80: 0 | W80: 0 | X80: 0 | Y80: 0 | Z80: 0 | AA80: 0 | AB80: 0 | AC80: =T80+SUM(U80:AB80) -> 9125000 | AD80: =Q80-AC80 -> 0 | AE80: =IF(O80="Aktif",AB80,0) -> 0 | AF80: =IF(AE80>0,MAX(0,AD80)/AE80,0) -> 0 | AG80: =IF($O80="Aktif",MAX(0,MIN($AE80,$AD80-0)),0) -> 0 | AH80: =IF($O80="Aktif",MAX(0,MIN($AE80,$AD80-SUM($AG80:AG80))),0) -> 0 | AI80: =IF($O80="Aktif",MAX(0,MIN($AE80,$AD80-SUM($AG80:AH80))),0) -> 0 | AJ80: =IF($O80="Aktif",MAX(0,MIN($AE80,$AD80-SUM($AG80:AI80))),0) -> 0 | AK80: =IF($O80="Aktif",MAX(0,MIN($AE80,$AD80-SUM($AG80:AJ80))),0) -> 0 | AL80: =IF($O80="Aktif",MAX(0,MIN($AE80,$AD80-SUM($AG80:AK80))),0) -> 0 | AM80: =IF($O80="Aktif",MAX(0,MIN($AE80,$AD80-SUM($AG80:AL80))),0) -> 0 | AN80: =IF($O80="Aktif",MAX(0,MIN($AE80,$AD80-SUM($AG80:AM80))),0) -> 0 | AO80: =IF($O80="Aktif",MAX(0,MIN($AE80,$AD80-SUM($AG80:AN80))),0) -> 0 | ... AV80: =IF($O80="Aktif",MAX(0,MIN($AE80,$AD80-SUM($AG80:AU80))),0) -> 0 | AW80: =SUM(AG80:AV80) -> 0 | AX80: =AD80-AW80 -> 0
A81: 75 | B81: FA Inventaris Kantor | C81: 13 | D81: Office Furniture and Equipment | E81: Value Gol 1 | F81: 1201-011 | G81: 1202-011 | H81: 6500-009 | I81: Depreciation Expenses | K81: Asset Cost Value 1 | L81: 02-02-2008 | M81: Fax Panasonic | N81: Beli Fax Panasonic | O81: Aktif | P81: 1 | Q81: 980000 | R81: 48 | S81: 0 | T81: 980000 | U81: 0 | V81: 0 | W81: 0 | X81: 0 | Y81: 0 | Z81: 0 | AA81: 0 | AB81: 0 | AC81: =T81+SUM(U81:AB81) -> 980000 | AD81: =Q81-AC81 -> 0 | AE81: =IF(O81="Aktif",AB81,0) -> 0 | AF81: =IF(AE81>0,MAX(0,AD81)/AE81,0) -> 0 | AG81: =IF($O81="Aktif",MAX(0,MIN($AE81,$AD81-0)),0) -> 0 | AH81: =IF($O81="Aktif",MAX(0,MIN($AE81,$AD81-SUM($AG81:AG81))),0) -> 0 | AI81: =IF($O81="Aktif",MAX(0,MIN($AE81,$AD81-SUM($AG81:AH81))),0) -> 0 | AJ81: =IF($O81="Aktif",MAX(0,MIN($AE81,$AD81-SUM($AG81:AI81))),0) -> 0 | AK81: =IF($O81="Aktif",MAX(0,MIN($AE81,$AD81-SUM($AG81:AJ81))),0) -> 0 | AL81: =IF($O81="Aktif",MAX(0,MIN($AE81,$AD81-SUM($AG81:AK81))),0) -> 0 | AM81: =IF($O81="Aktif",MAX(0,MIN($AE81,$AD81-SUM($AG81:AL81))),0) -> 0 | AN81: =IF($O81="Aktif",MAX(0,MIN($AE81,$AD81-SUM($AG81:AM81))),0) -> 0 | AO81: =IF($O81="Aktif",MAX(0,MIN($AE81,$AD81-SUM($AG81:AN81))),0) -> 0 | ... AV81: =IF($O81="Aktif",MAX(0,MIN($AE81,$AD81-SUM($AG81:AU81))),0) -> 0 | AW81: =SUM(AG81:AV81) -> 0 | AX81: =AD81-AW81 -> 0
