Workbook

Sheet RINGKASAN
A1: RINGKASAN WP COSTING
A3: Status kontrol semua sheet + kontrol ke GL/LK (bagian 5) | C3: =IF(AND('REKON & KONTROL'!$D$69="LULUS",$I$50="LULUS"),"LULUS","GAGAL") -> LULUS
A4: di dalamnya: kontrol ke GL, Neraca, Laba Rugi (bagian 5) | C4: =$I$50 -> LULUS
A5: 1. Biaya produksi dan HPP per produk (Rp juta; Rp/kg per kg produksi)
A6: Pos | B6: FCC | C6: Ubi Ungu | D6: Ubi Orange | E6: Lain-lain | F6: Total
A7: Produksi (kg) | B7: ='REKON & KONTROL'!B6 -> 236923 | C7: ='REKON & KONTROL'!C6 -> 467.5 | D7: ='REKON & KONTROL'!D6 -> 6715.5 | E7: ='REKON & KONTROL'!E6 -> 45653.42 | F7: ='REKON & KONTROL'!F6 -> 289759.42
A8: Total biaya produksi | B8: ='REKON & KONTROL'!B12 -> 5562.5685 | C8: ='REKON & KONTROL'!C12 -> 18.227721 | D8: ='REKON & KONTROL'!D12 -> 252.5666 | E8: ='REKON & KONTROL'!E12 -> 870.97808 | F8: ='REKON & KONTROL'!F12 -> 6704.3409
A9: Biaya produksi per kg (Rp) | B9: ='REKON & KONTROL'!B13 -> 23478.381 | C9: ='REKON & KONTROL'!C13 -> 38989.777 | D9: ='REKON & KONTROL'!D13 -> 37609.501 | E9: ='REKON & KONTROL'!E13 -> 19078.047 | F9: ='REKON & KONTROL'!F13 -> 23137.611
A10: HPP | B10: ='REKON & KONTROL'!B14 -> 5106.3121 | C10: ='REKON & KONTROL'!C14 -> 232.70642 | D10: ='REKON & KONTROL'!D14 -> 252.5666 | E10: ='REKON & KONTROL'!E14 -> 871.58173 | F10: ='REKON & KONTROL'!F14 -> 6463.1669
A11: Pendapatan (total = GL) | B11: ='REKON & KONTROL'!B15 -> 5901.3131 | C11: ='REKON & KONTROL'!C15 -> 321.7005 | D11: ='REKON & KONTROL'!D15 -> 321.67245 | E11: ='REKON & KONTROL'!E15 -> 917.67406 | F11: ='REKON & KONTROL'!F15 -> 7462.3602
A12: Margin kotor (%) | B12: ='REKON & KONTROL'!B16 -> 0.13471595 | C12: ='REKON & KONTROL'!C16 -> 0.27663644 | D12: ='REKON & KONTROL'!D16 -> 0.21483297 | E12: ='REKON & KONTROL'!E16 -> 0.050227349 | F12: ='REKON & KONTROL'!F16 -> 0.13389775
A14: 2. FCC, UU, UO: Rp/kg aktual vs budget dan penyebab selisih (Rp/kg)
A15: Produk | B15: Rp/kg aktual | C15: Rp/kg budget | D15: Selisih | E15: Harga / belanja | F15: Pemakaian / yield | G15: Volume | H15: Metode alokasi | I15: Bulan budget
A16: FCC | B16: =FCC!F133 -> 23301.541 | C16: =FCC!G133 -> 0 | D16: =FCC!H133 -> 23301.541 | E16: =FCC!I133 -> 23958.869 | F16: =FCC!J133 -> 40.796406 | G16: =FCC!K133 -> 0 | H16: =FCC!L133 -> -698.12472 | I16: =FCC!$C$5 -> Sep-26
A17: UU | B17: =UU!F126 -> 38989.777 | C17: =UU!G126 -> 0 | D17: =UU!H126 -> 38989.777 | E17: =UU!I126 -> 32383.525 | F17: =UU!J126 -> 74.749813 | G17: =UU!K126 -> 0 | H17: =UU!L126 -> 6531.5017 | I17: =UU!$C$5 -> Sep-26
A18: UO | B18: =UO!F122 -> 37609.501 | C18: =UO!G122 -> 0 | D18: =UO!H122 -> 37609.501 | E18: =UO!I122 -> 31682.571 | F18: =UO!J122 -> 49.472884 | G18: =UO!K122 -> 0 | H18: =UO!L122 -> 5877.4567 | I18: =UO!$C$3 -> Sep-26
A21: 3. Biaya yang tidak terlihat di margin (memo)
A22: Pos | B22: FCC | C22: Ubi Ungu | D22: Ubi Orange | F22: Catatan
A23: Biaya waste (kerugian normal) yang terserap ke HPP (Rp jt) | B23: =FCC!$B$23 -> 155.53505 | C23: =UU!$B$23 -> 0 | D23: =UO!$B$21 -> 0
A24: KW 2 dikreditkan pada NRV (Rp jt) | B24: =FCC!$B$24 -> 74.121493 | C24: =UU!$B$24 -> 0 | D24: =UO!$B$22 -> 0
A25: Kenaikan WIP + FG (Rp jt) | B25: =(FCC!$E$79+FCC!$E$92-FCC!$E$72-FCC!$E$86)/10^6 -> -111.4571 | C25: =UU!$B$25 -> -214.4787 | D25: =(UO!$E$73+UO!$E$85-UO!$E$66-UO!$E$80)/10^6 -> 0
A26: Biaya jam operator tidak terpakai untuk produk (Rp jt; % jam) | B26: ='BIAYA BERSAMA'!$C$109/10^6 -> 61.594633 | C26: ='BIAYA BERSAMA'!$D$107 -> 0.13124381
A28: 4. Rekonsiliasi ke GL (Rp juta)
A29: Total HPP kartu baru | B29: ='REKON & KONTROL'!$C$37 -> 6463.1669
A30: Varian material (GL − kartu) | B30: ='REKON & KONTROL'!$C$38 -> -121.14819
A31: Selisih kenaikan persediaan kartu baru vs GL | B31: ='REKON & KONTROL'!$C$47 -> 82.766047
A32: Kenaikan persediaan KW 2 pada NRV | B32: ='REKON & KONTROL'!$C$41 -> -25.596896
A33: Jam menganggur dibebankan ke periode | B33: ='REKON & KONTROL'!$C$43 -> 0
A34: HPP menurut GL | B34: ='REKON & KONTROL'!$C$45 -> 6375.4123
A35: Cek (harus nol) | B35: ='REKON & KONTROL'!$C$46 -> 7.2142293e-06
A37: 5. Kontrol ke GL Accurate dan LK: Laba Rugi dan Neraca (Rp juta; toleransi Rp 0,001 jt)
A38: Pos | B38: Menurut WP | C38: GL Accurate | D38: LK (LR / Neraca) | E38: Selisih WP − GL | F38: Dijelaskan pos rekon | G38: Sisa WP − GL | H38: Selisih GL − LK | I38: Status | J38: Penjelasan / sumber
A39: Laba rugi bulan ini
A40: Pendapatan | B40: ='REKON & KONTROL'!$F$15 -> 7462.3602 | C40: ='REKON & KONTROL'!$C$73/10^6 -> 7462.3602 | D40: =$B$58/10^6 -> 7462.3602 | E40: =B40-C40 -> 0 | F40: 0 | G40: =E40-F40 -> 0 | H40: =C40-D40 -> 0 | I40: =IF(OR(ISERROR(G40),ISERROR(H40)),"GAGAL",IF(AND(ABS(G40)<=0.001,ABS(H40)<=0.001),"LULUS","GAGAL")) -> LULUS | J40: WP: REKON F15 (pendapatan per produk). GL: 4101-007 (REKON C72).
A41: Pemakaian bahan baku | B41: ='REKON & KONTROL'!$B$28 -> 4496.3664 | C41: ='REKON MATERIAL'!$C$69/10^6 -> 4375.2182 | D41: =$B$59/10^6 -> 4375.2182 | E41: =B41-C41 -> 121.14818 | F41: =-'REKON & KONTROL'!$B$30 -> 121.14819 | G41: =E41-F41 -> -7.2142302e-06 | H41: =C41-D41 -> 7.2100001e-06 | I41: =IF(OR(ISERROR(G41),ISERROR(H41)),"GAGAL",IF(AND(ABS(G41)<=0.001,ABS(H41)<=0.001),"LULUS","GAGAL")) -> LULUS | J41: WP: material kartu semua produk (REKON B28). GL: 1106-001 Penyesuaian Persediaan neto (REKON MATERIAL). Sisa dijelaskan varian material GL − kartu (REKON B30; rincian per item di REKON MATERIAL).
A42: Biaya konversi (DL + FOH) | B42: ='REKON & KONTROL'!$F$9+'REKON & KONTROL'!$F$10+'REKON & KONTROL'!$F$11+'BIAYA BERSAMA'!$C$111/10^6 -> 1572.7667 | C42: ='BIAYA BERSAMA'!$C$23/10^6 -> 1590.8886 | D42: =$B$60/10^6 -> 1590.8886 | E42: =B42-C42 -> -18.121908 | F42: =('BIAYA BERSAMA'!$C$157+'BIAYA BERSAMA'!$C$158)/10^6 -> -18.121908 | G42: =E42-F42 -> 1.7053026e-13 | H42: =C42-D42 -> 0 | I42: =IF(OR(ISERROR(G42),ISERROR(H42)),"GAGAL",IF(AND(ABS(G42)<=0.001,ABS(H42)<=0.001),"LULUS","GAGAL")) -> LULUS | J42: WP: upah kupas + DL + FOH di semua kartu (REKON F9:F11) + jam menganggur dibebankan ke periode. GL: 16 akun (BIAYA BERSAMA C23). Dijelaskan: penyesuaian BIAYA BERSAMA bagian 8 ke pool dan THR (reklas opex pabrik, THR tertukar, tali asih per bulan jasa, ongkos kirim singkong keluar ke material, pisau Urschel).
A43: HPP | B43: ='REKON & KONTROL'!$F$14 -> 6463.1669 | C43: ='REKON & KONTROL'!$C$45 -> 6375.4123 | D43: =$B$61/10^6 -> 6375.4123 | E43: =B43-C43 -> 87.754589 | F43: =-SUM('REKON & KONTROL'!$C$38:$C$43) -> 87.754597 | G43: =E43-F43 -> -7.2142289e-06 | H43: =C43-D43 -> 0 | I43: =IF(OR(ISERROR(G43),ISERROR(H43)),"GAGAL",IF(AND(ABS(G43)<=0.001,ABS(H43)<=0.001),"LULUS","GAGAL")) -> LULUS | J43: WP: HPP semua kartu (REKON F14). GL: 5101/5102/6500-006/007 (REKON C44). Pos rekon: REKON C38:C42 (varian material, beda kenaikan persediaan kartu vs GL, KW 2 pada NRV, jam menganggur). Ditambah REKON C42: penyesuaian bagian 8 yang masuk kartu (tanda dibalik).
A44: Laba kotor | B44: ='REKON & KONTROL'!$F$15-'REKON & KONTROL'!$F$14 -> 999.19326 | C44: ='REKON & KONTROL'!$C$73/10^6-'REKON & KONTROL'!$C$45 -> 1086.9478 | D44: =$B$58/10^6-$B$61/10^6 -> 1086.9478 | E44: =B44-C44 -> -87.754589 | F44: =SUM('REKON & KONTROL'!$C$38:$C$43) -> -87.754597 | G44: =E44-F44 -> 7.2142298e-06 | H44: =C44-D44 -> 0 | I44: =IF(OR(ISERROR(G44),ISERROR(H44)),"GAGAL",IF(AND(ABS(G44)<=0.001,ABS(H44)<=0.001),"LULUS","GAGAL")) -> LULUS | J44: Pendapatan − HPP. Pos rekon sama dengan baris HPP, tanda dibalik.
A45: Neraca akhir bulan
A46: Persediaan bahan baku 1106-001 | B46: ='REKON MATERIAL'!$N$62/10^6 -> 826.03128 | C46: ='REKON MATERIAL'!$C$70/10^6 -> 947.17946 | D46: =$B$62/10^6 -> 947.1794 | E46: =B46-C46 -> -121.14818 | F46: ='REKON & KONTROL'!$B$30 -> -121.14819 | G46: =E46-F46 -> 7.2289072e-06 | H46: =C46-D46 -> 5.58e-05 | I46: =IF(OR(ISERROR(G46),ISERROR(H46)),"GAGAL",IF(AND(ABS(G46)<=0.001,ABS(H46)<=0.001),"LULUS","GAGAL")) -> LULUS | J46: WP: saldo awal + penerimaan GL − pemakaian kartu (REKON MATERIAL kolom N). GL: saldo awal + penerimaan − penyesuaian. Sisa dijelaskan varian material.
A47: Persediaan barang setengah jadi 1106-002 | B47: =(FCC!$E$79+UU!$E$77+UO!$E$73)/10^6 -> 51.984599 | C47: =$B$63/10^6+'REKON & KONTROL'!$C$75/10^6 -> 297.85071 | D47: =$B$64/10^6 -> 297.85071 | E47: =B47-C47 -> -245.86611 | F47: ='REKON PERSEDIAAN'!$D$23/10^6 -> -245.86611 | G47: =E47-F47 -> 3.126388e-13 | H47: =C47-D47 -> 0 | I47: =IF(OR(ISERROR(G47),ISERROR(H47)),"GAGAL",IF(AND(ABS(G47)<=0.001,ABS(H47)<=0.001,'REKON PERSEDIAAN'!$C$3="LULUS"),"LULUS","GAGAL")) -> LULUS | J47: WP: WIP akhir kartu baru FCC + UU + UO. GL: saldo awal LK + mutasi GL (REKON C74). Selisih dijelaskan per item di REKON PERSEDIAAN: beda penilaian kartu baru vs kartu lama (K1), olein ditahan di WIP-022 (K2), bahan/kemasan di WIP (K3), beda konstan subledger vs GL.
A48: Persediaan barang jadi 1106-003 | B48: =(FCC!$E$92+UU!$E$89+UO!$E$85+'LAIN-LAIN'!$F$93)/10^6 -> 14.171281 | C48: =$B$65/10^6+'REKON & KONTROL'!$C$76/10^6 -> 286.53664 | D48: =$B$66/10^6 -> 286.53664 | E48: =B48-C48 -> -272.36536 | F48: ='REKON PERSEDIAAN'!$G$23/10^6 -> -272.36536 | G48: =E48-F48 -> 9.6633812e-13 | H48: =C48-D48 -> -9.094947e-13 | I48: =IF(OR(ISERROR(G48),ISERROR(H48)),"GAGAL",IF(AND(ABS(G48)<=0.001,ABS(H48)<=0.001,'REKON PERSEDIAAN'!$C$3="LULUS"),"LULUS","GAGAL")) -> LULUS | J48: WP: FG akhir kartu baru FCC + UU + UO + sheet SKU Lain-lain. GL: saldo awal LK + mutasi GL (REKON C75). Selisih dijelaskan per item di REKON PERSEDIAAN: beda penilaian (K1), FG tanpa mutasi (K4), FG tanpa sheet WP (K5), beda konstan subledger vs GL.
A49: Kenaikan persediaan WIP + FG | B49: ='REKON & KONTROL'!$C$39 -> -326.53944 | C49: =-'REKON & KONTROL'!$C$40 -> -409.30549 | D49: =$B$64/10^6+$B$66/10^6-$B$63/10^6-$B$65/10^6 -> -409.30549 | E49: =B49-C49 -> 82.766047 | F49: ='REKON & KONTROL'!$C$47 -> 82.766047 | G49: =E49-F49 -> 0 | H49: =C49-D49 -> -9.6633812e-13 | I49: =IF(OR(ISERROR(G49),ISERROR(H49)),"GAGAL",IF(AND(ABS(G49)<=0.001,ABS(H49)<=0.001),"LULUS","GAGAL")) -> LULUS | J49: WP: kenaikan menurut kartu baru (REKON C39). GL: mutasi 1106-002 + 1106-003 (REKON C74:C75). Sisa dijelaskan REKON C46 (pos rekon HPP). Rincian per kategori: REKON PERSEDIAAN kolom Δ.
A50: Status bagian 5 (semua baris harus LULUS; persediaan WIP/FG dirinci per item di REKON PERSEDIAAN) | I50: =IF(COUNTIF(I39:I49,"GAGAL")=0,"LULUS","GAGAL") -> LULUS
A56: 6. Input LK (Rp) – sel biru
A57: Pos | B57: Nilai (Rp) | C57: Sumber
A58: Pendapatan 4101-007 | B58: 7.4623602e+09 | C58: LK Sep-26 sheet Income Statement, 4101-007, kolom Sep
A59: Pemakaian Bahan Baku | B59: 4.3752182e+09 | C59: LK Sep-26 sheet Income Statement, baris Pemakaian Bahan Baku, kolom Sep
A60: Biaya konversi pabrik (16 akun 5101-002 s/d 5101-016, 6500-006/007) | B60: 1.5908886e+09 | C60: LK Sep-26 sheet Income Statement, jumlah 16 akun, kolom Sep
A61: Total Cost of Goods Sold | B61: 6.3754123e+09 | C61: LK Sep-26 sheet Income Statement, baris Total Cost of Goods Sold, kolom Sep
A62: Persediaan bahan baku 1106-001, akhir bulan | B62: 9.471794e+08 | C62: LK Sep-26 sheet Balance Sheet, 1106-001, kolom September
A63: Persediaan barang setengah jadi 1106-002, awal bulan | B63: 4.9400277e+08 | C63: LK Sep-26 sheet Balance Sheet, 1106-002, kolom Agustus
A64: Persediaan barang setengah jadi 1106-002, akhir bulan | B64: 2.9785071e+08 | C64: LK Sep-26 sheet Balance Sheet, 1106-002, kolom September
A65: Persediaan barang jadi 1106-003, awal bulan | B65: 4.9969006e+08 | C65: LK Sep-26 sheet Balance Sheet, 1106-003, kolom Agustus
A66: Persediaan barang jadi 1106-003, akhir bulan | B66: 2.8653664e+08 | C66: LK Sep-26 sheet Balance Sheet, 1106-003, kolom September

Sheet FCC
A1: KARTU BIAYA PRODUKSI - FCC (Flat Cassava Chips)
A5: Bulan budget pembanding | C5: Sep-26 | D5: posisi: | E5: =MATCH(C5,BUDGET!$C$4:$R$4,0) -> 1
A6: Status kontrol (bagian 6) | C6: =IF(COUNTIF(D159:D169,"GAGAL")=0,"LULUS","GAGAL") -> LULUS
A8: 1. Ringkasan (Rp juta; Rp/kg per kg produksi bulan ini)
A9: Komponen | B9: Aktual (Rp jt) | C9: Aktual Rp/kg | D9: Budget Rp/kg | E9: Selisih Rp/kg | F9: Harga / belanja | G9: Pemakaian / yield | H9: Volume | I9: Metode alokasi
A10: Raw materials | B10: =E44/10^6 -> 2351.873 | C10: =F44 -> 9926.7401 | D10: =G112 -> 0 | E10: =H112 -> 9749.9001 | F10: =I112 -> 9749.9001 | G10: =J112 -> 0 | H10: =K112 -> 0 | I10: =L112 -> 0
A11: Oil | B11: =E46/10^6 -> 1013.4281 | C11: =F46 -> 4277.4576 | D11: =G114 -> 0 | E11: =H114 -> 4277.4576 | F11: =I114 -> 4277.4576 | G11: =J114 -> 0 | H11: =K114 -> 0 | I11: =L114 -> 0
A12: CNG | B12: =E47/10^6 -> 774.66226 | C12: =F47 -> 3269.6794 | D12: =G116 -> 0 | E12: =H116 -> 3269.6794 | F12: =I116 -> 3269.6794 | G12: =J116 -> 0 | H12: =K116 -> 0 | I12: =L116 -> 0
A13: Material - others | B13: =E55/10^6 -> 135.57866 | C13: =F55 -> 572.24777 | D13: =G123 -> 0 | E13: =H123 -> 572.24777 | F13: =I123 -> 531.45136 | G13: =J123 -> 40.796406 | H13: =K123 -> 0 | I13: =L123 -> 0
A14: Upah kupas | B14: =E58/10^6 -> 53.598625 | C14: =F58 -> 226.22804 | D14: =G125 -> 0 | E14: =H125 -> 226.22804 | F14: =I125 -> 226.22804 | G14: =J125 -> 0 | H14: =K125 -> 0 | I14: =L125 -> 0
A15: Direct labour (Grup A) | B15: =E59/10^6 -> 384.85655 | C15: =F59 -> 1624.3951 | D15: =G127 -> 0 | E15: =H127 -> 1624.3951 | F15: =I127 -> 1922.5851 | G15: =J127 -> 0 | H15: =K127 -> 0 | I15: =L127 -> -298.19004
A16: Factory overhead (Grup B–E) | B16: =E64/10^6 -> 848.57125 | C16: =F64 -> 3581.633 | D16: =G132 -> 0 | E16: =H132 -> 3581.633 | F16: =I132 -> 3981.5677 | G16: =J132 -> 0 | H16: =K132 -> 0 | I16: =L132 -> -399.93468
A17: Total biaya produksi | B17: =E66/10^6 -> 5562.5685 | C17: =F66 -> 23478.381 | D17: =G133 -> 0 | E17: =H133 -> 23301.541 | F17: =I133 -> 23958.869 | G17: =J133 -> 40.796406 | H17: =K133 -> 0 | I17: =L133 -> -698.12472
A18: Produksi bulan ini (kg; aktual, budget) | C18: =$B$30 -> 236923 | D18: =$D$30 -> 0
A19: Biaya konversi per kg (aktual, budget) | C19: =F65 -> 5432.2561 | D19: =G125+G127+G132 -> 0
A20: HPP (Rp jt) dan HPP per kg terjual (aktual, budget) | B20: =E104/10^6 -> 5106.3121 | C20: =D105 -> 24631.839 | D20: =F105 -> 0
A21: Pendapatan (Rp jt; aktual) | B21: =$C$211/10^6 -> 5901.3131
A22: Margin kotor (Rp jt; %) | B22: =B21-B20 -> 795.00099 | C22: =IF(B21=0,0,B22/B21) -> 0.13471595
A23: biaya waste (kerugian normal) yang masuk HPP (Rp jt; % biaya produksi) | B23: =E78/10^6 -> 155.53505 | C23: =IF(E66=0,0,E78/E66) -> 0.027961013
A24: KW 2 dikreditkan pada NRV (Rp jt) | B24: =-E74/10^6 -> 74.121493
A26: 2. Laporan biaya produksi
A27: 2a. Kuantitas (kg)
A28: Pos | B28: Aktual kg | C28: % dari produksi | D28: Budget kg | E28: % budget
A29: WIP awal | B29: =$C$191 -> 357.5
A30: Produksi bulan ini (masuk proses) | B30: =$C$192 -> 236923 | D30: =INDEX(BUDGET!$C$14:$R$14,$E$5) -> 0
A31: Total untuk dipertanggungjawabkan | B31: =B29+B30 -> 237280.5
A32: Premium ke barang jadi | B32: =B31-B33-B34-B35 -> 221027 | C32: =IF(B30=0,0,B32/B30) -> 0.93290647 | D32: =INDEX(BUDGET!$C$10:$R$10,$E$5) -> 0 | E32: =IF(D30=0,0,D32/D30) -> 0
A33: KW 2 (produk sampingan) | B33: =$C$194 -> 7581 | C33: =IF(B30=0,0,B33/B30) -> 0.031997738 | D33: =INDEX(BUDGET!$C$11:$R$11,$E$5) -> 0 | E33: =IF(D30=0,0,D33/D30) -> 0
A34: Keripik waste (kerugian normal) | B34: =$C$195 -> 6500 | C34: =IF(B30=0,0,B34/B30) -> 0.027435074 | D34: =INDEX(BUDGET!$C$12:$R$12,$E$5) -> 0 | E34: =IF(D30=0,0,D34/D30) -> 0
A35: WIP akhir | B35: =$C$193 -> 2172.5 | C35: =IF(B30=0,0,B35/B30) -> 0.0091696458 | D35: =INDEX(BUDGET!$C$13:$R$13,$E$5) -> 0 | E35: =IF(D30=0,0,D35/D30) -> 0
A36: Total dipertanggungjawabkan | B36: =SUM(B32:B35) -> 237280.5
A38: 2b. Biaya produksi bulan ini (aktual)
A39: Komponen | B39: Qty | C39: Satuan | D39: Harga | E39: Nilai (Rp) | F39: Rp/kg
A40: Raw materials
A41: Singkong kulit premium | B41: =D215 -> 347092.26 | C41: kg | D41: =F215 -> 2942.8302 | E41: =G215 -> 1.0214336e+09 | F41: =IF($B$30=0,0,E41/$B$30) -> 4311.247
A42: Singkong daging premium | B42: =D216 -> 280280 | C42: kg | D42: =F216 -> 4597.3384 | E42: =G216 -> 1.288542e+09 | F42: =IF($B$30=0,0,E42/$B$30) -> 5438.6531
A43: Ongkos kirim singkong (5101-016 per tanggal kirim; BIAYA BERSAMA bagian 8) | C43: Rp | E43: ='BIAYA BERSAMA'!$C$159 -> 41897465 | F43: =IF($B$30=0,0,E43/$B$30) -> 176.84001
A44: Subtotal raw materials | E44: =E41+E42+E43 -> 2.351873e+09 | F44: =IF($B$30=0,0,E44/$B$30) -> 9926.7401
A45: Oil & CNG
A46: Minyak olein | B46: =D217 -> 57870 | C46: kg | D46: =F217 -> 17512.15 | E46: =G217 -> 1.0134281e+09 | F46: =IF($B$30=0,0,E46/$B$30) -> 4277.4576
A47: CNG | B47: =D218/$C$210 -> 3425.0221 | C47: MMBTU | D47: =IF(B47=0,0,E47/B47) -> 226177.3 | E47: =G218 -> 7.7466226e+08 | F47: =IF($B$30=0,0,E47/$B$30) -> 3269.6794
A48: Material - others
A49: Amonium bicarbonate | B49: =D219 -> 1700 | C49: kg | D49: =F219 -> 4638.5866 | E49: =G219 -> 7885597.3 | F49: =IF($B$30=0,0,E49/$B$30) -> 33.283376
A50: HDPE 0,03 | B50: =D220 -> 252.7 | C50: kg | D50: =F220 -> 32673.742 | E50: =G220 -> 8256654.7 | F50: =IF($B$30=0,0,E50/$B$30) -> 34.849528
A51: HDPE 0,05 | B51: =D221 -> 1861 | C51: kg | D51: =F221 -> 34380.541 | E51: =G221 -> 63982188 | F51: =IF($B$30=0,0,E51/$B$30) -> 270.05478
A52: HDPE 0,07 | B52: =D222 -> 1374 | C52: kg | D52: =F222 -> 32614.581 | E52: =G222 -> 44812435 | F52: =IF($B$30=0,0,E52/$B$30) -> 189.14345
A53: Packaging IFM (karton) | B53: =D223 -> 100 | C53: pcs | D53: =F223 -> 9761.7671 | E53: =G223 -> 976176.71 | F53: =IF($B$30=0,0,E53/$B$30) -> 4.1202277
A54: Other cost (plakban, tali, label, plastik) | C54: Rp | E54: =SUMIF($C$215:$C$228,"Other cost",$G$215:$G$228) -> 9665606.9 | F54: =IF($B$30=0,0,E54/$B$30) -> 40.796406
A55: Subtotal material - others | E55: =E49+E50+E51+E52+E53+E54 -> 1.3557866e+08 | F55: =IF($B$30=0,0,E55/$B$30) -> 572.24777
A56: Total material | E56: =E44+E46+E47+E55 -> 4.275542e+09 | F56: =IF($B$30=0,0,E56/$B$30) -> 18046.125
A57: Konversi (dari BIAYA BERSAMA)
A58: Upah borongan kupas | B58: =$C$198 -> 215224 | C58: kg dikupas | D58: =IF(B58=0,0,E58/B58) -> 249.03647 | E58: ='BIAYA BERSAMA'!C116 -> 53598625 | F58: =IF($B$30=0,0,E58/$B$30) -> 226.22804
A59: Grup A – DL operator | E59: ='BIAYA BERSAMA'!C115 -> 3.8485655e+08 | F59: =IF($B$30=0,0,E59/$B$30) -> 1624.3951
A60: Grup B – IDL (support, staf, THR, BPJS) | E60: ='BIAYA BERSAMA'!C117 -> 3.4406175e+08 | F60: =IF($B$30=0,0,E60/$B$30) -> 1452.2092
A61: Grup C – energi & utilitas | E61: ='BIAYA BERSAMA'!C118 -> 35253314 | F61: =IF($B$30=0,0,E61/$B$30) -> 148.7965
A62: Grup D – pemeliharaan & penyusutan mesin | E62: ='BIAYA BERSAMA'!C119 -> 2.1497261e+08 | F62: =IF($B$30=0,0,E62/$B$30) -> 907.35221
A63: Grup E – pabrik umum & penyusutan inventaris | E63: ='BIAYA BERSAMA'!C120 -> 2.5428357e+08 | F63: =IF($B$30=0,0,E63/$B$30) -> 1073.2752
A64: Subtotal factory overhead (Grup B–E) | E64: =E60+E61+E62+E63 -> 8.4857125e+08 | F64: =IF($B$30=0,0,E64/$B$30) -> 3581.633
A65: Total konversi | E65: =E58+E59+E64 -> 1.2870264e+09 | F65: =IF($B$30=0,0,E65/$B$30) -> 5432.2561
A66: TOTAL BIAYA PRODUKSI BULAN INI | E66: =E56+E65 -> 5.5625685e+09 | F66: =IF($B$30=0,0,E66/$B$30) -> 23478.381
A67: Memo: kebutuhan ekuivalen singkong kulit per kg produksi | B67: =IF($B$30=0,0,(B41+IF($D$230=0,0,B42/$D$230))/$B$30) -> 3.3728278 | C67: kg/kg | D67: budget: | E67: =INDEX(BUDGET!$C$15:$R$15,$E$5) -> 0
A68: Memo: porsi singkong daging (ekuivalen kulit) | B68: =IF(B67*$B$30=0,0,IF($D$230=0,0,B42/$D$230)/(B67*$B$30)) -> 0.56564629 | D68: budget: | E68: =INDEX(BUDGET!$C$21:$R$21,$E$5) -> 0
A70: 2c. Penilaian hasil (biaya dipertanggungjawabkan = biaya dibebankan)
A71: Pos | B71: Kg | D71: Rp/kg | E71: Nilai (Rp) | F71: Budget Rp/kg
A72: WIP awal | B72: =B29 -> 357.5 | E72: =$C$196 -> 7910432.2
A73: Biaya produksi bulan ini | B73: =B30 -> 236923 | E73: =E66 -> 5.5625685e+09
A74: Dikurangi: KW 2 dinilai NRV (ke persediaan KW 2) | B74: =-B33 -> -7581 | D74: =$C$209 -> 9777.2712 | E74: =-B33*$C$209 -> -74121493
A75: Biaya untuk premium, waste, dan WIP akhir | B75: =SUM(B72:B74) -> 229699.5 | E75: =SUM(E72:E74) -> 5.4963574e+09
A76: Biaya rata-rata tertimbang per kg | D76: =IF(B75=0,0,E75/B75) -> 23928.469 | F76: =INDEX(BUDGET!$C$80:$R$80,$E$5) -> 0
A77: Premium ke barang jadi | B77: =B32 -> 221027 | E77: =B77*$D$76 -> 5.2888378e+09
A78: Keripik waste ke HPP (kerugian normal) | B78: =B34 -> 6500 | E78: =B78*$D$76 -> 1.5553505e+08
A79: WIP akhir | B79: =B35 -> 2172.5 | E79: =B79*$D$76 -> 51984599
A80: Total dibebankan | B80: =SUM(B77:B79) -> 229699.5 | E80: =SUM(E77:E79) -> 5.4963574e+09
B81: =B75-B80 -> 0 | E81: =E75-E80 -> 0
A84: 3. Barang jadi (FG-001 Keripik Singkong Tanpa Bumbu) dan HPP
A85: Pos | B85: Kg | D85: Rp/kg | E85: Nilai (Rp) | F85: Budget Rp/kg
A86: Saldo awal | B86: =$C$201 -> 7029 | E86: =IF($C$201=0,0,$C$202) -> 1.5553127e+08
A87: Masuk dari produksi | B87: =B77 -> 221027 | E87: =E77 -> 5.2888378e+09
A88: Tersedia | B88: =B86+B87 -> 228056 | E88: =E86+E87 -> 5.444369e+09
A89: Biaya rata-rata tertimbang per kg | D89: =IF(B88=0,0,E88/B88) -> 23872.948 | F89: =INDEX(BUDGET!$C$81:$R$81,$E$5) -> 0
A90: Keluar: penjualan ke IFM | B90: =$C$203 -> 204950.5 | E90: =B90*$D$89 -> 4.8927726e+09
A91: Keluar: transfer ke Lain-lain (FCC premium untuk cem-cem) | B91: ='LAIN-LAIN'!$D$43 -> 23115.5 | E91: =B91*$D$89 -> 5.5183513e+08
A92: Saldo akhir (kg menurut Accurate) | B92: =$C$204 -> 0 | E92: =B92*$D$89 -> 0
A93: Selisih kuantitas (tersedia − keluar − saldo akhir) | B93: =B88-B90-B91-B92 -> -10 | E93: =B93*$D$89 -> -238729.48
A94: nilai saldo akhir menurut Accurate | E94: =$C$205 -> -17.84
A95: residu nilai saldo awal tanpa kuantitas (tidak ikut rata-rata) | E95: =$C$202-E86 -> 0
A96: FG-001 masuk − premium kartu | B96: =$C$206-B87 -> -9047.5
A97: transfer ke item lain − transfer ke cem-cem | B97: =$C$207-B91 -> -9057.5
A99: HPP
A100: HPP penjualan ke IFM | E100: =E90 -> 4.8927726e+09
A101: HPP keripik waste | E101: =E78 -> 1.5553505e+08
A102: HPP selisih kuantitas FG | E102: =E93 -> -238729.48
A103: HPP KW 2 tawar terjual ke KGS (pada NRV) | B103: =$C$208 -> 5957 | D103: =$C$209 -> 9777.2712 | E103: =B103*$C$209 -> 58243204
A104: Total HPP | E104: =E100+E101+E102+E103 -> 5.1063121e+09
A105: HPP (IFM + waste) per kg terjual ke IFM | D105: =IF(B90=0,0,(E100+E101)/B90) -> 24631.839 | F105: =IF(INDEX(BUDGET!$C$10:$R$10,$E$5)=0,0,INDEX(BUDGET!$C$84:$R$84,$E$5)/INDEX(BUDGET!$C$10:$R$10,$E$5)) -> 0
A106: Budget total HPP (volume budget) | E106: =INDEX(BUDGET!$C$84:$R$84,$E$5) -> 0
A108: 4. Selisih vs budget per komponen (Rp/kg produksi)
A109: Komponen | B109: Qty/kg aktual | C109: Qty/kg budget | D109: Harga aktual | E109: Harga budget | F109: Rp/kg aktual | G109: Rp/kg budget | H109: Selisih | I109: Harga / belanja | J109: Pemakaian / yield | K109: Volume | L109: Metode alokasi | M109: Cek
A110: Singkong kulit premium | B110: =IF($B$30=0,0,B41/$B$30) -> 1.4650003 | C110: =IF($D$30=0,0,INDEX(BUDGET!$C$18:$R$18,$E$5)/$D$30) -> 0 | D110: =D41 -> 2942.8302 | E110: =IF(INDEX(BUDGET!$C$18:$R$18,$E$5)=0,0,INDEX(BUDGET!$C$20:$R$20,$E$5)/INDEX(BUDGET!$C$18:$R$18,$E$5)) -> 0 | F110: =F41 -> 4311.247 | G110: =IF($D$30=0,0,INDEX(BUDGET!$C$20:$R$20,$E$5)/$D$30) -> 0 | H110: =F110-G110 -> 4311.247 | I110: =(D110-E110)*B110 -> 4311.247 | J110: =(B110-C110)*E110 -> 0 | K110: 0 | L110: 0 | M110: =H110-I110-J110-K110-L110 -> 0
A111: Singkong daging premium | B111: =IF($B$30=0,0,B42/$B$30) -> 1.1830004 | C111: =IF($D$30=0,0,INDEX(BUDGET!$C$22:$R$22,$E$5)/$D$30) -> 0 | D111: =D42 -> 4597.3384 | E111: =IF(INDEX(BUDGET!$C$22:$R$22,$E$5)=0,0,INDEX(BUDGET!$C$24:$R$24,$E$5)/INDEX(BUDGET!$C$22:$R$22,$E$5)) -> 0 | F111: =F42 -> 5438.6531 | G111: =IF($D$30=0,0,INDEX(BUDGET!$C$24:$R$24,$E$5)/$D$30) -> 0 | H111: =F111-G111 -> 5438.6531 | I111: =(D111-E111)*B111 -> 5438.6531 | J111: =(B111-C111)*E111 -> 0 | K111: 0 | L111: 0 | M111: =H111-I111-J111-K111-L111 -> 0
...

Sheet UU
A1: KARTU BIAYA PRODUKSI - UBI UNGU IFM (QKSP)
A5: Bulan budget pembanding | C5: Sep-26 | D5: posisi: | E5: =MATCH(C5,BUDGET!$C$4:$R$4,0) -> 1
A6: Status kontrol (bagian 6) | C6: =IF(COUNTIF(D148:D158,"GAGAL")=0,"LULUS","GAGAL") -> LULUS
A8: 1. Ringkasan (Rp juta; Rp/kg per kg produksi bulan ini)
A9: Komponen | B9: Aktual (Rp jt) | C9: Aktual Rp/kg | D9: Budget Rp/kg | E9: Selisih Rp/kg | F9: Harga / belanja | G9: Pemakaian / yield | H9: Volume | I9: Metode alokasi
A10: Raw materials | B10: =E44/10^6 -> 8.4016 | C10: =F44 -> 17971.337 | D10: =G105 -> 0 | E10: =H105 -> 17971.337 | F10: =I105 -> 17971.337 | G10: =J105 -> 0 | H10: =K105 -> 0 | I10: =L105 -> 0
A11: Oil | B11: =E46/10^6 -> 2.2415551 | C11: =F46 -> 4794.7703 | D11: =G107 -> 0 | E11: =H107 -> 4794.7703 | F11: =I107 -> 4794.7703 | G11: =J107 -> 0 | H11: =K107 -> 0 | I11: =L107 -> 0
A12: CNG | B12: =E47/10^6 -> 1.4432029 | C12: =F47 -> 3087.065 | D12: =G109 -> 0 | E12: =H109 -> 3087.065 | F12: =I109 -> 3087.065 | G12: =J109 -> 0 | H12: =K109 -> 0 | I12: =L109 -> 0
A13: Material - others | B13: =E55/10^6 -> 0.36109135 | C13: =F55 -> 772.38791 | D13: =G116 -> 0 | E13: =H116 -> 772.38791 | F13: =I116 -> 697.6381 | G13: =J116 -> 74.749813 | H13: =K116 -> 0 | I13: =L116 -> 0
A14: Upah kupas | B14: =E58/10^6 -> 0 | C14: =F58 -> 0 | D14: =G118 -> 0 | E14: =H118 -> 0 | F14: =I118 -> 0 | G14: =J118 -> 0 | H14: =K118 -> 0 | I14: =L118 -> 0
A15: Direct labour (Grup A) | B15: =E59/10^6 -> 1.9761847 | C15: =F59 -> 4227.1331 | D15: =G120 -> 0 | E15: =H120 -> 4227.1331 | F15: =I120 -> 1922.5851 | G15: =J120 -> 0 | H15: =K120 -> 0 | I15: =L120 -> 2304.548
A16: Factory overhead (Grup B–E) | B16: =E64/10^6 -> 3.8040866 | C16: =F64 -> 8137.0837 | D16: =G125 -> 0 | E16: =H125 -> 8137.0837 | F16: =I125 -> 3910.1301 | G16: =J125 -> 0 | H16: =K125 -> 0 | I16: =L125 -> 4226.9537
A17: Total biaya produksi | B17: =E66/10^6 -> 18.227721 | C17: =F66 -> 38989.777 | D17: =G126 -> 0 | E17: =H126 -> 38989.777 | F17: =I126 -> 32383.525 | G17: =J126 -> 74.749813 | H17: =K126 -> 0 | I17: =L126 -> 6531.5017
A18: Produksi bulan ini (kg; aktual, budget) | C18: =$B$32 -> 467.5 | D18: =$D$32 -> 0
A19: Biaya konversi per kg (aktual, budget) | C19: =F65 -> 12364.217 | D19: =G118+G120+G125 -> 0
A20: HPP (Rp jt) dan HPP per kg terjual (aktual, budget) | B20: =E98/10^6 -> 232.70642 | C20: =D99 -> 35083.132 | D20: =F99 -> 0
A21: Pendapatan (Rp jt; aktual) | B21: =$C$207/10^6 -> 321.7005
A22: Margin kotor (Rp jt; %) | B22: =B21-B20 -> 88.994083 | C22: =IF(B21=0,0,B22/B21) -> 0.27663644
A23: biaya waste (kerugian normal) yang masuk HPP (Rp jt; % biaya produksi) | B23: =E76/10^6 -> 0 | C23: =IF(E66=0,0,E76/E66) -> 0
A24: KW 2 dikreditkan pada NRV (Rp jt) | B24: =-E72/10^6 -> 0
A25: kenaikan WIP + FG (Rp jt) dan porsi biaya konversi di dalamnya | B25: =(E77+E89-E70-E84)/10^6 -> -214.4787 | C25: =IF(E66=0,0,B25*E65/E66) -> -68.014267
A28: 2. Laporan biaya produksi
A29: 2a. Kuantitas (kg)
A30: Pos | B30: Aktual kg | C30: % dari produksi | D30: Budget kg | E30: % budget
A31: WIP awal | B31: =$C$191 -> 4042.5
A32: Produksi bulan ini (masuk proses) | B32: =$C$192 -> 467.5 | D32: =INDEX(BUDGET!$C$99:$R$99,$E$5) -> 0
A33: Total untuk dipertanggungjawabkan | B33: =B31+B32 -> 4510
A34: Premium ke barang jadi | B34: =B33-B35-B36-B37 -> 4510 | C34: =IF(B32=0,0,B34/B32) -> 9.6470588 | D34: =INDEX(BUDGET!$C$95:$R$95,$E$5) -> 0 | E34: =IF(D32=0,0,D34/D32) -> 0
A35: KW 2 (produk sampingan) | B35: =$C$194 -> 0 | C35: =IF(B32=0,0,B35/B32) -> 0 | D35: =INDEX(BUDGET!$C$96:$R$96,$E$5) -> 0 | E35: =IF(D32=0,0,D35/D32) -> 0
A36: Keripik waste (kerugian normal) | B36: =$C$195 -> 0 | C36: =IF(B32=0,0,B36/B32) -> 0 | D36: =INDEX(BUDGET!$C$97:$R$97,$E$5) -> 0 | E36: =IF(D32=0,0,D36/D32) -> 0
A37: WIP akhir | B37: =$C$193 -> 0 | C37: =IF(B32=0,0,B37/B32) -> 0 | D37: =INDEX(BUDGET!$C$98:$R$98,$E$5) -> 0 | E37: =IF(D32=0,0,D37/D32) -> 0
A38: Total dipertanggungjawabkan | B38: =SUM(B34:B37) -> 4510
A40: 2b. Biaya produksi bulan ini (aktual)
A41: Komponen | B41: Qty | C41: Satuan | D41: Harga | E41: Nilai (Rp) | F41: Rp/kg
A42: Raw materials
A43: Ubi ungu | B43: =D211 -> 1424 | C43: kg | D43: =F211 -> 5900 | E43: =G211 -> 8401600 | F43: =IF($B$32=0,0,E43/$B$32) -> 17971.337
A44: Subtotal raw materials | E44: =E43 -> 8401600 | F44: =IF($B$32=0,0,E44/$B$32) -> 17971.337
A45: Oil & CNG
A46: Minyak olein | B46: =D212 -> 128 | C46: kg | D46: =F212 -> 17512.15 | E46: =G212 -> 2241555.1 | F46: =IF($B$32=0,0,E46/$B$32) -> 4794.7703
A47: CNG | B47: =D213/$C$206 -> 6.3808475 | C47: MMBTU | D47: =IF(B47=0,0,E47/B47) -> 226177.3 | E47: =G213 -> 1443202.9 | F47: =IF($B$32=0,0,E47/$B$32) -> 3087.065
A48: Material - others
A49: Amonium | B49: 0 | C49: kg | D49: 0 | E49: 0 | F49: =IF($B$32=0,0,E49/$B$32) -> 0
A50: HDPE 0,03 | B50: 0 | C50: kg | D50: 0 | E50: 0 | F50: =IF($B$32=0,0,E50/$B$32) -> 0
A51: HDPE 0,06 | B51: 0 | C51: kg | D51: 0 | E51: 0 | F51: =IF($B$32=0,0,E51/$B$32) -> 0
A52: HDPE 0,07 | B52: =D214 -> 10 | C52: kg | D52: =F214 -> 32614.581 | E52: =G214 -> 326145.81 | F52: =IF($B$32=0,0,E52/$B$32) -> 697.6381
A53: Packaging IFM | B53: 0 | C53: kg | D53: 0 | E53: 0 | F53: =IF($B$32=0,0,E53/$B$32) -> 0
A54: Other cost (plakban, tali, label, plastik) | C54: Rp | E54: =SUMIF($C$211:$C$217,"Other cost",$G$211:$G$217) -> 34945.538 | F54: =IF($B$32=0,0,E54/$B$32) -> 74.749813
A55: Subtotal material - others | E55: =E49+E50+E51+E52+E53+E54 -> 361091.35 | F55: =IF($B$32=0,0,E55/$B$32) -> 772.38791
A56: Total material | E56: =E44+E46+E47+E55 -> 12447449 | F56: =IF($B$32=0,0,E56/$B$32) -> 26625.56
A57: Konversi (dari BIAYA BERSAMA)
A58: Upah borongan kupas | B58: =$C$198 -> 0 | C58: kg dikupas | D58: =IF(B58=0,0,E58/B58) -> 0 | E58: ='BIAYA BERSAMA'!D116 -> 0 | F58: =IF($B$32=0,0,E58/$B$32) -> 0
A59: Grup A – DL operator | E59: ='BIAYA BERSAMA'!D115 -> 1976184.7 | F59: =IF($B$32=0,0,E59/$B$32) -> 4227.1331
A60: Grup B – IDL (support, staf, THR, BPJS) | E60: ='BIAYA BERSAMA'!D117 -> 1766709.2 | F60: =IF($B$32=0,0,E60/$B$32) -> 3779.057
A61: Grup C – energi & utilitas | E61: ='BIAYA BERSAMA'!D118 -> 27926.783 | F61: =IF($B$32=0,0,E61/$B$32) -> 59.736433
A62: Grup D – pemeliharaan & penyusutan mesin | E62: ='BIAYA BERSAMA'!D119 -> 1261824.9 | F62: =IF($B$32=0,0,E62/$B$32) -> 2699.0908
A63: Grup E – pabrik umum & penyusutan inventaris | E63: ='BIAYA BERSAMA'!D120 -> 747625.78 | F63: =IF($B$32=0,0,E63/$B$32) -> 1599.1995
A64: Subtotal factory overhead (Grup B–E) | E64: =E60+E61+E62+E63 -> 3804086.6 | F64: =IF($B$32=0,0,E64/$B$32) -> 8137.0837
A65: Total konversi | E65: =E58+E59+E64 -> 5780271.4 | F65: =IF($B$32=0,0,E65/$B$32) -> 12364.217
A66: TOTAL BIAYA PRODUKSI BULAN INI | E66: =E56+E65 -> 18227721 | F66: =IF($B$32=0,0,E66/$B$32) -> 38989.777
A68: 2c. Penilaian hasil (biaya dipertanggungjawabkan = biaya dibebankan)
A69: Pos | B69: Kg | D69: Rp/kg | E69: Nilai (Rp) | F69: Budget Rp/kg
A70: WIP awal | B70: =B31 -> 4042.5 | E70: =$C$196 -> 1.4062609e+08
A71: Biaya produksi bulan ini | B71: =B32 -> 467.5 | E71: =E66 -> 18227721
A72: Dikurangi: KW 2 dinilai NRV (ke persediaan KW 2) | B72: =-B35 -> 0 | E72: 0
A73: Biaya untuk premium, waste, dan WIP akhir | B73: =SUM(B70:B72) -> 4510 | E73: =SUM(E70:E72) -> 1.5885381e+08
A74: Biaya rata-rata tertimbang per kg | D74: =IF(B73=0,0,E73/B73) -> 35222.573 | F74: =INDEX(BUDGET!$C$126:$R$126,$E$5) -> 0
A75: Premium ke barang jadi | B75: =B34 -> 4510 | E75: =B75*$D$74 -> 1.5885381e+08
A76: Keripik waste ke HPP (kerugian normal) | B76: =B36 -> 0 | E76: =B76*$D$74 -> 0
A77: WIP akhir | B77: =B37 -> 0 | E77: =B77*$D$74 -> 0
A78: Total dibebankan | B78: =SUM(B75:B77) -> 4510 | E78: =SUM(E75:E77) -> 1.5885381e+08
A79: dibebankan (harus nol) | B79: =B73-B78 -> 0 | E79: =E73-E78 -> 0
A80: nilai WIP akhir menurut Accurate | E80: =$C$197 -> 0.12
A82: 3. Barang jadi (FG-101 FSPC Ungu Premium) dan HPP
A83: Pos | B83: Kg | D83: Rp/kg | E83: Nilai (Rp) | F83: Budget Rp/kg
A84: Saldo awal | B84: =$C$201 -> 2123 | E84: =IF($C$201=0,0,$C$202) -> 73852611
A85: Masuk dari produksi | B85: =B75 -> 4510 | E85: =E75 -> 1.5885381e+08
A86: Tersedia | B86: =B84+B85 -> 6633 | E86: =E84+E85 -> 2.3270642e+08
A87: Biaya rata-rata tertimbang per kg | D87: =IF(B86=0,0,E86/B86) -> 35083.132 | F87: =INDEX(BUDGET!$C$127:$R$127,$E$5) -> 0
A88: Keluar: penjualan ke IFM | B88: =$C$203 -> 6633 | E88: =B88*$D$87 -> 2.3270642e+08
A89: Saldo akhir (kg menurut Accurate) | B89: =$C$204 -> 0 | E89: =B89*$D$87 -> 0
A90: Selisih kuantitas (tersedia − keluar − saldo akhir) | B90: =B86-B88-B89 -> 0 | E90: =B90*$D$87 -> 0
A91: Nilai saldo akhir menurut Accurate | E91: =$C$205 -> 1692347.2
A92: Residu nilai saldo awal tanpa kuantitas (tidak ikut rata-rata) | E92: =$C$202-E84 -> 0
A94: HPP
A95: HPP penjualan ke IFM | E95: =E88 -> 2.3270642e+08
A96: HPP keripik waste | E96: =E76 -> 0
A97: HPP selisih kuantitas FG | E97: =E90 -> 0
A98: Total HPP | E98: =E95+E96+E97 -> 2.3270642e+08
A99: HPP (IFM + waste) per kg terjual ke IFM | D99: =IF(B88=0,0,(E95+E96)/B88) -> 35083.132 | F99: =IF(INDEX(BUDGET!$C$95:$R$95,$E$5)=0,0,INDEX(BUDGET!$C$128:$R$128,$E$5)/INDEX(BUDGET!$C$95:$R$95,$E$5)) -> 0
A100: Budget total HPP (volume budget) | E100: =INDEX(BUDGET!$C$128:$R$128,$E$5) -> 0
A102: 4. Selisih vs budget per komponen (Rp/kg produksi)
A103: Komponen | B103: Qty/kg aktual | C103: Qty/kg budget | D103: Harga aktual | E103: Harga budget | F103: Rp/kg aktual | G103: Rp/kg budget | H103: Selisih | I103: Harga / belanja | J103: Pemakaian / yield | K103: Volume | L103: Metode alokasi | M103: Cek
A104: Ubi ungu | B104: =IF($B$32=0,0,B43/$B$32) -> 3.0459893 | C104: =IF($D$32=0,0,INDEX(BUDGET!$C$101:$R$101,$E$5)/$D$32) -> 0 | D104: =D43 -> 5900 | E104: =IF(INDEX(BUDGET!$C$101:$R$101,$E$5)=0,0,INDEX(BUDGET!$C$102:$R$102,$E$5)/INDEX(BUDGET!$C$101:$R$101,$E$5)) -> 0 | F104: =F43 -> 17971.337 | G104: =IF($D$32=0,0,INDEX(BUDGET!$C$102:$R$102,$E$5)/$D$32) -> 0 | H104: =F104-G104 -> 17971.337 | I104: =(D104-E104)*B104 -> 17971.337 | J104: =(B104-C104)*E104 -> 0 | K104: 0 | L104: 0 | M104: =H104-I104-J104-K104-L104 -> 0
A105: Raw materials | F105: =F104 -> 17971.337 | G105: =G104 -> 0 | H105: =H104 -> 17971.337 | I105: =I104 -> 17971.337 | J105: =J104 -> 0 | K105: =K104 -> 0 | L105: =L104 -> 0 | M105: =M104 -> 0
A106: Minyak olein | B106: =IF($B$32=0,0,B46/$B$32) -> 0.27379679 | C106: =IF($D$32=0,0,INDEX(BUDGET!$C$103:$R$103,$E$5)/$D$32) -> 0 | D106: =D46 -> 17512.15 | E106: =IF(INDEX(BUDGET!$C$103:$R$103,$E$5)=0,0,INDEX(BUDGET!$C$104:$R$104,$E$5)/INDEX(BUDGET!$C$103:$R$103,$E$5)) -> 0 | F106: =F46 -> 4794.7703 | G106: =IF($D$32=0,0,INDEX(BUDGET!$C$104:$R$104,$E$5)/$D$32) -> 0 | H106: =F106-G106 -> 4794.7703 | I106: =(D106-E106)*B106 -> 4794.7703 | J106: =(B106-C106)*E106 -> 0 | K106: 0 | L106: 0 | M106: =H106-I106-J106-K106-L106 -> 0
A107: Oil | F107: =F106 -> 4794.7703 | G107: =G106 -> 0 | H107: =H106 -> 4794.7703 | I107: =I106 -> 4794.7703 | J107: =J106 -> 0 | K107: =K106 -> 0 | L107: =L106 -> 0 | M107: =M106 -> 0
A108: CNG (MMBTU) | B108: =IF($B$32=0,0,B47/$B$32) -> 0.013648872 | C108: =IF($D$32=0,0,INDEX(BUDGET!$C$105:$R$105,$E$5)/$D$32) -> 0 | D108: =D47 -> 226177.3 | E108: =IF(INDEX(BUDGET!$C$105:$R$105,$E$5)=0,0,INDEX(BUDGET!$C$106:$R$106,$E$5)/INDEX(BUDGET!$C$105:$R$105,$E$5)) -> 0 | F108: =F47 -> 3087.065 | G108: =IF($D$32=0,0,INDEX(BUDGET!$C$106:$R$106,$E$5)/$D$32) -> 0 | H108: =F108-G108 -> 3087.065 | I108: =(D108-E108)*B108 -> 3087.065 | J108: =(B108-C108)*E108 -> 0 | K108: 0 | L108: 0 | M108: =H108-I108-J108-K108-L108 -> 0
A109: CNG | F109: =F108 -> 3087.065 | G109: =G108 -> 0 | H109: =H108 -> 3087.065 | I109: =I108 -> 3087.065 | J109: =J108 -> 0 | K109: =K108 -> 0 | L109: =L108 -> 0 | M109: =M108 -> 0
A110: Amonium | B110: =IF($B$32=0,0,B49/$B$32) -> 0 | C110: =IF($D$32=0,0,INDEX(BUDGET!$C$107:$R$107,$E$5)/$D$32) -> 0 | D110: =D49 -> 0 | E110: =IF(INDEX(BUDGET!$C$107:$R$107,$E$5)=0,0,INDEX(BUDGET!$C$108:$R$108,$E$5)/INDEX(BUDGET!$C$107:$R$107,$E$5)) -> 0 | F110: =F49 -> 0 | G110: =IF($D$32=0,0,INDEX(BUDGET!$C$108:$R$108,$E$5)/$D$32) -> 0 | H110: =F110-G110 -> 0 | I110: =(D110-E110)*B110 -> 0 | J110: =(B110-C110)*E110 -> 0 | K110: 0 | L110: 0 | M110: =H110-I110-J110-K110-L110 -> 0
A111: HDPE 0,03 | B111: =IF($B$32=0,0,B50/$B$32) -> 0 | C111: =IF($D$32=0,0,INDEX(BUDGET!$C$109:$R$109,$E$5)/$D$32) -> 0 | D111: =D50 -> 0 | E111: =IF(INDEX(BUDGET!$C$109:$R$109,$E$5)=0,0,INDEX(BUDGET!$C$110:$R$110,$E$5)/INDEX(BUDGET!$C$109:$R$109,$E$5)) -> 0 | F111: =F50 -> 0 | G111: =IF($D$32=0,0,INDEX(BUDGET!$C$110:$R$110,$E$5)/$D$32) -> 0 | H111: =F111-G111 -> 0 | I111: =(D111-E111)*B111 -> 0 | J111: =(B111-C111)*E111 -> 0 | K111: 0 | L111: 0 | M111: =H111-I111-J111-K111-L111 -> 0
...

Sheet UO
A1: KARTU BIAYA PRODUKSI - UBI ORANGE IFM (QKSO)
A3: Bulan budget pembanding | C3: Sep-26 | D3: posisi: | E3: =MATCH(C3,BUDGET!$C$4:$R$4,0) -> 1
A4: Status kontrol (bagian 6) | C4: =IF(COUNTIF(D144:D154,"GAGAL")=0,"LULUS","GAGAL") -> LULUS
A6: 1. Ringkasan (Rp juta; Rp/kg per kg produksi bulan ini)
A7: Komponen | B7: Aktual (Rp jt) | C7: Aktual Rp/kg | D7: Budget Rp/kg | E7: Selisih Rp/kg | F7: Harga / belanja | G7: Pemakaian / yield | H7: Volume | I7: Metode alokasi
A8: Raw materials | B8: =E40/10^6 -> 113.0153 | C8: =F40 -> 16829.022 | D8: =G101 -> 0 | E8: =H101 -> 16829.022 | F8: =I101 -> 16829.022 | G8: =J101 -> 0 | H8: =K101 -> 0 | I8: =L101 -> 0
A9: Oil | B9: =E42/10^6 -> 32.502549 | C9: =F42 -> 4839.9299 | D9: =G103 -> 0 | E9: =H103 -> 4839.9299 | F9: =I103 -> 4839.9299 | G9: =J103 -> 0 | H9: =K103 -> 0 | I9: =L103 -> 0
A10: CNG | B10: =E43/10^6 -> 23.315035 | C10: =F43 -> 3471.8241 | D10: =G105 -> 0 | E10: =H105 -> 3471.8241 | F10: =I105 -> 3471.8241 | G10: =J105 -> 0 | H10: =K105 -> 0 | I10: =L105 -> 0
A11: Material - others | B11: =E51/10^6 -> 4.7678182 | C11: =F51 -> 709.97218 | D11: =G112 -> 0 | E11: =H112 -> 709.97218 | F11: =I112 -> 660.4993 | G11: =J112 -> 49.472884 | H11: =K112 -> 0 | I11: =L112 -> 0
A12: Upah kupas | B12: =E54/10^6 -> 0 | C12: =F54 -> 0 | D12: =G114 -> 0 | E12: =H114 -> 0 | F12: =I114 -> 0 | G12: =J114 -> 0 | H12: =K114 -> 0 | I12: =L114 -> 0
A13: Direct labour (Grup A) | B13: =E55/10^6 -> 24.083394 | C13: =F55 -> 3586.2399 | D13: =G116 -> 0 | E13: =H116 -> 3586.2399 | F13: =I116 -> 1922.5851 | G13: =J116 -> 0 | H13: =K116 -> 0 | I13: =L116 -> 1663.6548
A14: Factory overhead (Grup B–E) | B14: =E60/10^6 -> 54.882506 | C14: =F60 -> 8172.5123 | D14: =G121 -> 0 | E14: =H121 -> 8172.5123 | F14: =I121 -> 3958.7104 | G14: =J121 -> 0 | H14: =K121 -> 0 | I14: =L121 -> 4213.8019
A15: Total biaya produksi | B15: =E62/10^6 -> 252.5666 | C15: =F62 -> 37609.501 | D15: =G122 -> 0 | E15: =H122 -> 37609.501 | F15: =I122 -> 31682.571 | G15: =J122 -> 49.472884 | H15: =K122 -> 0 | I15: =L122 -> 5877.4567
A16: Produksi bulan ini (kg; aktual, budget) | C16: =$B$28 -> 6715.5 | D16: =$D$28 -> 0
A17: Biaya konversi per kg (aktual, budget) | C17: =F61 -> 11758.752 | D17: =G114+G116+G121 -> 0
A18: HPP (Rp jt) dan HPP per kg terjual (aktual, budget) | B18: =E94/10^6 -> 252.5666 | C18: =D95 -> 37609.501 | D18: =F95 -> 0
A19: Pendapatan (Rp jt; aktual) | B19: =$C$203/10^6 -> 321.67245
A20: Margin kotor (Rp jt; %) | B20: =B19-B18 -> 69.105847 | C20: =IF(B19=0,0,B20/B19) -> 0.21483297
A21: Biaya waste (kerugian normal) yang masuk HPP (Rp jt; % biaya produksi) | B21: =E72/10^6 -> 0 | C21: =IF(E62=0,0,E72/E62) -> 0
A22: KW 2 dikreditkan pada NRV (Rp jt) | B22: =-E68/10^6 -> 0
A24: 2. Laporan biaya produksi
A25: 2a. Kuantitas (kg)
A26: Pos | B26: Aktual kg | C26: % dari produksi | D26: Budget kg | E26: % budget
A27: WIP awal | B27: =$C$187 -> 0
A28: Produksi bulan ini (masuk proses) | B28: =$C$188 -> 6715.5 | D28: =INDEX(BUDGET!$C$152:$R$152,$E$3) -> 0
A29: Total untuk dipertanggungjawabkan | B29: =B27+B28 -> 6715.5
A30: Premium ke barang jadi | B30: =B29-B31-B32-B33 -> 6715.5 | C30: =IF(B28=0,0,B30/B28) -> 1 | D30: =INDEX(BUDGET!$C$148:$R$148,$E$3) -> 0 | E30: =IF(D28=0,0,D30/D28) -> 0
A31: KW 2 (produk sampingan) | B31: =$C$190 -> 0 | C31: =IF(B28=0,0,B31/B28) -> 0 | D31: =INDEX(BUDGET!$C$149:$R$149,$E$3) -> 0 | E31: =IF(D28=0,0,D31/D28) -> 0
A32: Keripik waste (kerugian normal) | B32: =$C$191 -> 0 | C32: =IF(B28=0,0,B32/B28) -> 0 | D32: =INDEX(BUDGET!$C$150:$R$150,$E$3) -> 0 | E32: =IF(D28=0,0,D32/D28) -> 0
A33: WIP akhir | B33: =$C$189 -> 0 | C33: =IF(B28=0,0,B33/B28) -> 0 | D33: =INDEX(BUDGET!$C$151:$R$151,$E$3) -> 0 | E33: =IF(D28=0,0,D33/D28) -> 0
A34: Total dipertanggungjawabkan | B34: =SUM(B30:B33) -> 6715.5
A36: 2b. Biaya produksi bulan ini (aktual)
A37: Komponen | B37: Qty | C37: Satuan | D37: Harga | E37: Nilai (Rp) | F37: Rp/kg
A38: Raw materials
A39: Ubi orange | B39: =D207 -> 24028 | C39: kg | D39: =F207 -> 4703.4834 | E39: =G207 -> 1.130153e+08 | F39: =IF($B$28=0,0,E39/$B$28) -> 16829.022
A40: Subtotal raw materials | E40: =E39 -> 1.130153e+08 | F40: =IF($B$28=0,0,E40/$B$28) -> 16829.022
A41: Oil & CNG
A42: Minyak olein | B42: =D208 -> 1856 | C42: kg | D42: =F208 -> 17512.15 | E42: =G208 -> 32502549 | F42: =IF($B$28=0,0,E42/$B$28) -> 4839.9299
A43: CNG | B43: =D209/$C$202 -> 103.083 | C43: MMBTU | D43: =IF(B43=0,0,E43/B43) -> 226177.3 | E43: =G209 -> 23315035 | F43: =IF($B$28=0,0,E43/$B$28) -> 3471.8241
A44: Material - others
A45: Amonium | B45: 0 | C45: kg | D45: 0 | E45: 0 | F45: =IF($B$28=0,0,E45/$B$28) -> 0
A46: HDPE 0,03 | B46: 0 | C46: kg | D46: 0 | E46: 0 | F46: =IF($B$28=0,0,E46/$B$28) -> 0
A47: HDPE 0,05 | B47: 0 | C47: kg | D47: 0 | E47: 0 | F47: =IF($B$28=0,0,E47/$B$28) -> 0
A48: HDPE 0,07 | B48: =D210 -> 136 | C48: kg | D48: =F210 -> 32614.581 | E48: =G210 -> 4435583 | F48: =IF($B$28=0,0,E48/$B$28) -> 660.4993
A49: Packaging IFM | B49: 0 | C49: kg | D49: 0 | E49: 0 | F49: =IF($B$28=0,0,E49/$B$28) -> 0
A50: Other cost (plakban, tali, label, plastik) | C50: Rp | E50: =SUMIF($C$207:$C$213,"Other cost",$G$207:$G$213) -> 332235.15 | F50: =IF($B$28=0,0,E50/$B$28) -> 49.472884
A51: Subtotal material - others | E51: =E45+E46+E47+E48+E49+E50 -> 4767818.2 | F51: =IF($B$28=0,0,E51/$B$28) -> 709.97218
A52: Total material | E52: =E40+E42+E43+E51 -> 1.736007e+08 | F52: =IF($B$28=0,0,E52/$B$28) -> 25850.749
A53: Konversi (dari BIAYA BERSAMA)
A54: Upah borongan kupas | B54: =$C$194 -> 0 | C54: kg dikupas | D54: =IF(B54=0,0,E54/B54) -> 0 | E54: ='BIAYA BERSAMA'!E116 -> 0 | F54: =IF($B$28=0,0,E54/$B$28) -> 0
A55: Grup A – DL operator | E55: ='BIAYA BERSAMA'!E115 -> 24083394 | F55: =IF($B$28=0,0,E55/$B$28) -> 3586.2399
A56: Grup B – IDL (support, staf, THR, BPJS) | E56: ='BIAYA BERSAMA'!E117 -> 21530554 | F56: =IF($B$28=0,0,E56/$B$28) -> 3206.0985
A57: Grup C – energi & utilitas | E57: ='BIAYA BERSAMA'!E118 -> 496392.3 | F57: =IF($B$28=0,0,E57/$B$28) -> 73.9174
A58: Grup D – pemeliharaan & penyusutan mesin | E58: ='BIAYA BERSAMA'!E119 -> 22428655 | F58: =IF($B$28=0,0,E58/$B$28) -> 3339.834
A59: Grup E – pabrik umum & penyusutan inventaris | E59: ='BIAYA BERSAMA'!E120 -> 10426904 | F59: =IF($B$28=0,0,E59/$B$28) -> 1552.6624
A60: Subtotal factory overhead (Grup B–E) | E60: =E56+E57+E58+E59 -> 54882506 | F60: =IF($B$28=0,0,E60/$B$28) -> 8172.5123
A61: Total konversi | E61: =E54+E55+E60 -> 78965900 | F61: =IF($B$28=0,0,E61/$B$28) -> 11758.752
A62: TOTAL BIAYA PRODUKSI BULAN INI | E62: =E52+E61 -> 2.525666e+08 | F62: =IF($B$28=0,0,E62/$B$28) -> 37609.501
A64: 2c. Penilaian hasil (biaya dipertanggungjawabkan = biaya dibebankan)
A65: Pos | B65: Kg | D65: Rp/kg | E65: Nilai (Rp) | F65: Budget Rp/kg
A66: WIP awal | B66: =B27 -> 0 | E66: =$C$192 -> 0
A67: Biaya produksi bulan ini | B67: =B28 -> 6715.5 | E67: =E62 -> 2.525666e+08
A68: Dikurangi: KW 2 dinilai NRV (ke persediaan KW 2) | B68: =-B31 -> 0 | E68: 0
A69: Biaya untuk premium, waste, dan WIP akhir | B69: =SUM(B66:B68) -> 6715.5 | E69: =SUM(E66:E68) -> 2.525666e+08
A70: Biaya rata-rata tertimbang per kg | D70: =IF(B69=0,0,E69/B69) -> 37609.501 | F70: =INDEX(BUDGET!$C$179:$R$179,$E$3) -> 0
A71: Premium ke barang jadi | B71: =B30 -> 6715.5 | E71: =B71*$D$70 -> 2.525666e+08
A72: Keripik waste ke HPP (kerugian normal) | B72: =B32 -> 0 | E72: =B72*$D$70 -> 0
A73: WIP akhir | B73: =B33 -> 0 | E73: =B73*$D$70 -> 0
A74: Total dibebankan | B74: =SUM(B71:B73) -> 6715.5 | E74: =SUM(E71:E73) -> 2.525666e+08
A75: Cek: dipertanggungjawabkan − dibebankan (harus nol) | B75: =B69-B74 -> 0 | E75: =E69-E74 -> 0
A76: Memo: nilai WIP akhir menurut Accurate | E76: =$C$193 -> 0
A78: 3. Barang jadi (FG-102 FSPC Orange Premium) dan HPP
A79: Pos | B79: Kg | D79: Rp/kg | E79: Nilai (Rp) | F79: Budget Rp/kg
A80: Saldo awal | B80: =$C$197 -> 0 | E80: =IF($C$197=0,0,$C$198) -> 0
A81: Masuk dari produksi | B81: =B71 -> 6715.5 | E81: =E71 -> 2.525666e+08
A82: Tersedia | B82: =B80+B81 -> 6715.5 | E82: =E80+E81 -> 2.525666e+08
A83: Biaya rata-rata tertimbang per kg | D83: =IF(B82=0,0,E82/B82) -> 37609.501 | F83: =INDEX(BUDGET!$C$180:$R$180,$E$3) -> 0
A84: Keluar: penjualan ke IFM | B84: =$C$199 -> 6715.5 | E84: =B84*$D$83 -> 2.525666e+08
A85: Saldo akhir (kg menurut Accurate) | B85: =$C$200 -> 0 | E85: =B85*$D$83 -> 0
A86: Selisih kuantitas (tersedia − keluar − saldo akhir) | B86: =B82-B84-B85 -> 0 | E86: =B86*$D$83 -> 0
A87: Memo: nilai saldo akhir menurut Accurate | E87: =$C$201 -> -974521.91
A88: Memo: residu nilai saldo awal tanpa kuantitas (tidak ikut rata-rata) | E88: =$C$198-E80 -> 0
A90: HPP
A91: HPP penjualan ke IFM | E91: =E84 -> 2.525666e+08
A92: HPP keripik waste | E92: =E72 -> 0
A93: HPP selisih kuantitas FG | E93: =E86 -> 0
A94: Total HPP | E94: =E91+E92+E93 -> 2.525666e+08
A95: HPP (IFM + waste) per kg terjual ke IFM | D95: =IF(B84=0,0,(E91+E92)/B84) -> 37609.501 | F95: =IF(INDEX(BUDGET!$C$148:$R$148,$E$3)=0,0,INDEX(BUDGET!$C$181:$R$181,$E$3)/INDEX(BUDGET!$C$148:$R$148,$E$3)) -> 0
A96: Budget total HPP (volume budget) | E96: =INDEX(BUDGET!$C$181:$R$181,$E$3) -> 0
A98: 4. Selisih vs budget per komponen (Rp/kg produksi)
A99: Komponen | B99: Qty/kg aktual | C99: Qty/kg budget | D99: Harga aktual | E99: Harga budget | F99: Rp/kg aktual | G99: Rp/kg budget | H99: Selisih | I99: Harga / belanja | J99: Pemakaian / yield | K99: Volume | L99: Metode alokasi | M99: Cek
A100: Ubi orange | B100: =IF($B$28=0,0,B39/$B$28) -> 3.5779912 | C100: =IF($D$28=0,0,INDEX(BUDGET!$C$154:$R$154,$E$3)/$D$28) -> 0 | D100: =D39 -> 4703.4834 | E100: =IF(INDEX(BUDGET!$C$154:$R$154,$E$3)=0,0,INDEX(BUDGET!$C$155:$R$155,$E$3)/INDEX(BUDGET!$C$154:$R$154,$E$3)) -> 0 | F100: =F39 -> 16829.022 | G100: =IF($D$28=0,0,INDEX(BUDGET!$C$155:$R$155,$E$3)/$D$28) -> 0 | H100: =F100-G100 -> 16829.022 | I100: =(D100-E100)*B100 -> 16829.022 | J100: =(B100-C100)*E100 -> 0 | K100: 0 | L100: 0 | M100: =H100-I100-J100-K100-L100 -> 0
A101: Raw materials | F101: =F100 -> 16829.022 | G101: =G100 -> 0 | H101: =H100 -> 16829.022 | I101: =I100 -> 16829.022 | J101: =J100 -> 0 | K101: =K100 -> 0 | L101: =L100 -> 0 | M101: =M100 -> 0
A102: Minyak olein | B102: =IF($B$28=0,0,B42/$B$28) -> 0.27637555 | C102: =IF($D$28=0,0,INDEX(BUDGET!$C$156:$R$156,$E$3)/$D$28) -> 0 | D102: =D42 -> 17512.15 | E102: =IF(INDEX(BUDGET!$C$156:$R$156,$E$3)=0,0,INDEX(BUDGET!$C$157:$R$157,$E$3)/INDEX(BUDGET!$C$156:$R$156,$E$3)) -> 0 | F102: =F42 -> 4839.9299 | G102: =IF($D$28=0,0,INDEX(BUDGET!$C$157:$R$157,$E$3)/$D$28) -> 0 | H102: =F102-G102 -> 4839.9299 | I102: =(D102-E102)*B102 -> 4839.9299 | J102: =(B102-C102)*E102 -> 0 | K102: 0 | L102: 0 | M102: =H102-I102-J102-K102-L102 -> 9.094947e-13
A103: Oil | F103: =F102 -> 4839.9299 | G103: =G102 -> 0 | H103: =H102 -> 4839.9299 | I103: =I102 -> 4839.9299 | J103: =J102 -> 0 | K103: =K102 -> 0 | L103: =L102 -> 0 | M103: =M102 -> 9.094947e-13
A104: CNG (MMBTU) | B104: =IF($B$28=0,0,B43/$B$28) -> 0.015350011 | C104: =IF($D$28=0,0,INDEX(BUDGET!$C$158:$R$158,$E$3)/$D$28) -> 0 | D104: =D43 -> 226177.3 | E104: =IF(INDEX(BUDGET!$C$158:$R$158,$E$3)=0,0,INDEX(BUDGET!$C$159:$R$159,$E$3)/INDEX(BUDGET!$C$158:$R$158,$E$3)) -> 0 | F104: =F43 -> 3471.8241 | G104: =IF($D$28=0,0,INDEX(BUDGET!$C$159:$R$159,$E$3)/$D$28) -> 0 | H104: =F104-G104 -> 3471.8241 | I104: =(D104-E104)*B104 -> 3471.8241 | J104: =(B104-C104)*E104 -> 0 | K104: 0 | L104: 0 | M104: =H104-I104-J104-K104-L104 -> 0
A105: CNG | F105: =F104 -> 3471.8241 | G105: =G104 -> 0 | H105: =H104 -> 3471.8241 | I105: =I104 -> 3471.8241 | J105: =J104 -> 0 | K105: =K104 -> 0 | L105: =L104 -> 0 | M105: =M104 -> 0
A106: Amonium | B106: =IF($B$28=0,0,B45/$B$28) -> 0 | C106: =IF($D$28=0,0,INDEX(BUDGET!$C$160:$R$160,$E$3)/$D$28) -> 0 | D106: =D45 -> 0 | E106: =IF(INDEX(BUDGET!$C$160:$R$160,$E$3)=0,0,INDEX(BUDGET!$C$161:$R$161,$E$3)/INDEX(BUDGET!$C$160:$R$160,$E$3)) -> 0 | F106: =F45 -> 0 | G106: =IF($D$28=0,0,INDEX(BUDGET!$C$161:$R$161,$E$3)/$D$28) -> 0 | H106: =F106-G106 -> 0 | I106: =(D106-E106)*B106 -> 0 | J106: =(B106-C106)*E106 -> 0 | K106: 0 | L106: 0 | M106: =H106-I106-J106-K106-L106 -> 0
A107: HDPE 0,03 | B107: =IF($B$28=0,0,B46/$B$28) -> 0 | C107: =IF($D$28=0,0,INDEX(BUDGET!$C$162:$R$162,$E$3)/$D$28) -> 0 | D107: =D46 -> 0 | E107: =IF(INDEX(BUDGET!$C$162:$R$162,$E$3)=0,0,INDEX(BUDGET!$C$163:$R$163,$E$3)/INDEX(BUDGET!$C$162:$R$162,$E$3)) -> 0 | F107: =F46 -> 0 | G107: =IF($D$28=0,0,INDEX(BUDGET!$C$163:$R$163,$E$3)/$D$28) -> 0 | H107: =F107-G107 -> 0 | I107: =(D107-E107)*B107 -> 0 | J107: =(B107-C107)*E107 -> 0 | K107: 0 | L107: 0 | M107: =H107-I107-J107-K107-L107 -> 0
A108: HDPE 0,05 | B108: =IF($B$28=0,0,B47/$B$28) -> 0 | C108: =IF($D$28=0,0,INDEX(BUDGET!$C$164:$R$164,$E$3)/$D$28) -> 0 | D108: =D47 -> 0 | E108: =IF(INDEX(BUDGET!$C$164:$R$164,$E$3)=0,0,INDEX(BUDGET!$C$165:$R$165,$E$3)/INDEX(BUDGET!$C$164:$R$164,$E$3)) -> 0 | F108: =F47 -> 0 | G108: =IF($D$28=0,0,INDEX(BUDGET!$C$165:$R$165,$E$3)/$D$28) -> 0 | H108: =F108-G108 -> 0 | I108: =(D108-E108)*B108 -> 0 | J108: =(B108-C108)*E108 -> 0 | K108: 0 | L108: 0 | M108: =H108-I108-J108-K108-L108 -> 0
...

Sheet LAIN-LAIN
A1: KARTU BIAYA PRODUKSI – LAIN-LAIN (retail, koperasi, maklon), September 2026
A5: Bulan budget pembanding | C5: Sep-26 | D5: posisi: | E5: =MATCH(C5,BUDGET!$C$4:$R$4,0) -> 1
A6: Status kontrol (bagian 4) | C6: =IF(AND(COUNTIF(D72:D75,"GAGAL")=0,COUNTIF(D107:D110,"GAGAL")=0),"LULUS","GAGAL") -> LULUS
A7: Nilai KW 2 ubi (Rp/kg) | C7: 0
A9: 1. Ringkasan (Rp juta)
A10: Pos | B10: Aktual (Rp jt) | C10: Budget (Rp jt) | D10: Selisih
A11: Material eksternal + konversi (tanpa bahan antarproduk) | B11: =(D68+E68+F68)/10^6 -> 277.66776 | C11: =INDEX(BUDGET!$C$198:$R$198,$E$5)/10^6 -> 0 | D11: =B11-C11 -> 277.66776
A12: Bahan antarproduk (FCC premium, KW 2) | B12: =(B68+C68)/10^6 -> 593.31031
A13: di dalamnya: konversi (DL + FOH) | B13: =(E68+F68)/10^6 -> 200.99415
A14: Total biaya produksi Lain-lain | B14: =G68/10^6 -> 870.97808 | C14: =INDEX(BUDGET!$C$199:$R$199,$E$5)/10^6 -> 0 | D14: =B14-C14 -> 870.97808
A15: Output (kg) | B15: =C43 -> 45653.42
A16: Biaya per kg (Rp) | B16: =H68 -> 19078.047
A17: Pendapatan Others: retail & maklon + KW 2 berbumbu (Rp jt; BP Data Aktual P68 + P65) | B17: ='REKON & KONTROL'!$C$74/10^6 -> 917.67406
A18: Margin kotor Others (Rp jt; %) | B18: =B17-B19 -> 46.092335 | C18: =IF(B17=0,0,B18/B17) -> 0.050227349
A19: HPP Lain-lain (biaya produksi − kenaikan barang jadi; bagian 5) | B19: =G93/10^6 -> 871.58173
A20: 2. Input per kelompok produk – ditautkan dari sheet per SKU (sel hijau)
A21: Kelompok produk | B21: Lini bahan utama (akun varian) | C21: Output (kg) | D21: Input FCC premium (kg) | E21: Input KW 2 FCC (kg) | F21: Input KW 2 ubi (kg) | G21: Material eksternal (Rp) | H21: Man-hour | I21: kWh | J21: Sumber
A22: Cem-cem ORI | B22: Singkong | C22: ='CEM-CEM ORI'!$B$21 -> 11035.8 | D22: ='CEM-CEM ORI'!$B$23 -> 10411.5 | E22: ='CEM-CEM ORI'!$B$24 -> 0 | F22: ='CEM-CEM ORI'!$B$25 -> 0 | G22: ='CEM-CEM ORI'!$E$34 -> 712800 | H22: ='CEM-CEM ORI'!$C$106 -> 882.2823 | I22: ='CEM-CEM ORI'!$C$107 -> 3936.4737 | J22: Tautan ke sheet CEM-CEM ORI
A23: Cem-cem BBQ | B23: Singkong | C23: ='CEM-CEM BBQ'!$B$21 -> 10305 | D23: ='CEM-CEM BBQ'!$B$23 -> 9669 | E23: ='CEM-CEM BBQ'!$B$24 -> 0 | F23: ='CEM-CEM BBQ'!$B$25 -> 0 | G23: ='CEM-CEM BBQ'!$E$34 -> 0 | H23: ='CEM-CEM BBQ'!$C$106 -> 787.7177 | I23: ='CEM-CEM BBQ'!$C$107 -> 3528.262 | J23: Tautan ke sheet CEM-CEM BBQ
A24: Koperasi (KW 2 berbumbu, 11 SKU) | B24: Singkong | C24: =KOPERASI!$M$7 -> 2967.5 | D24: =KOPERASI!$M$9 -> 10 | E24: =KOPERASI!$M$10 -> 2002 | F24: =KOPERASI!$M$11 -> 770 | G24: =KOPERASI!$M$15 -> 6333602.8 | H24: =KOPERASI!$M$12 -> 89.3397 | I24: 0 | J24: Tautan ke sheet KOPERASI
A25: Maicih basreng (maklon, 3 SKU) | B25: Singkong (maklon) | C25: ='MCH BASRENG L0'!$B$21+'MCH BASRENG L5'!$B$21+'MCH BASRENG L10'!$B$21 -> 926.56 | D25: ='MCH BASRENG L0'!$B$23+'MCH BASRENG L5'!$B$23+'MCH BASRENG L10'!$B$23 -> 0 | E25: ='MCH BASRENG L0'!$B$24+'MCH BASRENG L5'!$B$24+'MCH BASRENG L10'!$B$24 -> 0 | F25: ='MCH BASRENG L0'!$B$25+'MCH BASRENG L5'!$B$25+'MCH BASRENG L10'!$B$25 -> 0 | G25: ='MCH BASRENG L0'!$E$34+'MCH BASRENG L5'!$E$34+'MCH BASRENG L10'!$E$34 -> 42696.287 | H25: ='MCH BASRENG L0'!$C$106+'MCH BASRENG L5'!$C$106+'MCH BASRENG L10'!$C$106 -> 61.9399 | I25: ='MCH BASRENG L0'!$C$107+'MCH BASRENG L5'!$C$107+'MCH BASRENG L10'!$C$107 -> 342.8894 | J25: Tautan ke sheet MCH BASRENG L0, MCH BASRENG L5, MCH BASRENG L10
A26: Maicih keripik (LV 3 & 10) | B26: Singkong | C26: ='MCH KERIPIK LV3'!$B$21+'MCH KERIPIK LV10'!$B$21 -> 4015.04 | D26: ='MCH KERIPIK LV3'!$B$23+'MCH KERIPIK LV10'!$B$23 -> 2123 | E26: ='MCH KERIPIK LV3'!$B$24+'MCH KERIPIK LV10'!$B$24 -> 1627.7814 | F26: ='MCH KERIPIK LV3'!$B$25+'MCH KERIPIK LV10'!$B$25 -> 0 | G26: ='MCH KERIPIK LV3'!$E$34+'MCH KERIPIK LV10'!$E$34 -> 604941.04 | H26: ='MCH KERIPIK LV3'!$C$106+'MCH KERIPIK LV10'!$C$106 -> 257.6489 | I26: ='MCH KERIPIK LV3'!$C$107+'MCH KERIPIK LV10'!$C$107 -> 1557.5873 | J26: Tautan ke sheet MCH KERIPIK LV3, MCH KERIPIK LV10
A27: Maicih keripik LV 5 | B27: Singkong | C27: ='MCH KERIPIK LV5'!$B$21 -> 1601.04 | D27: ='MCH KERIPIK LV5'!$B$23 -> 902 | E27: ='MCH KERIPIK LV5'!$B$24 -> 612.21865 | F27: ='MCH KERIPIK LV5'!$B$25 -> 0 | G27: ='MCH KERIPIK LV5'!$E$34 -> 231126.4 | H27: ='MCH KERIPIK LV5'!$C$106 -> 145.2214 | I27: ='MCH KERIPIK LV5'!$C$107 -> 617.8482 | J27: Tautan ke sheet MCH KERIPIK LV5
A28: FCC Maicih | B28: Singkong | C28: 0 | D28: 0 | E28: 0 | F28: 0 | G28: 0 | H28: 0 | I28: 0
A29: FCC Putih | B29: Singkong | C29: 0 | D29: 0 | E29: 0 | F29: 0 | G29: 0 | H29: 0 | I29: 0
A30: Kecimpring (goreng & bagging) | B30: Singkong | C30: 0 | D30: 0 | E30: 0 | F30: 0 | G30: 0 | H30: 0 | I30: 0
A31: Whole chips rempah 15/90 gr | B31: Singkong | C31: 0 | D31: 0 | E31: 0 | F31: 0 | G31: 0 | H31: 0 | I31: 0
A32: Maxi (pellet & goreng) | B32: Singkong – cek bahan | C32: 0 | D32: 0 | E32: 0 | F32: 0 | G32: 0 | H32: 0 | I32: 0
A33: Pellet ubi ungu FG (1,2x1,5 & 3x3) | B33: Ubi Ungu | C33: 0 | D33: 0 | E33: 0 | F33: 0 | G33: 0 | H33: 0 | I33: 0
A34: Keripik ubi ungu retail (goreng, bagging bakar/ori, NYEE) | B34: Ubi Ungu | C34: 0 | D34: 0 | E34: 0 | F34: 0 | G34: 0 | H34: 0 | I34: 0
A35: Whole chips ubi ungu 15/90 gr | B35: Ubi Ungu | C35: 0 | D35: 0 | E35: 0 | F35: 0 | G35: 0 | H35: 0 | I35: 0
A36: Umbiis (goreng & bagging) | B36: Ubi Ungu – cek bahan | C36: 0 | D36: 0 | E36: 0 | F36: 0 | G36: 0 | H36: 0 | I36: 0
A37: Ubi ungu chips | B37: Ubi Ungu | C37: 0 | D37: 0 | E37: 0 | F37: 0 | G37: 0 | H37: 0 | I37: 0
A38: Pellet ubi orange FG 3x3 | B38: Ubi Orange | C38: 0 | D38: 0 | E38: 0 | F38: 0 | G38: 0 | H38: 0 | I38: 0
A39: Ubi orange chips | B39: Ubi Orange | C39: 0 | D39: 0 | E39: 0 | F39: 0 | G39: 0 | H39: 0 | I39: 0
A40: Pellet lainnya | B40: Cek bahan | C40: 0 | D40: 0 | E40: 0 | F40: 0 | G40: 0 | H40: 0 | I40: 0
A41: Ubi putih ACE (Sweet Potato N110), ubi putih & talas chips | B41: Singkong (lain) | C41: ='UBI PUTIH ACE'!$B$21 -> 14802.48 | D41: ='UBI PUTIH ACE'!$B$23 -> 0 | E41: ='UBI PUTIH ACE'!$B$24 -> 0 | F41: ='UBI PUTIH ACE'!$B$25 -> 0 | G41: ='UBI PUTIH ACE'!$E$34 -> 68748452 | H41: ='UBI PUTIH ACE'!$C$106 -> 465 | I41: ='UBI PUTIH ACE'!$C$107 -> 134.9986 | J41: Tautan ke sheet UBI PUTIH ACE
A42: WRP (Delichips, Mixfruit, chips) – maklon | B42: Singkong (maklon) | C42: 0 | D42: 0 | E42: 0 | F42: 0 | G42: 0 | H42: 0 | I42: 0
A43: Total | C43: =SUM(C22:C42) -> 45653.42 | D43: =SUM(D22:D42) -> 23115.5 | E43: =SUM(E22:E42) -> 4242 | F43: =SUM(F22:F42) -> 770 | G43: =SUM(G22:G42) -> 76673619 | H43: =SUM(H22:H42) -> 2689.1499 | I43: =SUM(I22:I42) -> 10118.059
A45: 3. Biaya produksi per kelompok (Rp)
A46: Kelompok produk | B46: FCC premium | C46: KW 2 | D46: Material eksternal | E46: DL (Grup A) | F46: FOH (Grup B–E) | G46: Total biaya | H46: Rp/kg
A47: =A22 -> Cem-cem ORI | B47: =D22*FCC!$D$89 -> 2.485532e+08 | C47: =E22*FCC!$C$209+F22*$C$7 -> 0 | D47: =G22 -> 712800 | E47: =IF($H$43=0,0,H22/$H$43)*'BIAYA BERSAMA'!$F$115 -> 19159921 | F47: =IF($H$43=0,0,H22/$H$43)*'BIAYA BERSAMA'!$F$117+IF($I$43=0,0,I22/$I$43)*'BIAYA BERSAMA'!$F$118+IF('BIAYA BERSAMA'!$F$172=0,0,I22/'BIAYA BERSAMA'!$F$172)*'BIAYA BERSAMA'!$F$176+IF($G$43=0,0,G22/$G$43)*'BIAYA BERSAMA'!$F$120 -> 50035306 | G47: =SUM(B47:F47) -> 3.1846122e+08 | H47: =IF(C22=0,0,G47/C22) -> 28857.104
A48: =A23 -> Cem-cem BBQ | B48: =D23*FCC!$D$89 -> 2.3082753e+08 | C48: =E23*FCC!$C$209+F23*$C$7 -> 0 | D48: =G23 -> 0 | E48: =IF($H$43=0,0,H23/$H$43)*'BIAYA BERSAMA'!$F$115 -> 17106326 | F48: =IF($H$43=0,0,H23/$H$43)*'BIAYA BERSAMA'!$F$117+IF($I$43=0,0,I23/$I$43)*'BIAYA BERSAMA'!$F$118+IF('BIAYA BERSAMA'!$F$172=0,0,I23/'BIAYA BERSAMA'!$F$172)*'BIAYA BERSAMA'!$F$176+IF($G$43=0,0,G23/$G$43)*'BIAYA BERSAMA'!$F$120 -> 44748638 | G48: =SUM(B48:F48) -> 2.926825e+08 | H48: =IF(C23=0,0,G48/C23) -> 28401.989
A49: =A24 -> Koperasi (KW 2 berbumbu, 11 SKU) | B49: =D24*FCC!$D$89 -> 238729.48 | C49: =E24*FCC!$C$209+F24*$C$7 -> 19574097 | D49: =G24 -> 6333602.8 | E49: =IF($H$43=0,0,H24/$H$43)*'BIAYA BERSAMA'!$F$115 -> 1940129.1 | F49: =IF($H$43=0,0,H24/$H$43)*'BIAYA BERSAMA'!$F$117+IF($I$43=0,0,I24/$I$43)*'BIAYA BERSAMA'!$F$118+IF('BIAYA BERSAMA'!$F$172=0,0,I24/'BIAYA BERSAMA'!$F$172)*'BIAYA BERSAMA'!$F$176+IF($G$43=0,0,G24/$G$43)*'BIAYA BERSAMA'!$F$120 -> 2114887.9 | G49: =SUM(B49:F49) -> 30201446 | H49: =IF(C24=0,0,G49/C24) -> 10177.404
A50: =A25 -> Maicih basreng (maklon, 3 SKU) | B50: =D25*FCC!$D$89 -> 0 | C50: =E25*FCC!$C$209+F25*$C$7 -> 0 | D50: =G25 -> 42696.287 | E50: =IF($H$43=0,0,H25/$H$43)*'BIAYA BERSAMA'!$F$115 -> 1345106.4 | F50: =IF($H$43=0,0,H25/$H$43)*'BIAYA BERSAMA'!$F$117+IF($I$43=0,0,I25/$I$43)*'BIAYA BERSAMA'!$F$118+IF('BIAYA BERSAMA'!$F$172=0,0,I25/'BIAYA BERSAMA'!$F$172)*'BIAYA BERSAMA'!$F$176+IF($G$43=0,0,G25/$G$43)*'BIAYA BERSAMA'!$F$120 -> 4067690.7 | G50: =SUM(B50:F50) -> 5455493.4 | H50: =IF(C25=0,0,G50/C25) -> 5887.9009
A51: =A26 -> Maicih keripik (LV 3 & 10) | B51: =D26*FCC!$D$89 -> 50682269 | C51: =E26*FCC!$C$209+F26*$C$7 -> 15915260 | D51: =G26 -> 604941.04 | E51: =IF($H$43=0,0,H26/$H$43)*'BIAYA BERSAMA'!$F$115 -> 5595184.9 | F51: =IF($H$43=0,0,H26/$H$43)*'BIAYA BERSAMA'!$F$117+IF($I$43=0,0,I26/$I$43)*'BIAYA BERSAMA'!$F$118+IF('BIAYA BERSAMA'!$F$172=0,0,I26/'BIAYA BERSAMA'!$F$172)*'BIAYA BERSAMA'!$F$176+IF($G$43=0,0,G26/$G$43)*'BIAYA BERSAMA'!$F$120 -> 18041897 | G51: =SUM(B51:F51) -> 90839551 | H51: =IF(C26=0,0,G51/C26) -> 22624.818
A52: =A27 -> Maicih keripik LV 5 | B52: =D27*FCC!$D$89 -> 21533399 | C52: =E27*FCC!$C$209+F27*$C$7 -> 5985827.8 | D52: =G27 -> 231126.4 | E52: =IF($H$43=0,0,H27/$H$43)*'BIAYA BERSAMA'!$F$115 -> 3153673.8 | F52: =IF($H$43=0,0,H27/$H$43)*'BIAYA BERSAMA'!$F$117+IF($I$43=0,0,I27/$I$43)*'BIAYA BERSAMA'!$F$118+IF('BIAYA BERSAMA'!$F$172=0,0,I27/'BIAYA BERSAMA'!$F$172)*'BIAYA BERSAMA'!$F$176+IF($G$43=0,0,G27/$G$43)*'BIAYA BERSAMA'!$F$120 -> 7991352.2 | G52: =SUM(B52:F52) -> 38895379 | H52: =IF(C27=0,0,G52/C27) -> 24293.821
A53: =A28 -> FCC Maicih | B53: =D28*FCC!$D$89 -> 0 | C53: =E28*FCC!$C$209+F28*$C$7 -> 0 | D53: =G28 -> 0 | E53: =IF($H$43=0,0,H28/$H$43)*'BIAYA BERSAMA'!$F$115 -> 0 | F53: =IF($H$43=0,0,H28/$H$43)*'BIAYA BERSAMA'!$F$117+IF($I$43=0,0,I28/$I$43)*'BIAYA BERSAMA'!$F$118+IF('BIAYA BERSAMA'!$F$172=0,0,I28/'BIAYA BERSAMA'!$F$172)*'BIAYA BERSAMA'!$F$176+IF($G$43=0,0,G28/$G$43)*'BIAYA BERSAMA'!$F$120 -> 0 | G53: =SUM(B53:F53) -> 0 | H53: =IF(C28=0,0,G53/C28) -> 0
A54: =A29 -> FCC Putih | B54: =D29*FCC!$D$89 -> 0 | C54: =E29*FCC!$C$209+F29*$C$7 -> 0 | D54: =G29 -> 0 | E54: =IF($H$43=0,0,H29/$H$43)*'BIAYA BERSAMA'!$F$115 -> 0 | F54: =IF($H$43=0,0,H29/$H$43)*'BIAYA BERSAMA'!$F$117+IF($I$43=0,0,I29/$I$43)*'BIAYA BERSAMA'!$F$118+IF('BIAYA BERSAMA'!$F$172=0,0,I29/'BIAYA BERSAMA'!$F$172)*'BIAYA BERSAMA'!$F$176+IF($G$43=0,0,G29/$G$43)*'BIAYA BERSAMA'!$F$120 -> 0 | G54: =SUM(B54:F54) -> 0 | H54: =IF(C29=0,0,G54/C29) -> 0
A55: =A30 -> Kecimpring (goreng & bagging) | B55: =D30*FCC!$D$89 -> 0 | C55: =E30*FCC!$C$209+F30*$C$7 -> 0 | D55: =G30 -> 0 | E55: =IF($H$43=0,0,H30/$H$43)*'BIAYA BERSAMA'!$F$115 -> 0 | F55: =IF($H$43=0,0,H30/$H$43)*'BIAYA BERSAMA'!$F$117+IF($I$43=0,0,I30/$I$43)*'BIAYA BERSAMA'!$F$118+IF('BIAYA BERSAMA'!$F$172=0,0,I30/'BIAYA BERSAMA'!$F$172)*'BIAYA BERSAMA'!$F$176+IF($G$43=0,0,G30/$G$43)*'BIAYA BERSAMA'!$F$120 -> 0 | G55: =SUM(B55:F55) -> 0 | H55: =IF(C30=0,0,G55/C30) -> 0
A56: =A31 -> Whole chips rempah 15/90 gr | B56: =D31*FCC!$D$89 -> 0 | C56: =E31*FCC!$C$209+F31*$C$7 -> 0 | D56: =G31 -> 0 | E56: =IF($H$43=0,0,H31/$H$43)*'BIAYA BERSAMA'!$F$115 -> 0 | F56: =IF($H$43=0,0,H31/$H$43)*'BIAYA BERSAMA'!$F$117+IF($I$43=0,0,I31/$I$43)*'BIAYA BERSAMA'!$F$118+IF('BIAYA BERSAMA'!$F$172=0,0,I31/'BIAYA BERSAMA'!$F$172)*'BIAYA BERSAMA'!$F$176+IF($G$43=0,0,G31/$G$43)*'BIAYA BERSAMA'!$F$120 -> 0 | G56: =SUM(B56:F56) -> 0 | H56: =IF(C31=0,0,G56/C31) -> 0
A57: =A32 -> Maxi (pellet & goreng) | B57: =D32*FCC!$D$89 -> 0 | C57: =E32*FCC!$C$209+F32*$C$7 -> 0 | D57: =G32 -> 0 | E57: =IF($H$43=0,0,H32/$H$43)*'BIAYA BERSAMA'!$F$115 -> 0 | F57: =IF($H$43=0,0,H32/$H$43)*'BIAYA BERSAMA'!$F$117+IF($I$43=0,0,I32/$I$43)*'BIAYA BERSAMA'!$F$118+IF('BIAYA BERSAMA'!$F$172=0,0,I32/'BIAYA BERSAMA'!$F$172)*'BIAYA BERSAMA'!$F$176+IF($G$43=0,0,G32/$G$43)*'BIAYA BERSAMA'!$F$120 -> 0 | G57: =SUM(B57:F57) -> 0 | H57: =IF(C32=0,0,G57/C32) -> 0
A58: =A33 -> Pellet ubi ungu FG (1,2x1,5 & 3x3) | B58: =D33*FCC!$D$89 -> 0 | C58: =E33*FCC!$C$209+F33*$C$7 -> 0 | D58: =G33 -> 0 | E58: =IF($H$43=0,0,H33/$H$43)*'BIAYA BERSAMA'!$F$115 -> 0 | F58: =IF($H$43=0,0,H33/$H$43)*'BIAYA BERSAMA'!$F$117+IF($I$43=0,0,I33/$I$43)*'BIAYA BERSAMA'!$F$118+IF('BIAYA BERSAMA'!$F$172=0,0,I33/'BIAYA BERSAMA'!$F$172)*'BIAYA BERSAMA'!$F$176+IF($G$43=0,0,G33/$G$43)*'BIAYA BERSAMA'!$F$120 -> 0 | G58: =SUM(B58:F58) -> 0 | H58: =IF(C33=0,0,G58/C33) -> 0
... A65: =A40 -> Pellet lainnya | B65: =D40*FCC!$D$89 -> 0 | C65: =E40*FCC!$C$209+F40*$C$7 -> 0 | D65: =G40 -> 0 | E65: =IF($H$43=0,0,H40/$H$43)*'BIAYA BERSAMA'!$F$115 -> 0 | F65: =IF($H$43=0,0,H40/$H$43)*'BIAYA BERSAMA'!$F$117+IF($I$43=0,0,I40/$I$43)*'BIAYA BERSAMA'!$F$118+IF('BIAYA BERSAMA'!$F$172=0,0,I40/'BIAYA BERSAMA'!$F$172)*'BIAYA BERSAMA'!$F$176+IF($G$43=0,0,G40/$G$43)*'BIAYA BERSAMA'!$F$120 -> 0 | G65: =SUM(B65:F65) -> 0 | H65: =IF(C40=0,0,G65/C40) -> 0
A66: =A41 -> Ubi putih ACE (Sweet Potato N110), ubi putih & talas chips | B66: =D41*FCC!$D$89 -> 0 | C66: =E41*FCC!$C$209+F41*$C$7 -> 0 | D66: =G41 -> 68748452 | E66: =IF($H$43=0,0,H41/$H$43)*'BIAYA BERSAMA'!$F$115 -> 10098087 | F66: =IF($H$43=0,0,H41/$H$43)*'BIAYA BERSAMA'!$F$117+IF($I$43=0,0,I41/$I$43)*'BIAYA BERSAMA'!$F$118+'BIAYA BERSAMA'!$F$177+IF($G$43=0,0,G41/$G$43)*'BIAYA BERSAMA'!$F$120 -> 15595946 | G66: =SUM(B66:F66) -> 94442485 | H66: =IF(C41=0,0,G66/C41) -> 6380.1799
A67: =A42 -> WRP (Delichips, Mixfruit, chips) – maklon | B67: =D42*FCC!$D$89 -> 0 | C67: =E42*FCC!$C$209+F42*$C$7 -> 0 | D67: =G42 -> 0 | E67: =IF($H$43=0,0,H42/$H$43)*'BIAYA BERSAMA'!$F$115 -> 0 | F67: =IF($H$43=0,0,H42/$H$43)*'BIAYA BERSAMA'!$F$117+IF($I$43=0,0,I42/$I$43)*'BIAYA BERSAMA'!$F$118+IF('BIAYA BERSAMA'!$F$172=0,0,I42/'BIAYA BERSAMA'!$F$172)*'BIAYA BERSAMA'!$F$176+IF($G$43=0,0,G42/$G$43)*'BIAYA BERSAMA'!$F$120 -> 0 | G67: =SUM(B67:F67) -> 0 | H67: =IF(C42=0,0,G67/C42) -> 0
A68: Total | B68: =SUM(B47:B67) -> 5.5183513e+08 | C68: =SUM(C47:C67) -> 41475184 | D68: =SUM(D47:D67) -> 76673619 | E68: =SUM(E47:E67) -> 58398429 | F68: =SUM(F47:F67) -> 1.4259572e+08 | G68: =SUM(G47:G67) -> 8.7097808e+08 | H68: =IF(C43=0,0,G68/C43) -> 19078.047
A70: 4. Kontrol
A71: Cek | C71: Nilai | D71: Status
A72: Man-hour Lain-lain = driver di BIAYA BERSAMA | C72: =H43-'BIAYA BERSAMA'!$F$91 -> 0 | D72: =IF(ISERROR(C72),"GAGAL",IF(ABS(C72)<=0.01,"LULUS","GAGAL")) -> LULUS
A73: kWh Lain-lain = driver di BIAYA BERSAMA | C73: =I43-'BIAYA BERSAMA'!$F$93 -> 0 | D73: =IF(ISERROR(C73),"GAGAL",IF(ABS(C73)<=0.01,"LULUS","GAGAL")) -> LULUS
A74: Konversi teralokasi = pool Lain-lain | C74: =E68+F68-('BIAYA BERSAMA'!$F$121-'BIAYA BERSAMA'!$F$116) -> 0 | D74: =IF(ISERROR(C74),"GAGAL",IF(ABS(C74)<=1,"LULUS","GAGAL")) -> LULUS
A75: Tidak ada sel error | C75: =SUMPRODUCT(--ISERROR(A9:L70)) -> 0 | D75: =IF(ISERROR(C75),"GAGAL",IF(ABS(C75)<=0.5,"LULUS","GAGAL")) -> LULUS
A80: 5. Rekap per SKU: biaya produksi, barang jadi, HPP, pendapatan (Rp)
A81: Sheet SKU | B81: Baris driver | C81: Output (kg) | D81: Total biaya produksi | E81: Barang jadi awal | F81: Barang jadi akhir | G81: HPP | H81: Pendapatan | I81: Margin kotor | J81: Margin % | K81: Status sheet
A82: CEM-CEM ORI | B82: 22 | C82: ='CEM-CEM ORI'!$B$21 -> 11035.8 | D82: ='CEM-CEM ORI'!$E$43 -> 3.1846122e+08 | E82: ='CEM-CEM ORI'!$D$47 -> 14727247 | F82: ='CEM-CEM ORI'!$D$52 -> 828183.25 | G82: ='CEM-CEM ORI'!$D$54 -> 3.3236029e+08 | H82: ='CEM-CEM ORI'!$C$118 -> 329346000 | I82: =H82-G82 -> -3014288.6 | J82: =IF(H82=0,0,I82/H82) -> -0.0091523462 | K82: ='CEM-CEM ORI'!$C$4 -> LULUS
A83: CEM-CEM BBQ | B83: 23 | C83: ='CEM-CEM BBQ'!$B$21 -> 10305 | D83: ='CEM-CEM BBQ'!$E$43 -> 2.926825e+08 | E83: ='CEM-CEM BBQ'!$D$47 -> 47681.866 | F83: ='CEM-CEM BBQ'!$D$52 -> 13343098 | G83: ='CEM-CEM BBQ'!$D$54 -> 2.7938708e+08 | H83: ='CEM-CEM BBQ'!$C$118 -> 277895250 | I83: =H83-G83 -> -1491832.1 | J83: =IF(H83=0,0,I83/H83) -> -0.0053683253 | K83: ='CEM-CEM BBQ'!$C$4 -> LULUS
A84: KOPERASI | B84: 24 | C84: =KOPERASI!$M$7 -> 2967.5 | D84: =KOPERASI!$M$22 -> 30201446 | E84: =KOPERASI!$M$28 -> 0 | F84: =KOPERASI!$M$35 -> 0 | G84: =KOPERASI!$M$38 -> 30201446 | H84: =KOPERASI!$M$136 -> 28518903 | I84: =H84-G84 -> -1682542.8 | J84: =IF(H84=0,0,I84/H84) -> -0.058997458 | K84: =KOPERASI!$C$4 -> LULUS
A85: MCH BASRENG L0 | B85: 25 | C85: ='MCH BASRENG L0'!$B$21 -> 0 | D85: ='MCH BASRENG L0'!$E$43 -> 0 | E85: ='MCH BASRENG L0'!$D$47 -> 0 | F85: ='MCH BASRENG L0'!$D$52 -> 0 | G85: ='MCH BASRENG L0'!$D$54 -> 0 | H85: ='MCH BASRENG L0'!$C$118 -> 0 | I85: =H85-G85 -> 0 | J85: =IF(H85=0,0,I85/H85) -> 0 | K85: ='MCH BASRENG L0'!$C$4 -> LULUS
A86: MCH BASRENG L5 | B86: 25 | C86: ='MCH BASRENG L5'!$B$21 -> 353.28 | D86: ='MCH BASRENG L5'!$E$43 -> 2187051.9 | E86: ='MCH BASRENG L5'!$D$47 -> 0 | F86: ='MCH BASRENG L5'!$D$52 -> 0 | G86: ='MCH BASRENG L5'!$D$54 -> 2187051.9 | H86: ='MCH BASRENG L5'!$C$118 -> 1766400 | I86: =H86-G86 -> -420651.88 | J86: =IF(H86=0,0,I86/H86) -> -0.23814079 | K86: ='MCH BASRENG L5'!$C$4 -> LULUS
A87: MCH BASRENG L10 | B87: 25 | C87: ='MCH BASRENG L10'!$B$21 -> 573.28 | D87: ='MCH BASRENG L10'!$E$43 -> 3268441.6 | E87: ='MCH BASRENG L10'!$D$47 -> 0 | F87: ='MCH BASRENG L10'!$D$52 -> 0 | G87: ='MCH BASRENG L10'!$D$54 -> 3268441.6 | H87: ='MCH BASRENG L10'!$C$118 -> 2866400 | I87: =H87-G87 -> -402041.55 | J87: =IF(H87=0,0,I87/H87) -> -0.1402601 | K87: ='MCH BASRENG L10'!$C$4 -> LULUS
A88: MCH KERIPIK LV3 | B88: 26 | C88: ='MCH KERIPIK LV3'!$B$21 -> 1966 | D88: ='MCH KERIPIK LV3'!$E$43 -> 39680414 | E88: ='MCH KERIPIK LV3'!$D$47 -> 0 | F88: ='MCH KERIPIK LV3'!$D$52 -> 0 | G88: ='MCH KERIPIK LV3'!$D$54 -> 39680414 | H88: ='MCH KERIPIK LV3'!$C$118 -> 55850000 | I88: =H88-G88 -> 16169586 | J88: =IF(H88=0,0,I88/H88) -> 0.2895181 | K88: ='MCH KERIPIK LV3'!$C$4 -> LULUS
A89: MCH KERIPIK LV10 | B89: 26 | C89: ='MCH KERIPIK LV10'!$B$21 -> 2049.04 | D89: ='MCH KERIPIK LV10'!$E$43 -> 51159137 | E89: ='MCH KERIPIK LV10'!$D$47 -> 0 | F89: ='MCH KERIPIK LV10'!$D$52 -> 0 | G89: ='MCH KERIPIK LV10'!$D$54 -> 51159137 | H89: ='MCH KERIPIK LV10'!$C$118 -> 67482000 | I89: =H89-G89 -> 16322863 | J89: =IF(H89=0,0,I89/H89) -> 0.2418847 | K89: ='MCH KERIPIK LV10'!$C$4 -> LULUS
A90: MCH KERIPIK LV5 | B90: 27 | C90: ='MCH KERIPIK LV5'!$B$21 -> 1601.04 | D90: ='MCH KERIPIK LV5'!$E$43 -> 38895379 | E90: ='MCH KERIPIK LV5'!$D$47 -> 0 | F90: ='MCH KERIPIK LV5'!$D$52 -> 0 | G90: ='MCH KERIPIK LV5'!$D$54 -> 38895379 | H90: ='MCH KERIPIK LV5'!$C$118 -> 49606000 | I90: =H90-G90 -> 10710621 | J90: =IF(H90=0,0,I90/H90) -> 0.21591382 | K90: ='MCH KERIPIK LV5'!$C$4 -> LULUS
A91: UBI PUTIH ACE | B91: 41 | C91: ='UBI PUTIH ACE'!$B$21 -> 14802.48 | D91: ='UBI PUTIH ACE'!$E$43 -> 94442485 | E91: ='UBI PUTIH ACE'!$D$47 -> 0 | F91: ='UBI PUTIH ACE'!$D$52 -> 0 | G91: ='UBI PUTIH ACE'!$D$54 -> 94442485 | H91: ='UBI PUTIH ACE'!$C$118 -> 103910690 | I91: =H91-G91 -> 9468205.3 | J91: =IF(H91=0,0,I91/H91) -> 0.091118683 | K91: ='UBI PUTIH ACE'!$C$4 -> LULUS
A92: Produk tanpa kartu bulan ini (mis. whole chips, Umbiis, chips mix sampel) | G92: 0 | H92: ='REKON & KONTROL'!$C$74-SUM(H82:H91) -> 432417.12 | I92: =H92-G92 -> 432417.12 | K92: Tidak ada kartu → HPP 0 di WP (terserap di rekonsiliasi HPP. REKON). Memo HPP Accurate: Rp 980.075 (FG-041 Umbiis Kerupuk Ubi Ungu 55gr 980.075)
A93: Total Lain-lain | C93: =SUM(C82:C92) -> 45653.42 | D93: =SUM(D82:D92) -> 8.7097808e+08 | E93: =SUM(E82:E92) -> 14774929 | F93: =SUM(F82:F92) -> 14171281 | G93: =SUM(G82:G92) -> 8.7158173e+08 | H93: =SUM(H82:H92) -> 9.1767406e+08 | I93: =SUM(I82:I92) -> 46092335 | J93: =IF(H93=0,0,I93/H93) -> 0.050227349
A95: Cek: biaya per baris driver bagian 3 = jumlah sheet SKU
A96: Baris | B96: Σ sheet SKU | C96: Bagian 3 kolom G | D96: Selisih
A97: =A22 -> Cem-cem ORI | B97: =SUMIF($B$82:$B$91,22,$D$82:$D$91) -> 3.1846122e+08 | C97: =G47 -> 3.1846122e+08 | D97: =B97-C97 -> 0
A98: =A23 -> Cem-cem BBQ | B98: =SUMIF($B$82:$B$91,23,$D$82:$D$91) -> 2.926825e+08 | C98: =G48 -> 2.926825e+08 | D98: =B98-C98 -> 0
A99: =A24 -> Koperasi (KW 2 berbumbu, 11 SKU) | B99: =SUMIF($B$82:$B$91,24,$D$82:$D$91) -> 30201446 | C99: =G49 -> 30201446 | D99: =B99-C99 -> 0
A100: =A25 -> Maicih basreng (maklon, 3 SKU) | B100: =SUMIF($B$82:$B$91,25,$D$82:$D$91) -> 5455493.4 | C100: =G50 -> 5455493.4 | D100: =B100-C100 -> 0
A101: =A26 -> Maicih keripik (LV 3 & 10) | B101: =SUMIF($B$82:$B$91,26,$D$82:$D$91) -> 90839551 | C101: =G51 -> 90839551 | D101: =B101-C101 -> 0
A102: =A27 -> Maicih keripik LV 5 | B102: =SUMIF($B$82:$B$91,27,$D$82:$D$91) -> 38895379 | C102: =G52 -> 38895379 | D102: =B102-C102 -> 0
A103: =A41 -> Ubi putih ACE (Sweet Potato N110), ubi putih & talas chips | B103: =SUMIF($B$82:$B$91,41,$D$82:$D$91) -> 94442485 | C103: =G66 -> 94442485 | D103: =B103-C103 -> 0
A105: 5b. Kontrol rekap per SKU
A106: Cek | C106: Nilai | D106: Status
A107: Biaya per baris driver = jumlah sheet SKU (Σ |selisih|) | C107: =SUMPRODUCT(ABS(D97:D103)) -> 0 | D107: =IF(ISERROR(C107),"GAGAL",IF(ABS(C107)<=1,"LULUS","GAGAL")) -> LULUS
A108: Total biaya sheet SKU = total biaya produksi Lain-lain (G68) | C108: =D93-G68 -> 0 | D108: =IF(ISERROR(C108),"GAGAL",IF(ABS(C108)<=1,"LULUS","GAGAL")) -> LULUS
A109: Semua sheet SKU LULUS (jumlah sheet GAGAL) | C109: =COUNTIF(K82:K91,"GAGAL") -> 0 | D109: =IF(ISERROR(C109),"GAGAL",IF(ABS(C109)<=0.5,"LULUS","GAGAL")) -> LULUS
A110: Pendapatan produk tanpa kartu tidak negatif | C110: =MIN(0,H92) -> 0 | D110: =IF(ISERROR(C110),"GAGAL",IF(ABS(C110)<=1,"LULUS","GAGAL")) -> LULUS

Sheet CEM-CEM ORI
A1: KARTU BIAYA PRODUKSI – Cem-cem ORI (Keripik Singkong Original, Cem-Cem Cazva), September 2026
A2: Sumber: kartu 'LAP BAG CEMCEM ORI' di WP CoGM September 2026; driver man-hour & kWh: sheet Labor & Overhead Allocation; barang jadi: Inventory Valuation Accurate FG-180; pendapatan: LK Sales By Item.
A4: Status kontrol (bagian 5) | C4: =IF(COUNTIF(C70:C75,"GAGAL")=0,"LULUS","GAGAL") -> LULUS
A5: 1. Ringkasan (Rp juta; Rp/kg per kg produksi bulan ini)
A6: Komponen | B6: Aktual (Rp jt) | C6: Rp/kg | D6: Porsi
A7: FCC premium (antarproduk) | B7: =E31/10^6 -> 248.5532 | C7: =F31 -> 22522.445 | D7: =IF($B$12=0,0,B7/$B$12) -> 0.78048182
A8: KW 2 (antarproduk, NRV) | B8: =(E32+E33)/10^6 -> 0 | C8: =F32+F33 -> 0 | D8: =IF($B$12=0,0,B8/$B$12) -> 0
A9: Material eksternal | B9: =E34/10^6 -> 0.7128 | C9: =F34 -> 64.58979 | D9: =IF($B$12=0,0,B9/$B$12) -> 0.0022382631
A10: Direct labour (Grup A) | B10: =E37/10^6 -> 19.159921 | C10: =F37 -> 1736.1606 | D10: =IF($B$12=0,0,B10/$B$12) -> 0.060164063
A11: Factory overhead (Grup B–E) | B11: =E41/10^6 -> 50.035306 | C11: =F41 -> 4533.9084 | D11: =IF($B$12=0,0,B11/$B$12) -> 0.15711585
A12: Total biaya produksi | B12: =E43/10^6 -> 318.46122 | C12: =F43 -> 28857.104 | D12: =IF($B$12=0,0,B12/$B$12) -> 1
A13: Produksi (kg; satuan FG) | B13: =B21 -> 11035.8 | C13: =C21 -> 183930
A14: HPP (Rp jt) dan HPP per satuan terjual | B14: =D54/10^6 -> 332.36029 | C14: =C55 -> 1725.6505
A15: Pendapatan (Rp jt) dan harga per satuan | B15: =$C$118/10^6 -> 329.346 | C15: =IF($C$117=0,0,$C$118/$C$117) -> 1710
A16: Margin kotor (Rp jt; %) | B16: =B15-B14 -> -3.0142886 | C16: =IF(B15=0,0,B16/B15) -> -0.0091523462
A18: 2. Laporan biaya produksi
A19: 2a. Kuantitas
A20: Pos | B20: Kg | C20: Satuan FG (bag) | D20: Keterangan
A21: Output produksi | B21: =$C$102 -> 11035.8 | C21: =$C$103 -> 183930
A22: Sampel | B22: =$C$104 -> 19.44 | C22: =$C$105 -> 324 | D22: memo, tidak masuk barang jadi
A23: Input FCC premium | B23: =SUMIF($B$128:$B$130,"FCC",$C$128:$C$130) -> 10411.5 | D23: Lampiran B
A24: Input KW 2 FCC | B24: =SUMIF($B$128:$B$130,"KW2",$C$128:$C$130) -> 0 | D24: Lampiran B
A25: Input KW 2 ubi | B25: =SUMIF($B$128:$B$130,"KW2UBI",$C$128:$C$130) -> 0 | D25: Lampiran B
A26: Rendemen output ÷ input keripik (kg/kg) | B26: =IF(SUM(B23:B25)=0,0,B21/SUM(B23:B25)) -> 1.0599625
A28: 2b. Biaya produksi bulan ini (aktual)
A29: Komponen | B29: Qty / driver | C29: Satuan | D29: Harga / porsi | E29: Nilai (Rp) | F29: Rp/kg | G29: Dasar
A30: Bahan
A31: FCC premium (antarproduk) | B31: =B23 -> 10411.5 | C31: kg | D31: =FCC!$D$89 -> 23872.948 | E31: =B31*D31 -> 2.485532e+08 | F31: =IF($B$21=0,0,E31/$B$21) -> 22522.445 | G31: Biaya rata-rata FG FCC kartu baru (FCC D88)
A32: KW 2 FCC (antarproduk, NRV) | B32: =B24 -> 0 | C32: kg | D32: =FCC!$C$209 -> 9777.2712 | E32: =B32*D32 -> 0 | F32: =IF($B$21=0,0,E32/$B$21) -> 0 | G32: NRV KW 2 (FCC C208)
A33: KW 2 ubi (antarproduk) | B33: =B25 -> 0 | C33: kg | D33: ='LAIN-LAIN'!$C$7 -> 0 | E33: =B33*D33 -> 0 | F33: =IF($B$21=0,0,E33/$B$21) -> 0 | G33: Nilai KW 2 ubi (LAIN-LAIN C7)
A34: Material eksternal (Lampiran B) | E34: =SUMIF($B$128:$B$130,"EXT",$F$128:$F$130) -> 712800 | F34: =IF($B$21=0,0,E34/$B$21) -> 64.58979 | G34: Nilai kartu per baris material
A35: Subtotal bahan | E35: =SUM(E31:E34) -> 2.49266e+08 | F35: =IF($B$21=0,0,E35/$B$21) -> 22587.035
A36: Konversi (pool BIAYA BERSAMA, porsi Lain-lain dibagi dengan driver yang sama dengan sheet LAIN-LAIN)
A37: Grup A – DL operator | B37: =$C$106 -> 882.2823 | C37: jam | D37: =IF('LAIN-LAIN'!$H$43=0,0,B37/'LAIN-LAIN'!$H$43) -> 0.32808967 | E37: =D37*'BIAYA BERSAMA'!$F$115 -> 19159921 | F37: =IF($B$21=0,0,E37/$B$21) -> 1736.1606 | G37: Man-hour ÷ total man-hour Lain-lain × pool Grup A Lain-lain
A38: Grup B – IDL (support, staf, THR, BPJS) | B38: =$C$106 -> 882.2823 | C38: jam | D38: =IF('LAIN-LAIN'!$H$43=0,0,B38/'LAIN-LAIN'!$H$43) -> 0.32808967 | E38: =D38*'BIAYA BERSAMA'!$F$117 -> 17128969 | F38: =IF($B$21=0,0,E38/$B$21) -> 1552.1276 | G38: Man-hour
A39: Grup C + D – energi (kWh) dan mesin (bagging: kWh; Ubi putih ACE: jam mesin) | B39: =$C$107 -> 3936.4737 | C39: kWh | D39: =IF('LAIN-LAIN'!$I$43=0,0,B39/'LAIN-LAIN'!$I$43) -> 0.38905423 | E39: =D39*'BIAYA BERSAMA'!$F$118+IF('BIAYA BERSAMA'!$F$172=0,0,B39/'BIAYA BERSAMA'!$F$172)*'BIAYA BERSAMA'!$F$176 -> 32863524 | F39: =IF($B$21=0,0,E39/$B$21) -> 2977.9014 | G39: kWh
A40: Grup E – pabrik umum | B40: =E34 -> 712800 | C40: Rp | D40: =IF('LAIN-LAIN'!$G$43=0,0,B40/'LAIN-LAIN'!$G$43) -> 0.0092965483 | E40: =D40*'BIAYA BERSAMA'!$F$120 -> 42812.599 | F40: =IF($B$21=0,0,E40/$B$21) -> 3.8794287 | G40: Nilai material eksternal
A41: Subtotal factory overhead (Grup B–E) | E41: =SUM(E38:E40) -> 50035306 | F41: =IF($B$21=0,0,E41/$B$21) -> 4533.9084
A42: Total konversi | E42: =E37+E41 -> 69195227 | F42: =IF($B$21=0,0,E42/$B$21) -> 6270.069
A43: TOTAL BIAYA PRODUKSI BULAN INI | E43: =E35+E42 -> 3.1846122e+08 | F43: =IF($B$21=0,0,E43/$B$21) -> 28857.104
A45: 3. Barang jadi (FG-180 Keripik Singkong Original (Cem-Cem Cazva)) dan HPP
A46: Pos | B46: Qty (bag) | C46: Rp/satuan | D46: Nilai WP (Rp) | E46: Qty Accurate | F46: Nilai Accurate (Rp) | G46: Selisih nilai WP − Accurate
A47: Saldo awal | B47: =$C$108 -> 9180 | D47: =$C$109 -> 14727247 | E47: =$C$108 -> 9180 | F47: =$C$110 -> 12074637 | G47: =D47-F47 -> 2652610.2
A48: Masuk dari produksi | B48: =C21 -> 183930 | D48: =E43 -> 3.1846122e+08 | E48: =$C$111 -> 183900 | F48: =$C$112 -> 2.3828352e+08 | G48: =D48-F48 -> 80177703
A49: Tersedia | B49: =B47+B48 -> 193110 | D49: =D47+D48 -> 3.3318847e+08 | E49: =E47+E48 -> 193080 | F49: =F47+F48 -> 2.5035816e+08 | G49: =D49-F49 -> 82830313
A50: Biaya rata-rata tertimbang per satuan | C50: =IF(B49=0,0,D49/B49) -> 1725.3818
A51: Keluar: penjualan (pengiriman pesanan) | B51: =$C$113 -> 192600 | D51: =B51*$C$50 -> 3.3230853e+08 | E51: =$C$113 -> 192600 | F51: =$C$114 -> 249720345 | G51: =D51-F51 -> 82588182
A52: Saldo akhir (qty menurut Accurate) | B52: =$C$115 -> 480 | D52: =B52*$C$50 -> 828183.25 | E52: =$C$115 -> 480 | F52: =$C$116 -> 637813.81 | G52: =D52-F52 -> 190369.44
A53: Selisih kuantitas (tersedia − penjualan − saldo akhir) ke HPP | B53: =B49-B51-B52 -> 30 | D53: =B53*$C$50 -> 51761.453 | E53: =E49-E51-E52 -> 0 | F53: =F49-F51-F52 -> 2.3283064e-09 | G53: =D53-F53 -> 51761.453
A54: HPP (penjualan + selisih kuantitas) | D54: =D51+D53 -> 3.3236029e+08 | F54: =F51+F53 -> 249720345 | G54: =D54-F54 -> 82639944
A55: HPP per satuan terjual | C55: =IF(B51=0,0,D54/B51) -> 1725.6505
A56: Memo: penjualan Sales By Item − pengiriman Accurate (qty) | B56: =$C$117-B51 -> 0
A57: Memo: produksi kartu − masuk menurut Accurate (qty) | B57: =B48-E48 -> 30
A59: 4. Pembanding kartu lama (WP CoGM)
A60: Komponen | B60: Kartu lama (Rp) | C60: WP (Rp) | D60: Selisih (Rp) | E60: Keterangan
A61: Material (DM + IDM) | B61: =$C$119 -> 2.2444082e+08 | C61: =E35 -> 2.49266e+08 | D61: =C61-B61 -> 24825179 | E61: Kartu: FCC premium pada harga kartu lama; WP: pada biaya FCC kartu baru (FCC D88) dan KW 2 pada NRV
A62: Tenaga kerja (DL + IDL) | B62: =$C$120 -> 15819480 | C62: =E37+E38 -> 36288891 | D62: =C62-B62 -> 20469410 | E62: Kartu: man-hour × tarif; WP: pool Grup A + B
A63: Listrik / overhead | B63: =$C$121 -> 4257557.7 | C63: =E39+E40 -> 32906337 | D63: =C63-B63 -> 28648779 | E63: Kartu: kWh × tarif; WP: pool Grup C, D, E
A64: Total biaya produksi | B64: =SUM(B61:B63) -> 2.4451786e+08 | C64: =SUM(C61:C63) -> 3.1846122e+08 | D64: =C64-B64 -> 73943369
A65: Man-hour: kartu lama vs driver Labor | B65: =$C$122 -> 882.2823 | C65: =$C$106 -> 882.2823 | D65: =C65-B65 -> 0
A66: kWh: kartu lama vs driver Overhead Allocation | B66: =$C$123 -> 3936.4737 | C66: =$C$107 -> 3936.4737 | D66: =C66-B66 -> 0
A68: 5. Kontrol (toleransi Rp 1; 0,01 qty)
A69: Cek | B69: Nilai | C69: Status
A70: Material eksternal di 2b = Lampiran B kelompok EXT | B70: =E34-SUMIF($B$128:$B$130,"EXT",$F$128:$F$130) -> 0 | C70: =IF(ISERROR(B70),"GAGAL",IF(ABS(B70)<=1,"LULUS","GAGAL")) -> LULUS
A71: Semua baris Lampiran B punya kelompok yang dikenal | B71: =COUNTA($A$128:$A$130)-COUNTIF($B$128:$B$130,"FCC")-COUNTIF($B$128:$B$130,"KW2")-COUNTIF($B$128:$B$130,"KW2UBI")-COUNTIF($B$128:$B$130,"EXT") -> 0 | C71: =IF(ISERROR(B71),"GAGAL",IF(ABS(B71)<=0.5,"LULUS","GAGAL")) -> LULUS
A72: Total biaya = bahan + konversi | B72: =E43-E35-E42 -> 0 | C72: =IF(ISERROR(B72),"GAGAL",IF(ABS(B72)<=1,"LULUS","GAGAL")) -> LULUS
A73: Barang jadi: tersedia = penjualan + saldo akhir + selisih kuantitas (Rp) | B73: =D49-D51-D52-D53 -> -1.6028935e-08 | C73: =IF(ISERROR(B73),"GAGAL",IF(ABS(B73)<=1,"LULUS","GAGAL")) -> LULUS
A74: Ringkasan = 2b (Rp jt) | B74: =B12*10^6-E43 -> 0 | C74: =IF(ISERROR(B74),"GAGAL",IF(ABS(B74)<=1,"LULUS","GAGAL")) -> LULUS
A75: Tidak ada sel error | B75: =SUMPRODUCT(--ISERROR(A5:H66)) -> 0 | C75: =IF(ISERROR(B75),"GAGAL",IF(ABS(B75)<=0.5,"LULUS","GAGAL")) -> LULUS
A76: Info (bukan kontrol): selisih kuantitas barang jadi (B53) dan memo B56–B57 menunjukkan beda kartu vs Accurate.
A100: LAMPIRAN A. Input bulan ini
A101: Pos | B101: Satuan | C101: Nilai | D101: Status angka | E101: Sumber
A102: Output produksi | B102: kg | C102: 11035.8 | D102: Aktual | E102: Kartu E7 (kg)
A103: Output produksi | B103: bag | C103: 183930 | D103: Aktual | E103: Kartu E6 (bag)
A104: Sampel | B104: kg | C104: 19.44 | D104: Aktual | E104: Kartu E10
A105: Sampel | B105: bag | C105: 324 | D105: Aktual | E105: Kartu E9
A106: Man-hour (driver Grup A & B) | B106: jam | C106: 882.2823 | D106: Aktual | E106: Labor: LAP BAG CEMCEM ORI
A107: Pemakaian listrik (driver Grup C & D) | B107: kWh | C107: 3936.4737 | D107: Aktual | E107: Overhead Allocation: LAP BAG CEMCEM ORI
A108: Saldo awal FG-180 | B108: bag | C108: 9180 | D108: Aktual | E108: Inventory Valuation (Kts. saldo awal bulan)
A109: Nilai saldo awal FG-180 (WP) | B109: Rp | C109: 14727247 | D109: Roll-forward | E109: Roll-forward: WP DI - WP Costing BMG Agu26_4.xlsx sheet CEM-CEM ORI D52 (saldo akhir WP)
A110: Nilai saldo awal FG-180 menurut Accurate | B110: Rp | C110: 12074637 | D110: Aktual | E110: Inventory Valuation
A111: Masuk FG-180 menurut Accurate (penyesuaian masuk − keluar) | B111: bag | C111: 183900 | D111: Aktual | E111: Inventory Valuation, Penyesuaian persediaan
A112: Nilai masuk FG-180 menurut Accurate | B112: Rp | C112: 2.3828352e+08 | D112: Aktual | E112: Inventory Valuation, Penyesuaian persediaan
A113: Keluar FG-180: pengiriman pesanan | B113: bag | C113: 192600 | D113: Aktual | E113: Inventory Valuation, Pengiriman Pesanan
... A123: Kartu lama: kWh di operasi | B123: kWh | C123: 3936.4737 | D123: Aktual | E123: Kartu, baris Operation (Elc)
A126: LAMPIRAN B. Material per baris kartu (qty kartu; nilai kartu = qty × harga kartu)
A127: Material | B127: Kelompok | C127: Qty | D127: Satuan | E127: Harga kartu | F127: Nilai kartu (Rp) | G127: Sumber
A128: FCC Premium Tanpa Bumbu @5,5kg | B128: FCC | C128: 10411.5 | D128: kg | E128: 21488.548 | F128: 2.2372802e+08 | G128: Kartu C13:R13; kelompok: FCC premium (antarproduk)
A129: Bumbu Seors 132003 | B129: EXT | C129: 622.55 | D129: kg | E129: 0 | F129: 0 | G129: Kartu C14:R14; kelompok: Eksternal
A130: Plakban Ukuran 100 Yard | B130: EXT | C130: 108 | D130: roll | E130: 6600 | F130: 712800 | G130: Kartu C15:R15; kelompok: Eksternal
A131: Total | F131: =SUM(F128:F130) -> 2.2444082e+08
A132: Kode kelompok: FCC = FCC premium (dinilai ulang pada biaya FCC kartu baru), KW2 = KW 2 FCC (NRV), KW2UBI = KW 2 ubi, EXT = material eksternal (nilai kartu).

Sheet CEM-CEM BBQ
A1: KARTU BIAYA PRODUKSI – Cem-cem BBQ (Keripik Singkong BBQ, Cem-Cem Cazva), September 2026
A2: Sumber: kartu 'LAP BAG CEMCEM BBQ' di WP CoGM September 2026; driver man-hour & kWh: sheet Labor & Overhead Allocation; barang jadi: Inventory Valuation Accurate FG-181; pendapatan: LK Sales By Item.
A4: Status kontrol (bagian 5) | C4: =IF(COUNTIF(C70:C75,"GAGAL")=0,"LULUS","GAGAL") -> LULUS
A5: 1. Ringkasan (Rp juta; Rp/kg per kg produksi bulan ini)
A6: Komponen | B6: Aktual (Rp jt) | C6: Rp/kg | D6: Porsi
A7: FCC premium (antarproduk) | B7: =E31/10^6 -> 230.82753 | C7: =F31 -> 22399.567 | D7: =IF($B$12=0,0,B7/$B$12) -> 0.7886619
A8: KW 2 (antarproduk, NRV) | B8: =(E32+E33)/10^6 -> 0 | C8: =F32+F33 -> 0 | D8: =IF($B$12=0,0,B8/$B$12) -> 0
A9: Material eksternal | B9: =E34/10^6 -> 0 | C9: =F34 -> 0 | D9: =IF($B$12=0,0,B9/$B$12) -> 0
A10: Direct labour (Grup A) | B10: =E37/10^6 -> 17.106326 | C10: =F37 -> 1660.0026 | D10: =IF($B$12=0,0,B10/$B$12) -> 0.058446701
A11: Factory overhead (Grup B–E) | B11: =E41/10^6 -> 44.748638 | C11: =F41 -> 4342.4199 | D11: =IF($B$12=0,0,B11/$B$12) -> 0.1528914
A12: Total biaya produksi | B12: =E43/10^6 -> 292.6825 | C12: =F43 -> 28401.989 | D12: =IF($B$12=0,0,B12/$B$12) -> 1
A13: Produksi (kg; satuan FG) | B13: =B21 -> 10305 | C13: =C21 -> 171750
A14: HPP (Rp jt) dan HPP per satuan terjual | B14: =D54/10^6 -> 279.38708 | C14: =C55 -> 1704.0993
A15: Pendapatan (Rp jt) dan harga per satuan | B15: =$C$118/10^6 -> 277.89525 | C15: =IF($C$117=0,0,$C$118/$C$117) -> 1695
A16: Margin kotor (Rp jt; %) | B16: =B15-B14 -> -1.4918321 | C16: =IF(B15=0,0,B16/B15) -> -0.0053683253
A18: 2. Laporan biaya produksi
A19: 2a. Kuantitas
A20: Pos | B20: Kg | C20: Satuan FG (bag) | D20: Keterangan
A21: Output produksi | B21: =$C$102 -> 10305 | C21: =$C$103 -> 171750
A22: Sampel | B22: =$C$104 -> 12.24 | C22: =$C$105 -> 204 | D22: memo, tidak masuk barang jadi
A23: Input FCC premium | B23: =SUMIF($B$128:$B$130,"FCC",$C$128:$C$130) -> 9669 | D23: Lampiran B
A24: Input KW 2 FCC | B24: =SUMIF($B$128:$B$130,"KW2",$C$128:$C$130) -> 0 | D24: Lampiran B
A25: Input KW 2 ubi | B25: =SUMIF($B$128:$B$130,"KW2UBI",$C$128:$C$130) -> 0 | D25: Lampiran B
A26: Rendemen output ÷ input keripik (kg/kg) | B26: =IF(SUM(B23:B25)=0,0,B21/SUM(B23:B25)) -> 1.0657772
A28: 2b. Biaya produksi bulan ini (aktual)
A29: Komponen | B29: Qty / driver | C29: Satuan | D29: Harga / porsi | E29: Nilai (Rp) | F29: Rp/kg | G29: Dasar
A30: Bahan
A31: FCC premium (antarproduk) | B31: =B23 -> 9669 | C31: kg | D31: =FCC!$D$89 -> 23872.948 | E31: =B31*D31 -> 2.3082753e+08 | F31: =IF($B$21=0,0,E31/$B$21) -> 22399.567 | G31: Biaya rata-rata FG FCC kartu baru (FCC D88)
A32: KW 2 FCC (antarproduk, NRV) | B32: =B24 -> 0 | C32: kg | D32: =FCC!$C$209 -> 9777.2712 | E32: =B32*D32 -> 0 | F32: =IF($B$21=0,0,E32/$B$21) -> 0 | G32: NRV KW 2 (FCC C208)
A33: KW 2 ubi (antarproduk) | B33: =B25 -> 0 | C33: kg | D33: ='LAIN-LAIN'!$C$7 -> 0 | E33: =B33*D33 -> 0 | F33: =IF($B$21=0,0,E33/$B$21) -> 0 | G33: Nilai KW 2 ubi (LAIN-LAIN C7)
A34: Material eksternal (Lampiran B) | E34: =SUMIF($B$128:$B$130,"EXT",$F$128:$F$130) -> 0 | F34: =IF($B$21=0,0,E34/$B$21) -> 0 | G34: Nilai kartu per baris material
A35: Subtotal bahan | E35: =SUM(E31:E34) -> 2.3082753e+08 | F35: =IF($B$21=0,0,E35/$B$21) -> 22399.567
A36: Konversi (pool BIAYA BERSAMA, porsi Lain-lain dibagi dengan driver yang sama dengan sheet LAIN-LAIN)
A37: Grup A – DL operator | B37: =$C$106 -> 787.7177 | C37: jam | D37: =IF('LAIN-LAIN'!$H$43=0,0,B37/'LAIN-LAIN'!$H$43) -> 0.29292443 | E37: =D37*'BIAYA BERSAMA'!$F$115 -> 17106326 | F37: =IF($B$21=0,0,E37/$B$21) -> 1660.0026 | G37: Man-hour ÷ total man-hour Lain-lain × pool Grup A Lain-lain
A38: Grup B – IDL (support, staf, THR, BPJS) | B38: =$C$106 -> 787.7177 | C38: jam | D38: =IF('LAIN-LAIN'!$H$43=0,0,B38/'LAIN-LAIN'!$H$43) -> 0.29292443 | E38: =D38*'BIAYA BERSAMA'!$F$117 -> 15293056 | F38: =IF($B$21=0,0,E38/$B$21) -> 1484.0423 | G38: Man-hour
A39: Grup C + D – energi (kWh) dan mesin (bagging: kWh; Ubi putih ACE: jam mesin) | B39: =$C$107 -> 3528.262 | C39: kWh | D39: =IF('LAIN-LAIN'!$I$43=0,0,B39/'LAIN-LAIN'!$I$43) -> 0.34870937 | E39: =D39*'BIAYA BERSAMA'!$F$118+IF('BIAYA BERSAMA'!$F$172=0,0,B39/'BIAYA BERSAMA'!$F$172)*'BIAYA BERSAMA'!$F$176 -> 29455582 | F39: =IF($B$21=0,0,E39/$B$21) -> 2858.3777 | G39: kWh
A40: Grup E – pabrik umum | B40: =E34 -> 0 | C40: Rp | D40: =IF('LAIN-LAIN'!$G$43=0,0,B40/'LAIN-LAIN'!$G$43) -> 0 | E40: =D40*'BIAYA BERSAMA'!$F$120 -> 0 | F40: =IF($B$21=0,0,E40/$B$21) -> 0 | G40: Nilai material eksternal
A41: Subtotal factory overhead (Grup B–E) | E41: =SUM(E38:E40) -> 44748638 | F41: =IF($B$21=0,0,E41/$B$21) -> 4342.4199
A42: Total konversi | E42: =E37+E41 -> 61854964 | F42: =IF($B$21=0,0,E42/$B$21) -> 6002.4225
A43: TOTAL BIAYA PRODUKSI BULAN INI | E43: =E35+E42 -> 2.926825e+08 | F43: =IF($B$21=0,0,E43/$B$21) -> 28401.989
A45: 3. Barang jadi (FG-181 Keripik Singkong BBQ (Cem-Cem Cazva)) dan HPP
A46: Pos | B46: Qty (bag) | C46: Rp/satuan | D46: Nilai WP (Rp) | E46: Qty Accurate | F46: Nilai Accurate (Rp) | G46: Selisih nilai WP − Accurate
A47: Saldo awal | B47: =$C$108 -> 30 | D47: =$C$109 -> 47681.866 | E47: =$C$108 -> 30 | F47: =$C$110 -> 38991.89 | G47: =D47-F47 -> 8689.9758
A48: Masuk dari produksi | B48: =C21 -> 171750 | D48: =E43 -> 2.926825e+08 | E48: =$C$111 -> 171750 | F48: =$C$112 -> 2.2065644e+08 | G48: =D48-F48 -> 72026055
A49: Tersedia | B49: =B47+B48 -> 171780 | D49: =D47+D48 -> 2.9273018e+08 | E49: =E47+E48 -> 171780 | F49: =F47+F48 -> 2.2069544e+08 | G49: =D49-F49 -> 72034745
A50: Biaya rata-rata tertimbang per satuan | C50: =IF(B49=0,0,D49/B49) -> 1704.0993
A51: Keluar: penjualan (pengiriman pesanan) | B51: =$C$113 -> 163950 | D51: =B51*$C$50 -> 2.7938708e+08 | E51: =$C$113 -> 163950 | F51: =$C$114 -> 2.103852e+08 | G51: =D51-F51 -> 69001884
A52: Saldo akhir (qty menurut Accurate) | B52: =$C$115 -> 7830 | D52: =B52*$C$50 -> 13343098 | E52: =$C$115 -> 7830 | F52: =$C$116 -> 10310237 | G52: =D52-F52 -> 3032860.3
A53: Selisih kuantitas (tersedia − penjualan − saldo akhir) ke HPP | B53: =B49-B51-B52 -> 0 | D53: =B53*$C$50 -> 0 | E53: =E49-E51-E52 -> 0 | F53: =F49-F51-F52 -> -0.01000003 | G53: =D53-F53 -> 0.01000003
A54: HPP (penjualan + selisih kuantitas) | D54: =D51+D53 -> 2.7938708e+08 | F54: =F51+F53 -> 2.103852e+08 | G54: =D54-F54 -> 69001884
A55: HPP per satuan terjual | C55: =IF(B51=0,0,D54/B51) -> 1704.0993
A56: Memo: penjualan Sales By Item − pengiriman Accurate (qty) | B56: =$C$117-B51 -> 0
A57: Memo: produksi kartu − masuk menurut Accurate (qty) | B57: =B48-E48 -> 0
A59: 4. Pembanding kartu lama (WP CoGM)
A60: Komponen | B60: Kartu lama (Rp) | C60: WP (Rp) | D60: Selisih (Rp) | E60: Keterangan
A61: Material (DM + IDM) | B61: =$C$119 -> 2.0777277e+08 | C61: =E35 -> 2.3082753e+08 | D61: =C61-B61 -> 23054763 | E61: Kartu: FCC premium pada harga kartu lama; WP: pada biaya FCC kartu baru (FCC D88) dan KW 2 pada NRV
A62: Tenaga kerja (DL + IDL) | B62: =$C$120 -> 14123920 | C62: =E37+E38 -> 32399382 | D62: =C62-B62 -> 18275462 | E62: Kartu: man-hour × tarif; WP: pool Grup A + B
A63: Listrik / overhead | B63: =$C$121 -> 4257557.7 | C63: =E39+E40 -> 29455582 | D63: =C63-B63 -> 25198024 | E63: Kartu: kWh × tarif; WP: pool Grup C, D, E
A64: Total biaya produksi | B64: =SUM(B61:B63) -> 2.2615425e+08 | C64: =SUM(C61:C63) -> 2.926825e+08 | D64: =C64-B64 -> 66528249
A65: Man-hour: kartu lama vs driver Labor | B65: =$C$122 -> 787.7177 | C65: =$C$106 -> 787.7177 | D65: =C65-B65 -> 0
A66: kWh: kartu lama vs driver Overhead Allocation | B66: =$C$123 -> 3936.4737 | C66: =$C$107 -> 3528.262 | D66: =C66-B66 -> -408.2117
A68: 5. Kontrol (toleransi Rp 1; 0,01 qty)
A69: Cek | B69: Nilai | C69: Status
A70: Material eksternal di 2b = Lampiran B kelompok EXT | B70: =E34-SUMIF($B$128:$B$130,"EXT",$F$128:$F$130) -> 0 | C70: =IF(ISERROR(B70),"GAGAL",IF(ABS(B70)<=1,"LULUS","GAGAL")) -> LULUS
A71: Semua baris Lampiran B punya kelompok yang dikenal | B71: =COUNTA($A$128:$A$130)-COUNTIF($B$128:$B$130,"FCC")-COUNTIF($B$128:$B$130,"KW2")-COUNTIF($B$128:$B$130,"KW2UBI")-COUNTIF($B$128:$B$130,"EXT") -> 0 | C71: =IF(ISERROR(B71),"GAGAL",IF(ABS(B71)<=0.5,"LULUS","GAGAL")) -> LULUS
A72: Total biaya = bahan + konversi | B72: =E43-E35-E42 -> 0 | C72: =IF(ISERROR(B72),"GAGAL",IF(ABS(B72)<=1,"LULUS","GAGAL")) -> LULUS
A73: Barang jadi: tersedia = penjualan + saldo akhir + selisih kuantitas (Rp) | B73: =D49-D51-D52-D53 -> -1.8626451e-08 | C73: =IF(ISERROR(B73),"GAGAL",IF(ABS(B73)<=1,"LULUS","GAGAL")) -> LULUS
A74: Ringkasan = 2b (Rp jt) | B74: =B12*10^6-E43 -> 0 | C74: =IF(ISERROR(B74),"GAGAL",IF(ABS(B74)<=1,"LULUS","GAGAL")) -> LULUS
A75: Tidak ada sel error | B75: =SUMPRODUCT(--ISERROR(A5:H66)) -> 0 | C75: =IF(ISERROR(B75),"GAGAL",IF(ABS(B75)<=0.5,"LULUS","GAGAL")) -> LULUS
A76: Info (bukan kontrol): selisih kuantitas barang jadi (B53) dan memo B56–B57 menunjukkan beda kartu vs Accurate.
A100: LAMPIRAN A. Input bulan ini
A101: Pos | B101: Satuan | C101: Nilai | D101: Status angka | E101: Sumber
A102: Output produksi | B102: kg | C102: 10305 | D102: Aktual | E102: Kartu E7 (kg)
A103: Output produksi | B103: bag | C103: 171750 | D103: Aktual | E103: Kartu E6 (bag)
A104: Sampel | B104: kg | C104: 12.24 | D104: Aktual | E104: Kartu E10
A105: Sampel | B105: bag | C105: 204 | D105: Aktual | E105: Kartu E9
A106: Man-hour (driver Grup A & B) | B106: jam | C106: 787.7177 | D106: Aktual | E106: Labor: LAP BAG CEMCEM BBQ
A107: Pemakaian listrik (driver Grup C & D) | B107: kWh | C107: 3528.262 | D107: Aktual | E107: Overhead Allocation: LAP BAG CEMCEM BBQ
A108: Saldo awal FG-181 | B108: bag | C108: 30 | D108: Aktual | E108: Inventory Valuation (Kts. saldo awal bulan)
A109: Nilai saldo awal FG-181 (WP) | B109: Rp | C109: 47681.866 | D109: Roll-forward | E109: Roll-forward: WP DI - WP Costing BMG Agu26_4.xlsx sheet CEM-CEM BBQ D52 (saldo akhir WP)
A110: Nilai saldo awal FG-181 menurut Accurate | B110: Rp | C110: 38991.89 | D110: Aktual | E110: Inventory Valuation
A111: Masuk FG-181 menurut Accurate (penyesuaian masuk − keluar) | B111: bag | C111: 171750 | D111: Aktual | E111: Inventory Valuation, Penyesuaian persediaan
A112: Nilai masuk FG-181 menurut Accurate | B112: Rp | C112: 2.2065644e+08 | D112: Aktual | E112: Inventory Valuation, Penyesuaian persediaan
A113: Keluar FG-181: pengiriman pesanan | B113: bag | C113: 163950 | D113: Aktual | E113: Inventory Valuation, Pengiriman Pesanan
... A123: Kartu lama: kWh di operasi | B123: kWh | C123: 3936.4737 | D123: Aktual | E123: Kartu, baris Operation (Elc)
A126: LAMPIRAN B. Material per baris kartu (qty kartu; nilai kartu = qty × harga kartu)
A127: Material | B127: Kelompok | C127: Qty | D127: Satuan | E127: Harga kartu | F127: Nilai kartu (Rp) | G127: Sumber
A128: FCC Premium Tanpa Bumbu @5,5kg | B128: FCC | C128: 9669 | D128: kg | E128: 21488.548 | F128: 2.0777277e+08 | G128: Kartu C13:R13; kelompok: FCC premium (antarproduk)
A129: Bumbu BBQ SSF-01110 | B129: EXT | C129: 671.55 | D129: kg | E129: 0 | F129: 0 | G129: Kartu C14:R14; kelompok: Eksternal
A130: Plakban Ukuran 100 Yard | B130: EXT | C130: 0 | D130: roll | E130: 6600 | F130: 0 | G130: Kartu C15:R15; kelompok: Eksternal
A131: Total | F131: =SUM(F128:F130) -> 2.0777277e+08
A132: Kode kelompok: FCC = FCC premium (dinilai ulang pada biaya FCC kartu baru), KW2 = KW 2 FCC (NRV), KW2UBI = KW 2 ubi, EXT = material eksternal (nilai kartu).

Sheet KOPERASI
A1: KARTU BIAYA PRODUKSI – Koperasi – KW 2 berbumbu (per SKU), September 2026
A2: Sumber: kartu 'Bagging Kop' di WP CoGM September 2026 (satu kolom per SKU); driver man-hour: Labor 'Koperasi' dibagi per SKU dengan porsi man-hour kartu; barang jadi: Inventory Valuation; pendapatan: LK Sales By Item.
A4: Status kontrol (bagian 5) | C4: =IF(COUNTIF(C56:C60,"GAGAL")=0,"LULUS","GAGAL") -> LULUS
A5: 1–2. Kuantitas dan biaya produksi per SKU (Rp)
A6: Pos | B6: FCC Kw 2 Bumbu BBQ 1kg | C6: FCC Kw 2 Bumbu Balado 1kg | D6: FCC Kw 2 Bumbu Jagung Manis 1kg | E6: FCC Kw 2 Bumbu Asin 1kg | F6: FCC Kw2 Suka-Suka Bumbu BBQ 2,5kg | G6: FCC Kw2 Suka-suka Bumbu Balado 2,5kg | H6: FCC Kw2 Suka-suka Bumbu Jagung Manis 2,5kg | I6: FCC KW2 Suka-suka Bumbu Asin 2,5kg | J6: FCC Premium Bumbu Asin 250gr | K6: Keripik Ubi Mix Kw2 Rasa Balado 1 Kg | L6: Keripik Ubi Mix Kw2 Rasa BBQ 1 Kg | M6: Total | N6: Dasar
A7: Output produksi (kg) | B7: =B122 -> 434 | C7: =C122 -> 808 | D7: =D122 -> 209 | E7: =E122 -> 70 | F7: =F122 -> 150 | G7: =G122 -> 452.5 | H7: =H122 -> 7.5 | I7: =I122 -> 7.5 | ... L7: =L122 -> 404 | M7: =SUM(B7:L7) -> 2967.5
A8: Output produksi (satuan FG) | B8: =IF(B123=0,0,B7/B123) -> 434 | C8: =IF(C123=0,0,C7/C123) -> 808 | D8: =IF(D123=0,0,D7/D123) -> 209 | E8: =IF(E123=0,0,E7/E123) -> 70 | F8: =IF(F123=0,0,F7/F123) -> 60 | G8: =IF(G123=0,0,G7/G123) -> 181 | H8: =IF(H123=0,0,H7/H123) -> 3 | I8: =IF(I123=0,0,I7/I123) -> 3 | ... L8: =IF(L123=0,0,L7/L123) -> 404 | M8: =SUM(B8:L8) -> 2597
A9: Input FCC premium (kg) | B9: =SUMIF($N$143:$N$167,"FCC",B$143:B$167) -> 0 | C9: =SUMIF($N$143:$N$167,"FCC",C$143:C$167) -> 0 | D9: =SUMIF($N$143:$N$167,"FCC",D$143:D$167) -> 0 | E9: =SUMIF($N$143:$N$167,"FCC",E$143:E$167) -> 0 | F9: =SUMIF($N$143:$N$167,"FCC",F$143:F$167) -> 0 | G9: =SUMIF($N$143:$N$167,"FCC",G$143:G$167) -> 0 | H9: =SUMIF($N$143:$N$167,"FCC",H$143:H$167) -> 0 | I9: =SUMIF($N$143:$N$167,"FCC",I$143:I$167) -> 0 | ... L9: =SUMIF($N$143:$N$167,"FCC",L$143:L$167) -> 0 | M9: =SUM(B9:L9) -> 10 | N9: Lampiran B
A10: Input KW 2 FCC (kg) | B10: =SUMIF($N$143:$N$167,"KW2",B$143:B$167) -> 406 | C10: =SUMIF($N$143:$N$167,"KW2",C$143:C$167) -> 756 | D10: =SUMIF($N$143:$N$167,"KW2",D$143:D$167) -> 195.5 | E10: =SUMIF($N$143:$N$167,"KW2",E$143:E$167) -> 70 | F10: =SUMIF($N$143:$N$167,"KW2",F$143:F$167) -> 140 | G10: =SUMIF($N$143:$N$167,"KW2",G$143:G$167) -> 420 | H10: =SUMIF($N$143:$N$167,"KW2",H$143:H$167) -> 7 | I10: =SUMIF($N$143:$N$167,"KW2",I$143:I$167) -> 7.5 | ... L10: =SUMIF($N$143:$N$167,"KW2",L$143:L$167) -> 0 | M10: =SUM(B10:L10) -> 2002 | N10: Lampiran B
A11: Input KW 2 ubi (kg) | B11: =SUMIF($N$143:$N$167,"KW2UBI",B$143:B$167) -> 0 | C11: =SUMIF($N$143:$N$167,"KW2UBI",C$143:C$167) -> 0 | D11: =SUMIF($N$143:$N$167,"KW2UBI",D$143:D$167) -> 0 | E11: =SUMIF($N$143:$N$167,"KW2UBI",E$143:E$167) -> 0 | F11: =SUMIF($N$143:$N$167,"KW2UBI",F$143:F$167) -> 0 | G11: =SUMIF($N$143:$N$167,"KW2UBI",G$143:G$167) -> 0 | H11: =SUMIF($N$143:$N$167,"KW2UBI",H$143:H$167) -> 0 | I11: =SUMIF($N$143:$N$167,"KW2UBI",I$143:I$167) -> 0 | ... L11: =SUMIF($N$143:$N$167,"KW2UBI",L$143:L$167) -> 378 | M11: =SUM(B11:L11) -> 770 | N11: Lampiran B
A12: Man-hour (driver) | B12: =B125 -> 14.763 | C12: =C125 -> 27.4851 | D12: =D125 -> 7.1094 | E12: =E125 -> 2.3811 | F12: =F125 -> 2.041 | G12: =G125 -> 6.1569 | H12: =H125 -> 0.102 | I12: =I125 -> 0.102 | ... L12: =L125 -> 13.7426 | M12: =SUM(B12:L12) -> 89.3397
A13: FCC premium (antarproduk) – Rp | B13: =B9*FCC!$D$89 -> 0 | C13: =C9*FCC!$D$89 -> 0 | D13: =D9*FCC!$D$89 -> 0 | E13: =E9*FCC!$D$89 -> 0 | F13: =F9*FCC!$D$89 -> 0 | G13: =G9*FCC!$D$89 -> 0 | H13: =H9*FCC!$D$89 -> 0 | I13: =I9*FCC!$D$89 -> 0 | ... L13: =L9*FCC!$D$89 -> 0 | M13: =SUM(B13:L13) -> 238729.48 | N13: Kg × biaya rata-rata FG FCC (FCC D88)
A14: KW 2 (antarproduk, NRV) – Rp | B14: =B10*FCC!$C$209+B11*'LAIN-LAIN'!$C$7 -> 3969572.1 | C14: =C10*FCC!$C$209+C11*'LAIN-LAIN'!$C$7 -> 7391617 | D14: =D10*FCC!$C$209+D11*'LAIN-LAIN'!$C$7 -> 1911456.5 | E14: =E10*FCC!$C$209+E11*'LAIN-LAIN'!$C$7 -> 684408.98 | F14: =F10*FCC!$C$209+F11*'LAIN-LAIN'!$C$7 -> 1368818 | G14: =G10*FCC!$C$209+G11*'LAIN-LAIN'!$C$7 -> 4106453.9 | H14: =H10*FCC!$C$209+H11*'LAIN-LAIN'!$C$7 -> 68440.898 | I14: =I10*FCC!$C$209+I11*'LAIN-LAIN'!$C$7 -> 73329.534 | ... L14: =L10*FCC!$C$209+L11*'LAIN-LAIN'!$C$7 -> 0 | M14: =SUM(B14:L14) -> 19574097 | N14: KW 2 FCC × NRV (FCC C208) + KW 2 ubi × LAIN-LAIN C7
A15: Material eksternal – Rp | B15: =SUMIF($N$170:$N$194,"EXT",B$170:B$194) -> 842769.4 | C15: =SUMIF($N$170:$N$194,"EXT",C$170:C$194) -> 1634122.6 | D15: =SUMIF($N$170:$N$194,"EXT",D$170:D$194) -> 416489.31 | E15: =SUMIF($N$170:$N$194,"EXT",E$170:E$194) -> 20360.126 | F15: =SUMIF($N$170:$N$194,"EXT",F$170:F$194) -> 379194.36 | G15: =SUMIF($N$170:$N$194,"EXT",G$170:G$194) -> 1319934.6 | H15: =SUMIF($N$170:$N$194,"EXT",H$170:H$194) -> 17899.059 | I15: =SUMIF($N$170:$N$194,"EXT",I$170:I$194) -> 213.75 | ... L15: =SUMIF($N$170:$N$194,"EXT",L$170:L$194) -> 796250.69 | M15: =SUM(B15:L15) -> 6333602.8 | N15: Lampiran B kelompok EXT
A16: Subtotal bahan | B16: =SUM(B13:B15) -> 4812341.5 | C16: =SUM(C13:C15) -> 9025739.6 | D16: =SUM(D13:D15) -> 2327945.8 | E16: =SUM(E13:E15) -> 704769.11 | F16: =SUM(F13:F15) -> 1748012.3 | G16: =SUM(G13:G15) -> 5426388.5 | H16: =SUM(H13:H15) -> 86339.957 | I16: =SUM(I13:I15) -> 73543.284 | ... L16: =SUM(L13:L15) -> 796250.69 | M16: =SUM(B16:L16) -> 26146429
A17: Grup A – DL operator | B17: =IF('LAIN-LAIN'!$H$43=0,0,B12/'LAIN-LAIN'!$H$43)*'BIAYA BERSAMA'!$F$115 -> 320597.97 | C17: =IF('LAIN-LAIN'!$H$43=0,0,C12/'LAIN-LAIN'!$H$43)*'BIAYA BERSAMA'!$F$115 -> 596875.11 | D17: =IF('LAIN-LAIN'!$H$43=0,0,D12/'LAIN-LAIN'!$H$43)*'BIAYA BERSAMA'!$F$115 -> 154389.98 | E17: =IF('LAIN-LAIN'!$H$43=0,0,E12/'LAIN-LAIN'!$H$43)*'BIAYA BERSAMA'!$F$115 -> 51708.72 | F17: =IF('LAIN-LAIN'!$H$43=0,0,F12/'LAIN-LAIN'!$H$43)*'BIAYA BERSAMA'!$F$115 -> 44323.001 | G17: =IF('LAIN-LAIN'!$H$43=0,0,G12/'LAIN-LAIN'!$H$43)*'BIAYA BERSAMA'!$F$115 -> 133705.18 | H17: =IF('LAIN-LAIN'!$H$43=0,0,H12/'LAIN-LAIN'!$H$43)*'BIAYA BERSAMA'!$F$115 -> 2215.0642 | I17: =IF('LAIN-LAIN'!$H$43=0,0,I12/'LAIN-LAIN'!$H$43)*'BIAYA BERSAMA'!$F$115 -> 2215.0642 | ... L17: =IF('LAIN-LAIN'!$H$43=0,0,L12/'LAIN-LAIN'!$H$43)*'BIAYA BERSAMA'!$F$115 -> 298438.64 | M17: =SUM(B17:L17) -> 1940129.1 | N17: Man-hour ÷ total man-hour Lain-lain × pool
A18: Grup B – IDL | B18: =IF('LAIN-LAIN'!$H$43=0,0,B12/'LAIN-LAIN'!$H$43)*'BIAYA BERSAMA'!$F$117 -> 286614.59 | C18: =IF('LAIN-LAIN'!$H$43=0,0,C12/'LAIN-LAIN'!$H$43)*'BIAYA BERSAMA'!$F$117 -> 533606.35 | D18: =IF('LAIN-LAIN'!$H$43=0,0,D12/'LAIN-LAIN'!$H$43)*'BIAYA BERSAMA'!$F$117 -> 138024.64 | E18: =IF('LAIN-LAIN'!$H$43=0,0,E12/'LAIN-LAIN'!$H$43)*'BIAYA BERSAMA'!$F$117 -> 46227.595 | F18: =IF('LAIN-LAIN'!$H$43=0,0,F12/'LAIN-LAIN'!$H$43)*'BIAYA BERSAMA'!$F$117 -> 39624.763 | G18: =IF('LAIN-LAIN'!$H$43=0,0,G12/'LAIN-LAIN'!$H$43)*'BIAYA BERSAMA'!$F$117 -> 119532.44 | H18: =IF('LAIN-LAIN'!$H$43=0,0,H12/'LAIN-LAIN'!$H$43)*'BIAYA BERSAMA'!$F$117 -> 1980.2674 | I18: =IF('LAIN-LAIN'!$H$43=0,0,I12/'LAIN-LAIN'!$H$43)*'BIAYA BERSAMA'!$F$117 -> 1980.2674 | ... L18: =IF('LAIN-LAIN'!$H$43=0,0,L12/'LAIN-LAIN'!$H$43)*'BIAYA BERSAMA'!$F$117 -> 266804.15 | M18: =SUM(B18:L18) -> 1734475.5 | N18: Man-hour
A19: Grup C + D – energi & mesin | B19: =0 -> 0 | C19: =0 -> 0 | D19: =0 -> 0 | E19: =0 -> 0 | F19: =0 -> 0 | G19: =0 -> 0 | H19: =0 -> 0 | I19: =0 -> 0 | ... L19: =0 -> 0 | M19: =SUM(B19:L19) -> 0 | N19: kWh Koperasi = 0 (sesuai Overhead Allocation)
A20: Grup E – pabrik umum | B20: =IF('LAIN-LAIN'!$G$43=0,0,B15/'LAIN-LAIN'!$G$43)*'BIAYA BERSAMA'!$F$120 -> 50618.895 | C20: =IF('LAIN-LAIN'!$G$43=0,0,C15/'LAIN-LAIN'!$G$43)*'BIAYA BERSAMA'!$F$120 -> 98149.601 | D20: =IF('LAIN-LAIN'!$G$43=0,0,D15/'LAIN-LAIN'!$G$43)*'BIAYA BERSAMA'!$F$120 -> 25015.418 | E20: =IF('LAIN-LAIN'!$G$43=0,0,E15/'LAIN-LAIN'!$G$43)*'BIAYA BERSAMA'!$F$120 -> 1222.8814 | F20: =IF('LAIN-LAIN'!$G$43=0,0,F15/'LAIN-LAIN'!$G$43)*'BIAYA BERSAMA'!$F$120 -> 22775.387 | G20: =IF('LAIN-LAIN'!$G$43=0,0,G15/'LAIN-LAIN'!$G$43)*'BIAYA BERSAMA'!$F$120 -> 79278.66 | H20: =IF('LAIN-LAIN'!$G$43=0,0,H15/'LAIN-LAIN'!$G$43)*'BIAYA BERSAMA'!$F$120 -> 1075.0635 | I20: =IF('LAIN-LAIN'!$G$43=0,0,I15/'LAIN-LAIN'!$G$43)*'BIAYA BERSAMA'!$F$120 -> 12.838374 | ... L20: =IF('LAIN-LAIN'!$G$43=0,0,L15/'LAIN-LAIN'!$G$43)*'BIAYA BERSAMA'!$F$120 -> 47824.862 | M20: =SUM(B20:L20) -> 380412.46 | N20: Nilai material eksternal
A21: Subtotal factory overhead (Grup B–E) | B21: =SUM(B18:B20) -> 337233.48 | C21: =SUM(C18:C20) -> 631755.95 | D21: =SUM(D18:D20) -> 163040.06 | E21: =SUM(E18:E20) -> 47450.477 | F21: =SUM(F18:F20) -> 62400.15 | G21: =SUM(G18:G20) -> 198811.1 | H21: =SUM(H18:H20) -> 3055.3309 | I21: =SUM(I18:I20) -> 1993.1058 | ... L21: =SUM(L18:L20) -> 314629.01 | M21: =SUM(B21:L21) -> 2114887.9
A22: TOTAL BIAYA PRODUKSI | B22: =B16+B17+B21 -> 5470173 | C22: =C16+C17+C21 -> 10254371 | D22: =D16+D17+D21 -> 2645375.9 | E22: =E16+E17+E21 -> 803928.3 | F22: =F16+F17+F21 -> 1854735.5 | G22: =G16+G17+G21 -> 5758904.7 | H22: =H16+H17+H21 -> 91610.352 | I22: =I16+I17+I21 -> 77751.454 | ... L22: =L16+L17+L21 -> 1409318.3 | M22: =SUM(B22:L22) -> 30201446
A23: Biaya per kg | B23: =IF(B7=0,0,B22/B7) -> 12604.085 | C23: =IF(C7=0,0,C22/C7) -> 12691.053 | D23: =IF(D7=0,0,D22/D7) -> 12657.301 | E23: =IF(E7=0,0,E22/E7) -> 11484.69 | F23: =IF(F7=0,0,F22/F7) -> 12364.903 | G23: =IF(G7=0,0,G22/G7) -> 12726.861 | H23: =IF(H7=0,0,H22/H7) -> 12214.714 | I23: =IF(I7=0,0,I22/I7) -> 10366.861 | ... M23: =IF(M7=0,0,M22/M7) -> 10177.404
A25: 3. Barang jadi dan HPP per SKU (qty dalam satuan FG)
A26: Pos | B26: FCC Kw 2 Bumbu BBQ 1kg | C26: FCC Kw 2 Bumbu Balado 1kg | D26: FCC Kw 2 Bumbu Jagung Manis 1kg | E26: FCC Kw 2 Bumbu Asin 1kg | F26: FCC Kw2 Suka-Suka Bumbu BBQ 2,5kg | G26: FCC Kw2 Suka-suka Bumbu Balado 2,5kg | H26: FCC Kw2 Suka-suka Bumbu Jagung Manis 2,5kg | I26: FCC KW2 Suka-suka Bumbu Asin 2,5kg | J26: FCC Premium Bumbu Asin 250gr | K26: Keripik Ubi Mix Kw2 Rasa Balado 1 Kg | L26: Keripik Ubi Mix Kw2 Rasa BBQ 1 Kg | M26: Total | N26: Dasar
A27: Saldo awal – qty | B27: =B126 -> 0 | C27: =C126 -> 0 | D27: =D126 -> 0 | E27: =E126 -> 0 | F27: =F126 -> 0 | G27: =G126 -> 0 | H27: =H126 -> 0 | I27: =I126 -> 0 | ... L27: =L126 -> 0 | M27: =SUM(B27:L27) -> 0
A28: Saldo awal – nilai WP | B28: =B127 -> 0 | C28: =C127 -> 0 | D28: =D127 -> 0 | E28: =E127 -> 0 | F28: =F127 -> 0 | G28: =G127 -> 0 | H28: =H127 -> 0 | I28: =I127 -> 0 | ... L28: =L127 -> 0 | M28: =SUM(B28:L28) -> 0
A29: Masuk dari produksi – qty | B29: =B8 -> 434 | C29: =C8 -> 808 | D29: =D8 -> 209 | E29: =E8 -> 70 | F29: =F8 -> 60 | G29: =G8 -> 181 | H29: =H8 -> 3 | I29: =I8 -> 3 | ... L29: =L8 -> 404 | M29: =SUM(B29:L29) -> 2597
A30: Masuk dari produksi – nilai | B30: =B22 -> 5470173 | C30: =C22 -> 10254371 | D30: =D22 -> 2645375.9 | E30: =E22 -> 803928.3 | F30: =F22 -> 1854735.5 | G30: =G22 -> 5758904.7 | H30: =H22 -> 91610.352 | I30: =I22 -> 77751.454 | ... L30: =L22 -> 1409318.3 | M30: =SUM(B30:L30) -> 30201446
A31: Biaya rata-rata per satuan | B31: =IF(B27+B29=0,0,(B28+B30)/(B27+B29)) -> 12604.085 | C31: =IF(C27+C29=0,0,(C28+C30)/(C27+C29)) -> 12691.053 | D31: =IF(D27+D29=0,0,(D28+D30)/(D27+D29)) -> 12657.301 | E31: =IF(E27+E29=0,0,(E28+E30)/(E27+E29)) -> 11484.69 | F31: =IF(F27+F29=0,0,(F28+F30)/(F27+F29)) -> 30912.258 | G31: =IF(G27+G29=0,0,(G28+G30)/(G27+G29)) -> 31817.153 | H31: =IF(H27+H29=0,0,(H28+H30)/(H27+H29)) -> 30536.784 | I31: =IF(I27+I29=0,0,(I28+I30)/(I27+I29)) -> 25917.151 | ... L31: =IF(L27+L29=0,0,(L28+L30)/(L27+L29)) -> 3488.4117
A32: Keluar: penjualan – qty | B32: =B131 -> 434 | C32: =C131 -> 808 | D32: =D131 -> 209 | E32: =E131 -> 70 | F32: =F131 -> 59 | G32: =G131 -> 179 | H32: =H131 -> 3 | I32: =I131 -> 3 | ... L32: =L131 -> 404 | M32: =SUM(B32:L32) -> 2584 | N32: Pengiriman pesanan (Accurate)
A33: Keluar: penjualan – nilai | B33: =B32*B31 -> 5470173 | C33: =C32*C31 -> 10254371 | D33: =D32*D31 -> 2645375.9 | E33: =E32*E31 -> 803928.3 | F33: =F32*F31 -> 1823823.2 | G33: =G32*G31 -> 5695270.4 | H33: =H32*H31 -> 91610.352 | I33: =I32*I31 -> 77751.454 | ... L33: =L32*L31 -> 1409318.3 | M33: =SUM(B33:L33) -> 29812757
A34: Saldo akhir – qty (Accurate) | B34: =B133 -> 0 | C34: =C133 -> 0 | D34: =D133 -> 0 | E34: =E133 -> 0 | F34: =F133 -> 0 | G34: =G133 -> 0 | H34: =H133 -> 0 | I34: =I133 -> 0 | ... L34: =L133 -> 0 | M34: =SUM(B34:L34) -> 0
A35: Saldo akhir – nilai WP | B35: =B34*B31 -> 0 | C35: =C34*C31 -> 0 | D35: =D34*D31 -> 0 | E35: =E34*E31 -> 0 | F35: =F34*F31 -> 0 | G35: =G34*G31 -> 0 | H35: =H34*H31 -> 0 | I35: =I34*I31 -> 0 | ... L35: =L34*L31 -> 0 | M35: =SUM(B35:L35) -> 0
A36: Selisih kuantitas ke HPP – qty | B36: =B27+B29-B32-B34 -> 0 | C36: =C27+C29-C32-C34 -> 0 | D36: =D27+D29-D32-D34 -> 0 | E36: =E27+E29-E32-E34 -> 0 | F36: =F27+F29-F32-F34 -> 1 | G36: =G27+G29-G32-G34 -> 2 | H36: =H27+H29-H32-H34 -> 0 | I36: =I27+I29-I32-I34 -> 0 | ... L36: =L27+L29-L32-L34 -> 0 | M36: =SUM(B36:L36) -> 13
A37: Selisih kuantitas ke HPP – nilai | B37: =B36*B31 -> 0 | C37: =C36*C31 -> 0 | D37: =D36*D31 -> 0 | E37: =E36*E31 -> 0 | F37: =F36*F31 -> 30912.258 | G37: =G36*G31 -> 63634.306 | H37: =H36*H31 -> 0 | I37: =I36*I31 -> 0 | ... L37: =L36*L31 -> 0 | M37: =SUM(B37:L37) -> 388689.19
A38: HPP (penjualan + selisih kuantitas) | B38: =B33+B37 -> 5470173 | C38: =C33+C37 -> 10254371 | D38: =D33+D37 -> 2645375.9 | E38: =E33+E37 -> 803928.3 | F38: =F33+F37 -> 1854735.5 | G38: =G33+G37 -> 5758904.7 | H38: =H33+H37 -> 91610.352 | I38: =I33+I37 -> 77751.454 | ... L38: =L33+L37 -> 1409318.3 | M38: =SUM(B38:L38) -> 30201446
A39: Pendapatan | B39: =B136 -> 3518915.4 | C39: =C136 -> 6551344.8 | D39: =D136 -> 1694592.9 | E39: =E136 -> 567567 | F39: =F136 -> 1594594.2 | G39: =G136 -> 4837836.6 | H39: =H136 -> 81081.06 | I39: =I136 -> 81081.06 | ... L39: =L136 -> 4731530.8 | M39: =SUM(B39:L39) -> 28518903
A40: Margin kotor | B40: =B39-B38 -> -1951257.6 | C40: =C39-C38 -> -3703025.9 | D40: =D39-D38 -> -950782.95 | E40: =E39-E38 -> -236361.3 | F40: =F39-F38 -> -260141.29 | G40: =G39-G38 -> -921068.15 | H40: =H39-H38 -> -10529.292 | I40: =I39-I38 -> 3329.6061 | ... L40: =L39-L38 -> 3322212.5 | M40: =SUM(B40:L40) -> -1682542.8
A41: Margin kotor (%) | B41: =IF(B39=0,0,B40/B39) -> -0.55450539 | C41: =IF(C39=0,0,C40/C39) -> -0.56523141 | D41: =IF(D39=0,0,D40/D39) -> -0.56106865 | E41: =IF(E39=0,0,E40/E39) -> -0.41644652 | F41: =IF(F39=0,0,F40/F39) -> -0.1631395 | G41: =IF(G39=0,0,G40/G39) -> -0.19038844 | H41: =IF(H39=0,0,H40/H39) -> -0.12986131 | I41: =IF(I39=0,0,I40/I39) -> 0.041065153 | ... M41: =IF(M39=0,0,M40/M39) -> -0.058997458
A42: Memo: HPP menurut Accurate (nilai pengiriman) | B42: =B132 -> 1129237.5 | C42: =C132 -> 2163993.3 | D42: =D132 -> 552711.22 | E42: =E132 -> 66714.18 | F42: =F132 -> 408859.57 | G42: =G132 -> 1414524.8 | H42: =H132 -> 19728.81 | I42: =I132 -> 2043.5 | ... L42: =L132 -> 1042657.2 | M42: =SUM(B42:L42) -> 7959669.7
A43: Memo: penjualan Sales By Item − pengiriman Accurate (qty) | B43: =B135-B32 -> 0 | C43: =C135-C32 -> 0 | D43: =D135-D32 -> 0 | E43: =E135-E32 -> 0 | F43: =F135-F32 -> 0 | G43: =G135-G32 -> 0 | H43: =H135-H32 -> 0 | I43: =I135-I32 -> 0 | ... L43: =L135-L32 -> 0 | M43: =SUM(B43:L43) -> 0
A44: Memo: produksi kartu − masuk Accurate (qty) | B44: =B29-B129 -> 0 | C44: =C29-C129 -> 0 | D44: =D29-D129 -> 0 | E44: =E29-E129 -> 0 | F44: =F29-F129 -> 1 | G44: =G29-G129 -> 2 | H44: =H29-H129 -> 0 | I44: =I29-I129 -> 0 | ... L44: =L29-L129 -> 0 | M44: =SUM(B44:L44) -> 13
A46: 4. Pembanding kartu lama (WP CoGM)
A47: Pos | B47: FCC Kw 2 Bumbu BBQ 1kg | C47: FCC Kw 2 Bumbu Balado 1kg | D47: FCC Kw 2 Bumbu Jagung Manis 1kg | E47: FCC Kw 2 Bumbu Asin 1kg | F47: FCC Kw2 Suka-Suka Bumbu BBQ 2,5kg | G47: FCC Kw2 Suka-suka Bumbu Balado 2,5kg | H47: FCC Kw2 Suka-suka Bumbu Jagung Manis 2,5kg | I47: FCC KW2 Suka-suka Bumbu Asin 2,5kg | J47: FCC Premium Bumbu Asin 250gr | K47: Keripik Ubi Mix Kw2 Rasa Balado 1 Kg | L47: Keripik Ubi Mix Kw2 Rasa BBQ 1 Kg | M47: Total | N47: Keterangan
A48: Kartu lama: material | B48: =B137 -> 842769.4 | C48: =C137 -> 1634122.6 | D48: =D137 -> 416489.31 | E48: =E137 -> 20360.126 | F48: =F137 -> 379194.36 | G48: =G137 -> 1319934.6 | H48: =H137 -> 17899.059 | I48: =I137 -> 213.75 | ... L48: =L137 -> 796250.69 | M48: =SUM(B48:L48) -> 6548488.3
A49: WP: bahan | B49: =B16 -> 4812341.5 | C49: =C16 -> 9025739.6 | D49: =D16 -> 2327945.8 | E49: =E16 -> 704769.11 | F49: =F16 -> 1748012.3 | G49: =G16 -> 5426388.5 | H49: =H16 -> 86339.957 | I49: =I16 -> 73543.284 | ... L49: =L16 -> 796250.69 | M49: =SUM(B49:L49) -> 26146429
A50: Kartu lama: tenaga kerja | B50: =B138 -> 264704.06 | C50: =C138 -> 492813.1 | D50: =D138 -> 127472.69 | E50: =E138 -> 42694.204 | F50: =F138 -> 36595.032 | G50: =G138 -> 110395.01 | H50: =H138 -> 1829.7516 | I50: =I138 -> 1829.7516 | ... L50: =L138 -> 246406.55 | M50: =SUM(B50:L50) -> 1601881
A51: WP: konversi (Grup A–E) | B51: =B17+B21 -> 657831.45 | C51: =C17+C21 -> 1228631.1 | D51: =D17+D21 -> 317430.03 | E51: =E17+E21 -> 99159.196 | F51: =F17+F21 -> 106723.15 | G51: =G17+G21 -> 332516.28 | H51: =H17+H21 -> 5270.3951 | I51: =I17+I21 -> 4208.17 | ... L51: =L17+L21 -> 613067.65 | M51: =SUM(B51:L51) -> 4055017
A52: Selisih total WP − kartu lama | B52: =B49+B51-B48-B50 -> 4362699.5 | C52: =C49+C51-C48-C50 -> 8127435 | D52: =D49+D51-D48-D50 -> 2101413.9 | E52: =E49+E51-E48-E50 -> 740873.98 | F52: =F49+F51-F48-F50 -> 1438946.1 | G52: =G49+G51-G48-G50 -> 4328575.2 | H52: =H49+H51-H48-H50 -> 71881.542 | I52: =I49+I51-I48-I50 -> 75707.952 | ... L52: =L49+L51-L48-L50 -> 366661.1 | M52: =SUM(B52:L52) -> 22051077
A54: 5. Kontrol (toleransi Rp 1)
A55: Cek | B55: Nilai | C55: Status
A56: Material eksternal per SKU = Lampiran B kelompok EXT (total) | B56: =M15-SUMIF($N$170:$N$194,"EXT",M$170:M$194) -> 0 | C56: =IF(ISERROR(B56),"GAGAL",IF(ABS(B56)<=1,"LULUS","GAGAL")) -> LULUS
A57: Semua baris Lampiran B punya kelompok yang dikenal | B57: =COUNTA($A$143:$A$167)-COUNTIF($N$143:$N$167,"FCC")-COUNTIF($N$143:$N$167,"KW2")-COUNTIF($N$143:$N$167,"KW2UBI")-COUNTIF($N$143:$N$167,"EXT") -> 0 | C57: =IF(ISERROR(B57),"GAGAL",IF(ABS(B57)<=0.5,"LULUS","GAGAL")) -> LULUS
A58: Man-hour driver per SKU = Labor Koperasi | B58: =M12-M125 -> 0 | C58: =IF(ISERROR(B58),"GAGAL",IF(ABS(B58)<=0.01,"LULUS","GAGAL")) -> LULUS
A59: Barang jadi: awal + masuk = penjualan + akhir + selisih (Rp) | B59: =M28+M30-M33-M35-M37 -> 1.3387762e-09 | C59: =IF(ISERROR(B59),"GAGAL",IF(ABS(B59)<=1,"LULUS","GAGAL")) -> LULUS
A60: Tidak ada sel error | B60: =SUMPRODUCT(--ISERROR(A5:N52)) -> 0 | C60: =IF(ISERROR(B60),"GAGAL",IF(ABS(B60)<=0.5,"LULUS","GAGAL")) -> LULUS
A120: LAMPIRAN A. Input bulan ini per SKU
A121: Pos | B121: FCC Kw 2 Bumbu BBQ 1kg | C121: FCC Kw 2 Bumbu Balado 1kg | D121: FCC Kw 2 Bumbu Jagung Manis 1kg | E121: FCC Kw 2 Bumbu Asin 1kg | F121: FCC Kw2 Suka-Suka Bumbu BBQ 2,5kg | G121: FCC Kw2 Suka-suka Bumbu Balado 2,5kg | H121: FCC Kw2 Suka-suka Bumbu Jagung Manis 2,5kg | I121: FCC KW2 Suka-suka Bumbu Asin 2,5kg | J121: FCC Premium Bumbu Asin 250gr | K121: Keripik Ubi Mix Kw2 Rasa Balado 1 Kg | L121: Keripik Ubi Mix Kw2 Rasa BBQ 1 Kg | M121: Total | N121: Sumber
A122: Output produksi (kg) | B122: 434 | C122: 808 | D122: 209 | E122: 70 | F122: 150 | G122: 452.5 | H122: 7.5 | I122: 7.5 | J122: 10 | K122: 415 | L122: 404 | M122: =SUM(B122:L122) -> 2967.5 | N122: Kartu Bagging Kop baris 10
A123: Kg per satuan FG | B123: 1 | C123: 1 | D123: 1 | E123: 1 | F123: 2.5 | G123: 2.5 | H123: 2.5 | I123: 2.5 | J123: 1 | K123: 1 | L123: 1 | N123: Kemasan SKU (1 kg / 2,5 kg)
A124: Man-hour kartu per SKU | B124: 14.763 | C124: 27.4851 | D124: 7.1094 | E124: 2.3811 | F124: 2.041 | G124: 6.1569 | H124: 0.102 | I124: 0.102 | J124: 1.3399 | K124: 14.1167 | L124: 13.7426 | M124: =SUM(B124:L124) -> 89.3397 | N124: Kartu baris 40–41
A125: Man-hour driver (Labor Koperasi × porsi kartu) | B125: 14.763 | C125: 27.4851 | D125: 7.1094 | E125: 2.3811 | F125: 2.041 | G125: 6.1569 | H125: 0.102 | I125: 0.102 | J125: 1.3399 | K125: 14.1167 | L125: 13.7426 | M125: =SUM(B125:L125) -> 89.3397 | N125: Labor: Koperasi × porsi kartu
A126: Saldo awal FG (satuan FG) | B126: 0 | C126: 0 | D126: 0 | E126: 0 | F126: 0 | G126: 0 | H126: 0 | I126: 0 | J126: 0 | K126: 0 | L126: 0 | M126: =SUM(B126:L126) -> 0 | N126: Inventory Valuation
A127: Nilai saldo awal FG (WP) | B127: 0 | C127: 0 | D127: 0 | E127: 0 | F127: 0 | G127: 0 | H127: 0 | I127: 0 | J127: 0 | K127: 0 | L127: 0 | M127: =SUM(B127:L127) -> 0 | N127: Roll-forward: WP DI - WP Costing BMG Agu26_4.xlsx sheet KOPERASI baris 35 (saldo akhir WP)
A128: Nilai saldo awal FG menurut Accurate | B128: 0 | C128: 0.05 | D128: 0.01 | E128: 0.03 | F128: 0.01 | G128: -0.01 | H128: 0 | I128: 0 | J128: 0 | K128: 0 | L128: 0 | M128: =SUM(B128:L128) -> 0.09 | N128: Inventory Valuation
A129: Masuk FG menurut Accurate (penyesuaian masuk − keluar) | B129: 434 | C129: 808 | D129: 209 | E129: 70 | F129: 59 | G129: 179 | H129: 3 | I129: 3 | J129: 0 | K129: 415 | L129: 404 | M129: =SUM(B129:L129) -> 2584 | N129: Inventory Valuation
A130: Nilai masuk FG menurut Accurate | B130: 1129237.5 | C130: 2163993.3 | D130: 552711.22 | E130: 66714.17 | F130: 408859.57 | G130: 1414524.8 | H130: 19728.81 | I130: 2043.5 | J130: 0 | K130: 1159199.6 | L130: 1042657.2 | M130: =SUM(B130:L130) -> 7959669.7 | N130: Inventory Valuation
A131: Keluar FG: pengiriman pesanan | B131: 434 | C131: 808 | D131: 209 | E131: 70 | F131: 59 | G131: 179 | H131: 3 | I131: 3 | J131: 0 | K131: 415 | L131: 404 | M131: =SUM(B131:L131) -> 2584 | N131: Inventory Valuation, Pengiriman Pesanan
A132: Nilai pengiriman menurut Accurate | B132: 1129237.5 | C132: 2163993.3 | D132: 552711.22 | E132: 66714.18 | F132: 408859.57 | G132: 1414524.8 | H132: 19728.81 | I132: 2043.5 | J132: 0 | K132: 1159199.6 | L132: 1042657.2 | M132: =SUM(B132:L132) -> 7959669.7 | N132: Inventory Valuation, Pengiriman Pesanan
A133: Saldo akhir FG | B133: 0 | C133: 0 | D133: 0 | E133: 0 | F133: 0 | G133: 0 | H133: 0 | I133: 0 | J133: 0 | K133: 0 | L133: 0 | M133: =SUM(B133:L133) -> 0 | N133: Inventory Valuation
A134: Nilai saldo akhir FG menurut Accurate | B134: 0 | C134: 0.05 | D134: 0.01 | E134: 0.03 | F134: 0.01 | G134: -0.01 | H134: 0 | I134: 0 | J134: 0 | K134: 0 | L134: 0 | M134: =SUM(B134:L134) -> 0.09 | N134: Inventory Valuation
A135: Penjualan menurut Sales By Item (satuan FG) | B135: 434 | C135: 808 | D135: 209 | E135: 70 | F135: 59 | G135: 179 | H135: 3 | I135: 3 | J135: 0 | K135: 415 | L135: 404 | M135: =SUM(B135:L135) -> 2584 | N135: LK Sales By Item
... A138: Kartu lama: tenaga kerja | B138: 264704.06 | C138: 492813.1 | D138: 127472.69 | E138: 42694.204 | F138: 36595.032 | G138: 110395.01 | H138: 1829.7516 | I138: 1829.7516 | J138: 24025.212 | K138: 253115.64 | L138: 246406.55 | M138: =SUM(B138:L138) -> 1601881 | N138: Kartu baris 72–73
A139: FG per SKU: FCC Kw 2 Bumbu BBQ 1kg = FG-014; FCC Kw 2 Bumbu Balado 1kg = FG-013; FCC Kw 2 Bumbu Jagung Manis 1kg = FG-016; FCC Kw 2 Bumbu Asin 1kg = FG-018; FCC Kw2 Suka-Suka Bumbu BBQ 2,5kg = FG-012; FCC Kw2 Suka-suka Bumbu Balado 2,5kg = FG-009; FCC Kw2 Suka-suka Bumbu Jagung Manis 2,5kg = FG-010; FCC KW2 Suka-suka Bumbu Asin 2,5kg = FG-011; FCC Premium Bumbu Asin 250gr = FG-190; Keripik Ubi Mix Kw2 Rasa Balado 1 Kg = FG-167; Keripik Ubi Mix Kw2 Rasa BBQ 1 Kg = FG-170
A141: LAMPIRAN B. Material per SKU – qty (atas) dan nilai kartu Rp (bawah)
A142: Material (qty) | B142: FCC Kw 2 Bumbu BBQ 1kg | C142: FCC Kw 2 Bumbu Balado 1kg | D142: FCC Kw 2 Bumbu Jagung Manis 1kg | E142: FCC Kw 2 Bumbu Asin 1kg | F142: FCC Kw2 Suka-Suka Bumbu BBQ 2,5kg | G142: FCC Kw2 Suka-suka Bumbu Balado 2,5kg | H142: FCC Kw2 Suka-suka Bumbu Jagung Manis 2,5kg | I142: FCC KW2 Suka-suka Bumbu Asin 2,5kg | J142: FCC Premium Bumbu Asin 250gr | K142: Keripik Ubi Mix Kw2 Rasa Balado 1 Kg | L142: Keripik Ubi Mix Kw2 Rasa BBQ 1 Kg | M142: Total | N142: Kelompok
A143: FCC Kw 2 Tanpa Bumbu 7 kg | B143: 406 | C143: 756 | D143: 195.5 | E143: 70 | F143: 140 | G143: 420 | H143: 7 | I143: 7.5 | J143: 0 | K143: 0 | L143: 0 | M143: =SUM(B143:L143) -> 2002 | N143: KW2
A144: FSPC Orange KW2 Tanpa Bumbu | B144: 0 | C144: 0 | D144: 0 | E144: 0 | F144: 0 | G144: 0 | H144: 0 | I144: 0 | J144: 0 | K144: 291.2 | L144: 280.8 | M144: =SUM(B144:L144) -> 572 | N144: KW2UBI
A145: FCC Premium Tanpa Bumbu | B145: 0 | C145: 0 | D145: 0 | E145: 0 | F145: 0 | G145: 0 | H145: 0 | I145: 0 | J145: 10 | K145: 0 | L145: 0 | M145: =SUM(B145:L145) -> 10 | N145: FCC
A146: FSPC Ungu KW2 Tanpa Bumbu | B146: 0 | C146: 0 | D146: 0 | E146: 0 | F146: 0 | G146: 0 | H146: 0 | I146: 0 | J146: 0 | K146: 100.8 | L146: 97.2 | M146: =SUM(B146:L146) -> 198 | N146: KW2UBI
A147: Keripik Talas KW2 Tanpa Bumbu | B147: 0 | C147: 0 | D147: 0 | E147: 0 | F147: 0 | G147: 0 | H147: 0 | I147: 0 | J147: 0 | K147: 0 | L147: 0 | M147: =SUM(B147:L147) -> 0 | N147: KW2UBI
A148: Keripik Putih KW2 Tanpa Bumbu | B148: 0 | C148: 0 | D148: 0 | E148: 0 | F148: 0 | G148: 0 | H148: 0 | I148: 0 | J148: 0 | K148: 0 | L148: 0 | M148: =SUM(B148:L148) -> 0 | N148: KW2UBI
A149: FSPC Orange Premium Tanpa Bumbu | B149: 0 | C149: 0 | D149: 0 | E149: 0 | F149: 0 | G149: 0 | H149: 0 | I149: 0 | J149: 0 | K149: 0 | L149: 0 | M149: =SUM(B149:L149) -> 0 | N149: KW2UBI
A150: Keripik Talas Premium Tanpa Bumbu | B150: 0 | C150: 0 | D150: 0 | E150: 0 | F150: 0 | G150: 0 | H150: 0 | I150: 0 | J150: 0 | K150: 0 | L150: 0 | M150: =SUM(B150:L150) -> 0 | N150: FCC
A151: Bumbu BBQ Pachira | B151: 28.42 | C151: 0 | D151: 0 | E151: 0 | F151: 11.2 | G151: 0 | H151: 0 | I151: 0 | J151: 0 | K151: 0 | L151: 26.46 | M151: =SUM(B151:L151) -> 66.08 | N151: EXT
A152: Bumbu Balado Jeruk | B152: 0 | C152: 0 | D152: 0 | E152: 0 | F152: 0 | G152: 0 | H152: 0 | I152: 0 | J152: 0 | K152: 0 | L152: 0 | M152: =SUM(B152:L152) -> 0 | N152: EXT
A153: Bumbu Ubi Bakar Neo 321209 | B153: 0 | C153: 0 | D153: 0 | E153: 0 | F153: 0 | G153: 0 | H153: 0 | I153: 0 | J153: 0 | K153: 0 | L153: 0 | M153: =SUM(B153:L153) -> 0 | N153: EXT
A154: Bumbu Balado FII-A-01014 | B154: 0 | C154: 44.58 | D154: 0 | E154: 0 | F154: 0 | G154: 33.6 | H154: 0 | I154: 0 | J154: 0 | K154: 23.52 | L154: 0 | M154: =SUM(B154:L154) -> 101.7 | N154: EXT
... A167: Tali Rafia 1 kg | B167: 0 | C167: 0 | D167: 0 | E167: 0 | F167: 0 | G167: 0 | H167: 0 | I167: 0 | J167: 0 | K167: 0 | L167: 0 | M167: =SUM(B167:L167) -> 0 | N167: EXT
A169: Material (nilai kartu Rp) | B169: FCC Kw 2 Bumbu BBQ 1kg | C169: FCC Kw 2 Bumbu Balado 1kg | D169: FCC Kw 2 Bumbu Jagung Manis 1kg | E169: FCC Kw 2 Bumbu Asin 1kg | F169: FCC Kw2 Suka-Suka Bumbu BBQ 2,5kg | G169: FCC Kw2 Suka-suka Bumbu Balado 2,5kg | H169: FCC Kw2 Suka-suka Bumbu Jagung Manis 2,5kg | I169: FCC KW2 Suka-suka Bumbu Asin 2,5kg | J169: FCC Premium Bumbu Asin 250gr | K169: Keripik Ubi Mix Kw2 Rasa Balado 1 Kg | L169: Keripik Ubi Mix Kw2 Rasa BBQ 1 Kg | M169: Total | N169: Kelompok
A170: FCC Kw 2 Tanpa Bumbu 7 kg | B170: 0 | C170: 0 | D170: 0 | E170: 0 | F170: 0 | G170: 0 | H170: 0 | I170: 0 | J170: 0 | K170: 0 | L170: 0 | M170: =SUM(B170:L170) -> 0 | N170: KW2
A171: FSPC Orange KW2 Tanpa Bumbu | B171: 0 | C171: 0 | D171: 0 | E171: 0 | F171: 0 | G171: 0 | H171: 0 | I171: 0 | J171: 0 | K171: 0 | L171: 0 | M171: =SUM(B171:L171) -> 0 | N171: KW2UBI
A172: FCC Premium Tanpa Bumbu | B172: 0 | C172: 0 | D172: 0 | E172: 0 | F172: 0 | G172: 0 | H172: 0 | I172: 0 | J172: 214885.48 | K172: 0 | L172: 0 | M172: =SUM(B172:L172) -> 214885.48 | N172: FCC
A173: FSPC Ungu KW2 Tanpa Bumbu | B173: 0 | C173: 0 | D173: 0 | E173: 0 | F173: 0 | G173: 0 | H173: 0 | I173: 0 | J173: 0 | K173: 0 | L173: 0 | M173: =SUM(B173:L173) -> 0 | N173: KW2UBI
A174: Keripik Talas KW2 Tanpa Bumbu | B174: 0 | C174: 0 | D174: 0 | E174: 0 | F174: 0 | G174: 0 | H174: 0 | I174: 0 | J174: 0 | K174: 0 | L174: 0 | M174: =SUM(B174:L174) -> 0 | N174: KW2UBI
A175: Keripik Putih KW2 Tanpa Bumbu | B175: 0 | C175: 0 | D175: 0 | E175: 0 | F175: 0 | G175: 0 | H175: 0 | I175: 0 | J175: 0 | K175: 0 | L175: 0 | M175: =SUM(B175:L175) -> 0 | N175: KW2UBI
A176: FSPC Orange Premium Tanpa Bumbu | B176: 0 | C176: 0 | D176: 0 | E176: 0 | F176: 0 | G176: 0 | H176: 0 | I176: 0 | J176: 0 | K176: 0 | L176: 0 | M176: =SUM(B176:L176) -> 0 | N176: KW2UBI
A177: Keripik Talas Premium Tanpa Bumbu | B177: 0 | C177: 0 | D177: 0 | E177: 0 | F177: 0 | G177: 0 | H177: 0 | I177: 0 | J177: 0 | K177: 0 | L177: 0 | M177: =SUM(B177:L177) -> 0 | N177: FCC
A178: Bumbu BBQ Pachira | B178: 755306.48 | C178: 0 | D178: 0 | E178: 0 | F178: 297657.72 | G178: 0 | H178: 0 | I178: 0 | J178: 0 | K178: 0 | L178: 703216.37 | M178: =SUM(B178:L178) -> 1756180.6 | N178: EXT
A179: Bumbu Balado Jeruk | B179: 0 | C179: 0 | D179: 0 | E179: 0 | F179: 0 | G179: 0 | H179: 0 | I179: 0 | J179: 0 | K179: 0 | L179: 0 | M179: =SUM(B179:L179) -> 0 | N179: EXT
...

Sheet MCH BASRENG L0
A1: KARTU BIAYA PRODUKSI – Maicih Basreng 80 gr Level 0 (maklon), September 2026
A2: Sumber: kartu 'LAP BAG MAICIH BASRENG L.0 LOK' di WP CoGM September 2026; driver man-hour & kWh: sheet Labor & Overhead Allocation; barang jadi: Inventory Valuation Accurate FG-138; pendapatan: LK Sales By Item.
A3: Tidak ada kartu / produksi bulan ini – hanya pergerakan barang jadi.
A4: Status kontrol (bagian 5) | C4: =IF(COUNTIF(C70:C75,"GAGAL")=0,"LULUS","GAGAL") -> LULUS
A5: 1. Ringkasan (Rp juta; Rp/kg per kg produksi bulan ini)
A6: Komponen | B6: Aktual (Rp jt) | C6: Rp/kg | D6: Porsi
A7: FCC premium (antarproduk) | B7: =E31/10^6 -> 0 | C7: =F31 -> 0 | D7: =IF($B$12=0,0,B7/$B$12) -> 0
A8: KW 2 (antarproduk, NRV) | B8: =(E32+E33)/10^6 -> 0 | C8: =F32+F33 -> 0 | D8: =IF($B$12=0,0,B8/$B$12) -> 0
A9: Material eksternal | B9: =E34/10^6 -> 0 | C9: =F34 -> 0 | D9: =IF($B$12=0,0,B9/$B$12) -> 0
A10: Direct labour (Grup A) | B10: =E37/10^6 -> 0 | C10: =F37 -> 0 | D10: =IF($B$12=0,0,B10/$B$12) -> 0
A11: Factory overhead (Grup B–E) | B11: =E41/10^6 -> 0 | C11: =F41 -> 0 | D11: =IF($B$12=0,0,B11/$B$12) -> 0
A12: Total biaya produksi | B12: =E43/10^6 -> 0 | C12: =F43 -> 0 | D12: =IF($B$12=0,0,B12/$B$12) -> 0
A13: Produksi (kg; satuan FG) | B13: =B21 -> 0 | C13: =C21 -> 0
A14: HPP (Rp jt) dan HPP per satuan terjual | B14: =D54/10^6 -> 0 | C14: =C55 -> 0
A15: Pendapatan (Rp jt) dan harga per satuan | B15: =$C$118/10^6 -> 0 | C15: =IF($C$117=0,0,$C$118/$C$117) -> 0
A16: Margin kotor (Rp jt; %) | B16: =B15-B14 -> 0 | C16: =IF(B15=0,0,B16/B15) -> 0
A18: 2. Laporan biaya produksi
A19: 2a. Kuantitas
A20: Pos | B20: Kg | C20: Satuan FG (bag) | D20: Keterangan
A21: Output produksi | B21: =$C$102 -> 0 | C21: =$C$103 -> 0
A22: Sampel | B22: =$C$104 -> 0 | C22: =$C$105 -> 0 | D22: memo, tidak masuk barang jadi
A23: Input FCC premium | B23: =SUMIF($B$128:$B$128,"FCC",$C$128:$C$128) -> 0 | D23: Lampiran B
A24: Input KW 2 FCC | B24: =SUMIF($B$128:$B$128,"KW2",$C$128:$C$128) -> 0 | D24: Lampiran B
A25: Input KW 2 ubi | B25: =SUMIF($B$128:$B$128,"KW2UBI",$C$128:$C$128) -> 0 | D25: Lampiran B
A26: Rendemen output ÷ input keripik (kg/kg) | B26: =IF(SUM(B23:B25)=0,0,B21/SUM(B23:B25)) -> 0
A28: 2b. Biaya produksi bulan ini (aktual)
A29: Komponen | B29: Qty / driver | C29: Satuan | D29: Harga / porsi | E29: Nilai (Rp) | F29: Rp/kg | G29: Dasar
A30: Bahan
A31: FCC premium (antarproduk) | B31: =B23 -> 0 | C31: kg | D31: =FCC!$D$89 -> 23872.948 | E31: =B31*D31 -> 0 | F31: =IF($B$21=0,0,E31/$B$21) -> 0 | G31: Biaya rata-rata FG FCC kartu baru (FCC D88)
A32: KW 2 FCC (antarproduk, NRV) | B32: =B24 -> 0 | C32: kg | D32: =FCC!$C$209 -> 9777.2712 | E32: =B32*D32 -> 0 | F32: =IF($B$21=0,0,E32/$B$21) -> 0 | G32: NRV KW 2 (FCC C208)
A33: KW 2 ubi (antarproduk) | B33: =B25 -> 0 | C33: kg | D33: ='LAIN-LAIN'!$C$7 -> 0 | E33: =B33*D33 -> 0 | F33: =IF($B$21=0,0,E33/$B$21) -> 0 | G33: Nilai KW 2 ubi (LAIN-LAIN C7)
A34: Material eksternal (Lampiran B) | E34: =SUMIF($B$128:$B$128,"EXT",$F$128:$F$128) -> 0 | F34: =IF($B$21=0,0,E34/$B$21) -> 0 | G34: Nilai kartu per baris material
A35: Subtotal bahan | E35: =SUM(E31:E34) -> 0 | F35: =IF($B$21=0,0,E35/$B$21) -> 0
A36: Konversi (pool BIAYA BERSAMA, porsi Lain-lain dibagi dengan driver yang sama dengan sheet LAIN-LAIN)
A37: Grup A – DL operator | B37: =$C$106 -> 0 | C37: jam | D37: =IF('LAIN-LAIN'!$H$43=0,0,B37/'LAIN-LAIN'!$H$43) -> 0 | E37: =D37*'BIAYA BERSAMA'!$F$115 -> 0 | F37: =IF($B$21=0,0,E37/$B$21) -> 0 | G37: Man-hour ÷ total man-hour Lain-lain × pool Grup A Lain-lain
A38: Grup B – IDL (support, staf, THR, BPJS) | B38: =$C$106 -> 0 | C38: jam | D38: =IF('LAIN-LAIN'!$H$43=0,0,B38/'LAIN-LAIN'!$H$43) -> 0 | E38: =D38*'BIAYA BERSAMA'!$F$117 -> 0 | F38: =IF($B$21=0,0,E38/$B$21) -> 0 | G38: Man-hour
A39: Grup C + D – energi (kWh) dan mesin (bagging: kWh; Ubi putih ACE: jam mesin) | B39: =$C$107 -> 0 | C39: kWh | D39: =IF('LAIN-LAIN'!$I$43=0,0,B39/'LAIN-LAIN'!$I$43) -> 0 | E39: =D39*'BIAYA BERSAMA'!$F$118+IF('BIAYA BERSAMA'!$F$172=0,0,B39/'BIAYA BERSAMA'!$F$172)*'BIAYA BERSAMA'!$F$176 -> 0 | F39: =IF($B$21=0,0,E39/$B$21) -> 0 | G39: kWh
A40: Grup E – pabrik umum | B40: =E34 -> 0 | C40: Rp | D40: =IF('LAIN-LAIN'!$G$43=0,0,B40/'LAIN-LAIN'!$G$43) -> 0 | E40: =D40*'BIAYA BERSAMA'!$F$120 -> 0 | F40: =IF($B$21=0,0,E40/$B$21) -> 0 | G40: Nilai material eksternal
A41: Subtotal factory overhead (Grup B–E) | E41: =SUM(E38:E40) -> 0 | F41: =IF($B$21=0,0,E41/$B$21) -> 0
A42: Total konversi | E42: =E37+E41 -> 0 | F42: =IF($B$21=0,0,E42/$B$21) -> 0
A43: TOTAL BIAYA PRODUKSI BULAN INI | E43: =E35+E42 -> 0 | F43: =IF($B$21=0,0,E43/$B$21) -> 0
A45: 3. Barang jadi (FG-138 Maicih Basreng 80GR Level.0) dan HPP
A46: Pos | B46: Qty (bag) | C46: Rp/satuan | D46: Nilai WP (Rp) | E46: Qty Accurate | F46: Nilai Accurate (Rp) | G46: Selisih nilai WP − Accurate
A47: Saldo awal | B47: =$C$108 -> 0 | D47: =$C$109 -> 0 | E47: =$C$108 -> 0 | F47: =$C$110 -> 0 | G47: =D47-F47 -> 0
A48: Masuk dari produksi | B48: =C21 -> 0 | D48: =E43 -> 0 | E48: =$C$111 -> 0 | F48: =$C$112 -> 0 | G48: =D48-F48 -> 0
A49: Tersedia | B49: =B47+B48 -> 0 | D49: =D47+D48 -> 0 | E49: =E47+E48 -> 0 | F49: =F47+F48 -> 0 | G49: =D49-F49 -> 0
A50: Biaya rata-rata tertimbang per satuan | C50: =IF(B49=0,0,D49/B49) -> 0
A51: Keluar: penjualan (pengiriman pesanan) | B51: =$C$113 -> 0 | D51: =B51*$C$50 -> 0 | E51: =$C$113 -> 0 | F51: =$C$114 -> 0 | G51: =D51-F51 -> 0
A52: Saldo akhir (qty menurut Accurate) | B52: =$C$115 -> 0 | D52: =B52*$C$50 -> 0 | E52: =$C$115 -> 0 | F52: =$C$116 -> 0 | G52: =D52-F52 -> 0
A53: Selisih kuantitas (tersedia − penjualan − saldo akhir) ke HPP | B53: =B49-B51-B52 -> 0 | D53: =B53*$C$50 -> 0 | E53: =E49-E51-E52 -> 0 | F53: =F49-F51-F52 -> 0 | G53: =D53-F53 -> 0
A54: HPP (penjualan + selisih kuantitas) | D54: =D51+D53 -> 0 | F54: =F51+F53 -> 0 | G54: =D54-F54 -> 0
A55: HPP per satuan terjual | C55: =IF(B51=0,0,D54/B51) -> 0
A56: Memo: penjualan Sales By Item − pengiriman Accurate (qty) | B56: =$C$117-B51 -> 0
A57: Memo: produksi kartu − masuk menurut Accurate (qty) | B57: =B48-E48 -> 0
A59: 4. Pembanding kartu lama (WP CoGM)
A60: Komponen | B60: Kartu lama (Rp) | C60: WP (Rp) | D60: Selisih (Rp) | E60: Keterangan
A61: Material (DM + IDM) | B61: =$C$119 -> 0 | C61: =E35 -> 0 | D61: =C61-B61 -> 0 | E61: Kartu: FCC premium pada harga kartu lama; WP: pada biaya FCC kartu baru (FCC D88) dan KW 2 pada NRV
A62: Tenaga kerja (DL + IDL) | B62: =$C$120 -> 0 | C62: =E37+E38 -> 0 | D62: =C62-B62 -> 0 | E62: Kartu: man-hour × tarif; WP: pool Grup A + B
A63: Listrik / overhead | B63: =$C$121 -> 0 | C63: =E39+E40 -> 0 | D63: =C63-B63 -> 0 | E63: Kartu: kWh × tarif; WP: pool Grup C, D, E
A64: Total biaya produksi | B64: =SUM(B61:B63) -> 0 | C64: =SUM(C61:C63) -> 0 | D64: =C64-B64 -> 0
A65: Man-hour: kartu lama vs driver Labor | B65: =$C$122 -> 0 | C65: =$C$106 -> 0 | D65: =C65-B65 -> 0
A66: kWh: kartu lama vs driver Overhead Allocation | B66: =$C$123 -> 0 | C66: =$C$107 -> 0 | D66: =C66-B66 -> 0
A68: 5. Kontrol (toleransi Rp 1; 0,01 qty)
A69: Cek | B69: Nilai | C69: Status
A70: Material eksternal di 2b = Lampiran B kelompok EXT | B70: =E34-SUMIF($B$128:$B$128,"EXT",$F$128:$F$128) -> 0 | C70: =IF(ISERROR(B70),"GAGAL",IF(ABS(B70)<=1,"LULUS","GAGAL")) -> LULUS
A71: Semua baris Lampiran B punya kelompok yang dikenal | B71: =COUNTA($A$128:$A$128)-COUNTIF($B$128:$B$128,"FCC")-COUNTIF($B$128:$B$128,"KW2")-COUNTIF($B$128:$B$128,"KW2UBI")-COUNTIF($B$128:$B$128,"EXT") -> 0 | C71: =IF(ISERROR(B71),"GAGAL",IF(ABS(B71)<=0.5,"LULUS","GAGAL")) -> LULUS
A72: Total biaya = bahan + konversi | B72: =E43-E35-E42 -> 0 | C72: =IF(ISERROR(B72),"GAGAL",IF(ABS(B72)<=1,"LULUS","GAGAL")) -> LULUS
A73: Barang jadi: tersedia = penjualan + saldo akhir + selisih kuantitas (Rp) | B73: =D49-D51-D52-D53 -> 0 | C73: =IF(ISERROR(B73),"GAGAL",IF(ABS(B73)<=1,"LULUS","GAGAL")) -> LULUS
A74: Ringkasan = 2b (Rp jt) | B74: =B12*10^6-E43 -> 0 | C74: =IF(ISERROR(B74),"GAGAL",IF(ABS(B74)<=1,"LULUS","GAGAL")) -> LULUS
A75: Tidak ada sel error | B75: =SUMPRODUCT(--ISERROR(A5:H66)) -> 0 | C75: =IF(ISERROR(B75),"GAGAL",IF(ABS(B75)<=0.5,"LULUS","GAGAL")) -> LULUS
A76: Info (bukan kontrol): selisih kuantitas barang jadi (B53) dan memo B56–B57 menunjukkan beda kartu vs Accurate.
A100: LAMPIRAN A. Input bulan ini
A101: Pos | B101: Satuan | C101: Nilai | D101: Status angka | E101: Sumber
A102: Output produksi | B102: kg | C102: 0 | D102: Aktual | E102: Kartu E7 (kg)
A103: Output produksi | B103: bag | C103: 0 | D103: Aktual | E103: Kartu E6 (bag)
A104: Sampel | B104: kg | C104: 0 | D104: Aktual | E104: Kartu E10
A105: Sampel | B105: bag | C105: 0 | D105: Aktual | E105: Kartu E9
A106: Man-hour (driver Grup A & B) | B106: jam | C106: 0 | D106: Aktual | E106: Labor: LAP BAG MAICIH BASRENG LV 0 LOK
A107: Pemakaian listrik (driver Grup C & D) | B107: kWh | C107: 0 | D107: Aktual | E107: Overhead Allocation: LAP BAG MAICIH BASRENG LV 0 LOK
A108: Saldo awal FG-138 | B108: bag | C108: 0 | D108: Aktual | E108: Inventory Valuation (Kts. saldo awal bulan)
A109: Nilai saldo awal FG-138 (WP) | B109: Rp | C109: 0 | D109: Roll-forward | E109: Roll-forward: WP DI - WP Costing BMG Agu26_4.xlsx sheet MCH BASRENG L0 D52 (saldo akhir WP)
A110: Nilai saldo awal FG-138 menurut Accurate | B110: Rp | C110: 0 | D110: Aktual | E110: Inventory Valuation
A111: Masuk FG-138 menurut Accurate (penyesuaian masuk − keluar) | B111: bag | C111: 0 | D111: Aktual | E111: Inventory Valuation, Penyesuaian persediaan
A112: Nilai masuk FG-138 menurut Accurate | B112: Rp | C112: 0 | D112: Aktual | E112: Inventory Valuation, Penyesuaian persediaan
A113: Keluar FG-138: pengiriman pesanan | B113: bag | C113: 0 | D113: Aktual | E113: Inventory Valuation, Pengiriman Pesanan
... A123: Kartu lama: kWh di operasi | B123: kWh | C123: 0 | D123: Aktual | E123: Kartu, baris Operation (Elc)
A126: LAMPIRAN B. Material per baris kartu (qty kartu; nilai kartu = qty × harga kartu)
A127: Material | B127: Kelompok | C127: Qty | D127: Satuan | E127: Harga kartu | F127: Nilai kartu (Rp) | G127: Sumber
A128: (tidak ada pemakaian) | B128: EXT | C128: 0 | E128: 0 | F128: 0 | G128: Kartu ; kelompok: Eksternal
A129: Total | F129: =SUM(F128:F128) -> 0
A130: Kode kelompok: FCC = FCC premium (dinilai ulang pada biaya FCC kartu baru), KW2 = KW 2 FCC (NRV), KW2UBI = KW 2 ubi, EXT = material eksternal (nilai kartu).

Sheet MCH BASRENG L5
A1: KARTU BIAYA PRODUKSI – Maicih Basreng 80 gr Level 5 (maklon), September 2026
A2: Sumber: kartu 'LAP BAG MAICIH BASRENG L.5 LOK' di WP CoGM September 2026; driver man-hour & kWh: sheet Labor & Overhead Allocation; barang jadi: Inventory Valuation Accurate FG-137; pendapatan: LK Sales By Item.
A4: Status kontrol (bagian 5) | C4: =IF(COUNTIF(C70:C75,"GAGAL")=0,"LULUS","GAGAL") -> LULUS
A5: 1. Ringkasan (Rp juta; Rp/kg per kg produksi bulan ini)
A6: Komponen | B6: Aktual (Rp jt) | C6: Rp/kg | D6: Porsi
A7: FCC premium (antarproduk) | B7: =E31/10^6 -> 0 | C7: =F31 -> 0 | D7: =IF($B$12=0,0,B7/$B$12) -> 0
A8: KW 2 (antarproduk, NRV) | B8: =(E32+E33)/10^6 -> 0 | C8: =F32+F33 -> 0 | D8: =IF($B$12=0,0,B8/$B$12) -> 0
A9: Material eksternal | B9: =E34/10^6 -> 0.01615023 | C9: =F34 -> 45.7151 | D9: =IF($B$12=0,0,B9/$B$12) -> 0.0073844752
A10: Direct labour (Grup A) | B10: =E37/10^6 -> 0.53139825 | C10: =F37 -> 1504.1844 | D10: =IF($B$12=0,0,B10/$B$12) -> 0.24297469
A11: Factory overhead (Grup B–E) | B11: =E41/10^6 -> 1.6395034 | C11: =F41 -> 4640.8045 | D11: =IF($B$12=0,0,B11/$B$12) -> 0.74964084
A12: Total biaya produksi | B12: =E43/10^6 -> 2.1870519 | C12: =F43 -> 6190.7039 | D12: =IF($B$12=0,0,B12/$B$12) -> 1
A13: Produksi (kg; satuan FG) | B13: =B21 -> 353.28 | C13: =C21 -> 4416
A14: HPP (Rp jt) dan HPP per satuan terjual | B14: =D54/10^6 -> 2.1870519 | C14: =C55 -> 495.25631
A15: Pendapatan (Rp jt) dan harga per satuan | B15: =$C$118/10^6 -> 1.7664 | C15: =IF($C$117=0,0,$C$118/$C$117) -> 400
A16: Margin kotor (Rp jt; %) | B16: =B15-B14 -> -0.42065188 | C16: =IF(B15=0,0,B16/B15) -> -0.23814079
A18: 2. Laporan biaya produksi
A19: 2a. Kuantitas
A20: Pos | B20: Kg | C20: Satuan FG (bag) | D20: Keterangan
A21: Output produksi | B21: =$C$102 -> 353.28 | C21: =$C$103 -> 4416
A22: Sampel | B22: =$C$104 -> 0.96 | C22: =$C$105 -> 12 | D22: memo, tidak masuk barang jadi
A23: Input FCC premium | B23: =SUMIF($B$128:$B$131,"FCC",$C$128:$C$131) -> 0 | D23: Lampiran B
A24: Input KW 2 FCC | B24: =SUMIF($B$128:$B$131,"KW2",$C$128:$C$131) -> 0 | D24: Lampiran B
A25: Input KW 2 ubi | B25: =SUMIF($B$128:$B$131,"KW2UBI",$C$128:$C$131) -> 0 | D25: Lampiran B
A26: Rendemen output ÷ input keripik (kg/kg) | B26: =IF(SUM(B23:B25)=0,0,B21/SUM(B23:B25)) -> 0
A28: 2b. Biaya produksi bulan ini (aktual)
A29: Komponen | B29: Qty / driver | C29: Satuan | D29: Harga / porsi | E29: Nilai (Rp) | F29: Rp/kg | G29: Dasar
A30: Bahan
A31: FCC premium (antarproduk) | B31: =B23 -> 0 | C31: kg | D31: =FCC!$D$89 -> 23872.948 | E31: =B31*D31 -> 0 | F31: =IF($B$21=0,0,E31/$B$21) -> 0 | G31: Biaya rata-rata FG FCC kartu baru (FCC D88)
A32: KW 2 FCC (antarproduk, NRV) | B32: =B24 -> 0 | C32: kg | D32: =FCC!$C$209 -> 9777.2712 | E32: =B32*D32 -> 0 | F32: =IF($B$21=0,0,E32/$B$21) -> 0 | G32: NRV KW 2 (FCC C208)
A33: KW 2 ubi (antarproduk) | B33: =B25 -> 0 | C33: kg | D33: ='LAIN-LAIN'!$C$7 -> 0 | E33: =B33*D33 -> 0 | F33: =IF($B$21=0,0,E33/$B$21) -> 0 | G33: Nilai KW 2 ubi (LAIN-LAIN C7)
A34: Material eksternal (Lampiran B) | E34: =SUMIF($B$128:$B$131,"EXT",$F$128:$F$131) -> 16150.23 | F34: =IF($B$21=0,0,E34/$B$21) -> 45.7151 | G34: Nilai kartu per baris material
A35: Subtotal bahan | E35: =SUM(E31:E34) -> 16150.23 | F35: =IF($B$21=0,0,E35/$B$21) -> 45.7151
A36: Konversi (pool BIAYA BERSAMA, porsi Lain-lain dibagi dengan driver yang sama dengan sheet LAIN-LAIN)
A37: Grup A – DL operator | B37: =$C$106 -> 24.47 | C37: jam | D37: =IF('LAIN-LAIN'!$H$43=0,0,B37/'LAIN-LAIN'!$H$43) -> 0.0090995299 | E37: =D37*'BIAYA BERSAMA'!$F$115 -> 531398.25 | F37: =IF($B$21=0,0,E37/$B$21) -> 1504.1844 | G37: Man-hour ÷ total man-hour Lain-lain × pool Grup A Lain-lain
A38: Grup B – IDL (support, staf, THR, BPJS) | B38: =$C$106 -> 24.47 | C38: jam | D38: =IF('LAIN-LAIN'!$H$43=0,0,B38/'LAIN-LAIN'!$H$43) -> 0.0090995299 | E38: =D38*'BIAYA BERSAMA'!$F$117 -> 475070.03 | F38: =IF($B$21=0,0,E38/$B$21) -> 1344.7408 | G38: Man-hour
A39: Grup C + D – energi (kWh) dan mesin (bagging: kWh; Ubi putih ACE: jam mesin) | B39: =$C$107 -> 139.3625 | C39: kWh | D39: =IF('LAIN-LAIN'!$I$43=0,0,B39/'LAIN-LAIN'!$I$43) -> 0.01377364 | E39: =D39*'BIAYA BERSAMA'!$F$118+IF('BIAYA BERSAMA'!$F$172=0,0,B39/'BIAYA BERSAMA'!$F$172)*'BIAYA BERSAMA'!$F$176 -> 1163463.3 | F39: =IF($B$21=0,0,E39/$B$21) -> 3293.3179 | G39: kWh
A40: Grup E – pabrik umum | B40: =E34 -> 16150.23 | C40: Rp | D40: =IF('LAIN-LAIN'!$G$43=0,0,B40/'LAIN-LAIN'!$G$43) -> 0.00021063608 | E40: =D40*'BIAYA BERSAMA'!$F$120 -> 970.02432 | F40: =IF($B$21=0,0,E40/$B$21) -> 2.7457663 | G40: Nilai material eksternal
A41: Subtotal factory overhead (Grup B–E) | E41: =SUM(E38:E40) -> 1639503.4 | F41: =IF($B$21=0,0,E41/$B$21) -> 4640.8045
A42: Total konversi | E42: =E37+E41 -> 2170901.7 | F42: =IF($B$21=0,0,E42/$B$21) -> 6144.9888
A43: TOTAL BIAYA PRODUKSI BULAN INI | E43: =E35+E42 -> 2187051.9 | F43: =IF($B$21=0,0,E43/$B$21) -> 6190.7039
A45: 3. Barang jadi (FG-137 Maicih Basreng 80GR Level.5) dan HPP
A46: Pos | B46: Qty (bag) | C46: Rp/satuan | D46: Nilai WP (Rp) | E46: Qty Accurate | F46: Nilai Accurate (Rp) | G46: Selisih nilai WP − Accurate
A47: Saldo awal | B47: =$C$108 -> 0 | D47: =$C$109 -> 0 | E47: =$C$108 -> 0 | F47: =$C$110 -> 0 | G47: =D47-F47 -> 0
A48: Masuk dari produksi | B48: =C21 -> 4416 | D48: =E43 -> 2187051.9 | E48: =$C$111 -> 4416 | F48: =$C$112 -> 605632.32 | G48: =D48-F48 -> 1581419.6
A49: Tersedia | B49: =B47+B48 -> 4416 | D49: =D47+D48 -> 2187051.9 | E49: =E47+E48 -> 4416 | F49: =F47+F48 -> 605632.32 | G49: =D49-F49 -> 1581419.6
A50: Biaya rata-rata tertimbang per satuan | C50: =IF(B49=0,0,D49/B49) -> 495.25631
A51: Keluar: penjualan (pengiriman pesanan) | B51: =$C$113 -> 4416 | D51: =B51*$C$50 -> 2187051.9 | E51: =$C$113 -> 4416 | F51: =$C$114 -> 605632.32 | G51: =D51-F51 -> 1581419.6
A52: Saldo akhir (qty menurut Accurate) | B52: =$C$115 -> 0 | D52: =B52*$C$50 -> 0 | E52: =$C$115 -> 0 | F52: =$C$116 -> 0 | G52: =D52-F52 -> 0
A53: Selisih kuantitas (tersedia − penjualan − saldo akhir) ke HPP | B53: =B49-B51-B52 -> 0 | D53: =B53*$C$50 -> 0 | E53: =E49-E51-E52 -> 0 | F53: =F49-F51-F52 -> 0 | G53: =D53-F53 -> 0
A54: HPP (penjualan + selisih kuantitas) | D54: =D51+D53 -> 2187051.9 | F54: =F51+F53 -> 605632.32 | G54: =D54-F54 -> 1581419.6
A55: HPP per satuan terjual | C55: =IF(B51=0,0,D54/B51) -> 495.25631
A56: Memo: penjualan Sales By Item − pengiriman Accurate (qty) | B56: =$C$117-B51 -> 0
A57: Memo: produksi kartu − masuk menurut Accurate (qty) | B57: =B48-E48 -> 0
A59: 4. Pembanding kartu lama (WP CoGM)
A60: Komponen | B60: Kartu lama (Rp) | C60: WP (Rp) | D60: Selisih (Rp) | E60: Keterangan
A61: Material (DM + IDM) | B61: =$C$119 -> 16150.23 | C61: =E35 -> 16150.23 | D61: =C61-B61 -> 1.47465e-05 | E61: Kartu: FCC premium pada harga kartu lama; WP: pada biaya FCC kartu baru (FCC D88) dan KW 2 pada NRV
A62: Tenaga kerja (DL + IDL) | B62: =$C$120 -> 438752.32 | C62: =E37+E38 -> 1006468.3 | D62: =C62-B62 -> 567715.96 | E62: Kartu: man-hour × tarif; WP: pool Grup A + B
A63: Listrik / overhead | B63: =$C$121 -> 150729.76 | C63: =E39+E40 -> 1164433.4 | D63: =C63-B63 -> 1013703.6 | E63: Kartu: kWh × tarif; WP: pool Grup C, D, E
A64: Total biaya produksi | B64: =SUM(B61:B63) -> 605632.31 | C64: =SUM(C61:C63) -> 2187051.9 | D64: =C64-B64 -> 1581419.6
A65: Man-hour: kartu lama vs driver Labor | B65: =$C$122 -> 24.47 | C65: =$C$106 -> 24.47 | D65: =C65-B65 -> 0
A66: kWh: kartu lama vs driver Overhead Allocation | B66: =$C$123 -> 139.3625 | C66: =$C$107 -> 139.3625 | D66: =C66-B66 -> 0
A68: 5. Kontrol (toleransi Rp 1; 0,01 qty)
A69: Cek | B69: Nilai | C69: Status
A70: Material eksternal di 2b = Lampiran B kelompok EXT | B70: =E34-SUMIF($B$128:$B$131,"EXT",$F$128:$F$131) -> 0 | C70: =IF(ISERROR(B70),"GAGAL",IF(ABS(B70)<=1,"LULUS","GAGAL")) -> LULUS
A71: Semua baris Lampiran B punya kelompok yang dikenal | B71: =COUNTA($A$128:$A$131)-COUNTIF($B$128:$B$131,"FCC")-COUNTIF($B$128:$B$131,"KW2")-COUNTIF($B$128:$B$131,"KW2UBI")-COUNTIF($B$128:$B$131,"EXT") -> 0 | C71: =IF(ISERROR(B71),"GAGAL",IF(ABS(B71)<=0.5,"LULUS","GAGAL")) -> LULUS
A72: Total biaya = bahan + konversi | B72: =E43-E35-E42 -> 0 | C72: =IF(ISERROR(B72),"GAGAL",IF(ABS(B72)<=1,"LULUS","GAGAL")) -> LULUS
A73: Barang jadi: tersedia = penjualan + saldo akhir + selisih kuantitas (Rp) | B73: =D49-D51-D52-D53 -> 0 | C73: =IF(ISERROR(B73),"GAGAL",IF(ABS(B73)<=1,"LULUS","GAGAL")) -> LULUS
A74: Ringkasan = 2b (Rp jt) | B74: =B12*10^6-E43 -> 0 | C74: =IF(ISERROR(B74),"GAGAL",IF(ABS(B74)<=1,"LULUS","GAGAL")) -> LULUS
A75: Tidak ada sel error | B75: =SUMPRODUCT(--ISERROR(A5:H66)) -> 0 | C75: =IF(ISERROR(B75),"GAGAL",IF(ABS(B75)<=0.5,"LULUS","GAGAL")) -> LULUS
A76: Info (bukan kontrol): selisih kuantitas barang jadi (B53) dan memo B56–B57 menunjukkan beda kartu vs Accurate.
A100: LAMPIRAN A. Input bulan ini
A101: Pos | B101: Satuan | C101: Nilai | D101: Status angka | E101: Sumber
A102: Output produksi | B102: kg | C102: 353.28 | D102: Aktual | E102: Kartu E7 (kg)
A103: Output produksi | B103: bag | C103: 4416 | D103: Aktual | E103: Kartu E6 (bag)
A104: Sampel | B104: kg | C104: 0.96 | D104: Aktual | E104: Kartu E10
A105: Sampel | B105: bag | C105: 12 | D105: Aktual | E105: Kartu E9
A106: Man-hour (driver Grup A & B) | B106: jam | C106: 24.47 | D106: Aktual | E106: Labor: LAP BAG MAICIH BASRENG LV 5 LOK
A107: Pemakaian listrik (driver Grup C & D) | B107: kWh | C107: 139.3625 | D107: Aktual | E107: Overhead Allocation: LAP BAG MAICIH BASRENG LV 5 LOK
A108: Saldo awal FG-137 | B108: bag | C108: 0 | D108: Aktual | E108: Inventory Valuation (Kts. saldo awal bulan)
A109: Nilai saldo awal FG-137 (WP) | B109: Rp | C109: 0 | D109: Roll-forward | E109: Roll-forward: WP DI - WP Costing BMG Agu26_4.xlsx sheet MCH BASRENG L5 D52 (saldo akhir WP)
A110: Nilai saldo awal FG-137 menurut Accurate | B110: Rp | C110: 0 | D110: Aktual | E110: Inventory Valuation
A111: Masuk FG-137 menurut Accurate (penyesuaian masuk − keluar) | B111: bag | C111: 4416 | D111: Aktual | E111: Inventory Valuation, Penyesuaian persediaan
A112: Nilai masuk FG-137 menurut Accurate | B112: Rp | C112: 605632.32 | D112: Aktual | E112: Inventory Valuation, Penyesuaian persediaan
A113: Keluar FG-137: pengiriman pesanan | B113: bag | C113: 4416 | D113: Aktual | E113: Inventory Valuation, Pengiriman Pesanan
... A123: Kartu lama: kWh di operasi | B123: kWh | C123: 139.3625 | D123: Aktual | E123: Kartu, baris Operation (Elc)
A126: LAMPIRAN B. Material per baris kartu (qty kartu; nilai kartu = qty × harga kartu)
A127: Material | B127: Kelompok | C127: Qty | D127: Satuan | E127: Harga kartu | F127: Nilai kartu (Rp) | G127: Sumber
A128: Basreng Bumbu Level 5 Maichi | B128: EXT | C128: 360 | D128: kg | E128: 0 | F128: 0 | G128: Kartu C13:R13; kelompok: Eksternal
A129: Polyfilm Maichi Basreng Level 5 | B129: EXT | C129: 44.84 | D129: kg | E129: 0 | F129: 0 | G129: Kartu C14:R14; kelompok: Eksternal
A130: Karton Maicih | B130: EXT | C130: 177 | D130: pcs | E130: 0 | F130: 0 | G130: Kartu C15:R15; kelompok: Eksternal
A131: Plakban Ukuran 100 Yard | B131: EXT | C131: 2.4470046 | D131: roll | E131: 6600 | F131: 16150.23 | G131: Kartu C16:R16; kelompok: Eksternal
A132: Total | F132: =SUM(F128:F131) -> 16150.23
A133: Kode kelompok: FCC = FCC premium (dinilai ulang pada biaya FCC kartu baru), KW2 = KW 2 FCC (NRV), KW2UBI = KW 2 ubi, EXT = material eksternal (nilai kartu).

Sheet MCH BASRENG L10
A1: KARTU BIAYA PRODUKSI – Maicih Basreng 80 gr Level 10 (maklon), September 2026
A2: Sumber: kartu 'LAP BAG MAICIH BASRENG L.10 LOK' di WP CoGM September 2026; driver man-hour & kWh: sheet Labor & Overhead Allocation; barang jadi: Inventory Valuation Accurate FG-153; pendapatan: LK Sales By Item.
A4: Status kontrol (bagian 5) | C4: =IF(COUNTIF(C70:C75,"GAGAL")=0,"LULUS","GAGAL") -> LULUS
A5: 1. Ringkasan (Rp juta; Rp/kg per kg produksi bulan ini)
A6: Komponen | B6: Aktual (Rp jt) | C6: Rp/kg | D6: Porsi
A7: FCC premium (antarproduk) | B7: =E31/10^6 -> 0 | C7: =F31 -> 0 | D7: =IF($B$12=0,0,B7/$B$12) -> 0
A8: KW 2 (antarproduk, NRV) | B8: =(E32+E33)/10^6 -> 0 | C8: =F32+F33 -> 0 | D8: =IF($B$12=0,0,B8/$B$12) -> 0
A9: Material eksternal | B9: =E34/10^6 -> 0.026546057 | C9: =F34 -> 46.305569 | D9: =IF($B$12=0,0,B9/$B$12) -> 0.008121931
A10: Direct labour (Grup A) | B10: =E37/10^6 -> 0.81370818 | C10: =F37 -> 1419.3905 | D10: =IF($B$12=0,0,B10/$B$12) -> 0.24895907
A11: Factory overhead (Grup B–E) | B11: =E41/10^6 -> 2.4281873 | C11: =F41 -> 4235.6044 | D11: =IF($B$12=0,0,B11/$B$12) -> 0.74291899
A12: Total biaya produksi | B12: =E43/10^6 -> 3.2684416 | C12: =F43 -> 5701.3005 | D12: =IF($B$12=0,0,B12/$B$12) -> 1
A13: Produksi (kg; satuan FG) | B13: =B21 -> 573.28 | C13: =C21 -> 7166
A14: HPP (Rp jt) dan HPP per satuan terjual | B14: =D54/10^6 -> 3.2684416 | C14: =C55 -> 456.10404
A15: Pendapatan (Rp jt) dan harga per satuan | B15: =$C$118/10^6 -> 2.8664 | C15: =IF($C$117=0,0,$C$118/$C$117) -> 400
A16: Margin kotor (Rp jt; %) | B16: =B15-B14 -> -0.40204155 | C16: =IF(B15=0,0,B16/B15) -> -0.1402601
A18: 2. Laporan biaya produksi
A19: 2a. Kuantitas
A20: Pos | B20: Kg | C20: Satuan FG (bag) | D20: Keterangan
A21: Output produksi | B21: =$C$102 -> 573.28 | C21: =$C$103 -> 7166
A22: Sampel | B22: =$C$104 -> 1.92 | C22: =$C$105 -> 24 | D22: memo, tidak masuk barang jadi
A23: Input FCC premium | B23: =SUMIF($B$128:$B$131,"FCC",$C$128:$C$131) -> 0 | D23: Lampiran B
A24: Input KW 2 FCC | B24: =SUMIF($B$128:$B$131,"KW2",$C$128:$C$131) -> 0 | D24: Lampiran B
A25: Input KW 2 ubi | B25: =SUMIF($B$128:$B$131,"KW2UBI",$C$128:$C$131) -> 0 | D25: Lampiran B
A26: Rendemen output ÷ input keripik (kg/kg) | B26: =IF(SUM(B23:B25)=0,0,B21/SUM(B23:B25)) -> 0
A28: 2b. Biaya produksi bulan ini (aktual)
A29: Komponen | B29: Qty / driver | C29: Satuan | D29: Harga / porsi | E29: Nilai (Rp) | F29: Rp/kg | G29: Dasar
A30: Bahan
A31: FCC premium (antarproduk) | B31: =B23 -> 0 | C31: kg | D31: =FCC!$D$89 -> 23872.948 | E31: =B31*D31 -> 0 | F31: =IF($B$21=0,0,E31/$B$21) -> 0 | G31: Biaya rata-rata FG FCC kartu baru (FCC D88)
A32: KW 2 FCC (antarproduk, NRV) | B32: =B24 -> 0 | C32: kg | D32: =FCC!$C$209 -> 9777.2712 | E32: =B32*D32 -> 0 | F32: =IF($B$21=0,0,E32/$B$21) -> 0 | G32: NRV KW 2 (FCC C208)
A33: KW 2 ubi (antarproduk) | B33: =B25 -> 0 | C33: kg | D33: ='LAIN-LAIN'!$C$7 -> 0 | E33: =B33*D33 -> 0 | F33: =IF($B$21=0,0,E33/$B$21) -> 0 | G33: Nilai KW 2 ubi (LAIN-LAIN C7)
A34: Material eksternal (Lampiran B) | E34: =SUMIF($B$128:$B$131,"EXT",$F$128:$F$131) -> 26546.057 | F34: =IF($B$21=0,0,E34/$B$21) -> 46.305569 | G34: Nilai kartu per baris material
A35: Subtotal bahan | E35: =SUM(E31:E34) -> 26546.057 | F35: =IF($B$21=0,0,E35/$B$21) -> 46.305569
A36: Konversi (pool BIAYA BERSAMA, porsi Lain-lain dibagi dengan driver yang sama dengan sheet LAIN-LAIN)
A37: Grup A – DL operator | B37: =$C$106 -> 37.4699 | C37: jam | D37: =IF('LAIN-LAIN'!$H$43=0,0,B37/'LAIN-LAIN'!$H$43) -> 0.013933734 | E37: =D37*'BIAYA BERSAMA'!$F$115 -> 813708.18 | F37: =IF($B$21=0,0,E37/$B$21) -> 1419.3905 | G37: Man-hour ÷ total man-hour Lain-lain × pool Grup A Lain-lain
A38: Grup B – IDL (support, staf, THR, BPJS) | B38: =$C$106 -> 37.4699 | C38: jam | D38: =IF('LAIN-LAIN'!$H$43=0,0,B38/'LAIN-LAIN'!$H$43) -> 0.013933734 | E38: =D38*'BIAYA BERSAMA'!$F$117 -> 727455.11 | F38: =IF($B$21=0,0,E38/$B$21) -> 1268.9351 | G38: Man-hour
A39: Grup C + D – energi (kWh) dan mesin (bagging: kWh; Ubi putih ACE: jam mesin) | B39: =$C$107 -> 203.5269 | C39: kWh | D39: =IF('LAIN-LAIN'!$I$43=0,0,B39/'LAIN-LAIN'!$I$43) -> 0.020115211 | E39: =D39*'BIAYA BERSAMA'!$F$118+IF('BIAYA BERSAMA'!$F$172=0,0,B39/'BIAYA BERSAMA'!$F$172)*'BIAYA BERSAMA'!$F$176 -> 1699137.8 | F39: =IF($B$21=0,0,E39/$B$21) -> 2963.8881 | G39: kWh
A40: Grup E – pabrik umum | B40: =E34 -> 26546.057 | C40: Rp | D40: =IF('LAIN-LAIN'!$G$43=0,0,B40/'LAIN-LAIN'!$G$43) -> 0.00034622152 | E40: =D40*'BIAYA BERSAMA'!$F$120 -> 1594.4244 | F40: =IF($B$21=0,0,E40/$B$21) -> 2.7812314 | G40: Nilai material eksternal
A41: Subtotal factory overhead (Grup B–E) | E41: =SUM(E38:E40) -> 2428187.3 | F41: =IF($B$21=0,0,E41/$B$21) -> 4235.6044
A42: Total konversi | E42: =E37+E41 -> 3241895.5 | F42: =IF($B$21=0,0,E42/$B$21) -> 5654.9949
A43: TOTAL BIAYA PRODUKSI BULAN INI | E43: =E35+E42 -> 3268441.6 | F43: =IF($B$21=0,0,E43/$B$21) -> 5701.3005
A45: 3. Barang jadi (FG-153 Maicih Basreng 80 Gr-Level 10) dan HPP
A46: Pos | B46: Qty (bag) | C46: Rp/satuan | D46: Nilai WP (Rp) | E46: Qty Accurate | F46: Nilai Accurate (Rp) | G46: Selisih nilai WP − Accurate
A47: Saldo awal | B47: =$C$108 -> 0 | D47: =$C$109 -> 0 | E47: =$C$108 -> 0 | F47: =$C$110 -> -0.12 | G47: =D47-F47 -> 0.12
A48: Masuk dari produksi | B48: =C21 -> 7166 | D48: =E43 -> 3268441.6 | E48: =$C$111 -> 7166 | F48: =$C$112 -> 918515.67 | G48: =D48-F48 -> 2349925.9
A49: Tersedia | B49: =B47+B48 -> 7166 | D49: =D47+D48 -> 3268441.6 | E49: =E47+E48 -> 7166 | F49: =F47+F48 -> 918515.55 | G49: =D49-F49 -> 2349926
A50: Biaya rata-rata tertimbang per satuan | C50: =IF(B49=0,0,D49/B49) -> 456.10404
A51: Keluar: penjualan (pengiriman pesanan) | B51: =$C$113 -> 7166 | D51: =B51*$C$50 -> 3268441.6 | E51: =$C$113 -> 7166 | F51: =$C$114 -> 918515.66 | G51: =D51-F51 -> 2349925.9
A52: Saldo akhir (qty menurut Accurate) | B52: =$C$115 -> 0 | D52: =B52*$C$50 -> 0 | E52: =$C$115 -> 0 | F52: =$C$116 -> -0.12 | G52: =D52-F52 -> 0.12
A53: Selisih kuantitas (tersedia − penjualan − saldo akhir) ke HPP | B53: =B49-B51-B52 -> 0 | D53: =B53*$C$50 -> 0 | E53: =E49-E51-E52 -> 0 | F53: =F49-F51-F52 -> 0.01 | G53: =D53-F53 -> -0.01
A54: HPP (penjualan + selisih kuantitas) | D54: =D51+D53 -> 3268441.6 | F54: =F51+F53 -> 918515.67 | G54: =D54-F54 -> 2349925.9
A55: HPP per satuan terjual | C55: =IF(B51=0,0,D54/B51) -> 456.10404
A56: Memo: penjualan Sales By Item − pengiriman Accurate (qty) | B56: =$C$117-B51 -> 0
A57: Memo: produksi kartu − masuk menurut Accurate (qty) | B57: =B48-E48 -> 0
A59: 4. Pembanding kartu lama (WP CoGM)
A60: Komponen | B60: Kartu lama (Rp) | C60: WP (Rp) | D60: Selisih (Rp) | E60: Keterangan
A61: Material (DM + IDM) | B61: =$C$119 -> 26546.057 | C61: =E35 -> 26546.057 | D61: =C61-B61 -> -2.37524e-05 | E61: Kartu: FCC premium pada harga kartu lama; WP: pada biaya FCC kartu baru (FCC D88) dan KW 2 pada NRV
A62: Tenaga kerja (DL + IDL) | B62: =$C$120 -> 671841.54 | C62: =E37+E38 -> 1541163.3 | D62: =C62-B62 -> 869321.75 | E62: Kartu: man-hour × tarif; WP: pool Grup A + B
A63: Listrik / overhead | B63: =$C$121 -> 220127.9 | C63: =E39+E40 -> 1700732.2 | D63: =C63-B63 -> 1480604.3 | E63: Kartu: kWh × tarif; WP: pool Grup C, D, E
A64: Total biaya produksi | B64: =SUM(B61:B63) -> 918515.5 | C64: =SUM(C61:C63) -> 3268441.6 | D64: =C64-B64 -> 2349926.1
A65: Man-hour: kartu lama vs driver Labor | B65: =$C$122 -> 37.4699 | C65: =$C$106 -> 37.4699 | D65: =C65-B65 -> 0
A66: kWh: kartu lama vs driver Overhead Allocation | B66: =$C$123 -> 203.5269 | C66: =$C$107 -> 203.5269 | D66: =C66-B66 -> 0
A68: 5. Kontrol (toleransi Rp 1; 0,01 qty)
A69: Cek | B69: Nilai | C69: Status
A70: Material eksternal di 2b = Lampiran B kelompok EXT | B70: =E34-SUMIF($B$128:$B$131,"EXT",$F$128:$F$131) -> 0 | C70: =IF(ISERROR(B70),"GAGAL",IF(ABS(B70)<=1,"LULUS","GAGAL")) -> LULUS
A71: Semua baris Lampiran B punya kelompok yang dikenal | B71: =COUNTA($A$128:$A$131)-COUNTIF($B$128:$B$131,"FCC")-COUNTIF($B$128:$B$131,"KW2")-COUNTIF($B$128:$B$131,"KW2UBI")-COUNTIF($B$128:$B$131,"EXT") -> 0 | C71: =IF(ISERROR(B71),"GAGAL",IF(ABS(B71)<=0.5,"LULUS","GAGAL")) -> LULUS
A72: Total biaya = bahan + konversi | B72: =E43-E35-E42 -> 0 | C72: =IF(ISERROR(B72),"GAGAL",IF(ABS(B72)<=1,"LULUS","GAGAL")) -> LULUS
A73: Barang jadi: tersedia = penjualan + saldo akhir + selisih kuantitas (Rp) | B73: =D49-D51-D52-D53 -> 0 | C73: =IF(ISERROR(B73),"GAGAL",IF(ABS(B73)<=1,"LULUS","GAGAL")) -> LULUS
A74: Ringkasan = 2b (Rp jt) | B74: =B12*10^6-E43 -> 0 | C74: =IF(ISERROR(B74),"GAGAL",IF(ABS(B74)<=1,"LULUS","GAGAL")) -> LULUS
A75: Tidak ada sel error | B75: =SUMPRODUCT(--ISERROR(A5:H66)) -> 0 | C75: =IF(ISERROR(B75),"GAGAL",IF(ABS(B75)<=0.5,"LULUS","GAGAL")) -> LULUS
A76: Info (bukan kontrol): selisih kuantitas barang jadi (B53) dan memo B56–B57 menunjukkan beda kartu vs Accurate.
A100: LAMPIRAN A. Input bulan ini
A101: Pos | B101: Satuan | C101: Nilai | D101: Status angka | E101: Sumber
A102: Output produksi | B102: kg | C102: 573.28 | D102: Aktual | E102: Kartu E7 (kg)
A103: Output produksi | B103: bag | C103: 7166 | D103: Aktual | E103: Kartu E6 (bag)
A104: Sampel | B104: kg | C104: 1.92 | D104: Aktual | E104: Kartu E10
A105: Sampel | B105: bag | C105: 24 | D105: Aktual | E105: Kartu E9
A106: Man-hour (driver Grup A & B) | B106: jam | C106: 37.4699 | D106: Aktual | E106: Labor: LAP BAG MAICIH BASRENG LV 10 LOK
A107: Pemakaian listrik (driver Grup C & D) | B107: kWh | C107: 203.5269 | D107: Aktual | E107: Overhead Allocation: LAP BAG MAICIH BASRENG LV 10 LOK
A108: Saldo awal FG-153 | B108: bag | C108: 0 | D108: Aktual | E108: Inventory Valuation (Kts. saldo awal bulan)
A109: Nilai saldo awal FG-153 (WP) | B109: Rp | C109: 0 | D109: Roll-forward | E109: Roll-forward: WP DI - WP Costing BMG Agu26_4.xlsx sheet MCH BASRENG L10 D52 (saldo akhir WP)
A110: Nilai saldo awal FG-153 menurut Accurate | B110: Rp | C110: -0.12 | D110: Aktual | E110: Inventory Valuation
A111: Masuk FG-153 menurut Accurate (penyesuaian masuk − keluar) | B111: bag | C111: 7166 | D111: Aktual | E111: Inventory Valuation, Penyesuaian persediaan
A112: Nilai masuk FG-153 menurut Accurate | B112: Rp | C112: 918515.67 | D112: Aktual | E112: Inventory Valuation, Penyesuaian persediaan
A113: Keluar FG-153: pengiriman pesanan | B113: bag | C113: 7166 | D113: Aktual | E113: Inventory Valuation, Pengiriman Pesanan
... A123: Kartu lama: kWh di operasi | B123: kWh | C123: 203.5269 | D123: Aktual | E123: Kartu, baris Operation (Elc)
A126: LAMPIRAN B. Material per baris kartu (qty kartu; nilai kartu = qty × harga kartu)
A127: Material | B127: Kelompok | C127: Qty | D127: Satuan | E127: Harga kartu | F127: Nilai kartu (Rp) | G127: Sumber
A128: Basreng Bumbu Level 10 Maichi | B128: EXT | C128: 580 | D128: kg | E128: 0 | F128: 0 | G128: Kartu C13:R13; kelompok: Eksternal
A129: Polyfilm Maichi Basreng Level 10 | B129: EXT | C129: 71.06 | D129: kg | E129: 0 | F129: 0 | G129: Kartu C14:R14; kelompok: Eksternal
A130: Karton Maicih | B130: EXT | C130: 287 | D130: pcs | E130: 0 | F130: 0 | G130: Kartu C15:R15; kelompok: Eksternal
A131: Plakban Ukuran 100 Yard | B131: EXT | C131: 4.0221298 | D131: roll | E131: 6600 | F131: 26546.057 | G131: Kartu C16:R16; kelompok: Eksternal
A132: Total | F132: =SUM(F128:F131) -> 26546.057
A133: Kode kelompok: FCC = FCC premium (dinilai ulang pada biaya FCC kartu baru), KW2 = KW 2 FCC (NRV), KW2UBI = KW 2 ubi, EXT = material eksternal (nilai kartu).

Sheet MCH KERIPIK LV3
A1: KARTU BIAYA PRODUKSI – Maicih Keripik Singkong 80 gr Level 3, September 2026
A2: Sumber: kartu 'LAP BAG MAICIH KERIPIK LV 3' di WP CoGM September 2026; driver man-hour & kWh: sheet Labor & Overhead Allocation; barang jadi: Inventory Valuation Accurate FG-110; pendapatan: LK Sales By Item.
A4: Status kontrol (bagian 5) | C4: =IF(COUNTIF(C70:C75,"GAGAL")=0,"LULUS","GAGAL") -> LULUS
A5: 1. Ringkasan (Rp juta; Rp/kg per kg produksi bulan ini)
A6: Komponen | B6: Aktual (Rp jt) | C6: Rp/kg | D6: Porsi
A7: FCC premium (antarproduk) | B7: =E31/10^6 -> 15.09964 | C7: =F31 -> 7680.3864 | D7: =IF($B$12=0,0,B7/$B$12) -> 0.3805313
A8: KW 2 (antarproduk, NRV) | B8: =(E32+E33)/10^6 -> 12.042077 | C8: =F32+F33 -> 6125.1663 | D8: =IF($B$12=0,0,B8/$B$12) -> 0.3034766
A9: Material eksternal | B9: =E34/10^6 -> 0.40595813 | C9: =F34 -> 206.48939 | D9: =IF($B$12=0,0,B9/$B$12) -> 0.010230693
A10: Direct labour (Grup A) | B10: =E37/10^6 -> 2.8247628 | C10: =F37 -> 1436.8071 | D10: =IF($B$12=0,0,B10/$B$12) -> 0.071187836
A11: Factory overhead (Grup B–E) | B11: =E41/10^6 -> 9.3079767 | C11: =F41 -> 4734.4744 | D11: =IF($B$12=0,0,B11/$B$12) -> 0.23457358
A12: Total biaya produksi | B12: =E43/10^6 -> 39.680414 | C12: =F43 -> 20183.324 | D12: =IF($B$12=0,0,B12/$B$12) -> 1
A13: Produksi (kg; satuan FG) | B13: =B21 -> 1966 | C13: =C21 -> 24575
A14: HPP (Rp jt) dan HPP per satuan terjual | B14: =D54/10^6 -> 39.680414 | C14: =C55 -> 1614.6659
A15: Pendapatan (Rp jt) dan harga per satuan | B15: =$C$118/10^6 -> 55.85 | C15: =IF($C$117=0,0,$C$118/$C$117) -> 2272.6348
A16: Margin kotor (Rp jt; %) | B16: =B15-B14 -> 16.169586 | C16: =IF(B15=0,0,B16/B15) -> 0.2895181
A18: 2. Laporan biaya produksi
A19: 2a. Kuantitas
A20: Pos | B20: Kg | C20: Satuan FG (bag) | D20: Keterangan
A21: Output produksi | B21: =$C$102 -> 1966 | C21: =$C$103 -> 24575
A22: Sampel | B22: =$C$104 -> 1.92 | C22: =$C$105 -> 24 | D22: memo, tidak masuk barang jadi
A23: Input FCC premium | B23: =SUMIF($B$128:$B$134,"FCC",$C$128:$C$134) -> 632.5 | D23: Lampiran B
A24: Input KW 2 FCC | B24: =SUMIF($B$128:$B$134,"KW2",$C$128:$C$134) -> 1231.6399 | D24: Lampiran B
A25: Input KW 2 ubi | B25: =SUMIF($B$128:$B$134,"KW2UBI",$C$128:$C$134) -> 0 | D25: Lampiran B
A26: Rendemen output ÷ input keripik (kg/kg) | B26: =IF(SUM(B23:B25)=0,0,B21/SUM(B23:B25)) -> 1.0546419
A28: 2b. Biaya produksi bulan ini (aktual)
A29: Komponen | B29: Qty / driver | C29: Satuan | D29: Harga / porsi | E29: Nilai (Rp) | F29: Rp/kg | G29: Dasar
A30: Bahan
A31: FCC premium (antarproduk) | B31: =B23 -> 632.5 | C31: kg | D31: =FCC!$D$89 -> 23872.948 | E31: =B31*D31 -> 15099640 | F31: =IF($B$21=0,0,E31/$B$21) -> 7680.3864 | G31: Biaya rata-rata FG FCC kartu baru (FCC D88)
A32: KW 2 FCC (antarproduk, NRV) | B32: =B24 -> 1231.6399 | C32: kg | D32: =FCC!$C$209 -> 9777.2712 | E32: =B32*D32 -> 12042077 | F32: =IF($B$21=0,0,E32/$B$21) -> 6125.1663 | G32: NRV KW 2 (FCC C208)
A33: KW 2 ubi (antarproduk) | B33: =B25 -> 0 | C33: kg | D33: ='LAIN-LAIN'!$C$7 -> 0 | E33: =B33*D33 -> 0 | F33: =IF($B$21=0,0,E33/$B$21) -> 0 | G33: Nilai KW 2 ubi (LAIN-LAIN C7)
A34: Material eksternal (Lampiran B) | E34: =SUMIF($B$128:$B$134,"EXT",$F$128:$F$134) -> 405958.13 | F34: =IF($B$21=0,0,E34/$B$21) -> 206.48939 | G34: Nilai kartu per baris material
A35: Subtotal bahan | E35: =SUM(E31:E34) -> 27547675 | F35: =IF($B$21=0,0,E35/$B$21) -> 14012.042
A36: Konversi (pool BIAYA BERSAMA, porsi Lain-lain dibagi dengan driver yang sama dengan sheet LAIN-LAIN)
A37: Grup A – DL operator | B37: =$C$106 -> 130.0756 | C37: jam | D37: =IF('LAIN-LAIN'!$H$43=0,0,B37/'LAIN-LAIN'!$H$43) -> 0.048370528 | E37: =D37*'BIAYA BERSAMA'!$F$115 -> 2824762.8 | F37: =IF($B$21=0,0,E37/$B$21) -> 1436.8071 | G37: Man-hour ÷ total man-hour Lain-lain × pool Grup A Lain-lain
A38: Grup B – IDL (support, staf, THR, BPJS) | B38: =$C$106 -> 130.0756 | C38: jam | D38: =IF('LAIN-LAIN'!$H$43=0,0,B38/'LAIN-LAIN'!$H$43) -> 0.048370528 | E38: =D38*'BIAYA BERSAMA'!$F$117 -> 2525338 | F38: =IF($B$21=0,0,E38/$B$21) -> 1284.5056 | G38: Man-hour
A39: Grup C + D – energi (kWh) dan mesin (bagging: kWh; Ubi putih ACE: jam mesin) | B39: =$C$107 -> 809.5205 | C39: kWh | D39: =IF('LAIN-LAIN'!$I$43=0,0,B39/'LAIN-LAIN'!$I$43) -> 0.080007488 | E39: =D39*'BIAYA BERSAMA'!$F$118+IF('BIAYA BERSAMA'!$F$172=0,0,B39/'BIAYA BERSAMA'!$F$172)*'BIAYA BERSAMA'!$F$176 -> 6758255.8 | F39: =IF($B$21=0,0,E39/$B$21) -> 3437.5666 | G39: kWh
A40: Grup E – pabrik umum | B40: =E34 -> 405958.13 | C40: Rp | D40: =IF('LAIN-LAIN'!$G$43=0,0,B40/'LAIN-LAIN'!$G$43) -> 0.005294626 | E40: =D40*'BIAYA BERSAMA'!$F$120 -> 24382.888 | F40: =IF($B$21=0,0,E40/$B$21) -> 12.402283 | G40: Nilai material eksternal
A41: Subtotal factory overhead (Grup B–E) | E41: =SUM(E38:E40) -> 9307976.7 | F41: =IF($B$21=0,0,E41/$B$21) -> 4734.4744
A42: Total konversi | E42: =E37+E41 -> 12132739 | F42: =IF($B$21=0,0,E42/$B$21) -> 6171.2815
A43: TOTAL BIAYA PRODUKSI BULAN INI | E43: =E35+E42 -> 39680414 | F43: =IF($B$21=0,0,E43/$B$21) -> 20183.324
A45: 3. Barang jadi (FG-110 Maicih Keripik Singkong 80gr-Level 3) dan HPP
A46: Pos | B46: Qty (bag) | C46: Rp/satuan | D46: Nilai WP (Rp) | E46: Qty Accurate | F46: Nilai Accurate (Rp) | G46: Selisih nilai WP − Accurate
A47: Saldo awal | B47: =$C$108 -> 0 | D47: =$C$109 -> 0 | E47: =$C$108 -> 0 | F47: =$C$110 -> -0.42 | G47: =D47-F47 -> 0.42
A48: Masuk dari produksi | B48: =C21 -> 24575 | D48: =E43 -> 39680414 | E48: =$C$111 -> 24575 | F48: =$C$112 -> 18102879 | G48: =D48-F48 -> 21577535
A49: Tersedia | B49: =B47+B48 -> 24575 | D49: =D47+D48 -> 39680414 | E49: =E47+E48 -> 24575 | F49: =F47+F48 -> 18102878 | G49: =D49-F49 -> 21577536
A50: Biaya rata-rata tertimbang per satuan | C50: =IF(B49=0,0,D49/B49) -> 1614.6659
A51: Keluar: penjualan (pengiriman pesanan) | B51: =$C$113 -> 24575 | D51: =B51*$C$50 -> 39680414 | E51: =$C$113 -> 24575 | F51: =$C$114 -> 18102879 | G51: =D51-F51 -> 21577535
A52: Saldo akhir (qty menurut Accurate) | B52: =$C$115 -> 0 | D52: =B52*$C$50 -> 0 | E52: =$C$115 -> 0 | F52: =$C$116 -> -0.42 | G52: =D52-F52 -> 0.42
A53: Selisih kuantitas (tersedia − penjualan − saldo akhir) ke HPP | B53: =B49-B51-B52 -> 0 | D53: =B53*$C$50 -> 0 | E53: =E49-E51-E52 -> 0 | F53: =F49-F51-F52 -> -1.7881394e-09 | G53: =D53-F53 -> 1.7881394e-09
A54: HPP (penjualan + selisih kuantitas) | D54: =D51+D53 -> 39680414 | F54: =F51+F53 -> 18102879 | G54: =D54-F54 -> 21577535
A55: HPP per satuan terjual | C55: =IF(B51=0,0,D54/B51) -> 1614.6659
A56: Memo: penjualan Sales By Item − pengiriman Accurate (qty) | B56: =$C$117-B51 -> 0
A57: Memo: produksi kartu − masuk menurut Accurate (qty) | B57: =B48-E48 -> 0
A59: 4. Pembanding kartu lama (WP CoGM)
A60: Komponen | B60: Kartu lama (Rp) | C60: WP (Rp) | D60: Selisih (Rp) | E60: Keterangan
A61: Material (DM + IDM) | B61: =$C$119 -> 13997465 | C61: =E35 -> 27547675 | D61: =C61-B61 -> 13550210 | E61: Kartu: FCC premium pada harga kartu lama; WP: pada biaya FCC kartu baru (FCC D88) dan KW 2 pada NRV
A62: Tenaga kerja (DL + IDL) | B62: =$C$120 -> 3606680.1 | C62: =E37+E38 -> 5350100.8 | D62: =C62-B62 -> 1743420.7 | E62: Kartu: man-hour × tarif; WP: pool Grup A + B
A63: Listrik / overhead | B63: =$C$121 -> 875550.13 | C63: =E39+E40 -> 6782638.7 | D63: =C63-B63 -> 5907088.6 | E63: Kartu: kWh × tarif; WP: pool Grup C, D, E
A64: Total biaya produksi | B64: =SUM(B61:B63) -> 18479695 | C64: =SUM(C61:C63) -> 39680414 | D64: =C64-B64 -> 21200719
A65: Man-hour: kartu lama vs driver Labor | B65: =$C$122 -> 201.1514 | C65: =$C$106 -> 130.0756 | D65: =C65-B65 -> -71.0758
A66: kWh: kartu lama vs driver Overhead Allocation | B66: =$C$123 -> 809.5205 | C66: =$C$107 -> 809.5205 | D66: =C66-B66 -> 0
A68: 5. Kontrol (toleransi Rp 1; 0,01 qty)
A69: Cek | B69: Nilai | C69: Status
A70: Material eksternal di 2b = Lampiran B kelompok EXT | B70: =E34-SUMIF($B$128:$B$134,"EXT",$F$128:$F$134) -> 0 | C70: =IF(ISERROR(B70),"GAGAL",IF(ABS(B70)<=1,"LULUS","GAGAL")) -> LULUS
A71: Semua baris Lampiran B punya kelompok yang dikenal | B71: =COUNTA($A$128:$A$134)-COUNTIF($B$128:$B$134,"FCC")-COUNTIF($B$128:$B$134,"KW2")-COUNTIF($B$128:$B$134,"KW2UBI")-COUNTIF($B$128:$B$134,"EXT") -> 0 | C71: =IF(ISERROR(B71),"GAGAL",IF(ABS(B71)<=0.5,"LULUS","GAGAL")) -> LULUS
A72: Total biaya = bahan + konversi | B72: =E43-E35-E42 -> 0 | C72: =IF(ISERROR(B72),"GAGAL",IF(ABS(B72)<=1,"LULUS","GAGAL")) -> LULUS
A73: Barang jadi: tersedia = penjualan + saldo akhir + selisih kuantitas (Rp) | B73: =D49-D51-D52-D53 -> 0 | C73: =IF(ISERROR(B73),"GAGAL",IF(ABS(B73)<=1,"LULUS","GAGAL")) -> LULUS
A74: Ringkasan = 2b (Rp jt) | B74: =B12*10^6-E43 -> 0 | C74: =IF(ISERROR(B74),"GAGAL",IF(ABS(B74)<=1,"LULUS","GAGAL")) -> LULUS
A75: Tidak ada sel error | B75: =SUMPRODUCT(--ISERROR(A5:H66)) -> 0 | C75: =IF(ISERROR(B75),"GAGAL",IF(ABS(B75)<=0.5,"LULUS","GAGAL")) -> LULUS
A76: Info (bukan kontrol): selisih kuantitas barang jadi (B53) dan memo B56–B57 menunjukkan beda kartu vs Accurate.
A100: LAMPIRAN A. Input bulan ini
A101: Pos | B101: Satuan | C101: Nilai | D101: Status angka | E101: Sumber
A102: Output produksi | B102: kg | C102: 1966 | D102: Aktual | E102: Kartu E7 (kg)
A103: Output produksi | B103: bag | C103: 24575 | D103: Aktual | E103: Kartu E6 (bag)
A104: Sampel | B104: kg | C104: 1.92 | D104: Aktual | E104: Kartu E10
A105: Sampel | B105: bag | C105: 24 | D105: Aktual | E105: Kartu E9
A106: Man-hour (driver Grup A & B) | B106: jam | C106: 130.0756 | D106: Aktual | E106: Labor: LAP BAG MAICIH KERIPIK LV 3 M
A107: Pemakaian listrik (driver Grup C & D) | B107: kWh | C107: 809.5205 | D107: Aktual | E107: Overhead Allocation: LAP BAG MAICIH KERIPIK LV 3 SA
A108: Saldo awal FG-110 | B108: bag | C108: 0 | D108: Aktual | E108: Inventory Valuation (Kts. saldo awal bulan)
A109: Nilai saldo awal FG-110 (WP) | B109: Rp | C109: 0 | D109: Roll-forward | E109: Roll-forward: WP DI - WP Costing BMG Agu26_4.xlsx sheet MCH KERIPIK LV3 D52 (saldo akhir WP)
A110: Nilai saldo awal FG-110 menurut Accurate | B110: Rp | C110: -0.42 | D110: Aktual | E110: Inventory Valuation
A111: Masuk FG-110 menurut Accurate (penyesuaian masuk − keluar) | B111: bag | C111: 24575 | D111: Aktual | E111: Inventory Valuation, Penyesuaian persediaan
A112: Nilai masuk FG-110 menurut Accurate | B112: Rp | C112: 18102879 | D112: Aktual | E112: Inventory Valuation, Penyesuaian persediaan
A113: Keluar FG-110: pengiriman pesanan | B113: bag | C113: 24575 | D113: Aktual | E113: Inventory Valuation, Pengiriman Pesanan
... A123: Kartu lama: kWh di operasi | B123: kWh | C123: 809.5205 | D123: Aktual | E123: Kartu, baris Operation (Elc)
A126: LAMPIRAN B. Material per baris kartu (qty kartu; nilai kartu = qty × harga kartu)
A127: Material | B127: Kelompok | C127: Qty | D127: Satuan | E127: Harga kartu | F127: Nilai kartu (Rp) | G127: Sumber
A128: Keripik Singkong Kw 2 | B128: KW2 | C128: 1231.6399 | D128: kg | E128: 0 | F128: 0 | G128: Kartu C13:R13; kelompok: KW 2 FCC (antarproduk, NRV)
A129: Keripik Singkong Premium | B129: FCC | C129: 632.5 | D129: kg | E129: 21488.548 | F129: 13591507 | G129: Kartu C14:R14; kelompok: FCC premium (antarproduk)
A130: Bumbu Maicih Level 3 | B130: EXT | C130: 146.1 | D130: kg | E130: 0 | F130: 0 | G130: Kartu C15:R15; kelompok: Eksternal
A131: Polyfilm Maichi Keripik Singkong Level-3 | B131: EXT | C131: 197.01 | D131: kg | E131: 0 | F131: 0 | G131: Kartu C16:R16; kelompok: Eksternal
A132: Karton Maicih | B132: EXT | C132: 985 | D132: pcs | E132: 0 | F132: 0 | G132: Kartu C17:R17; kelompok: Eksternal
A133: Plakban Ukuran 100 Yard | B133: EXT | C133: 13.733326 | D133: roll | E133: 6600 | F133: 90639.95 | G133: Kartu C18:R18; kelompok: Eksternal
A134: CNG | B134: EXT | C134: 31.084264 | D134: m³ | E134: 10143.981 | F134: 315318.18 | G134: Kartu C19:R19; kelompok: Eksternal
A135: Total | F135: =SUM(F128:F134) -> 13997465
A136: Kode kelompok: FCC = FCC premium (dinilai ulang pada biaya FCC kartu baru), KW2 = KW 2 FCC (NRV), KW2UBI = KW 2 ubi, EXT = material eksternal (nilai kartu).

Sheet MCH KERIPIK LV10
A1: KARTU BIAYA PRODUKSI – Maicih Keripik Singkong 80 gr Level 10, September 2026
A2: Sumber: kartu 'LAP BAG MAICIH KERIPIK LV 10' di WP CoGM September 2026; driver man-hour & kWh: sheet Labor & Overhead Allocation; barang jadi: Inventory Valuation Accurate FG-111; pendapatan: LK Sales By Item.
A4: Status kontrol (bagian 5) | C4: =IF(COUNTIF(C70:C75,"GAGAL")=0,"LULUS","GAGAL") -> LULUS
A5: 1. Ringkasan (Rp juta; Rp/kg per kg produksi bulan ini)
A6: Komponen | B6: Aktual (Rp jt) | C6: Rp/kg | D6: Porsi
A7: FCC premium (antarproduk) | B7: =E31/10^6 -> 35.582629 | C7: =F31 -> 17365.512 | D7: =IF($B$12=0,0,B7/$B$12) -> 0.69552833
A8: KW 2 (antarproduk, NRV) | B8: =(E32+E33)/10^6 -> 3.8731827 | C8: =F32+F33 -> 1890.2426 | D8: =IF($B$12=0,0,B8/$B$12) -> 0.075708522
A9: Material eksternal | B9: =E34/10^6 -> 0.19898291 | C9: =F34 -> 97.110309 | D9: =IF($B$12=0,0,B9/$B$12) -> 0.0038894891
A10: Direct labour (Grup A) | B10: =E37/10^6 -> 2.7704221 | C10: =F37 -> 1352.0586 | D10: =IF($B$12=0,0,B10/$B$12) -> 0.054153026
A11: Factory overhead (Grup B–E) | B11: =E41/10^6 -> 8.7339204 | C11: =F41 -> 4262.445 | D11: =IF($B$12=0,0,B11/$B$12) -> 0.17072064
A12: Total biaya produksi | B12: =E43/10^6 -> 51.159137 | C12: =F43 -> 24967.369 | D12: =IF($B$12=0,0,B12/$B$12) -> 1
A13: Produksi (kg; satuan FG) | B13: =B21 -> 2049.04 | C13: =C21 -> 25613
A14: HPP (Rp jt) dan HPP per satuan terjual | B14: =D54/10^6 -> 51.159137 | C14: =C55 -> 1997.3895
A15: Pendapatan (Rp jt) dan harga per satuan | B15: =$C$118/10^6 -> 67.482 | C15: =IF($C$117=0,0,$C$118/$C$117) -> 2634.6777
A16: Margin kotor (Rp jt; %) | B16: =B15-B14 -> 16.322863 | C16: =IF(B15=0,0,B16/B15) -> 0.2418847
A18: 2. Laporan biaya produksi
A19: 2a. Kuantitas
A20: Pos | B20: Kg | C20: Satuan FG (bag) | D20: Keterangan
A21: Output produksi | B21: =$C$102 -> 2049.04 | C21: =$C$103 -> 25613
A22: Sampel | B22: =$C$104 -> 1.92 | C22: =$C$105 -> 24 | D22: memo, tidak masuk barang jadi
A23: Input FCC premium | B23: =SUMIF($B$128:$B$134,"FCC",$C$128:$C$134) -> 1490.5 | D23: Lampiran B
A24: Input KW 2 FCC | B24: =SUMIF($B$128:$B$134,"KW2",$C$128:$C$134) -> 396.14148 | D24: Lampiran B
A25: Input KW 2 ubi | B25: =SUMIF($B$128:$B$134,"KW2UBI",$C$128:$C$134) -> 0 | D25: Lampiran B
A26: Rendemen output ÷ input keripik (kg/kg) | B26: =IF(SUM(B23:B25)=0,0,B21/SUM(B23:B25)) -> 1.0860781
A28: 2b. Biaya produksi bulan ini (aktual)
A29: Komponen | B29: Qty / driver | C29: Satuan | D29: Harga / porsi | E29: Nilai (Rp) | F29: Rp/kg | G29: Dasar
A30: Bahan
A31: FCC premium (antarproduk) | B31: =B23 -> 1490.5 | C31: kg | D31: =FCC!$D$89 -> 23872.948 | E31: =B31*D31 -> 35582629 | F31: =IF($B$21=0,0,E31/$B$21) -> 17365.512 | G31: Biaya rata-rata FG FCC kartu baru (FCC D88)
A32: KW 2 FCC (antarproduk, NRV) | B32: =B24 -> 396.14148 | C32: kg | D32: =FCC!$C$209 -> 9777.2712 | E32: =B32*D32 -> 3873182.7 | F32: =IF($B$21=0,0,E32/$B$21) -> 1890.2426 | G32: NRV KW 2 (FCC C208)
A33: KW 2 ubi (antarproduk) | B33: =B25 -> 0 | C33: kg | D33: ='LAIN-LAIN'!$C$7 -> 0 | E33: =B33*D33 -> 0 | F33: =IF($B$21=0,0,E33/$B$21) -> 0 | G33: Nilai KW 2 ubi (LAIN-LAIN C7)
A34: Material eksternal (Lampiran B) | E34: =SUMIF($B$128:$B$134,"EXT",$F$128:$F$134) -> 198982.91 | F34: =IF($B$21=0,0,E34/$B$21) -> 97.110309 | G34: Nilai kartu per baris material
A35: Subtotal bahan | E35: =SUM(E31:E34) -> 39654795 | F35: =IF($B$21=0,0,E35/$B$21) -> 19352.865
A36: Konversi (pool BIAYA BERSAMA, porsi Lain-lain dibagi dengan driver yang sama dengan sheet LAIN-LAIN)
A37: Grup A – DL operator | B37: =$C$106 -> 127.5733 | C37: jam | D37: =IF('LAIN-LAIN'!$H$43=0,0,B37/'LAIN-LAIN'!$H$43) -> 0.047440011 | E37: =D37*'BIAYA BERSAMA'!$F$115 -> 2770422.1 | F37: =IF($B$21=0,0,E37/$B$21) -> 1352.0586 | G37: Man-hour ÷ total man-hour Lain-lain × pool Grup A Lain-lain
A38: Grup B – IDL (support, staf, THR, BPJS) | B38: =$C$106 -> 127.5733 | C38: jam | D38: =IF('LAIN-LAIN'!$H$43=0,0,B38/'LAIN-LAIN'!$H$43) -> 0.047440011 | E38: =D38*'BIAYA BERSAMA'!$F$117 -> 2476757.3 | F38: =IF($B$21=0,0,E38/$B$21) -> 1208.7404 | G38: Man-hour
A39: Grup C + D – energi (kWh) dan mesin (bagging: kWh; Ubi putih ACE: jam mesin) | B39: =$C$107 -> 748.0668 | C39: kWh | D39: =IF('LAIN-LAIN'!$I$43=0,0,B39/'LAIN-LAIN'!$I$43) -> 0.073933823 | E39: =D39*'BIAYA BERSAMA'!$F$118+IF('BIAYA BERSAMA'!$F$172=0,0,B39/'BIAYA BERSAMA'!$F$172)*'BIAYA BERSAMA'!$F$176 -> 6245211.6 | F39: =IF($B$21=0,0,E39/$B$21) -> 3047.872 | G39: kWh
A40: Grup E – pabrik umum | B40: =E34 -> 198982.91 | C40: Rp | D40: =IF('LAIN-LAIN'!$G$43=0,0,B40/'LAIN-LAIN'!$G$43) -> 0.0025951939 | E40: =D40*'BIAYA BERSAMA'!$F$120 -> 11951.425 | F40: =IF($B$21=0,0,E40/$B$21) -> 5.8326946 | G40: Nilai material eksternal
A41: Subtotal factory overhead (Grup B–E) | E41: =SUM(E38:E40) -> 8733920.4 | F41: =IF($B$21=0,0,E41/$B$21) -> 4262.445
A42: Total konversi | E42: =E37+E41 -> 11504342 | F42: =IF($B$21=0,0,E42/$B$21) -> 5614.5036
A43: TOTAL BIAYA PRODUKSI BULAN INI | E43: =E35+E42 -> 51159137 | F43: =IF($B$21=0,0,E43/$B$21) -> 24967.369
A45: 3. Barang jadi (FG-111 Maicih Keripik Singkong 80gr-Level 10) dan HPP
A46: Pos | B46: Qty (bag) | C46: Rp/satuan | D46: Nilai WP (Rp) | E46: Qty Accurate | F46: Nilai Accurate (Rp) | G46: Selisih nilai WP − Accurate
A47: Saldo awal | B47: =$C$108 -> 0 | D47: =$C$109 -> 0 | E47: =$C$108 -> 0 | F47: =$C$110 -> -0.44 | G47: =D47-F47 -> 0.44
A48: Masuk dari produksi | B48: =C21 -> 25613 | D48: =E43 -> 51159137 | E48: =$C$111 -> 25613 | F48: =$C$112 -> 35155436 | G48: =D48-F48 -> 16003701
A49: Tersedia | B49: =B47+B48 -> 25613 | D49: =D47+D48 -> 51159137 | E49: =E47+E48 -> 25613 | F49: =F47+F48 -> 35155435 | G49: =D49-F49 -> 16003702
A50: Biaya rata-rata tertimbang per satuan | C50: =IF(B49=0,0,D49/B49) -> 1997.3895
A51: Keluar: penjualan (pengiriman pesanan) | B51: =$C$113 -> 25613 | D51: =B51*$C$50 -> 51159137 | E51: =$C$113 -> 25613 | F51: =$C$114 -> 35155436 | G51: =D51-F51 -> 16003701
A52: Saldo akhir (qty menurut Accurate) | B52: =$C$115 -> 0 | D52: =B52*$C$50 -> 0 | E52: =$C$115 -> 0 | F52: =$C$116 -> -0.44 | G52: =D52-F52 -> 0.44
A53: Selisih kuantitas (tersedia − penjualan − saldo akhir) ke HPP | B53: =B49-B51-B52 -> 0 | D53: =B53*$C$50 -> 0 | E53: =E49-E51-E52 -> 0 | F53: =F49-F51-F52 -> 2.3841858e-09 | G53: =D53-F53 -> -2.3841858e-09
A54: HPP (penjualan + selisih kuantitas) | D54: =D51+D53 -> 51159137 | F54: =F51+F53 -> 35155436 | G54: =D54-F54 -> 16003701
A55: HPP per satuan terjual | C55: =IF(B51=0,0,D54/B51) -> 1997.3895
A56: Memo: penjualan Sales By Item − pengiriman Accurate (qty) | B56: =$C$117-B51 -> 0
A57: Memo: produksi kartu − masuk menurut Accurate (qty) | B57: =B48-E48 -> 0
A59: 4. Pembanding kartu lama (WP CoGM)
A60: Komponen | B60: Kartu lama (Rp) | C60: WP (Rp) | D60: Selisih (Rp) | E60: Keterangan
A61: Material (DM + IDM) | B61: =$C$119 -> 32227664 | C61: =E35 -> 39654795 | D61: =C61-B61 -> 7427130.7 | E61: Kartu: FCC premium pada harga kartu lama; WP: pada biaya FCC kartu baru (FCC D88) dan KW 2 pada NRV
A62: Tenaga kerja (DL + IDL) | B62: =$C$120 -> 3006664.6 | C62: =E37+E38 -> 5247179.4 | D62: =C62-B62 -> 2240514.8 | E62: Kartu: man-hour × tarif; WP: pool Grup A + B
A63: Listrik / overhead | B63: =$C$121 -> 809083.89 | C63: =E39+E40 -> 6257163 | D63: =C63-B63 -> 5448079.1 | E63: Kartu: kWh × tarif; WP: pool Grup C, D, E
A64: Total biaya produksi | B64: =SUM(B61:B63) -> 36043412 | C64: =SUM(C61:C63) -> 51159137 | D64: =C64-B64 -> 15115725
A65: Man-hour: kartu lama vs driver Labor | B65: =$C$122 -> 167.6874 | C65: =$C$106 -> 127.5733 | D65: =C65-B65 -> -40.1141
A66: kWh: kartu lama vs driver Overhead Allocation | B66: =$C$123 -> 748.0668 | C66: =$C$107 -> 748.0668 | D66: =C66-B66 -> 0
A68: 5. Kontrol (toleransi Rp 1; 0,01 qty)
A69: Cek | B69: Nilai | C69: Status
A70: Material eksternal di 2b = Lampiran B kelompok EXT | B70: =E34-SUMIF($B$128:$B$134,"EXT",$F$128:$F$134) -> 0 | C70: =IF(ISERROR(B70),"GAGAL",IF(ABS(B70)<=1,"LULUS","GAGAL")) -> LULUS
A71: Semua baris Lampiran B punya kelompok yang dikenal | B71: =COUNTA($A$128:$A$134)-COUNTIF($B$128:$B$134,"FCC")-COUNTIF($B$128:$B$134,"KW2")-COUNTIF($B$128:$B$134,"KW2UBI")-COUNTIF($B$128:$B$134,"EXT") -> 0 | C71: =IF(ISERROR(B71),"GAGAL",IF(ABS(B71)<=0.5,"LULUS","GAGAL")) -> LULUS
A72: Total biaya = bahan + konversi | B72: =E43-E35-E42 -> 0 | C72: =IF(ISERROR(B72),"GAGAL",IF(ABS(B72)<=1,"LULUS","GAGAL")) -> LULUS
A73: Barang jadi: tersedia = penjualan + saldo akhir + selisih kuantitas (Rp) | B73: =D49-D51-D52-D53 -> 0 | C73: =IF(ISERROR(B73),"GAGAL",IF(ABS(B73)<=1,"LULUS","GAGAL")) -> LULUS
A74: Ringkasan = 2b (Rp jt) | B74: =B12*10^6-E43 -> 0 | C74: =IF(ISERROR(B74),"GAGAL",IF(ABS(B74)<=1,"LULUS","GAGAL")) -> LULUS
A75: Tidak ada sel error | B75: =SUMPRODUCT(--ISERROR(A5:H66)) -> 0 | C75: =IF(ISERROR(B75),"GAGAL",IF(ABS(B75)<=0.5,"LULUS","GAGAL")) -> LULUS
A76: Info (bukan kontrol): selisih kuantitas barang jadi (B53) dan memo B56–B57 menunjukkan beda kartu vs Accurate.
A100: LAMPIRAN A. Input bulan ini
A101: Pos | B101: Satuan | C101: Nilai | D101: Status angka | E101: Sumber
A102: Output produksi | B102: kg | C102: 2049.04 | D102: Aktual | E102: Kartu E7 (kg)
A103: Output produksi | B103: bag | C103: 25613 | D103: Aktual | E103: Kartu E6 (bag)
A104: Sampel | B104: kg | C104: 1.92 | D104: Aktual | E104: Kartu E10
A105: Sampel | B105: bag | C105: 24 | D105: Aktual | E105: Kartu E9
A106: Man-hour (driver Grup A & B) | B106: jam | C106: 127.5733 | D106: Aktual | E106: Labor: LAP BAG MAICIH KERIPIK LV 10 M
A107: Pemakaian listrik (driver Grup C & D) | B107: kWh | C107: 748.0668 | D107: Aktual | E107: Overhead Allocation: LAP BAG MAICIH KERIPIK LV 10 SA
A108: Saldo awal FG-111 | B108: bag | C108: 0 | D108: Aktual | E108: Inventory Valuation (Kts. saldo awal bulan)
A109: Nilai saldo awal FG-111 (WP) | B109: Rp | C109: 0 | D109: Roll-forward | E109: Roll-forward: WP DI - WP Costing BMG Agu26_4.xlsx sheet MCH KERIPIK LV10 D52 (saldo akhir WP)
A110: Nilai saldo awal FG-111 menurut Accurate | B110: Rp | C110: -0.44 | D110: Aktual | E110: Inventory Valuation
A111: Masuk FG-111 menurut Accurate (penyesuaian masuk − keluar) | B111: bag | C111: 25613 | D111: Aktual | E111: Inventory Valuation, Penyesuaian persediaan
A112: Nilai masuk FG-111 menurut Accurate | B112: Rp | C112: 35155436 | D112: Aktual | E112: Inventory Valuation, Penyesuaian persediaan
A113: Keluar FG-111: pengiriman pesanan | B113: bag | C113: 25613 | D113: Aktual | E113: Inventory Valuation, Pengiriman Pesanan
... A123: Kartu lama: kWh di operasi | B123: kWh | C123: 748.0668 | D123: Aktual | E123: Kartu, baris Operation (Elc)
A126: LAMPIRAN B. Material per baris kartu (qty kartu; nilai kartu = qty × harga kartu)
A127: Material | B127: Kelompok | C127: Qty | D127: Satuan | E127: Harga kartu | F127: Nilai kartu (Rp) | G127: Sumber
A128: Keripik Singkong Kw 2 | B128: KW2 | C128: 396.14148 | D128: kg | E128: 0 | F128: 0 | G128: Kartu C13:R13; kelompok: KW 2 FCC (antarproduk, NRV)
A129: Keripik Singkong Premium | B129: FCC | C129: 1490.5 | D129: kg | E129: 21488.548 | F129: 32028681 | G129: Kartu C14:R14; kelompok: FCC premium (antarproduk)
A130: Bumbu Maicih Level 10 | B130: EXT | C130: 149 | D130: kg | E130: 0 | F130: 0 | G130: Kartu C15:R15; kelompok: Eksternal
A131: Polyfilm Maichi Keripik Singkong Level-10 | B131: EXT | C131: 210.54 | D131: kg | E131: 0 | F131: 0 | G131: Kartu C16:R16; kelompok: Eksternal
A132: Karton Maicih | B132: EXT | C132: 1030 | D132: pcs | E132: 0 | F132: 0 | G132: Kartu C17:R17; kelompok: Eksternal
A133: Plakban Ukuran 100 Yard | B133: EXT | C133: 14.518675 | D133: roll | E133: 6600 | F133: 95823.254 | G133: Kartu C18:R18; kelompok: Eksternal
A134: CNG | B134: EXT | C134: 10.169543 | D134: m³ | E134: 10143.981 | F134: 103159.65 | G134: Kartu C19:R19; kelompok: Eksternal
A135: Total | F135: =SUM(F128:F134) -> 32227664
A136: Kode kelompok: FCC = FCC premium (dinilai ulang pada biaya FCC kartu baru), KW2 = KW 2 FCC (NRV), KW2UBI = KW 2 ubi, EXT = material eksternal (nilai kartu).

Sheet MCH KERIPIK LV5
A1: KARTU BIAYA PRODUKSI – Maicih Keripik Singkong 80 gr Level 5, September 2026
A2: Sumber: kartu 'LAP BAG MAICIH KERIPIK LV 5 SA' di WP CoGM September 2026; driver man-hour & kWh: sheet Labor & Overhead Allocation; barang jadi: Inventory Valuation Accurate FG-112; pendapatan: LK Sales By Item.
A4: Status kontrol (bagian 5) | C4: =IF(COUNTIF(C70:C75,"GAGAL")=0,"LULUS","GAGAL") -> LULUS
A5: 1. Ringkasan (Rp juta; Rp/kg per kg produksi bulan ini)
A6: Komponen | B6: Aktual (Rp jt) | C6: Rp/kg | D6: Porsi
A7: FCC premium (antarproduk) | B7: =E31/10^6 -> 21.533399 | C7: =F31 -> 13449.632 | D7: =IF($B$12=0,0,B7/$B$12) -> 0.55362358
A8: KW 2 (antarproduk, NRV) | B8: =(E32+E33)/10^6 -> 5.9858278 | C8: =F32+F33 -> 3738.7122 | D8: =IF($B$12=0,0,B8/$B$12) -> 0.1538956
A9: Material eksternal | B9: =E34/10^6 -> 0.2311264 | C9: =F34 -> 144.36016 | D9: =IF($B$12=0,0,B9/$B$12) -> 0.0059422585
A10: Direct labour (Grup A) | B10: =E37/10^6 -> 3.1536738 | C10: =F37 -> 1969.7658 | D10: =IF($B$12=0,0,B10/$B$12) -> 0.081080937
A11: Factory overhead (Grup B–E) | B11: =E41/10^6 -> 7.9913522 | C11: =F41 -> 4991.3508 | D11: =IF($B$12=0,0,B11/$B$12) -> 0.20545762
A12: Total biaya produksi | B12: =E43/10^6 -> 38.895379 | C12: =F43 -> 24293.821 | D12: =IF($B$12=0,0,B12/$B$12) -> 1
A13: Produksi (kg; satuan FG) | B13: =B21 -> 1601.04 | C13: =C21 -> 20013
A14: HPP (Rp jt) dan HPP per satuan terjual | B14: =D54/10^6 -> 38.895379 | C14: =C55 -> 1943.5057
A15: Pendapatan (Rp jt) dan harga per satuan | B15: =$C$118/10^6 -> 49.606 | C15: =IF($C$117=0,0,$C$118/$C$117) -> 2478.6889
A16: Margin kotor (Rp jt; %) | B16: =B15-B14 -> 10.710621 | C16: =IF(B15=0,0,B16/B15) -> 0.21591382
A18: 2. Laporan biaya produksi
A19: 2a. Kuantitas
A20: Pos | B20: Kg | C20: Satuan FG (bag) | D20: Keterangan
A21: Output produksi | B21: =$C$102 -> 1601.04 | C21: =$C$103 -> 20013
A22: Sampel | B22: =$C$104 -> 1.92 | C22: =$C$105 -> 24 | D22: memo, tidak masuk barang jadi
A23: Input FCC premium | B23: =SUMIF($B$128:$B$134,"FCC",$C$128:$C$134) -> 902 | D23: Lampiran B
A24: Input KW 2 FCC | B24: =SUMIF($B$128:$B$134,"KW2",$C$128:$C$134) -> 612.21865 | D24: Lampiran B
A25: Input KW 2 ubi | B25: =SUMIF($B$128:$B$134,"KW2UBI",$C$128:$C$134) -> 0 | D25: Lampiran B
A26: Rendemen output ÷ input keripik (kg/kg) | B26: =IF(SUM(B23:B25)=0,0,B21/SUM(B23:B25)) -> 1.0573374
A28: 2b. Biaya produksi bulan ini (aktual)
A29: Komponen | B29: Qty / driver | C29: Satuan | D29: Harga / porsi | E29: Nilai (Rp) | F29: Rp/kg | G29: Dasar
A30: Bahan
A31: FCC premium (antarproduk) | B31: =B23 -> 902 | C31: kg | D31: =FCC!$D$89 -> 23872.948 | E31: =B31*D31 -> 21533399 | F31: =IF($B$21=0,0,E31/$B$21) -> 13449.632 | G31: Biaya rata-rata FG FCC kartu baru (FCC D88)
A32: KW 2 FCC (antarproduk, NRV) | B32: =B24 -> 612.21865 | C32: kg | D32: =FCC!$C$209 -> 9777.2712 | E32: =B32*D32 -> 5985827.8 | F32: =IF($B$21=0,0,E32/$B$21) -> 3738.7122 | G32: NRV KW 2 (FCC C208)
A33: KW 2 ubi (antarproduk) | B33: =B25 -> 0 | C33: kg | D33: ='LAIN-LAIN'!$C$7 -> 0 | E33: =B33*D33 -> 0 | F33: =IF($B$21=0,0,E33/$B$21) -> 0 | G33: Nilai KW 2 ubi (LAIN-LAIN C7)
A34: Material eksternal (Lampiran B) | E34: =SUMIF($B$128:$B$134,"EXT",$F$128:$F$134) -> 231126.4 | F34: =IF($B$21=0,0,E34/$B$21) -> 144.36016 | G34: Nilai kartu per baris material
A35: Subtotal bahan | E35: =SUM(E31:E34) -> 27750353 | F35: =IF($B$21=0,0,E35/$B$21) -> 17332.705
A36: Konversi (pool BIAYA BERSAMA, porsi Lain-lain dibagi dengan driver yang sama dengan sheet LAIN-LAIN)
A37: Grup A – DL operator | B37: =$C$106 -> 145.2214 | C37: jam | D37: =IF('LAIN-LAIN'!$H$43=0,0,B37/'LAIN-LAIN'!$H$43) -> 0.054002717 | E37: =D37*'BIAYA BERSAMA'!$F$115 -> 3153673.8 | F37: =IF($B$21=0,0,E37/$B$21) -> 1969.7658 | G37: Man-hour ÷ total man-hour Lain-lain × pool Grup A Lain-lain
A38: Grup B – IDL (support, staf, THR, BPJS) | B38: =$C$106 -> 145.2214 | C38: jam | D38: =IF('LAIN-LAIN'!$H$43=0,0,B38/'LAIN-LAIN'!$H$43) -> 0.054002717 | E38: =D38*'BIAYA BERSAMA'!$F$117 -> 2819384.4 | F38: =IF($B$21=0,0,E38/$B$21) -> 1760.9706 | G38: Man-hour
A39: Grup C + D – energi (kWh) dan mesin (bagging: kWh; Ubi putih ACE: jam mesin) | B39: =$C$107 -> 617.8482 | C39: kWh | D39: =IF('LAIN-LAIN'!$I$43=0,0,B39/'LAIN-LAIN'!$I$43) -> 0.061063904 | E39: =D39*'BIAYA BERSAMA'!$F$118+IF('BIAYA BERSAMA'!$F$172=0,0,B39/'BIAYA BERSAMA'!$F$172)*'BIAYA BERSAMA'!$F$176 -> 5158085.8 | F39: =IF($B$21=0,0,E39/$B$21) -> 3221.7095 | G39: kWh
A40: Grup E – pabrik umum | B40: =E34 -> 231126.4 | C40: Rp | D40: =IF('LAIN-LAIN'!$G$43=0,0,B40/'LAIN-LAIN'!$G$43) -> 0.0030144188 | E40: =D40*'BIAYA BERSAMA'!$F$120 -> 13882.045 | F40: =IF($B$21=0,0,E40/$B$21) -> 8.6706422 | G40: Nilai material eksternal
A41: Subtotal factory overhead (Grup B–E) | E41: =SUM(E38:E40) -> 7991352.2 | F41: =IF($B$21=0,0,E41/$B$21) -> 4991.3508
A42: Total konversi | E42: =E37+E41 -> 11145026 | F42: =IF($B$21=0,0,E42/$B$21) -> 6961.1165
A43: TOTAL BIAYA PRODUKSI BULAN INI | E43: =E35+E42 -> 38895379 | F43: =IF($B$21=0,0,E43/$B$21) -> 24293.821
A45: 3. Barang jadi (FG-112 Maicih Keripik Singkong 80gr-Level 5) dan HPP
A46: Pos | B46: Qty (bag) | C46: Rp/satuan | D46: Nilai WP (Rp) | E46: Qty Accurate | F46: Nilai Accurate (Rp) | G46: Selisih nilai WP − Accurate
A47: Saldo awal | B47: =$C$108 -> 0 | D47: =$C$109 -> 0 | E47: =$C$108 -> 0 | F47: =$C$110 -> 0.08 | G47: =D47-F47 -> -0.08
A48: Masuk dari produksi | B48: =C21 -> 20013 | D48: =E43 -> 38895379 | E48: =$C$111 -> 20013 | F48: =$C$112 -> 22348513 | G48: =D48-F48 -> 16546866
A49: Tersedia | B49: =B47+B48 -> 20013 | D49: =D47+D48 -> 38895379 | E49: =E47+E48 -> 20013 | F49: =F47+F48 -> 22348513 | G49: =D49-F49 -> 16546866
A50: Biaya rata-rata tertimbang per satuan | C50: =IF(B49=0,0,D49/B49) -> 1943.5057
A51: Keluar: penjualan (pengiriman pesanan) | B51: =$C$113 -> 20013 | D51: =B51*$C$50 -> 38895379 | E51: =$C$113 -> 20013 | F51: =$C$114 -> 22348513 | G51: =D51-F51 -> 16546866
A52: Saldo akhir (qty menurut Accurate) | B52: =$C$115 -> 0 | D52: =B52*$C$50 -> 0 | E52: =$C$115 -> 0 | F52: =$C$116 -> 0.08 | G52: =D52-F52 -> -0.08
A53: Selisih kuantitas (tersedia − penjualan − saldo akhir) ke HPP | B53: =B49-B51-B52 -> 0 | D53: =B53*$C$50 -> 0 | E53: =E49-E51-E52 -> 0 | F53: =F49-F51-F52 -> -1.7881393e-09 | G53: =D53-F53 -> 1.7881393e-09
A54: HPP (penjualan + selisih kuantitas) | D54: =D51+D53 -> 38895379 | F54: =F51+F53 -> 22348513 | G54: =D54-F54 -> 16546866
A55: HPP per satuan terjual | C55: =IF(B51=0,0,D54/B51) -> 1943.5057
A56: Memo: penjualan Sales By Item − pengiriman Accurate (qty) | B56: =$C$117-B51 -> 0
A57: Memo: produksi kartu − masuk menurut Accurate (qty) | B57: =B48-E48 -> 0
A59: 4. Pembanding kartu lama (WP CoGM)
A60: Komponen | B60: Kartu lama (Rp) | C60: WP (Rp) | D60: Selisih (Rp) | E60: Keterangan
A61: Material (DM + IDM) | B61: =$C$119 -> 19613797 | C61: =E35 -> 27750353 | D61: =C61-B61 -> 8136556.5 | E61: Kartu: FCC premium pada harga kartu lama; WP: pada biaya FCC kartu baru (FCC D88) dan KW 2 pada NRV
A62: Tenaga kerja (DL + IDL) | B62: =$C$120 -> 2603844.9 | C62: =E37+E38 -> 5973058.2 | D62: =C62-B62 -> 3369213.2 | E62: Kartu: man-hour × tarif; WP: pool Grup A + B
A63: Listrik / overhead | B63: =$C$121 -> 668243.85 | C63: =E39+E40 -> 5171967.9 | D63: =C63-B63 -> 4503724 | E63: Kartu: kWh × tarif; WP: pool Grup C, D, E
A64: Total biaya produksi | B64: =SUM(B61:B63) -> 22885886 | C64: =SUM(C61:C63) -> 38895379 | D64: =C64-B64 -> 16009494
A65: Man-hour: kartu lama vs driver Labor | B65: =$C$122 -> 145.2214 | C65: =$C$106 -> 145.2214 | D65: =C65-B65 -> 0
A66: kWh: kartu lama vs driver Overhead Allocation | B66: =$C$123 -> 617.8482 | C66: =$C$107 -> 617.8482 | D66: =C66-B66 -> 0
A68: 5. Kontrol (toleransi Rp 1; 0,01 qty)
A69: Cek | B69: Nilai | C69: Status
A70: Material eksternal di 2b = Lampiran B kelompok EXT | B70: =E34-SUMIF($B$128:$B$134,"EXT",$F$128:$F$134) -> 0 | C70: =IF(ISERROR(B70),"GAGAL",IF(ABS(B70)<=1,"LULUS","GAGAL")) -> LULUS
A71: Semua baris Lampiran B punya kelompok yang dikenal | B71: =COUNTA($A$128:$A$134)-COUNTIF($B$128:$B$134,"FCC")-COUNTIF($B$128:$B$134,"KW2")-COUNTIF($B$128:$B$134,"KW2UBI")-COUNTIF($B$128:$B$134,"EXT") -> 0 | C71: =IF(ISERROR(B71),"GAGAL",IF(ABS(B71)<=0.5,"LULUS","GAGAL")) -> LULUS
A72: Total biaya = bahan + konversi | B72: =E43-E35-E42 -> 0 | C72: =IF(ISERROR(B72),"GAGAL",IF(ABS(B72)<=1,"LULUS","GAGAL")) -> LULUS
A73: Barang jadi: tersedia = penjualan + saldo akhir + selisih kuantitas (Rp) | B73: =D49-D51-D52-D53 -> 0 | C73: =IF(ISERROR(B73),"GAGAL",IF(ABS(B73)<=1,"LULUS","GAGAL")) -> LULUS
A74: Ringkasan = 2b (Rp jt) | B74: =B12*10^6-E43 -> 0 | C74: =IF(ISERROR(B74),"GAGAL",IF(ABS(B74)<=1,"LULUS","GAGAL")) -> LULUS
A75: Tidak ada sel error | B75: =SUMPRODUCT(--ISERROR(A5:H66)) -> 0 | C75: =IF(ISERROR(B75),"GAGAL",IF(ABS(B75)<=0.5,"LULUS","GAGAL")) -> LULUS
A76: Info (bukan kontrol): selisih kuantitas barang jadi (B53) dan memo B56–B57 menunjukkan beda kartu vs Accurate.
A100: LAMPIRAN A. Input bulan ini
A101: Pos | B101: Satuan | C101: Nilai | D101: Status angka | E101: Sumber
A102: Output produksi | B102: kg | C102: 1601.04 | D102: Aktual | E102: Kartu E7 (kg)
A103: Output produksi | B103: bag | C103: 20013 | D103: Aktual | E103: Kartu E6 (bag)
A104: Sampel | B104: kg | C104: 1.92 | D104: Aktual | E104: Kartu E10
A105: Sampel | B105: bag | C105: 24 | D105: Aktual | E105: Kartu E9
A106: Man-hour (driver Grup A & B) | B106: jam | C106: 145.2214 | D106: Aktual | E106: Labor: LAP BAG MAICIH KERIPIK LV 5 SA + LAP BAG MAICIH KERIPIK LV 5 M
A107: Pemakaian listrik (driver Grup C & D) | B107: kWh | C107: 617.8482 | D107: Aktual | E107: Overhead Allocation: LAP BAG MAICIH KERIPIK LV 5 SA
A108: Saldo awal FG-112 | B108: bag | C108: 0 | D108: Aktual | E108: Inventory Valuation (Kts. saldo awal bulan)
A109: Nilai saldo awal FG-112 (WP) | B109: Rp | C109: 0 | D109: Roll-forward | E109: Roll-forward: WP DI - WP Costing BMG Agu26_4.xlsx sheet MCH KERIPIK LV5 D52 (saldo akhir WP)
A110: Nilai saldo awal FG-112 menurut Accurate | B110: Rp | C110: 0.08 | D110: Aktual | E110: Inventory Valuation
A111: Masuk FG-112 menurut Accurate (penyesuaian masuk − keluar) | B111: bag | C111: 20013 | D111: Aktual | E111: Inventory Valuation, Penyesuaian persediaan
A112: Nilai masuk FG-112 menurut Accurate | B112: Rp | C112: 22348513 | D112: Aktual | E112: Inventory Valuation, Penyesuaian persediaan
A113: Keluar FG-112: pengiriman pesanan | B113: bag | C113: 20013 | D113: Aktual | E113: Inventory Valuation, Pengiriman Pesanan
... A123: Kartu lama: kWh di operasi | B123: kWh | C123: 617.8482 | D123: Aktual | E123: Kartu, baris Operation (Elc)
A126: LAMPIRAN B. Material per baris kartu (qty kartu; nilai kartu = qty × harga kartu)
A127: Material | B127: Kelompok | C127: Qty | D127: Satuan | E127: Harga kartu | F127: Nilai kartu (Rp) | G127: Sumber
A128: Keripik Singkong KW 2 | B128: KW2 | C128: 612.21865 | D128: kg | E128: 0 | F128: 0 | G128: Kartu C13:R13; kelompok: KW 2 FCC (antarproduk, NRV)
A129: Keripik Singkong Premium | B129: FCC | C129: 902 | D129: kg | E129: 21488.548 | F129: 19382670 | G129: Kartu C14:R14; kelompok: FCC premium (antarproduk)
A130: Bumbu Maicih Level 5 | B130: EXT | C130: 119.76 | D130: kg | E130: 0 | F130: 0 | G130: Kartu C15:R15; kelompok: Eksternal
A131: Polyfilm Maichi Keripik Singkong Level-5 | B131: EXT | C131: 171.6 | D131: kg | E131: 0 | F131: 0 | G131: Kartu C16:R16; kelompok: Eksternal
A132: Karton Maicih | B132: EXT | C132: 802 | D132: pcs | E132: 0 | F132: 0 | G132: Kartu C17:R17; kelompok: Eksternal
A133: Plakban Ukuran 100 Yard | B133: EXT | C133: 11.278865 | D133: roll | E133: 6600 | F133: 74440.508 | G133: Kartu C18:R18; kelompok: Eksternal
A134: CNG | B134: EXT | C134: 15.446193 | D134: m³ | E134: 10143.981 | F134: 156685.89 | G134: Kartu C19:R19; kelompok: Eksternal
A135: Total | F135: =SUM(F128:F134) -> 19613797
A136: Kode kelompok: FCC = FCC premium (dinilai ulang pada biaya FCC kartu baru), KW2 = KW 2 FCC (NRV), KW2UBI = KW 2 ubi, EXT = material eksternal (nilai kartu).

Sheet UBI PUTIH ACE
A1: KARTU BIAYA PRODUKSI – Ubi Putih ACE (Sweet Potato N110), September 2026
A2: Sumber: kartu 'Ubi Putih ACE' di WP CoGM September 2026; driver man-hour & kWh: sheet Labor & Overhead Allocation; barang jadi: Inventory Valuation Accurate FG-182; pendapatan: LK Sales By Item.
A4: Status kontrol (bagian 5) | C4: =IF(COUNTIF(C70:C75,"GAGAL")=0,"LULUS","GAGAL") -> LULUS
A5: 1. Ringkasan (Rp juta; Rp/kg per kg produksi bulan ini)
A6: Komponen | B6: Aktual (Rp jt) | C6: Rp/kg | D6: Porsi
A7: FCC premium (antarproduk) | B7: =E31/10^6 -> 0 | C7: =F31 -> 0 | D7: =IF($B$12=0,0,B7/$B$12) -> 0
A8: KW 2 (antarproduk, NRV) | B8: =(E32+E33)/10^6 -> 0 | C8: =F32+F33 -> 0 | D8: =IF($B$12=0,0,B8/$B$12) -> 0
A9: Material eksternal | B9: =E34/10^6 -> 68.748452 | C9: =F34 -> 4644.3874 | D9: =IF($B$12=0,0,B9/$B$12) -> 0.72793989
A10: Direct labour (Grup A) | B10: =E37/10^6 -> 10.098087 | C10: =F37 -> 682.18885 | D10: =IF($B$12=0,0,B10/$B$12) -> 0.10692314
A11: Factory overhead (Grup B–E) | B11: =E41/10^6 -> 15.595946 | C11: =F41 -> 1053.6036 | D11: =IF($B$12=0,0,B11/$B$12) -> 0.16513697
A12: Total biaya produksi | B12: =E43/10^6 -> 94.442485 | C12: =F43 -> 6380.1799 | D12: =IF($B$12=0,0,B12/$B$12) -> 1
A13: Produksi (kg; satuan FG) | B13: =B21 -> 14802.48 | C13: =C21 -> 14802.48
A14: HPP (Rp jt) dan HPP per satuan terjual | B14: =D54/10^6 -> 94.442485 | C14: =C55 -> 6380.223
A15: Pendapatan (Rp jt) dan harga per satuan | B15: =$C$118/10^6 -> 103.91069 | C15: =IF($C$117=0,0,$C$118/$C$117) -> 7019.8637
A16: Margin kotor (Rp jt; %) | B16: =B15-B14 -> 9.4682053 | C16: =IF(B15=0,0,B16/B15) -> 0.091118683
A18: 2. Laporan biaya produksi
A19: 2a. Kuantitas
A20: Pos | B20: Kg | C20: Satuan FG (kg) | D20: Keterangan
A21: Output produksi | B21: =$C$102 -> 14802.48 | C21: =$C$103 -> 14802.48
A22: Sampel | B22: =$C$104 -> 0 | C22: =$C$105 -> 0 | D22: memo, tidak masuk barang jadi
A23: Input FCC premium | B23: =SUMIF($B$128:$B$128,"FCC",$C$128:$C$128) -> 0 | D23: Lampiran B
A24: Input KW 2 FCC | B24: =SUMIF($B$128:$B$128,"KW2",$C$128:$C$128) -> 0 | D24: Lampiran B
A25: Input KW 2 ubi | B25: =SUMIF($B$128:$B$128,"KW2UBI",$C$128:$C$128) -> 0 | D25: Lampiran B
A26: Rendemen output ÷ input keripik (kg/kg) | B26: =IF(SUM(B23:B25)=0,0,B21/SUM(B23:B25)) -> 0
A28: 2b. Biaya produksi bulan ini (aktual)
A29: Komponen | B29: Qty / driver | C29: Satuan | D29: Harga / porsi | E29: Nilai (Rp) | F29: Rp/kg | G29: Dasar
A30: Bahan
A31: FCC premium (antarproduk) | B31: =B23 -> 0 | C31: kg | D31: =FCC!$D$89 -> 23872.948 | E31: =B31*D31 -> 0 | F31: =IF($B$21=0,0,E31/$B$21) -> 0 | G31: Biaya rata-rata FG FCC kartu baru (FCC D88)
A32: KW 2 FCC (antarproduk, NRV) | B32: =B24 -> 0 | C32: kg | D32: =FCC!$C$209 -> 9777.2712 | E32: =B32*D32 -> 0 | F32: =IF($B$21=0,0,E32/$B$21) -> 0 | G32: NRV KW 2 (FCC C208)
A33: KW 2 ubi (antarproduk) | B33: =B25 -> 0 | C33: kg | D33: ='LAIN-LAIN'!$C$7 -> 0 | E33: =B33*D33 -> 0 | F33: =IF($B$21=0,0,E33/$B$21) -> 0 | G33: Nilai KW 2 ubi (LAIN-LAIN C7)
A34: Material eksternal (Lampiran B) | E34: =SUMIF($B$128:$B$128,"EXT",$F$128:$F$128) -> 68748452 | F34: =IF($B$21=0,0,E34/$B$21) -> 4644.3874 | G34: Nilai kartu per baris material
A35: Subtotal bahan | E35: =SUM(E31:E34) -> 68748452 | F35: =IF($B$21=0,0,E35/$B$21) -> 4644.3874
A36: Konversi (pool BIAYA BERSAMA, porsi Lain-lain dibagi dengan driver yang sama dengan sheet LAIN-LAIN)
A37: Grup A – DL operator | B37: =$C$106 -> 465 | C37: jam | D37: =IF('LAIN-LAIN'!$H$43=0,0,B37/'LAIN-LAIN'!$H$43) -> 0.1729171 | E37: =D37*'BIAYA BERSAMA'!$F$115 -> 10098087 | F37: =IF($B$21=0,0,E37/$B$21) -> 682.18885 | G37: Man-hour ÷ total man-hour Lain-lain × pool Grup A Lain-lain
A38: Grup B – IDL (support, staf, THR, BPJS) | B38: =$C$106 -> 465 | C38: jam | D38: =IF('LAIN-LAIN'!$H$43=0,0,B38/'LAIN-LAIN'!$H$43) -> 0.1729171 | E38: =D38*'BIAYA BERSAMA'!$F$117 -> 9027689.6 | F38: =IF($B$21=0,0,E38/$B$21) -> 609.87683 | G38: Man-hour
A39: Grup C + D – energi (kWh) dan mesin (bagging: kWh; Ubi putih ACE: jam mesin) | B39: =$C$107 -> 134.9986 | C39: kWh | D39: =IF('LAIN-LAIN'!$I$43=0,0,B39/'LAIN-LAIN'!$I$43) -> 0.013342341 | E39: =D39*'BIAYA BERSAMA'!$F$118+'BIAYA BERSAMA'!$F$177 -> 2439047.7 | F39: =IF($B$21=0,0,E39/$B$21) -> 164.77291 | G39: kWh
A40: Grup E – pabrik umum | B40: =E34 -> 68748452 | C40: Rp | D40: =IF('LAIN-LAIN'!$G$43=0,0,B40/'LAIN-LAIN'!$G$43) -> 0.89663763 | E40: =D40*'BIAYA BERSAMA'!$F$120 -> 4129208.6 | F40: =IF($B$21=0,0,E40/$B$21) -> 278.95384 | G40: Nilai material eksternal
A41: Subtotal factory overhead (Grup B–E) | E41: =SUM(E38:E40) -> 15595946 | F41: =IF($B$21=0,0,E41/$B$21) -> 1053.6036
A42: Total konversi | E42: =E37+E41 -> 25694033 | F42: =IF($B$21=0,0,E42/$B$21) -> 1735.7924
A43: TOTAL BIAYA PRODUKSI BULAN INI | E43: =E35+E42 -> 94442485 | F43: =IF($B$21=0,0,E43/$B$21) -> 6380.1799
A45: 3. Barang jadi (FG-182 Sweet Potato N110) dan HPP
A46: Pos | B46: Qty (kg) | C46: Rp/satuan | D46: Nilai WP (Rp) | E46: Qty Accurate | F46: Nilai Accurate (Rp) | G46: Selisih nilai WP − Accurate
A47: Saldo awal | B47: =$C$108 -> 0 | D47: =$C$109 -> 0 | E47: =$C$108 -> 0 | F47: =$C$110 -> 0 | G47: =D47-F47 -> 0
A48: Masuk dari produksi | B48: =C21 -> 14802.48 | D48: =E43 -> 94442485 | E48: =$C$111 -> 14802.38 | F48: =$C$112 -> 77231474 | G48: =D48-F48 -> 17211011
A49: Tersedia | B49: =B47+B48 -> 14802.48 | D49: =D47+D48 -> 94442485 | E49: =E47+E48 -> 14802.38 | F49: =F47+F48 -> 77231474 | G49: =D49-F49 -> 17211011
A50: Biaya rata-rata tertimbang per satuan | C50: =IF(B49=0,0,D49/B49) -> 6380.1799
A51: Keluar: penjualan (pengiriman pesanan) | B51: =$C$113 -> 14802.38 | D51: =B51*$C$50 -> 94441847 | E51: =$C$113 -> 14802.38 | F51: =$C$114 -> 77231474 | G51: =D51-F51 -> 17210373
A52: Saldo akhir (qty menurut Accurate) | B52: =$C$115 -> 0 | D52: =B52*$C$50 -> 0 | E52: =$C$115 -> 0 | F52: =$C$116 -> 0 | G52: =D52-F52 -> 0
A53: Selisih kuantitas (tersedia − penjualan − saldo akhir) ke HPP | B53: =B49-B51-B52 -> 0.1 | D53: =B53*$C$50 -> 638.01799 | E53: =E49-E51-E52 -> 0 | F53: =F49-F51-F52 -> 0 | G53: =D53-F53 -> 638.01799
A54: HPP (penjualan + selisih kuantitas) | D54: =D51+D53 -> 94442485 | F54: =F51+F53 -> 77231474 | G54: =D54-F54 -> 17211011
A55: HPP per satuan terjual | C55: =IF(B51=0,0,D54/B51) -> 6380.223
A56: Memo: penjualan Sales By Item − pengiriman Accurate (qty) | B56: =$C$117-B51 -> 0
A57: Memo: produksi kartu − masuk menurut Accurate (qty) | B57: =B48-E48 -> 0.1
A59: 4. Pembanding kartu lama (WP CoGM)
A60: Komponen | B60: Kartu lama (Rp) | C60: WP (Rp) | D60: Selisih (Rp) | E60: Keterangan
A61: Material (DM + IDM) | B61: =$C$119 -> 68748452 | C61: =E35 -> 68748452 | D61: =C61-B61 -> 4.7296286e-05 | E61: Kartu: FCC premium pada harga kartu lama; WP: pada biaya FCC kartu baru (FCC D88) dan KW 2 pada NRV
A62: Tenaga kerja (DL + IDL) | B62: =$C$120 -> 8337533.5 | C62: =E37+E38 -> 19125777 | D62: =C62-B62 -> 10788243 | E62: Kartu: man-hour × tarif; WP: pool Grup A + B
A63: Listrik / overhead | B63: =$C$121 -> 146009.97 | C63: =E39+E40 -> 6568256.3 | D63: =C63-B63 -> 6422246.3 | E63: Kartu: kWh × tarif; WP: pool Grup C, D, E
A64: Total biaya produksi | B64: =SUM(B61:B63) -> 77231995 | C64: =SUM(C61:C63) -> 94442485 | D64: =C64-B64 -> 17210489
A65: Man-hour: kartu lama vs driver Labor | B65: =$C$122 -> 465 | C65: =$C$106 -> 465 | D65: =C65-B65 -> 0
A66: kWh: kartu lama vs driver Overhead Allocation | B66: =$C$123 -> 134.9986 | C66: =$C$107 -> 134.9986 | D66: =C66-B66 -> 0
A68: 5. Kontrol (toleransi Rp 1; 0,01 qty)
A69: Cek | B69: Nilai | C69: Status
A70: Material eksternal di 2b = Lampiran B kelompok EXT | B70: =E34-SUMIF($B$128:$B$128,"EXT",$F$128:$F$128) -> 0 | C70: =IF(ISERROR(B70),"GAGAL",IF(ABS(B70)<=1,"LULUS","GAGAL")) -> LULUS
A71: Semua baris Lampiran B punya kelompok yang dikenal | B71: =COUNTA($A$128:$A$128)-COUNTIF($B$128:$B$128,"FCC")-COUNTIF($B$128:$B$128,"KW2")-COUNTIF($B$128:$B$128,"KW2UBI")-COUNTIF($B$128:$B$128,"EXT") -> 0 | C71: =IF(ISERROR(B71),"GAGAL",IF(ABS(B71)<=0.5,"LULUS","GAGAL")) -> LULUS
A72: Total biaya = bahan + konversi | B72: =E43-E35-E42 -> 0 | C72: =IF(ISERROR(B72),"GAGAL",IF(ABS(B72)<=1,"LULUS","GAGAL")) -> LULUS
