Workbook

Sheet RINGKASAN
A1: RINGKASAN WP COSTING
A3: Status kontrol semua sheet | C3: ='REKON & KONTROL'!$D$68 -> LULUS
A5: 1. Biaya produksi dan HPP per produk (Rp juta; Rp/kg per kg produksi)
A6: Pos | B6: FCC | C6: Ubi Ungu | D6: Ubi Orange | E6: Lain-lain | F6: Total
A7: Produksi (kg) | B7: ='REKON & KONTROL'!B6 -> 338754 | C7: ='REKON & KONTROL'!C6 -> 13376 | D7: ='REKON & KONTROL'!D6 -> 7403 | E7: ='REKON & KONTROL'!E6 -> 17571.48 | F7: ='REKON & KONTROL'!F6 -> 377104.48
A8: Total biaya produksi | B8: ='REKON & KONTROL'!B12 -> 7327.4407 | C8: ='REKON & KONTROL'!C12 -> 465.30971 | D8: ='REKON & KONTROL'!D12 -> 238.93443 | E8: ='REKON & KONTROL'!E12 -> 355.58196 | F8: ='REKON & KONTROL'!F12 -> 8387.2668
A9: Biaya produksi per kg (Rp) | B9: ='REKON & KONTROL'!B13 -> 21630.566 | C9: ='REKON & KONTROL'!C13 -> 34786.91 | D9: ='REKON & KONTROL'!D13 -> 32275.352 | E9: ='REKON & KONTROL'!E13 -> 20236.313 | F9: ='REKON & KONTROL'!F13 -> 22241.228
A10: HPP | B10: ='REKON & KONTROL'!B14 -> 6925.005 | C10: ='REKON & KONTROL'!C14 -> 250.83102 | D10: ='REKON & KONTROL'!D14 -> 238.93443 | E10: ='REKON & KONTROL'!E14 -> 355.58196 | F10: ='REKON & KONTROL'!F14 -> 7770.3524
A11: Pendapatan (total = GL) | B11: ='REKON & KONTROL'!B15 -> 8672.0977 | C11: ='REKON & KONTROL'!C15 -> 349.70925 | D11: ='REKON & KONTROL'!D15 -> 354.6037 | E11: ='REKON & KONTROL'!E15 -> 416.7148 | F11: ='REKON & KONTROL'!F15 -> 9793.1255
A12: Margin kotor (%) | B12: ='REKON & KONTROL'!B16 -> 0.20146138 | C12: ='REKON & KONTROL'!C16 -> 0.28274411 | D12: ='REKON & KONTROL'!D16 -> 0.32619307 | E12: ='REKON & KONTROL'!E16 -> 0.14670186 | F12: ='REKON & KONTROL'!F16 -> 0.20655031
A14: 2. FCC, UU, UO: Rp/kg aktual vs budget dan penyebab selisih (Rp/kg)
A15: Produk | B15: Rp/kg aktual | C15: Rp/kg budget | D15: Selisih | E15: Harga / belanja | F15: Pemakaian / yield | G15: Volume | H15: Metode alokasi | I15: Bulan budget
A16: FCC | B16: =FCC!F132 -> 21630.566 | C16: =FCC!G132 -> 24247.024 | D16: =FCC!H132 -> -2616.4585 | E16: =FCC!I132 -> -975.29969 | F16: =FCC!J132 -> -783.96977 | G16: =FCC!K132 -> -571.13798 | H16: =FCC!L132 -> -286.05103 | I16: =FCC!$C$5 -> Okt-26
A17: UU | B17: =UU!F126 -> 34786.91 | C17: =UU!G126 -> 35657.071 | D17: =UU!H126 -> -870.16049 | E17: =UU!I126 -> 1410.2109 | F17: =UU!J126 -> -1899.4098 | G17: =UU!K126 -> -2805.881 | H17: =UU!L126 -> 2424.9195 | I17: =UU!$C$5 -> Okt-26
A18: UO | B18: =UO!F126 -> 32275.352 | C18: =UO!G126 -> 33916.194 | D18: =UO!H126 -> -1640.8416 | E18: =UO!I126 -> 977.27671 | F18: =UO!J126 -> -3689.6167 | G18: =UO!K126 -> -1144.747 | H18: =UO!L126 -> 2216.2455 | I18: =UO!$C$5 -> Okt-26
A21: 3. Biaya yang tidak terlihat di margin (memo)
A22: Pos | B22: FCC | C22: Ubi Ungu | D22: Ubi Orange | F22: Catatan
A23: Biaya waste (kerugian normal) yang terserap ke HPP (Rp jt) | B23: =FCC!$B$23 -> 207.1095 | C23: =UU!$B$23 -> 0 | D23: =UO!$B$23 -> 0
A24: KW 2 dikreditkan pada NRV (Rp jt) | B24: =FCC!$B$24 -> 134.48637 | C24: =UU!$B$24 -> 0 | D24: =UO!$B$24 -> 0
A25: Kenaikan WIP + FG (Rp jt) | B25: =FCC!#REF! -> #REF! | C25: =UU!$B$25 -> 214.4787 | D25: =UO!$B$25 -> 0
A26: Biaya jam operator tidak terpakai untuk produk (Rp jt; % jam) | B26: ='BIAYA BERSAMA'!$C$109/10^6 -> 61.206618 | C26: ='BIAYA BERSAMA'!$D$107 -> 0.094074868
A28: 4. Rekonsiliasi ke GL (Rp juta)
A29: Total HPP kartu baru | B29: ='REKON & KONTROL'!$C$37 -> 7770.3524
A30: Varian material (GL − kartu) | B30: ='REKON & KONTROL'!$C$38 -> 203.73054
A31: Selisih kenaikan persediaan kartu baru vs GL | B31: ='REKON & KONTROL'!$C$46 -> -152.227
A32: Kenaikan persediaan KW 2 pada NRV | B32: ='REKON & KONTROL'!$C$41 -> 20.289793
A33: Jam menganggur dibebankan ke periode | B33: ='REKON & KONTROL'!$C$42 -> 0
A34: HPP menurut GL | B34: ='REKON & KONTROL'!$C$44 -> 7842.1457
A35: Cek (harus nol) | B35: ='REKON & KONTROL'!$C$45 -> 0

Sheet FCC
A1: KARTU BIAYA PRODUKSI - FCC (Flat Cassava Chips)
A5: Bulan budget pembanding | C5: Okt-26 | D5: posisi: | E5: =MATCH(C5,BUDGET!$C$4:$R$4,0) -> 2
A6: Status kontrol (bagian 6) | C6: =IF(COUNTIF(D158:D168,"GAGAL")=0,"LULUS","GAGAL") -> LULUS
A8: 1. Ringkasan (Rp juta; Rp/kg per kg produksi bulan ini)
A9: Komponen | B9: Aktual (Rp jt) | C9: Aktual Rp/kg | D9: Budget Rp/kg | E9: Selisih Rp/kg | F9: Harga / belanja | G9: Pemakaian / yield | H9: Volume | I9: Metode alokasi
A10: Raw materials | B10: =E43/10^6 -> 3103.9859 | C10: =F43 -> 9162.9499 | D10: =G111 -> 9668.1757 | E10: =H111 -> -505.22578 | F10: =I111 -> -764.45659 | G10: =J111 -> 259.23081 | H10: =K111 -> 0 | I10: =L111 -> 0
A11: Oil | B11: =E45/10^6 -> 1362.1392 | C11: =F45 -> 4021.0278 | D11: =G113 -> 4729.8946 | E11: =H113 -> -708.86683 | F11: =I113 -> 112.62136 | G11: =J113 -> -821.48819 | H11: =K113 -> 0 | I11: =L113 -> 0
A12: CNG | B12: =E46/10^6 -> 1156.699 | C12: =F46 -> 3414.5694 | D12: =G115 -> 3489.2225 | E12: =H115 -> -74.653111 | F12: =I115 -> -40.154776 | G12: =J115 -> -34.498335 | H12: =K115 -> 0 | I12: =L115 -> 0
A13: Material - others | B13: =E54/10^6 -> 301.40266 | C13: =F54 -> 889.73903 | D13: =G122 -> 814.07396 | E13: =H122 -> 75.665076 | F13: =I122 -> 31.547097 | G13: =J122 -> 44.117978 | H13: =K122 -> 0 | I13: =L122 -> 0
A14: Upah kupas | B14: =E57/10^6 -> 110.02163 | C14: =F57 -> 324.78325 | D14: =G124 -> 555.87748 | E14: =H124 -> -231.09423 | F14: =I124 -> 0.23780258 | G14: =J124 -> -231.33203 | H14: =K124 -> 0 | I14: =L124 -> 0
A15: Direct labour (Grup A) | B15: =E58/10^6 -> 554.72766 | C15: =F58 -> 1637.5531 | D15: =G126 -> 2105.5178 | E15: =H126 -> -467.96476 | F15: =I126 -> -54.902774 | G15: =J126 -> 0 | H15: =K126 -> -241.00084 | I15: =L126 -> -172.06115
A16: Factory overhead (Grup B–E) | B16: =E63/10^6 -> 738.46455 | C16: =F63 -> 2179.9434 | D16: =G131 -> 2884.2623 | E16: =H131 -> -704.31884 | F16: =I131 -> -260.19181 | G16: =J131 -> 0 | H16: =K131 -> -330.13714 | I16: =L131 -> -113.98989
A17: Total biaya produksi | B17: =E65/10^6 -> 7327.4407 | C17: =F65 -> 21630.566 | D17: =G132 -> 24247.024 | E17: =H132 -> -2616.4585 | F17: =I132 -> -975.29969 | G17: =J132 -> -783.96977 | H17: =K132 -> -571.13798 | I17: =L132 -> -286.05103
A18: Produksi bulan ini (kg; aktual, budget) | C18: =$B$30 -> 338754 | D18: =$D$30 -> 299979.69
A19: Biaya konversi per kg (aktual, budget) | C19: =F64 -> 4142.2797 | D19: =G124+G126+G131 -> 5545.6576
A20: HPP (Rp jt) dan HPP per kg terjual (aktual, budget) | B20: =E103/10^6 -> 6925.005 | C20: =D104 -> 22814.982 | D20: =F104 -> 25736.788
A21: Pendapatan (Rp jt; aktual) | B21: =$C$210/10^6 -> 8672.0977
A22: Margin kotor (Rp jt; %) | B22: =B21-B20 -> 1747.0927 | C22: =IF(B21=0,0,B22/B21) -> 0.20146138
A23: biaya waste (kerugian normal) yang masuk HPP (Rp jt; % biaya produksi) | B23: =E77/10^6 -> 207.1095 | C23: =IF(E65=0,0,E77/E65) -> 0.028264916
A24: KW 2 dikreditkan pada NRV (Rp jt) | B24: =-E73/10^6 -> 134.48637
A26: 2. Laporan biaya produksi
A27: 2a. Kuantitas (kg)
A28: Pos | B28: Aktual kg | C28: % dari produksi | D28: Budget kg | E28: % budget
A29: WIP awal | B29: =$C$190 -> 2431
A30: Produksi bulan ini (masuk proses) | B30: =$C$191 -> 338754 | D30: =INDEX(BUDGET!$C$14:$R$14,$E$5) -> 299979.69
A31: Total untuk dipertanggungjawabkan | B31: =B29+B30 -> 341185
A32: Premium ke barang jadi | B32: =B31-B33-B34-B35 -> 317712.5 | C32: =IF(B30=0,0,B32/B30) -> 0.9378856 | D32: =INDEX(BUDGET!$C$10:$R$10,$E$5) -> 278373.52 | E32: =IF(D30=0,0,D32/D30) -> 0.92797454
A33: KW 2 (produk sampingan) | B33: =$C$193 -> 13755 | C33: =IF(B30=0,0,B33/B30) -> 0.040604687 | D33: =INDEX(BUDGET!$C$11:$R$11,$E$5) -> 10970.782 | E33: =IF(D30=0,0,D33/D30) -> 0.036571749
A34: Keripik waste (kerugian normal) | B34: =$C$194 -> 9360 | C34: =IF(B30=0,0,B34/B30) -> 0.02763067 | D34: =INDEX(BUDGET!$C$12:$R$12,$E$5) -> 10635.392 | E34: =IF(D30=0,0,D34/D30) -> 0.035453707
A35: WIP akhir | B35: =$C$192 -> 357.5 | C35: =IF(B30=0,0,B35/B30) -> 0.0010553381 | D35: =INDEX(BUDGET!$C$13:$R$13,$E$5) -> 0 | E35: =IF(D30=0,0,D35/D30) -> 0
A36: Total dipertanggungjawabkan | B36: =SUM(B32:B35) -> 341185
A38: 2b. Biaya produksi bulan ini (aktual)
A39: Komponen | B39: Qty | C39: Satuan | D39: Harga | E39: Nilai (Rp) | F39: Rp/kg
A40: Raw materials
A41: Singkong kulit premium | B41: =D214 -> 625461.89 | C41: kg | D41: =F214 -> 2673.5489 | E41: =G214 -> 1.6722029e+09 | F41: =IF($B$30=0,0,E41/$B$30) -> 4936.3341
A42: Singkong daging premium | B42: =D215 -> 316290 | C42: kg | D42: =F215 -> 4526.8045 | E42: =G215 -> 1.431783e+09 | F42: =IF($B$30=0,0,E42/$B$30) -> 4226.6158
A43: Subtotal raw materials | E43: =E41+E42 -> 3.1039859e+09 | F43: =IF($B$30=0,0,E43/$B$30) -> 9162.9499
A44: Oil & CNG
A45: Minyak olein | B45: =D216 -> 78928 | C45: kg | D45: =F216 -> 17257.998 | E45: =G216 -> 1.3621392e+09 | F45: =IF($B$30=0,0,E45/$B$30) -> 4021.0278
A46: CNG | B46: =D217/$C$209 -> 5099.3535 | C46: MMBTU | D46: =IF(B46=0,0,E46/B46) -> 226832.49 | E46: =G217 -> 1.156699e+09 | F46: =IF($B$30=0,0,E46/$B$30) -> 3414.5694
A47: Material - others
A48: Amonium bicarbonate | B48: =D218 -> 2300 | C48: kg | D48: =F218 -> 4638.5866 | E48: =G218 -> 10668749 | F48: =IF($B$30=0,0,E48/$B$30) -> 31.494091
A49: HDPE 0,03 | B49: =D219 -> 163.9 | C49: kg | D49: =F219 -> 34605.651 | E49: =G219 -> 5671866.1 | F49: =IF($B$30=0,0,E49/$B$30) -> 16.743319
A50: HDPE 0,05 | B50: =D220 -> 2587.33 | C50: kg | D50: =F220 -> 34879.084 | E50: =G220 -> 90243701 | F50: =IF($B$30=0,0,E50/$B$30) -> 266.39892
A51: HDPE 0,07 | B51: =D221 -> 2636.83 | C51: kg | D51: =F221 -> 33799.845 | E51: =G221 -> 89124445 | F51: =IF($B$30=0,0,E51/$B$30) -> 263.09489
A52: Packaging IFM (karton) | B52: =D222 -> 9430 | C52: pcs | D52: =F222 -> 9647.6886 | E52: =G222 -> 90977703 | F52: =IF($B$30=0,0,E52/$B$30) -> 268.56569
A53: Other cost (plakban, tali, label, plastik) | C53: Rp | E53: =SUMIF($C$214:$C$227,"Other cost",$G$214:$G$227) -> 14716191 | F53: =IF($B$30=0,0,E53/$B$30) -> 43.442118
A54: Subtotal material - others | E54: =E48+E49+E50+E51+E52+E53 -> 3.0140266e+08 | F54: =IF($B$30=0,0,E54/$B$30) -> 889.73903
A55: Total material | E55: =E43+E45+E46+E54 -> 5.9242269e+09 | F55: =IF($B$30=0,0,E55/$B$30) -> 17488.286
A56: Konversi (dari BIAYA BERSAMA)
A57: Upah borongan kupas | B57: =$C$197 -> 409266 | C57: kg dikupas | D57: =IF(B57=0,0,E57/B57) -> 268.82669 | E57: ='BIAYA BERSAMA'!C116 -> 110021625 | F57: =IF($B$30=0,0,E57/$B$30) -> 324.78325
A58: Grup A – DL operator | E58: ='BIAYA BERSAMA'!C115 -> 5.5472766e+08 | F58: =IF($B$30=0,0,E58/$B$30) -> 1637.5531
A59: Grup B – IDL (support, staf, THR, BPJS) | E59: ='BIAYA BERSAMA'!C117 -> 3.34936e+08 | F59: =IF($B$30=0,0,E59/$B$30) -> 988.72927
A60: Grup C – energi & utilitas | E60: ='BIAYA BERSAMA'!C118 -> 49949242 | F60: =IF($B$30=0,0,E60/$B$30) -> 147.4499
A61: Grup D – pemeliharaan & penyusutan mesin | E61: ='BIAYA BERSAMA'!C119 -> 2.2748761e+08 | F61: =IF($B$30=0,0,E61/$B$30) -> 671.5422
A62: Grup E – pabrik umum & penyusutan inventaris | E62: ='BIAYA BERSAMA'!C120 -> 1.2609171e+08 | F62: =IF($B$30=0,0,E62/$B$30) -> 372.22205
A63: Subtotal factory overhead (Grup B–E) | E63: =E59+E60+E61+E62 -> 7.3846455e+08 | F63: =IF($B$30=0,0,E63/$B$30) -> 2179.9434
A64: Total konversi | E64: =E57+E58+E63 -> 1.4032138e+09 | F64: =IF($B$30=0,0,E64/$B$30) -> 4142.2797
A65: TOTAL BIAYA PRODUKSI BULAN INI | E65: =E55+E64 -> 7.3274407e+09 | F65: =IF($B$30=0,0,E65/$B$30) -> 21630.566
A66: Memo: kebutuhan ekuivalen singkong kulit per kg produksi | B66: =IF($B$30=0,0,(B41+IF($D$229=0,0,B42/$D$229))/$B$30) -> 3.2732689 | C66: kg/kg | D66: budget: | E66: =INDEX(BUDGET!$C$15:$R$15,$E$5) -> 3.2
A67: Memo: porsi singkong daging (ekuivalen kulit) | B67: =IF(B66*$B$30=0,0,IF($D$229=0,0,B42/$D$229)/(B66*$B$30)) -> 0.43592776 | D67: budget: | E67: =INDEX(BUDGET!$C$21:$R$21,$E$5) -> 0.074774483
A69: 2c. Penilaian hasil (biaya dipertanggungjawabkan = biaya dibebankan)
A70: Pos | B70: Kg | D70: Rp/kg | E70: Nilai (Rp) | F70: Budget Rp/kg
A71: WIP awal | B71: =B29 -> 2431 | E71: =$C$195 -> 52116466
A72: Biaya produksi bulan ini | B72: =B30 -> 338754 | E72: =E65 -> 7.3274407e+09
A73: Dikurangi: KW 2 dinilai NRV (ke persediaan KW 2) | B73: =-B33 -> -13755 | D73: =$C$208 -> 9777.2712 | E73: =-B33*$C$208 -> -1.3448637e+08
A74: Biaya untuk premium, waste, dan WIP akhir | B74: =SUM(B71:B73) -> 327430 | E74: =SUM(E71:E73) -> 7.2450708e+09
A75: Biaya rata-rata tertimbang per kg | D75: =IF(B74=0,0,E74/B74) -> 22127.083 | F75: =INDEX(BUDGET!$C$80:$R$80,$E$5) -> 24796.092
A76: Premium ke barang jadi | B76: =B32 -> 317712.5 | E76: =B76*$D$75 -> 7.0300509e+09
A77: Keripik waste ke HPP (kerugian normal) | B77: =B34 -> 9360 | E77: =B77*$D$75 -> 2.071095e+08
A78: WIP akhir | B78: =B35 -> 357.5 | E78: =B78*$D$75 -> 7910432.2
A79: Total dibebankan | B79: =SUM(B76:B78) -> 327430 | E79: =SUM(E76:E78) -> 7.2450708e+09
B80: =B74-B79 -> 0 | E80: =E74-E79 -> 0
A83: 3. Barang jadi (FG-001 Keripik Singkong Tanpa Bumbu) dan HPP
A84: Pos | B84: Kg | D84: Rp/kg | E84: Nilai (Rp) | F84: Budget Rp/kg
A85: Saldo awal | B85: =$C$200 -> 0 | E85: =IF($C$200=0,0,$C$201) -> 0
A86: Masuk dari produksi | B86: =B76 -> 317712.5 | E86: =E76 -> 7.0300509e+09
A87: Tersedia | B87: =B85+B86 -> 317712.5 | E87: =E85+E86 -> 7.0300509e+09
A88: Biaya rata-rata tertimbang per kg | D88: =IF(B87=0,0,E87/B87) -> 22127.083 | F88: =INDEX(BUDGET!$C$81:$R$81,$E$5) -> 24789.441
A89: Keluar: penjualan ke IFM | B89: =$C$202 -> 301075.5 | E89: =B89*$D$88 -> 6.6619226e+09
A90: Keluar: transfer ke Lain-lain (FCC premium untuk cem-cem) | B90: ='LAIN-LAIN'!$D$43 -> 9757 | E90: =B90*$D$88 -> 2.1589395e+08
A91: Saldo akhir (kg menurut Accurate) | B91: =$C$203 -> 7029 | E91: =B91*$D$88 -> 1.5553127e+08
A92: Selisih kuantitas (tersedia − keluar − saldo akhir) | B92: =B87-B89-B90-B91 -> -149 | E92: =B92*$D$88 -> -3296935.4
A93: nilai saldo akhir menurut Accurate | E93: =$C$204 -> 1.455446e+08
A94: residu nilai saldo awal tanpa kuantitas (tidak ikut rata-rata) | E94: =$C$201-E85 -> -17.55
A95: FG-001 masuk − premium kartu | B95: =$C$205-B86 -> 14256
A96: transfer ke item lain − transfer ke cem-cem | B96: =$C$206-B90 -> 14107
A98: HPP
A99: HPP penjualan ke IFM | E99: =E89 -> 6.6619226e+09
A100: HPP keripik waste | E100: =E77 -> 2.071095e+08
A101: HPP selisih kuantitas FG | E101: =E92 -> -3296935.4
A102: HPP KW 2 tawar terjual ke KGS (pada NRV) | B102: =$C$207 -> 6062 | D102: =$C$208 -> 9777.2712 | E102: =B102*$C$208 -> 59269818
A103: Total HPP | E103: =E99+E100+E101+E102 -> 6.925005e+09
A104: HPP (IFM + waste) per kg terjual ke IFM | D104: =IF(B89=0,0,(E99+E100)/B89) -> 22814.982 | F104: =IF(INDEX(BUDGET!$C$10:$R$10,$E$5)=0,0,INDEX(BUDGET!$C$84:$R$84,$E$5)/INDEX(BUDGET!$C$10:$R$10,$E$5)) -> 25736.788
A105: Budget total HPP (volume budget) | E105: =INDEX(BUDGET!$C$84:$R$84,$E$5) -> 7.1644401e+09
A107: 4. Selisih vs budget per komponen (Rp/kg produksi)
A108: Komponen | B108: Qty/kg aktual | C108: Qty/kg budget | D108: Harga aktual | E108: Harga budget | F108: Rp/kg aktual | G108: Rp/kg budget | H108: Selisih | I108: Harga / belanja | J108: Pemakaian / yield | K108: Volume | L108: Metode alokasi | M108: Cek
A109: Singkong kulit premium | B109: =IF($B$30=0,0,B41/$B$30) -> 1.8463601 | C109: =IF($D$30=0,0,INDEX(BUDGET!$C$18:$R$18,$E$5)/$D$30) -> 2.9607217 | D109: =D41 -> 2673.5489 | E109: =IF(INDEX(BUDGET!$C$18:$R$18,$E$5)=0,0,INDEX(BUDGET!$C$20:$R$20,$E$5)/INDEX(BUDGET!$C$18:$R$18,$E$5)) -> 3000 | F109: =F41 -> 4936.3341 | G109: =IF($D$30=0,0,INDEX(BUDGET!$C$20:$R$20,$E$5)/$D$30) -> 8882.165 | H109: =F109-G109 -> -3945.8308 | I109: =(D109-E109)*B109 -> -602.74632 | J109: =(B109-C109)*E109 -> -3343.0845 | K109: 0 | L109: 0 | M109: =H109-I109-J109-K109-L109 -> 4.5474735e-13
A110: Singkong daging premium | B110: =IF($B$30=0,0,B42/$B$30) -> 0.93368639 | C110: =IF($D$30=0,0,INDEX(BUDGET!$C$22:$R$22,$E$5)/$D$30) -> 0.16723632 | D110: =D42 -> 4526.8045 | E110: =IF(INDEX(BUDGET!$C$22:$R$22,$E$5)=0,0,INDEX(BUDGET!$C$24:$R$24,$E$5)/INDEX(BUDGET!$C$22:$R$22,$E$5)) -> 4700 | F110: =F42 -> 4226.6158 | G110: =IF($D$30=0,0,INDEX(BUDGET!$C$24:$R$24,$E$5)/$D$30) -> 786.01071 | H110: =F110-G110 -> 3440.6051 | I110: =(D110-E110)*B110 -> -161.71027 | J110: =(B110-C110)*E110 -> 3602.3153 | K110: 0 | L110: 0 | M110: =H110-I110-J110-K110-L110 -> -4.5474735e-13
A111: Raw materials | F111: =F109+F110 -> 9162.9499 | G111: =G109+G110 -> 9668.1757 | H111: =H109+H110 -> -505.22578 | I111: =I109+I110 -> -764.45659 | J111: =J109+J110 -> 259.23081 | K111: =K109+K110 -> 0 | L111: =L109+L110 -> 0 | M111: =M109+M110 -> 0
...

Sheet UU
A1: KARTU BIAYA PRODUKSI - UBI UNGU IFM (QKSP)
A5: Bulan budget pembanding | C5: Okt-26 | D5: posisi: | E5: =MATCH(C5,BUDGET!$C$4:$R$4,0) -> 2
A6: Status kontrol (bagian 6) | C6: =IF(COUNTIF(D148:D158,"GAGAL")=0,"LULUS","GAGAL") -> LULUS
A8: 1. Ringkasan (Rp juta; Rp/kg per kg produksi bulan ini)
A9: Komponen | B9: Aktual (Rp jt) | C9: Aktual Rp/kg | D9: Budget Rp/kg | E9: Selisih Rp/kg | F9: Harga / belanja | G9: Pemakaian / yield | H9: Volume | I9: Metode alokasi
A10: Raw materials | B10: =E44/10^6 -> 246.3404 | C10: =F44 -> 18416.597 | D10: =G105 -> 18504.445 | E10: =H105 -> -87.848212 | F10: =I105 -> -87.848212 | G10: =J105 -> -7.8768592e-11 | H10: =K105 -> 0 | I10: =L105 -> 0
A11: Oil | B11: =E46/10^6 -> 71.810529 | C11: =F46 -> 5368.6101 | D11: =G107 -> 6660.2 | E11: =H107 -> -1291.5899 | F11: =I107 -> 150.36459 | G11: =J107 -> -1441.9545 | H11: =K107 -> 0 | I11: =L107 -> 0
A12: CNG | B12: =E47/10^6 -> 51.763471 | C12: =F47 -> 3869.8767 | D12: =G109 -> 4387.0104 | E12: =H109 -> -517.13365 | F12: =I109 -> -45.509116 | G12: =J109 -> -471.62453 | H12: =K109 -> 0 | I12: =L109 -> 0
A13: Material - others | B13: =E55/10^6 -> 9.7718105 | C13: =F55 -> 730.54803 | D13: =G116 -> 684.51551 | E13: =H116 -> 46.032524 | F13: =I116 -> 31.863332 | G13: =J116 -> 14.169192 | H13: =K116 -> 0 | I13: =L116 -> 0
A14: Upah kupas | B14: =E58/10^6 -> 0 | C14: =F58 -> 0 | D14: =G118 -> 0 | E14: =H118 -> 0 | F14: =I118 -> 0 | G14: =J118 -> 0 | H14: =K118 -> 0 | I14: =L118 -> 0
A15: Direct labour (Grup A) | B15: =E59/10^6 -> 45.171801 | C15: =F59 -> 3377.0785 | D15: =G120 -> 2105.5178 | E15: =H120 -> 1271.5606 | F15: =I120 -> 793.92141 | G15: =J120 -> 0 | H15: =K120 -> -1089.825 | I15: =L120 -> 1567.4642
A16: Factory overhead (Grup B–E) | B16: =E64/10^6 -> 40.451703 | C16: =F64 -> 3024.2003 | D16: =G125 -> 3315.3821 | E16: =H125 -> -291.18187 | F16: =I125 -> 567.41886 | G16: =J125 -> 0 | H16: =K125 -> -1716.056 | I16: =L125 -> 857.45524
A17: Total biaya produksi | B17: =E66/10^6 -> 465.30971 | C17: =F66 -> 34786.91 | D17: =G126 -> 35657.071 | E17: =H126 -> -870.16049 | F17: =I126 -> 1410.2109 | G17: =J126 -> -1899.4098 | H17: =K126 -> -2805.881 | I17: =L126 -> 2424.9195
A18: Produksi bulan ini (kg; aktual, budget) | C18: =$B$32 -> 13376 | D18: =$D$32 -> 6452.5253
A19: Biaya konversi per kg (aktual, budget) | C19: =F65 -> 6401.2787 | D19: =G118+G120+G125 -> 5420.9
A20: HPP (Rp jt) dan HPP per kg terjual (aktual, budget) | B20: =E98/10^6 -> 250.83102 | C20: =D99 -> 34786.91 | D20: =F99 -> 34950.461
A21: Pendapatan (Rp jt; aktual) | B21: =$C$207/10^6 -> 349.70925
A22: Margin kotor (Rp jt; %) | B22: =B21-B20 -> 98.878232 | C22: =IF(B21=0,0,B22/B21) -> 0.28274411
A23: biaya waste (kerugian normal) yang masuk HPP (Rp jt; % biaya produksi) | B23: =E76/10^6 -> 0 | C23: =IF(E66=0,0,E76/E66) -> 0
A24: KW 2 dikreditkan pada NRV (Rp jt) | B24: =-E72/10^6 -> 0
A25: kenaikan WIP + FG (Rp jt) dan porsi biaya konversi di dalamnya | B25: =(E77+E89-E70-E84)/10^6 -> 214.4787 | C25: =IF(E66=0,0,B25*E65/E66) -> 39.467084
A28: 2. Laporan biaya produksi
A29: 2a. Kuantitas (kg)
A30: Pos | B30: Aktual kg | C30: % dari produksi | D30: Budget kg | E30: % budget
A31: WIP awal | B31: =$C$191 -> 0
A32: Produksi bulan ini (masuk proses) | B32: =$C$192 -> 13376 | D32: =INDEX(BUDGET!$C$99:$R$99,$E$5) -> 6452.5253
A33: Total untuk dipertanggungjawabkan | B33: =B31+B32 -> 13376
A34: Premium ke barang jadi | B34: =B33-B35-B36-B37 -> 9333.5 | C34: =IF(B32=0,0,B34/B32) -> 0.69777961 | D34: =INDEX(BUDGET!$C$95:$R$95,$E$5) -> 6388 | E34: =IF(D32=0,0,D34/D32) -> 0.99
A35: KW 2 (produk sampingan) | B35: =$C$194 -> 0 | C35: =IF(B32=0,0,B35/B32) -> 0 | D35: =INDEX(BUDGET!$C$96:$R$96,$E$5) -> 0 | E35: =IF(D32=0,0,D35/D32) -> 0
A36: Keripik waste (kerugian normal) | B36: =$C$195 -> 0 | C36: =IF(B32=0,0,B36/B32) -> 0 | D36: =INDEX(BUDGET!$C$97:$R$97,$E$5) -> 64.525253 | E36: =IF(D32=0,0,D36/D32) -> 0.01
A37: WIP akhir | B37: =$C$193 -> 4042.5 | C37: =IF(B32=0,0,B37/B32) -> 0.30222039 | D37: =INDEX(BUDGET!$C$98:$R$98,$E$5) -> 0 | E37: =IF(D32=0,0,D37/D32) -> 0
A38: Total dipertanggungjawabkan | B38: =SUM(B34:B37) -> 13376
A40: 2b. Biaya produksi bulan ini (aktual)
A41: Komponen | B41: Qty | C41: Satuan | D41: Harga | E41: Nilai (Rp) | F41: Rp/kg
A42: Raw materials
A43: Ubi ungu | B43: =D211 -> 41864 | C43: kg | D43: =F211 -> 5884.3015 | E43: =G211 -> 2.463404e+08 | F43: =IF($B$32=0,0,E43/$B$32) -> 18416.597
A44: Subtotal raw materials | E44: =E43 -> 2.463404e+08 | F44: =IF($B$32=0,0,E44/$B$32) -> 18416.597
A45: Oil & CNG
A46: Minyak olein | B46: =D212 -> 4161 | C46: kg | D46: =F212 -> 17257.998 | E46: =G212 -> 71810529 | F46: =IF($B$32=0,0,E46/$B$32) -> 5368.6101
A47: CNG | B47: =D213/$C$206 -> 228.20131 | C47: MMBTU | D47: =IF(B47=0,0,E47/B47) -> 226832.49 | E47: =G213 -> 51763471 | F47: =IF($B$32=0,0,E47/$B$32) -> 3869.8767
A48: Material - others
A49: Amonium | B49: 0 | C49: kg | D49: 0 | E49: 0 | F49: =IF($B$32=0,0,E49/$B$32) -> 0
A50: HDPE 0,03 | B50: 0 | C50: kg | D50: 0 | E50: 0 | F50: =IF($B$32=0,0,E50/$B$32) -> 0
A51: HDPE 0,06 | B51: 0 | C51: kg | D51: 0 | E51: 0 | F51: =IF($B$32=0,0,E51/$B$32) -> 0
A52: HDPE 0,07 | B52: =D214 -> 269.67 | C52: kg | D52: =F214 -> 33799.845 | E52: =G214 -> 9114804.2 | F52: =IF($B$32=0,0,E52/$B$32) -> 681.42974
A53: Packaging IFM | B53: 0 | C53: kg | D53: 0 | E53: 0 | F53: =IF($B$32=0,0,E53/$B$32) -> 0
A54: Other cost (plakban, tali, label, plastik) | C54: Rp | E54: =SUMIF($C$211:$C$217,"Other cost",$G$211:$G$217) -> 657006.31 | F54: =IF($B$32=0,0,E54/$B$32) -> 49.118295
A55: Subtotal material - others | E55: =E49+E50+E51+E52+E53+E54 -> 9771810.5 | F55: =IF($B$32=0,0,E55/$B$32) -> 730.54803
A56: Total material | E56: =E44+E46+E47+E55 -> 3.7968621e+08 | F56: =IF($B$32=0,0,E56/$B$32) -> 28385.632
A57: Konversi (dari BIAYA BERSAMA)
A58: Upah borongan kupas | B58: =$C$198 -> 0 | C58: kg dikupas | D58: =IF(B58=0,0,E58/B58) -> 0 | E58: ='BIAYA BERSAMA'!D116 -> 0 | F58: =IF($B$32=0,0,E58/$B$32) -> 0
A59: Grup A – DL operator | E59: ='BIAYA BERSAMA'!D115 -> 45171801 | F59: =IF($B$32=0,0,E59/$B$32) -> 3377.0785
A60: Grup B – IDL (support, staf, THR, BPJS) | E60: ='BIAYA BERSAMA'!D117 -> 27274036 | F60: =IF($B$32=0,0,E60/$B$32) -> 2039.0278
A61: Grup C – energi & utilitas | E61: ='BIAYA BERSAMA'!D118 -> 917546.09 | F61: =IF($B$32=0,0,E61/$B$32) -> 68.596448
A62: Grup D – pemeliharaan & penyusutan mesin | E62: ='BIAYA BERSAMA'!D119 -> 4178849.5 | F62: =IF($B$32=0,0,E62/$B$32) -> 312.41399
A63: Grup E – pabrik umum & penyusutan inventaris | E63: ='BIAYA BERSAMA'!D120 -> 8081270.9 | F63: =IF($B$32=0,0,E63/$B$32) -> 604.162
A64: Subtotal factory overhead (Grup B–E) | E64: =E60+E61+E62+E63 -> 40451703 | F64: =IF($B$32=0,0,E64/$B$32) -> 3024.2003
A65: Total konversi | E65: =E58+E59+E64 -> 85623504 | F65: =IF($B$32=0,0,E65/$B$32) -> 6401.2787
A66: TOTAL BIAYA PRODUKSI BULAN INI | E66: =E56+E65 -> 4.6530971e+08 | F66: =IF($B$32=0,0,E66/$B$32) -> 34786.91
A68: 2c. Penilaian hasil (biaya dipertanggungjawabkan = biaya dibebankan)
A69: Pos | B69: Kg | D69: Rp/kg | E69: Nilai (Rp) | F69: Budget Rp/kg
A70: WIP awal | B70: =B31 -> 0 | E70: =$C$196 -> 0
A71: Biaya produksi bulan ini | B71: =B32 -> 13376 | E71: =E66 -> 4.6530971e+08
A72: Dikurangi: KW 2 dinilai NRV (ke persediaan KW 2) | B72: =-B35 -> 0 | E72: 0
A73: Biaya untuk premium, waste, dan WIP akhir | B73: =SUM(B70:B72) -> 13376 | E73: =SUM(E70:E72) -> 4.6530971e+08
A74: Biaya rata-rata tertimbang per kg | D74: =IF(B73=0,0,E73/B73) -> 34786.91 | F74: =INDEX(BUDGET!$C$126:$R$126,$E$5) -> 34988.714
A75: Premium ke barang jadi | B75: =B34 -> 9333.5 | E75: =B75*$D$74 -> 3.2468363e+08
A76: Keripik waste ke HPP (kerugian normal) | B76: =B36 -> 0 | E76: =B76*$D$74 -> 0
A77: WIP akhir | B77: =B37 -> 4042.5 | E77: =B77*$D$74 -> 1.4062609e+08
A78: Total dibebankan | B78: =SUM(B75:B77) -> 13376 | E78: =SUM(E75:E77) -> 4.6530971e+08
A79: dibebankan (harus nol) | B79: =B73-B78 -> 0 | E79: =E73-E78 -> 0
A80: nilai WIP akhir menurut Accurate | E80: =$C$197 -> 1.2574878e+08
A82: 3. Barang jadi (FG-101 FSPC Ungu Premium) dan HPP
A83: Pos | B83: Kg | D83: Rp/kg | E83: Nilai (Rp) | F83: Budget Rp/kg
A84: Saldo awal | B84: =$C$201 -> 0 | E84: =IF($C$201=0,0,$C$202) -> 0
A85: Masuk dari produksi | B85: =B75 -> 9333.5 | E85: =E75 -> 3.2468363e+08
A86: Tersedia | B86: =B84+B85 -> 9333.5 | E86: =E84+E85 -> 3.2468363e+08
A87: Biaya rata-rata tertimbang per kg | D87: =IF(B86=0,0,E86/B86) -> 34786.91 | F87: =INDEX(BUDGET!$C$127:$R$127,$E$5) -> 34597.04
A88: Keluar: penjualan ke IFM | B88: =$C$203 -> 7210.5 | E88: =B88*$D$87 -> 2.5083102e+08
A89: Saldo akhir (kg menurut Accurate) | B89: =$C$204 -> 2123 | E89: =B89*$D$87 -> 73852611
A90: Selisih kuantitas (tersedia − keluar − saldo akhir) | B90: =B86-B88-B89 -> 0 | E90: =B90*$D$87 -> 0
A91: Nilai saldo akhir menurut Accurate | E91: =$C$205 -> 67731842
A92: Residu nilai saldo awal tanpa kuantitas (tidak ikut rata-rata) | E92: =$C$202-E84 -> 1692346.9
A94: HPP
A95: HPP penjualan ke IFM | E95: =E88 -> 2.5083102e+08
A96: HPP keripik waste | E96: =E76 -> 0
A97: HPP selisih kuantitas FG | E97: =E90 -> 0
A98: Total HPP | E98: =E95+E96+E97 -> 2.5083102e+08
A99: HPP (IFM + waste) per kg terjual ke IFM | D99: =IF(B88=0,0,(E95+E96)/B88) -> 34786.91 | F99: =IF(INDEX(BUDGET!$C$95:$R$95,$E$5)=0,0,INDEX(BUDGET!$C$128:$R$128,$E$5)/INDEX(BUDGET!$C$95:$R$95,$E$5)) -> 34950.461
A100: Budget total HPP (volume budget) | E100: =INDEX(BUDGET!$C$128:$R$128,$E$5) -> 2.2326355e+08
A102: 4. Selisih vs budget per komponen (Rp/kg produksi)
A103: Komponen | B103: Qty/kg aktual | C103: Qty/kg budget | D103: Harga aktual | E103: Harga budget | F103: Rp/kg aktual | G103: Rp/kg budget | H103: Selisih | I103: Harga / belanja | J103: Pemakaian / yield | K103: Volume | L103: Metode alokasi | M103: Cek
A104: Ubi ungu | B104: =IF($B$32=0,0,B43/$B$32) -> 3.1297847 | C104: =IF($D$32=0,0,INDEX(BUDGET!$C$101:$R$101,$E$5)/$D$32) -> 3.1297847 | D104: =D43 -> 5884.3015 | E104: =IF(INDEX(BUDGET!$C$101:$R$101,$E$5)=0,0,INDEX(BUDGET!$C$102:$R$102,$E$5)/INDEX(BUDGET!$C$101:$R$101,$E$5)) -> 5912.37 | F104: =F43 -> 18416.597 | G104: =IF($D$32=0,0,INDEX(BUDGET!$C$102:$R$102,$E$5)/$D$32) -> 18504.445 | H104: =F104-G104 -> -87.848212 | I104: =(D104-E104)*B104 -> -87.848212 | J104: =(B104-C104)*E104 -> -7.8768592e-11 | K104: 0 | L104: 0 | M104: =H104-I104-J104-K104-L104 -> -2.3043345e-12
A105: Raw materials | F105: =F104 -> 18416.597 | G105: =G104 -> 18504.445 | H105: =H104 -> -87.848212 | I105: =I104 -> -87.848212 | J105: =J104 -> -7.8768592e-11 | K105: =K104 -> 0 | L105: =L104 -> 0 | M105: =M104 -> -2.3043345e-12
A106: Minyak olein | B106: =IF($B$32=0,0,B46/$B$32) -> 0.31107955 | C106: =IF($D$32=0,0,INDEX(BUDGET!$C$103:$R$103,$E$5)/$D$32) -> 0.39703996 | D106: =D46 -> 17257.998 | E106: =IF(INDEX(BUDGET!$C$103:$R$103,$E$5)=0,0,INDEX(BUDGET!$C$104:$R$104,$E$5)/INDEX(BUDGET!$C$103:$R$103,$E$5)) -> 16774.634 | F106: =F46 -> 5368.6101 | G106: =IF($D$32=0,0,INDEX(BUDGET!$C$104:$R$104,$E$5)/$D$32) -> 6660.2 | H106: =F106-G106 -> -1291.5899 | I106: =(D106-E106)*B106 -> 150.36459 | J106: =(B106-C106)*E106 -> -1441.9545 | K106: 0 | L106: 0 | M106: =H106-I106-J106-K106-L106 -> -2.2737368e-13
A107: Oil | F107: =F106 -> 5368.6101 | G107: =G106 -> 6660.2 | H107: =H106 -> -1291.5899 | I107: =I106 -> 150.36459 | J107: =J106 -> -1441.9545 | K107: =K106 -> 0 | L107: =L106 -> 0 | M107: =M106 -> -2.2737368e-13
A108: CNG (MMBTU) | B108: =IF($B$32=0,0,B47/$B$32) -> 0.017060505 | C108: =IF($D$32=0,0,INDEX(BUDGET!$C$105:$R$105,$E$5)/$D$32) -> 0.019115514 | D108: =D47 -> 226832.49 | E108: =IF(INDEX(BUDGET!$C$105:$R$105,$E$5)=0,0,INDEX(BUDGET!$C$106:$R$106,$E$5)/INDEX(BUDGET!$C$105:$R$105,$E$5)) -> 229500 | F108: =F47 -> 3869.8767 | G108: =IF($D$32=0,0,INDEX(BUDGET!$C$106:$R$106,$E$5)/$D$32) -> 4387.0104 | H108: =F108-G108 -> -517.13365 | I108: =(D108-E108)*B108 -> -45.509116 | J108: =(B108-C108)*E108 -> -471.62453 | K108: 0 | L108: 0 | M108: =H108-I108-J108-K108-L108 -> 0
A109: CNG | F109: =F108 -> 3869.8767 | G109: =G108 -> 4387.0104 | H109: =H108 -> -517.13365 | I109: =I108 -> -45.509116 | J109: =J108 -> -471.62453 | K109: =K108 -> 0 | L109: =L108 -> 0 | M109: =M108 -> 0
A110: Amonium | B110: =IF($B$32=0,0,B49/$B$32) -> 0 | C110: =IF($D$32=0,0,INDEX(BUDGET!$C$107:$R$107,$E$5)/$D$32) -> 0 | D110: =D49 -> 0 | E110: =IF(INDEX(BUDGET!$C$107:$R$107,$E$5)=0,0,INDEX(BUDGET!$C$108:$R$108,$E$5)/INDEX(BUDGET!$C$107:$R$107,$E$5)) -> 0 | F110: =F49 -> 0 | G110: =IF($D$32=0,0,INDEX(BUDGET!$C$108:$R$108,$E$5)/$D$32) -> 0 | H110: =F110-G110 -> 0 | I110: =(D110-E110)*B110 -> 0 | J110: =(B110-C110)*E110 -> 0 | K110: 0 | L110: 0 | M110: =H110-I110-J110-K110-L110 -> 0
A111: HDPE 0,03 | B111: =IF($B$32=0,0,B50/$B$32) -> 0 | C111: =IF($D$32=0,0,INDEX(BUDGET!$C$109:$R$109,$E$5)/$D$32) -> 0.00092582939 | D111: =D50 -> 0 | E111: =IF(INDEX(BUDGET!$C$109:$R$109,$E$5)=0,0,INDEX(BUDGET!$C$110:$R$110,$E$5)/INDEX(BUDGET!$C$109:$R$109,$E$5)) -> 31542.626 | F111: =F50 -> 0 | G111: =IF($D$32=0,0,INDEX(BUDGET!$C$110:$R$110,$E$5)/$D$32) -> 29.20309 | H111: =F111-G111 -> -29.20309 | I111: =(D111-E111)*B111 -> 0 | J111: =(B111-C111)*E111 -> -29.20309 | K111: 0 | L111: 0 | M111: =H111-I111-J111-K111-L111 -> 0
...

Sheet UO
A1: KARTU BIAYA PRODUKSI – UBI ORANGE IFM (QKSO), Agustus 2026
A2: Sistem biaya: biaya aktual, penyerapan penuh. Material ditelusuri per produk dari laporan produksi; biaya konversi dialokasikan dari BIAYA BERSAMA dengan driver aktual bulan berjalan. WIP/FG dinilai rata-rata tertimbang; KW 2 pada NRV.
A3: Biru = input (lampiran), hijau = tautan antarsheet, hitam = rumus. Ringkasan dalam Rp juta; rincian dalam Rp.
A5: Bulan budget pembanding | C5: Okt-26 | D5: posisi: | E5: =MATCH(C5,BUDGET!$C$4:$R$4,0) -> 2
A6: Status kontrol (bagian 6) | C6: =IF(COUNTIF(D149:D159,"GAGAL")=0,"LULUS","GAGAL") -> LULUS
A8: 1. Ringkasan (Rp juta; Rp/kg per kg produksi bulan ini)
A9: Komponen | B9: Aktual (Rp jt) | C9: Aktual Rp/kg | D9: Budget Rp/kg | E9: Selisih Rp/kg | F9: Harga / belanja | G9: Pemakaian / yield | H9: Volume | I9: Metode alokasi
A10: Raw materials | B10: =E44/10^6 -> 122.5183 | C10: =F44 -> 16549.818 | D10: =G105 -> 17002.503 | E10: =H105 -> -452.68502 | F10: =I105 -> 512.35428 | G10: =J105 -> -965.0393 | H10: =K105 -> 0 | I10: =L105 -> 0
A11: Oil | B11: =E46/10^6 -> 35.620507 | C11: =F46 -> 4811.6314 | D11: =G107 -> 7164.2475 | E11: =H107 -> -2352.616 | F11: =I107 -> 134.76467 | G11: =J107 -> -2487.3807 | H11: =K107 -> 0 | I11: =L107 -> 0
A12: CNG | B12: =E47/10^6 -> 29.661172 | C12: =F47 -> 4006.6422 | D12: =G109 -> 4275.0389 | E12: =H109 -> -268.39671 | F12: =I109 -> -47.117456 | G12: =J109 -> -221.27925 | H12: =K109 -> 0 | I12: =L109 -> 0
A13: Material - others | B13: =E55/10^6 -> 5.4466894 | C13: =F55 -> 735.74084 | D13: =G116 -> 719.74157 | E13: =H116 -> 15.999269 | F13: =I116 -> 31.91672 | G13: =J116 -> -15.917452 | H13: =K116 -> 0 | I13: =L116 -> 0
A14: Upah kupas | B14: =E58/10^6 -> 0 | C14: =F58 -> 0 | D14: =G118 -> 0 | E14: =H118 -> 0 | F14: =I118 -> 0 | G14: =J118 -> 0 | H14: =K118 -> 0 | I14: =L118 -> 0
A15: Direct labour (Grup A) | B15: =E59/10^6 -> 24.009429 | C15: =F59 -> 3243.2026 | D15: =G120 -> 2105.5178 | E15: =H120 -> 1137.6848 | F15: =I120 -> 211.02723 | G15: =J120 -> 0 | H15: =K120 -> -506.93085 | I15: =L120 -> 1433.5884
A16: Factory overhead (Grup B–E) | B16: =E64/10^6 -> 21.678333 | C16: =F64 -> 2928.3172 | D16: =G125 -> 2649.1451 | E16: =H125 -> 279.17215 | F16: =I125 -> 134.33127 | G16: =J125 -> 0 | H16: =K125 -> -637.81619 | I16: =L125 -> 782.65708
A17: Total biaya produksi | B17: =E66/10^6 -> 238.93443 | C17: =F66 -> 32275.352 | D17: =G126 -> 33916.194 | E17: =H126 -> -1640.8416 | F17: =I126 -> 977.27671 | G17: =J126 -> -3689.6167 | H17: =K126 -> -1144.747 | I17: =L126 -> 2216.2455
A18: Produksi bulan ini (kg; aktual, budget) | C18: =$B$32 -> 7403 | D18: =$D$32 -> 5620.6313
A19: Biaya konversi per kg (aktual, budget) | C19: =F65 -> 6171.5199 | D19: =G118+G120+G125 -> 4754.6629
A20: HPP (Rp jt) dan HPP per kg terjual (aktual, budget) | B20: =E98/10^6 -> 238.93443 | C20: =D99 -> 32275.352 | D20: =F99 -> 34110.89
A21: Pendapatan (Rp jt; aktual) | B21: =$C$208/10^6 -> 354.6037 | F21: Sumber: Lampiran A. Pendapatan dikelompokkan sejalan dengan biayanya
A22: Margin kotor (Rp jt; %) | B22: =B21-B20 -> 115.66927 | C22: =IF(B21=0,0,B22/B21) -> 0.32619307
A23: Memo: biaya waste (kerugian normal) yang masuk HPP (Rp jt; % biaya produksi) | B23: =E76/10^6 -> 0 | C23: =IF(E66=0,0,E76/E66) -> 0
A24: Memo: KW 2 dikreditkan pada NRV (Rp jt) | B24: =-E72/10^6 -> 0
A25: Memo: kenaikan WIP + FG (Rp jt) dan porsi biaya konversi di dalamnya | B25: =(E77+E89-E70-E84)/10^6 -> 0 | C25: =IF(E66=0,0,B25*E65/E66) -> 0 | F25: Biaya konversi yang tertahan di neraca bila produksi > penjualan
A26: Pemilik efek: harga → Purchasing; pemakaian/yield → Produksi; volume → PPIC; belanja pool → pemilik pool (Produksi/Engineering/HR); metode alokasi → Finance (costing).
A28: 2. Laporan biaya produksi
A29: 2a. Kuantitas (kg)
A30: Pos | B30: Aktual kg | C30: % dari produksi | D30: Budget kg | E30: % budget
A31: WIP awal | B31: =$C$192 -> 0
A32: Produksi bulan ini (masuk proses) | B32: =$C$193 -> 7403 | D32: =INDEX(BUDGET!$C$152:$R$152,$E$5) -> 5620.6313
A33: Total untuk dipertanggungjawabkan | B33: =B31+B32 -> 7403
A34: Premium ke barang jadi | B34: =B33-B35-B36-B37 -> 7403 | C34: =IF(B32=0,0,B34/B32) -> 1 | D34: =INDEX(BUDGET!$C$148:$R$148,$E$5) -> 5564.425 | E34: =IF(D32=0,0,D34/D32) -> 0.99
A35: KW 2 (produk sampingan) | B35: =$C$195 -> 0 | C35: =IF(B32=0,0,B35/B32) -> 0 | D35: =INDEX(BUDGET!$C$149:$R$149,$E$5) -> 0 | E35: =IF(D32=0,0,D35/D32) -> 0
A36: Keripik waste (kerugian normal) | B36: =$C$196 -> 0 | C36: =IF(B32=0,0,B36/B32) -> 0 | D36: =INDEX(BUDGET!$C$150:$R$150,$E$5) -> 56.206313 | E36: =IF(D32=0,0,D36/D32) -> 0.01
A37: WIP akhir | B37: =$C$194 -> 0 | C37: =IF(B32=0,0,B37/B32) -> 0 | D37: =INDEX(BUDGET!$C$151:$R$151,$E$5) -> 0 | E37: =IF(D32=0,0,D37/D32) -> 0
A38: Total dipertanggungjawabkan | B38: =SUM(B34:B37) -> 7403
A40: 2b. Biaya produksi bulan ini (aktual)
A41: Komponen | B41: Qty | C41: Satuan | D41: Harga | E41: Nilai (Rp) | F41: Rp/kg
A42: Raw materials
A43: Ubi orange | B43: =D212 -> 26039 | C43: kg | D43: =F212 -> 4705.1845 | E43: =G212 -> 1.225183e+08 | F43: =IF($B$32=0,0,E43/$B$32) -> 16549.818
A44: Subtotal raw materials | E44: =E43 -> 1.225183e+08 | F44: =IF($B$32=0,0,E44/$B$32) -> 16549.818
A45: Oil & CNG
A46: Minyak olein | B46: =D213 -> 2064 | C46: kg | D46: =F213 -> 17257.998 | E46: =G213 -> 35620507 | F46: =IF($B$32=0,0,E46/$B$32) -> 4811.6314
A47: CNG | B47: =D214/$C$207 -> 130.76245 | C47: MMBTU | D47: =IF(B47=0,0,E47/B47) -> 226832.49 | E47: =G214 -> 29661172 | F47: =IF($B$32=0,0,E47/$B$32) -> 4006.6422
A48: Material - others
A49: Amonium | B49: 0 | C49: kg | D49: 0 | E49: 0 | F49: =IF($B$32=0,0,E49/$B$32) -> 0
A50: HDPE 0,03 | B50: 0 | C50: kg | D50: 0 | E50: 0 | F50: =IF($B$32=0,0,E50/$B$32) -> 0
A51: HDPE 0,05 | B51: 0 | C51: kg | D51: 0 | E51: 0 | F51: =IF($B$32=0,0,E51/$B$32) -> 0
A52: HDPE 0,07 | B52: =D215 -> 149.5 | C52: kg | D52: =F215 -> 33799.845 | E52: =G215 -> 5053076.8 | F52: =IF($B$32=0,0,E52/$B$32) -> 682.5715
A53: Packaging IFM | B53: 0 | C53: kg | D53: 0 | E53: 0 | F53: =IF($B$32=0,0,E53/$B$32) -> 0
A54: Other cost (plakban, tali, label, plastik) | C54: Rp | E54: =SUMIF($C$212:$C$218,"Other cost",$G$212:$G$218) -> 393612.63 | F54: =IF($B$32=0,0,E54/$B$32) -> 53.16934
A55: Subtotal material - others | E55: =E49+E50+E51+E52+E53+E54 -> 5446689.4 | F55: =IF($B$32=0,0,E55/$B$32) -> 735.74084
A56: Total material | E56: =E44+E46+E47+E55 -> 1.9324667e+08 | F56: =IF($B$32=0,0,E56/$B$32) -> 26103.832
A57: Konversi (dari BIAYA BERSAMA)
A58: Upah borongan kupas | B58: =$C$199 -> 0 | C58: kg dikupas | D58: =IF(B58=0,0,E58/B58) -> 0 | E58: ='BIAYA BERSAMA'!E116 -> 0 | F58: =IF($B$32=0,0,E58/$B$32) -> 0
A59: Grup A – DL operator | E59: ='BIAYA BERSAMA'!E115 -> 24009429 | F59: =IF($B$32=0,0,E59/$B$32) -> 3243.2026
A60: Grup B – IDL (support, staf, THR, BPJS) | E60: ='BIAYA BERSAMA'!E117 -> 14496523 | F60: =IF($B$32=0,0,E60/$B$32) -> 1958.1957
A61: Grup C – energi & utilitas | E61: ='BIAYA BERSAMA'!E118 -> 552489.25 | F61: =IF($B$32=0,0,E61/$B$32) -> 74.630454
A62: Grup D – pemeliharaan & penyusutan mesin | E62: ='BIAYA BERSAMA'!E119 -> 2516243.5 | F62: =IF($B$32=0,0,E62/$B$32) -> 339.89512
A63: Grup E – pabrik umum & penyusutan inventaris | E63: ='BIAYA BERSAMA'!E120 -> 4113077.2 | F63: =IF($B$32=0,0,E63/$B$32) -> 555.596
A64: Subtotal factory overhead (Grup B–E) | E64: =E60+E61+E62+E63 -> 21678333 | F64: =IF($B$32=0,0,E64/$B$32) -> 2928.3172
A65: Total konversi | E65: =E58+E59+E64 -> 45687762 | F65: =IF($B$32=0,0,E65/$B$32) -> 6171.5199
A66: TOTAL BIAYA PRODUKSI BULAN INI | E66: =E56+E65 -> 2.3893443e+08 | F66: =IF($B$32=0,0,E66/$B$32) -> 32275.352
A68: 2c. Penilaian hasil (biaya dipertanggungjawabkan = biaya dibebankan)
A69: Pos | B69: Kg | D69: Rp/kg | E69: Nilai (Rp) | F69: Budget Rp/kg
A70: WIP awal | B70: =B31 -> 0 | E70: =$C$197 -> 0
A71: Biaya produksi bulan ini | B71: =B32 -> 7403 | E71: =E66 -> 2.3893443e+08
A72: Dikurangi: KW 2 dinilai NRV (ke persediaan KW 2) | B72: =-B35 -> 0 | E72: 0
A73: Biaya untuk premium, waste, dan WIP akhir | B73: =SUM(B70:B72) -> 7403 | E73: =SUM(E70:E72) -> 2.3893443e+08
A74: Biaya rata-rata tertimbang per kg | D74: =IF(B73=0,0,E73/B73) -> 32275.352 | F74: =INDEX(BUDGET!$C$179:$R$179,$E$5) -> 33916.194
A75: Premium ke barang jadi | B75: =B34 -> 7403 | E75: =B75*$D$74 -> 2.3893443e+08
A76: Keripik waste ke HPP (kerugian normal) | B76: =B36 -> 0 | E76: =B76*$D$74 -> 0
A77: WIP akhir | B77: =B37 -> 0 | E77: =B77*$D$74 -> 0
A78: Total dibebankan | B78: =SUM(B75:B77) -> 7403 | E78: =SUM(E75:E77) -> 2.3893443e+08
A79: Cek: dipertanggungjawabkan − dibebankan (harus nol) | B79: =B73-B78 -> 0 | E79: =E73-E78 -> 0
A80: Memo: nilai WIP akhir menurut Accurate | E80: =$C$198 -> 0
A82: 3. Barang jadi (FG-102 FSPC Orange Premium) dan HPP
A83: Pos | B83: Kg | D83: Rp/kg | E83: Nilai (Rp) | F83: Budget Rp/kg
A84: Saldo awal | B84: =$C$202 -> 0 | E84: =IF($C$202=0,0,$C$203) -> 0
A85: Masuk dari produksi | B85: =B75 -> 7403 | E85: =E75 -> 2.3893443e+08
A86: Tersedia | B86: =B84+B85 -> 7403 | E86: =E84+E85 -> 2.3893443e+08
A87: Biaya rata-rata tertimbang per kg | D87: =IF(B86=0,0,E86/B86) -> 32275.352 | F87: =INDEX(BUDGET!$C$180:$R$180,$E$5) -> 33768.302
A88: Keluar: penjualan ke IFM | B88: =$C$204 -> 7403 | E88: =B88*$D$87 -> 2.3893443e+08
A89: Saldo akhir (kg menurut Accurate) | B89: =$C$205 -> 0 | E89: =B89*$D$87 -> 0
A90: Selisih kuantitas (tersedia − keluar − saldo akhir) | B90: =B86-B88-B89 -> 0 | E90: =B90*$D$87 -> 0
A91: Memo: nilai saldo akhir menurut Accurate | E91: =$C$206 -> -974521.91
A92: Memo: residu nilai saldo awal tanpa kuantitas (tidak ikut rata-rata) | E92: =$C$203-E84 -> -974521.91
A94: HPP
A95: HPP penjualan ke IFM | E95: =E88 -> 2.3893443e+08
A96: HPP keripik waste | E96: =E76 -> 0
A97: HPP selisih kuantitas FG | E97: =E90 -> 0
A98: Total HPP | E98: =E95+E96+E97 -> 2.3893443e+08
A99: HPP (IFM + waste) per kg terjual ke IFM | D99: =IF(B88=0,0,(E95+E96)/B88) -> 32275.352 | F99: =IF(INDEX(BUDGET!$C$148:$R$148,$E$5)=0,0,INDEX(BUDGET!$C$181:$R$181,$E$5)/INDEX(BUDGET!$C$148:$R$148,$E$5)) -> 34110.89
A100: Budget total HPP (volume budget) | E100: =INDEX(BUDGET!$C$181:$R$181,$E$5) -> 1.8980749e+08
A102: 4. Selisih vs budget per komponen (Rp/kg produksi)
A103: Komponen | B103: Qty/kg aktual | C103: Qty/kg budget | D103: Harga aktual | E103: Harga budget | F103: Rp/kg aktual | G103: Rp/kg budget | H103: Selisih | I103: Harga / belanja | J103: Pemakaian / yield | K103: Volume | L103: Metode alokasi | M103: Cek
A104: Ubi orange | B104: =IF($B$32=0,0,B43/$B$32) -> 3.5173578 | C104: =IF($D$32=0,0,INDEX(BUDGET!$C$154:$R$154,$E$5)/$D$32) -> 3.7290115 | D104: =D43 -> 4705.1845 | E104: =IF(INDEX(BUDGET!$C$154:$R$154,$E$5)=0,0,INDEX(BUDGET!$C$155:$R$155,$E$5)/INDEX(BUDGET!$C$154:$R$154,$E$5)) -> 4559.52 | F104: =F43 -> 16549.818 | G104: =IF($D$32=0,0,INDEX(BUDGET!$C$155:$R$155,$E$5)/$D$32) -> 17002.503 | H104: =F104-G104 -> -452.68502 | I104: =(D104-E104)*B104 -> 512.35428 | J104: =(B104-C104)*E104 -> -965.0393 | K104: 0 | L104: 0 | M104: =H104-I104-J104-K104-L104 -> 1.8189894e-12
A105: Raw materials | F105: =F104 -> 16549.818 | G105: =G104 -> 17002.503 | H105: =H104 -> -452.68502 | I105: =I104 -> 512.35428 | J105: =J104 -> -965.0393 | K105: =K104 -> 0 | L105: =L104 -> 0 | M105: =M104 -> 1.8189894e-12
A106: Minyak olein | B106: =IF($B$32=0,0,B46/$B$32) -> 0.27880589 | C106: =IF($D$32=0,0,INDEX(BUDGET!$C$156:$R$156,$E$5)/$D$32) -> 0.42708815 | D106: =D46 -> 17257.998 | E106: =IF(INDEX(BUDGET!$C$156:$R$156,$E$5)=0,0,INDEX(BUDGET!$C$157:$R$157,$E$5)/INDEX(BUDGET!$C$156:$R$156,$E$5)) -> 16774.634 | F106: =F46 -> 4811.6314 | G106: =IF($D$32=0,0,INDEX(BUDGET!$C$157:$R$157,$E$5)/$D$32) -> 7164.2475 | H106: =F106-G106 -> -2352.616 | I106: =(D106-E106)*B106 -> 134.76467 | J106: =(B106-C106)*E106 -> -2487.3807 | K106: 0 | L106: 0 | M106: =H106-I106-J106-K106-L106 -> -4.5474735e-13
A107: Oil | F107: =F106 -> 4811.6314 | G107: =G106 -> 7164.2475 | H107: =H106 -> -2352.616 | I107: =I106 -> 134.76467 | J107: =J106 -> -2487.3807 | K107: =K106 -> 0 | L107: =L106 -> 0 | M107: =M106 -> -4.5474735e-13
A108: CNG (MMBTU) | B108: =IF($B$32=0,0,B47/$B$32) -> 0.017663441 | C108: =IF($D$32=0,0,INDEX(BUDGET!$C$158:$R$158,$E$5)/$D$32) -> 0.018627621 | D108: =D47 -> 226832.49 | E108: =IF(INDEX(BUDGET!$C$158:$R$158,$E$5)=0,0,INDEX(BUDGET!$C$159:$R$159,$E$5)/INDEX(BUDGET!$C$158:$R$158,$E$5)) -> 229500 | F108: =F47 -> 4006.6422 | G108: =IF($D$32=0,0,INDEX(BUDGET!$C$159:$R$159,$E$5)/$D$32) -> 4275.0389 | H108: =F108-G108 -> -268.39671 | I108: =(D108-E108)*B108 -> -47.117456 | J108: =(B108-C108)*E108 -> -221.27925 | K108: 0 | L108: 0 | M108: =H108-I108-J108-K108-L108 -> 2.8421709e-14
...

Sheet LAIN-LAIN
A1: KARTU BIAYA PRODUKSI – LAIN-LAIN (retail, koperasi, maklon), Agustus 2026
A2: Satu baris per kelompok produk. Bahan antarproduk (FCC premium, KW 2) dinilai dari sheet FCC. Konversi dari BIAYA BERSAMA kolom Lain-lain. HPP = biaya produksi (belum ada roll-forward persediaan Lain-lain).
A3: Biru = input (lampiran), hijau = tautan antarsheet, hitam = rumus. Ringkasan dalam Rp juta; rincian dalam Rp.
A5: Bulan budget pembanding | C5: Okt-26 | D5: posisi: | E5: =MATCH(C5,BUDGET!$C$4:$R$4,0) -> 2
A6: Status kontrol (bagian 4) | C6: =IF(COUNTIF(D72:D75,"GAGAL")=0,"LULUS","GAGAL") -> LULUS
A7: Nilai KW 2 ubi (Rp/kg) | C7: 0 | D7: ASUMSI no. 7: UU/UO tidak mencatat KW 2, jadi belum ada NRV; nol konsisten dengan tidak adanya kredit KW 2 di UU/UO
A9: 1. Ringkasan (Rp juta)
A10: Pos | B10: Aktual (Rp jt) | C10: Budget (Rp jt) | D10: Selisih
A11: Material eksternal + konversi (tanpa bahan antarproduk) | B11: =(D68+E68+F68)/10^6 -> 84.76126 | C11: =INDEX(BUDGET!$C$198:$R$198,$E$5)/10^6 -> 41.069007 | D11: =B11-C11 -> 43.692253 | E11: Budget Lain-lain di BP masih nilai beku dan tidak memuat bahan antarproduk
A12: Bahan antarproduk (FCC premium, KW 2) | B12: =(B68+C68)/10^6 -> 270.8207
A13: di dalamnya: konversi (DL + FOH) | B13: =(E68+F68)/10^6 -> 72.12766
A14: Total biaya produksi = HPP Lain-lain | B14: =G68/10^6 -> 355.58196 | C14: =INDEX(BUDGET!$C$199:$R$199,$E$5)/10^6 -> 41.069007 | D14: =B14-C14 -> 314.51296
A15: Output (kg) | B15: =C43 -> 17571.48
A16: Biaya per kg (Rp) | B16: =H68 -> 20236.313
A17: Pendapatan Others: retail & maklon + KW 2 berbumbu (Rp jt; BP Data Aktual P68 + P65) | B17: =416714799.61/10^6 -> 416.7148
A18: Margin kotor Others (Rp jt; %) | B18: =B17-B14 -> 61.132836 | C18: =IF(B17=0,0,B18/B17) -> 0.14670186
A20: 2. Input per kelompok produk (Lampiran: kartu LAP di WP lama)
A21: Kelompok produk | B21: Lini bahan utama (akun varian) | C21: Output (kg) | D21: Input FCC premium (kg) | E21: Input KW 2 FCC (kg) | F21: Input KW 2 ubi (kg) | G21: Material eksternal (Rp) | H21: Man-hour | I21: kWh | J21: Bulan aktif Jan–Agu | K21: Kartu sumber | L21: Catatan
A22: Cem-cem ORI | B22: Singkong | C22: 5124.6 | D22: 4950 | E22: 0 | F22: 0 | G22: 257400 | H22: 421.02738 | I22: 1982.0326 | J22: Agu | K22: LAP BAG CEMCEM ORI | L22: Bumbu Seors 295,83 kg belum berharga (harga 0)
A23: Cem-cem BBQ | B23: Singkong | C23: 5047.2 | D23: 4807 | E23: 0 | F23: 0 | G23: 316800 | H23: 414.97262 | I23: 1982.0326 | J23: Agu | K23: LAP BAG CEMCEM BBQ | L23: Bumbu BBQ 335,2 kg belum berharga; kWh sama persis dengan ORI
A24: Koperasi (KW 2 berbumbu, 11 SKU) | B24: Singkong | C24: 5874 | D24: 0 | E24: 4784.8 | F24: 740.94 | G24: 11730364 | H24: 237 | I24: 0 | J24: Jan–Agu | K24: Bagging Kop | L24: Input KW 2 di kartu lama bernilai nol
A25: Maicih basreng (maklon, 3 SKU) | B25: Singkong (maklon) | C25: 626 | D25: 0 | E25: 0 | F25: 0 | G25: 23956.193 | H25: 44.762947 | I25: 369.94888 | J25: Jan–Agu, tidak tiap bulan | K25: LAP BAG MAICIH BASRENG L.0/5/10 LOK | L25: Basreng, polyfilm, karton dari pelanggan
A26: Maicih keripik (LV 3 & 10) | B26: Singkong | C26: 899.68 | D26: 0 | E26: 833 | F26: 0 | G26: 305079.82 | H26: 73.575359 | I26: 423.79847 | J26: Jan–Agu kecuali Jun | K26: LAP BAG MAICIH KERIPIK LV 3/10 | L26: Nama kartu di Labor (M) dan Overhead Allocation (SA) berbeda
A27: Maicih keripik LV 5 | B27: Singkong | C27: 0 | D27: 0 | E27: 0 | F27: 0 | G27: 0 | H27: 0 | I27: 0 | J27: Jan–Jul kecuali Jun | K27: LAP BAG MAICIH KERIPIK LV 5 | L27: Tidak aktif di Agustus
A28: FCC Maicih | B28: Singkong | C28: 0 | D28: 0 | E28: 0 | F28: 0 | G28: 0 | H28: 0 | I28: 0 | J28: Jan, Feb, Jul | K28: FCC MAICIH | L28: Tidak aktif di Agustus
A29: FCC Putih | B29: Singkong | C29: 0 | D29: 0 | E29: 0 | F29: 0 | G29: 0 | H29: 0 | I29: 0 | J29: - | K29: FCCPUTIH | L29: Tidak aktif di Agustus
A30: Kecimpring (goreng & bagging) | B30: Singkong | C30: 0 | D30: 0 | E30: 0 | F30: 0 | G30: 0 | H30: 0 | I30: 0 | J30: Jan, Feb | K30: LAP GORENG/BAGGING KECIMPRING, KECIMPRING BMG/Sani | L30: Tidak aktif di Agustus
A31: Whole chips rempah 15/90 gr | B31: Singkong | C31: 0 | D31: 0 | E31: 0 | F31: 0 | G31: 0 | H31: 0 | I31: 0 | J31: Jul | K31: LAP WHOLE CHIPS REMPAH 15GR/90GR | L31: Tidak aktif di Agustus
A32: Maxi (pellet & goreng) | B32: Singkong – cek bahan | C32: 0 | D32: 0 | E32: 0 | F32: 0 | G32: 0 | H32: 0 | I32: 0 | J32: Jul | K32: PELELT MAXI BIONIC, LAP GORENG MAXI 3X3 | L32: Tidak aktif di Agustus
A33: Pellet ubi ungu FG (1,2x1,5 & 3x3) | B33: Ubi Ungu | C33: 0 | D33: 0 | E33: 0 | F33: 0 | G33: 0 | H33: 0 | I33: 0 | J33: Jan, Jun | K33: PELELT UBI UNGU FG 1.2x1.5 / 3x3 | L33: Tidak aktif di Agustus
... A42: WRP (Delichips, Mixfruit, chips) – maklon | B42: Singkong (maklon) | C42: 0 | D42: 0 | E42: 0 | F42: 0 | G42: 0 | H42: 0 | I42: 0 | J42: Apr, Jun, Jul | K42: LAP BAG WRP DELICHIPS/MIXFRUIT, WRP Chips | L42: Tidak aktif di Agustus
A43: Total | C43: =SUM(C22:C42) -> 17571.48 | D43: =SUM(D22:D42) -> 9757 | E43: =SUM(E22:E42) -> 5617.8 | F43: =SUM(F22:F42) -> 740.94 | G43: =SUM(G22:G42) -> 12633600 | H43: =SUM(H22:H42) -> 1191.3383 | I43: =SUM(I22:I42) -> 4757.8126
A45: 3. Biaya produksi per kelompok (Rp)
A46: Kelompok produk | B46: FCC premium | C46: KW 2 | D46: Material eksternal | E46: DL (Grup A) | F46: FOH (Grup B–E) | G46: Total biaya | H46: Rp/kg
A47: =A22 -> Cem-cem ORI | B47: =D22*FCC!$D$88 -> 1.0952906e+08 | C47: =E22*FCC!$C$208+F22*$C$7 -> 0 | D47: =G22 -> 257400 | E47: =IF($H$43=0,0,H22/$H$43)*'BIAYA BERSAMA'!$F$115 -> 9438493.9 | F47: =IF($H$43=0,0,H22/$H$43)*'BIAYA BERSAMA'!$F$117+IF($I$43=0,0,I22/$I$43)*('BIAYA BERSAMA'!$F$118+'BIAYA BERSAMA'!$F$119)+IF($G$43=0,0,G22/$G$43)*'BIAYA BERSAMA'!$F$120 -> 17796195 | G47: =SUM(B47:F47) -> 1.3702115e+08 | H47: =IF(C22=0,0,G47/C22) -> 26737.921
A48: =A23 -> Cem-cem BBQ | B48: =D23*FCC!$D$88 -> 1.0636489e+08 | C48: =E23*FCC!$C$208+F23*$C$7 -> 0 | D48: =G23 -> 316800 | E48: =IF($H$43=0,0,H23/$H$43)*'BIAYA BERSAMA'!$F$115 -> 9302759.7 | F48: =IF($H$43=0,0,H23/$H$43)*'BIAYA BERSAMA'!$F$117+IF($I$43=0,0,I23/$I$43)*('BIAYA BERSAMA'!$F$118+'BIAYA BERSAMA'!$F$119)+IF($G$43=0,0,G23/$G$43)*'BIAYA BERSAMA'!$F$120 -> 17715505 | G48: =SUM(B48:F48) -> 1.3369995e+08 | H48: =IF(C23=0,0,G48/C23) -> 26489.926
A49: =A24 -> Koperasi (KW 2 berbumbu, 11 SKU) | B49: =D24*FCC!$D$88 -> 0 | C49: =E24*FCC!$C$208+F24*$C$7 -> 46782287 | D49: =G24 -> 11730364 | E49: =IF($H$43=0,0,H24/$H$43)*'BIAYA BERSAMA'!$F$115 -> 5313010.9 | F49: =IF($H$43=0,0,H24/$H$43)*'BIAYA BERSAMA'!$F$117+IF($I$43=0,0,I24/$I$43)*('BIAYA BERSAMA'!$F$118+'BIAYA BERSAMA'!$F$119)+IF($G$43=0,0,G24/$G$43)*'BIAYA BERSAMA'!$F$120 -> 3457584 | G49: =SUM(B49:F49) -> 67283246 | H49: =IF(C24=0,0,G49/C24) -> 11454.417
A50: =A25 -> Maicih basreng (maklon, 3 SKU) | B50: =D25*FCC!$D$88 -> 0 | C50: =E25*FCC!$C$208+F25*$C$7 -> 0 | D50: =G25 -> 23956.193 | E50: =IF($H$43=0,0,H25/$H$43)*'BIAYA BERSAMA'!$F$115 -> 1003485.3 | F50: =IF($H$43=0,0,H25/$H$43)*'BIAYA BERSAMA'!$F$117+IF($I$43=0,0,I25/$I$43)*('BIAYA BERSAMA'!$F$118+'BIAYA BERSAMA'!$F$119)+IF($G$43=0,0,G25/$G$43)*'BIAYA BERSAMA'!$F$120 -> 2863367 | G50: =SUM(B50:F50) -> 3890808.5 | H50: =IF(C25=0,0,G50/C25) -> 6215.3491
A51: =A26 -> Maicih keripik (LV 3 & 10) | B51: =D26*FCC!$D$88 -> 0 | C51: =E26*FCC!$C$208+F26*$C$7 -> 8144466.9 | D51: =G26 -> 305079.82 | E51: =IF($H$43=0,0,H26/$H$43)*'BIAYA BERSAMA'!$F$115 -> 1649395.3 | F51: =IF($H$43=0,0,H26/$H$43)*'BIAYA BERSAMA'!$F$117+IF($I$43=0,0,I26/$I$43)*('BIAYA BERSAMA'!$F$118+'BIAYA BERSAMA'!$F$119)+IF($G$43=0,0,G26/$G$43)*'BIAYA BERSAMA'!$F$120 -> 3587864.2 | G51: =SUM(B51:F51) -> 13686806 | H51: =IF(C26=0,0,G51/C26) -> 15212.971
A52: =A27 -> Maicih keripik LV 5 | B52: =D27*FCC!$D$88 -> 0 | C52: =E27*FCC!$C$208+F27*$C$7 -> 0 | D52: =G27 -> 0 | E52: =IF($H$43=0,0,H27/$H$43)*'BIAYA BERSAMA'!$F$115 -> 0 | F52: =IF($H$43=0,0,H27/$H$43)*'BIAYA BERSAMA'!$F$117+IF($I$43=0,0,I27/$I$43)*('BIAYA BERSAMA'!$F$118+'BIAYA BERSAMA'!$F$119)+IF($G$43=0,0,G27/$G$43)*'BIAYA BERSAMA'!$F$120 -> 0 | G52: =SUM(B52:F52) -> 0 | H52: =IF(C27=0,0,G52/C27) -> 0
A53: =A28 -> FCC Maicih | B53: =D28*FCC!$D$88 -> 0 | C53: =E28*FCC!$C$208+F28*$C$7 -> 0 | D53: =G28 -> 0 | E53: =IF($H$43=0,0,H28/$H$43)*'BIAYA BERSAMA'!$F$115 -> 0 | F53: =IF($H$43=0,0,H28/$H$43)*'BIAYA BERSAMA'!$F$117+IF($I$43=0,0,I28/$I$43)*('BIAYA BERSAMA'!$F$118+'BIAYA BERSAMA'!$F$119)+IF($G$43=0,0,G28/$G$43)*'BIAYA BERSAMA'!$F$120 -> 0 | G53: =SUM(B53:F53) -> 0 | H53: =IF(C28=0,0,G53/C28) -> 0
A54: =A29 -> FCC Putih | B54: =D29*FCC!$D$88 -> 0 | C54: =E29*FCC!$C$208+F29*$C$7 -> 0 | D54: =G29 -> 0 | E54: =IF($H$43=0,0,H29/$H$43)*'BIAYA BERSAMA'!$F$115 -> 0 | F54: =IF($H$43=0,0,H29/$H$43)*'BIAYA BERSAMA'!$F$117+IF($I$43=0,0,I29/$I$43)*('BIAYA BERSAMA'!$F$118+'BIAYA BERSAMA'!$F$119)+IF($G$43=0,0,G29/$G$43)*'BIAYA BERSAMA'!$F$120 -> 0 | G54: =SUM(B54:F54) -> 0 | H54: =IF(C29=0,0,G54/C29) -> 0
A55: =A30 -> Kecimpring (goreng & bagging) | B55: =D30*FCC!$D$88 -> 0 | C55: =E30*FCC!$C$208+F30*$C$7 -> 0 | D55: =G30 -> 0 | E55: =IF($H$43=0,0,H30/$H$43)*'BIAYA BERSAMA'!$F$115 -> 0 | F55: =IF($H$43=0,0,H30/$H$43)*'BIAYA BERSAMA'!$F$117+IF($I$43=0,0,I30/$I$43)*('BIAYA BERSAMA'!$F$118+'BIAYA BERSAMA'!$F$119)+IF($G$43=0,0,G30/$G$43)*'BIAYA BERSAMA'!$F$120 -> 0 | G55: =SUM(B55:F55) -> 0 | H55: =IF(C30=0,0,G55/C30) -> 0
A56: =A31 -> Whole chips rempah 15/90 gr | B56: =D31*FCC!$D$88 -> 0 | C56: =E31*FCC!$C$208+F31*$C$7 -> 0 | D56: =G31 -> 0 | E56: =IF($H$43=0,0,H31/$H$43)*'BIAYA BERSAMA'!$F$115 -> 0 | F56: =IF($H$43=0,0,H31/$H$43)*'BIAYA BERSAMA'!$F$117+IF($I$43=0,0,I31/$I$43)*('BIAYA BERSAMA'!$F$118+'BIAYA BERSAMA'!$F$119)+IF($G$43=0,0,G31/$G$43)*'BIAYA BERSAMA'!$F$120 -> 0 | G56: =SUM(B56:F56) -> 0 | H56: =IF(C31=0,0,G56/C31) -> 0
A57: =A32 -> Maxi (pellet & goreng) | B57: =D32*FCC!$D$88 -> 0 | C57: =E32*FCC!$C$208+F32*$C$7 -> 0 | D57: =G32 -> 0 | E57: =IF($H$43=0,0,H32/$H$43)*'BIAYA BERSAMA'!$F$115 -> 0 | F57: =IF($H$43=0,0,H32/$H$43)*'BIAYA BERSAMA'!$F$117+IF($I$43=0,0,I32/$I$43)*('BIAYA BERSAMA'!$F$118+'BIAYA BERSAMA'!$F$119)+IF($G$43=0,0,G32/$G$43)*'BIAYA BERSAMA'!$F$120 -> 0 | G57: =SUM(B57:F57) -> 0 | H57: =IF(C32=0,0,G57/C32) -> 0
A58: =A33 -> Pellet ubi ungu FG (1,2x1,5 & 3x3) | B58: =D33*FCC!$D$88 -> 0 | C58: =E33*FCC!$C$208+F33*$C$7 -> 0 | D58: =G33 -> 0 | E58: =IF($H$43=0,0,H33/$H$43)*'BIAYA BERSAMA'!$F$115 -> 0 | F58: =IF($H$43=0,0,H33/$H$43)*'BIAYA BERSAMA'!$F$117+IF($I$43=0,0,I33/$I$43)*('BIAYA BERSAMA'!$F$118+'BIAYA BERSAMA'!$F$119)+IF($G$43=0,0,G33/$G$43)*'BIAYA BERSAMA'!$F$120 -> 0 | G58: =SUM(B58:F58) -> 0 | H58: =IF(C33=0,0,G58/C33) -> 0
... A67: =A42 -> WRP (Delichips, Mixfruit, chips) – maklon | B67: =D42*FCC!$D$88 -> 0 | C67: =E42*FCC!$C$208+F42*$C$7 -> 0 | D67: =G42 -> 0 | E67: =IF($H$43=0,0,H42/$H$43)*'BIAYA BERSAMA'!$F$115 -> 0 | F67: =IF($H$43=0,0,H42/$H$43)*'BIAYA BERSAMA'!$F$117+IF($I$43=0,0,I42/$I$43)*('BIAYA BERSAMA'!$F$118+'BIAYA BERSAMA'!$F$119)+IF($G$43=0,0,G42/$G$43)*'BIAYA BERSAMA'!$F$120 -> 0 | G67: =SUM(B67:F67) -> 0 | H67: =IF(C42=0,0,G67/C42) -> 0
A68: Total | B68: =SUM(B47:B67) -> 2.1589395e+08 | C68: =SUM(C47:C67) -> 54926754 | D68: =SUM(D47:D67) -> 12633600 | E68: =SUM(E47:E67) -> 26707145 | F68: =SUM(F47:F67) -> 45420515 | G68: =SUM(G47:G67) -> 3.5558196e+08 | H68: =IF(C43=0,0,G68/C43) -> 20236.313
A70: 4. Kontrol
A71: Cek | C71: Nilai | D71: Status
A72: Man-hour Lain-lain = driver di BIAYA BERSAMA | C72: =H43-'BIAYA BERSAMA'!$F$91 -> 0 | D72: =IF(ISERROR(C72),"GAGAL",IF(ABS(C72)<=0.01,"LULUS","GAGAL")) -> LULUS
A73: kWh Lain-lain = driver di BIAYA BERSAMA | C73: =I43-'BIAYA BERSAMA'!$F$93 -> 0 | D73: =IF(ISERROR(C73),"GAGAL",IF(ABS(C73)<=0.01,"LULUS","GAGAL")) -> LULUS
A74: Konversi teralokasi = pool Lain-lain | C74: =E68+F68-('BIAYA BERSAMA'!$F$121-'BIAYA BERSAMA'!$F$116) -> 0 | D74: =IF(ISERROR(C74),"GAGAL",IF(ABS(C74)<=1,"LULUS","GAGAL")) -> LULUS
A75: Tidak ada sel error | C75: =SUMPRODUCT(--ISERROR(A9:L70)) -> 0 | D75: =IF(ISERROR(C75),"GAGAL",IF(ABS(C75)<=0.5,"LULUS","GAGAL")) -> LULUS
A77: Dasar pembagian: DL dan IDL per man-hour, energi dan mesin per kWh, pabrik umum per nilai material eksternal, di dalam pool Lain-lain dari BIAYA BERSAMA.

Sheet BIAYA BERSAMA
A1: BIAYA BERSAMA PABRIK – Agustus 2026
A2: Saldo GL biaya konversi pabrik → pool → driver per produk → alokasi. Semua pool habis dialokasikan (penyerapan penuh), kecuali jam menganggur bila parameter di bagian 6 diaktifkan.
A3: Biru = input (lampiran), hijau = tautan antarsheet, hitam = rumus. Ringkasan dalam Rp juta; rincian dalam Rp.
A5: 1. Saldo akun biaya pabrik – GL Agustus 2026 (Rp)
A6: Kode | B6: Nama akun | C6: Agu-26 (Rp) | D6: Pool | E6: Akun baru mulai Okt-26 | F6: Sumber
A7: 5101-002 | B7: COGM - DL - Biaya Upah Langsung Pabrik | C7: 961759797 | D7: Dipecah (bagian 2) | E7: 5101-111/121/131/141 | F7: TB Accurate Agu-26
A8: 5101-003 | B8: COGM - DL - THR & Bonus Pabrik | C8: 63137128 | D8: Dipecah (bagian 2) | E8: 5101-112/113/122/132/133/142/143 | F8: TB Accurate Agu-26
A9: 5101-004 | B9: COGM - DL - Pesangon Pabrik | C9: 0 | D9: Grup A | E9: 5101-150 | F9: TB Accurate Agu-26
A10: 5101-005 | B10: COGM - DL - Biaya Jamsostek Pabrik | C10: 128572648 | D10: Dipecah (bagian 2) | E10: 5101-114/124/134/144 | F10: TB Accurate Agu-26
A11: 5101-006 | B11: COGM - OHP - Biaya Listrik Pabrik | C11: 56566114 | D11: Grup C | E11: 5101-006 | F11: TB Accurate Agu-26
A12: 5101-007 | B12: COGM - OHP - Biaya Air Pabrik | C12: 79000 | D12: Grup C | E12: 5101-007 | F12: TB Accurate Agu-26
A13: 5101-008 | B13: COGM - OHP - Biaya Utilitas Pabrik | C13: 0 | D13: Grup C | E13: 5101-008 | F13: TB Accurate Agu-26
A14: 5101-009 | B14: COGM - OHP - Biaya Rumah Tangga Pabrik | C14: 24213641 | D14: Grup E | E14: 5101-009 | F14: TB Accurate Agu-26
A15: 5101-010 | B15: COGM - OHP - Biaya Perbaikan & Pemeliharaan Mesin | C15: 1.0365535e+08 | D15: Grup D | E15: 5101-010 | F15: TB Accurate Agu-26
A16: 5101-011 | B16: COGM - OHP - Biaya Perbaikan & Pemeliharaan Pabrik | C16: 41591502 | D16: Grup E | E16: 5101-011 | F16: TB Accurate Agu-26
A17: 5101-012 | B17: COGM - OHP - Biaya Perbaikan & Pemeliharaan Inventaris Pabrik | C17: 4703135 | D17: Grup E | E17: 5101-012 | F17: TB Accurate Agu-26
A18: 5101-013 | B18: COGM - OHP - Biaya Peny. Mesin Gol 1 | C18: 16700889 | D18: Grup D | E18: 5101-013 | F18: TB Accurate Agu-26
... A22: 6500-007 | B22: COGM - OHP - Biaya Peny. Inventaris Pabrik Gol 2 | C22: 14533271 | D22: Grup E | E22: 5101-017 | F22: TB Accurate Agu-26
B23: Total biaya konversi pabrik | C23: =SUM(C7:C22) -> 1.6066528e+09
B24: Referensi: BP Model Details Q173 | C24: 1.6066528e+09 | F24: Untuk kontrol
A26: 2. Rincian upah 5101-002 per kelompok, dan pembagian THR/BPJS (sementara sampai akun payroll baru aktif)
A27: Kelompok | B27: Unit / departemen | C27: Agu-26 (Rp) | D27: Pool | E27: Sumber
A28: Operator harian | B28: Unit I | C28: 511029300 | D28: Grup A | E28: WP CoGM Agu, Labor!E6
A29: Operator harian | B29: Unit II | C29: 0 | D29: Grup A | E29: Labor!E7
A30: Operator harian | B30: Unit III | C30: 0 | D30: Grup A | E30: Labor!E8
A31: Support harian | B31: QC | C31: 60505300 | D31: Grup B | E31: Labor!E9
A32: Support harian | B32: Formulasi | C32: 0 | D32: Grup B | E32: Labor!E10
A33: Support harian | B33: RnD | C33: 0 | D33: Grup B | E33: Labor!E11
A34: Support harian | B34: Engineering | C34: 35012300 | D34: Grup B | E34: Labor!E12
A35: Support harian | B35: PPIC | C35: 2829600 | D35: Grup B | E35: Labor!E13
A36: Support harian | B36: Gudang | C36: 15710000 | D36: Grup B | E36: Labor!E14
A37: Support harian | B37: HRGA | C37: 39263300 | D37: Grup B | E37: Labor!E15
A38: Support harian | B38: Agro | C38: 0 | D38: Grup B | E38: Labor!E16
A39: Borongan kupas | B39: Kupas singkong | C39: 110021625 | D39: Kupas | E39: Labor!J6
... A41: Staf bulanan pabrik | B41: Semua departemen pabrik | C41: 165813709 | D41: Grup B | E41: BP Model Details Q134 (register payroll)
B42: Subtotal rekap payroll | C42: =SUM(C28:C41) -> 940185134
B43: GL 5101-002 | C43: =$C$7 -> 961759797
B44: Selisih GL − rekap (belum terpetakan, sementara di Grup A) | C44: =C43-C42 -> 21574663
A46: Parameter: kupas ikut THR & BPJS? (1 = ya, 0 = tidak) | C46: 0 | E46: Lihat sheet ASUMSI no. 3
A47: Basis pembagian THR & BPJS | C47: Upah/gaji pokok | D47: Porsi | E47: THR (5101-003) | F47: BPJS (5101-005)
A48: Operator harian | C48: =SUM(C28:C30) -> 511029300 | D48: =IF($C$52=0,0,C48/$C$52) -> 0.61557668 | E48: =D48*$C$8 -> 38865744 | F48: =D48*$C$10 -> 79146324
A49: Support harian | C49: =SUM(C31:C38) -> 153320500 | D49: =IF($C$52=0,0,C49/$C$52) -> 0.18468711 | E49: =D49*$C$8 -> 11660614 | F49: =D49*$C$10 -> 23745711
A50: Staf bulanan pabrik | C50: =C41 -> 165813709 | D50: =IF($C$52=0,0,C50/$C$52) -> 0.19973621 | E50: =D50*$C$8 -> 12610770 | F50: =D50*$C$10 -> 25680613
A51: Borongan kupas | C51: =SUM(C39:C40)*$C$46 -> 0 | D51: =IF($C$52=0,0,C51/$C$52) -> 0 | E51: =D51*$C$8 -> 0 | F51: =D51*$C$10 -> 0
A52: Total | C52: =SUM(C48:C51) -> 830163509 | D52: =SUM(D48:D51) -> 1 | E52: =SUM(E48:E51) -> 63137128 | F52: =SUM(F48:F51) -> 1.2857265e+08
A54: 3. Pool biaya pabrik
A55: Pool | B55: Komponen | C55: Agu-26 (Rp) | D55: Sifat biaya | E55: Driver alokasi
A56: Grup A – DL operator | B56: Upah harian operator | C56: =SUM(C28:C30) -> 511029300 | D56: Semi-variabel | E56: Man-hour
A57: Grup A – DL operator | B57: THR operator | C57: =E48 -> 38865744 | D57: Tetap | E57: Man-hour
A58: Grup A – DL operator | B58: BPJS operator | C58: =F48 -> 79146324 | D58: Tetap | E58: Man-hour
A59: Grup A – DL operator | B59: Pesangon pabrik (5101-004) | C59: =$C$9 -> 0 | D59: Tetap | E59: Man-hour
A60: Grup A – DL operator | B60: Selisih GL vs rekap payroll (belum terpetakan) | C60: =C44 -> 21574663 | D60: Semi-variabel | E60: Man-hour
A61: Kupas | B61: Upah borongan kupas | C61: =SUM(C39:C40) -> 110021625 | D61: Variabel | E61: Kg dikupas
A62: Kupas | B62: THR & BPJS kupas | C62: =E51+F51 -> 0 | D62: Tetap | E62: Kg dikupas
A63: Grup B – IDL | B63: Upah harian support | C63: =SUM(C31:C38) -> 153320500 | D63: Semi-variabel | E63: Man-hour
A64: Grup B – IDL | B64: Gaji staf bulanan pabrik | C64: =C41 -> 165813709 | D64: Tetap | E64: Man-hour
A65: Grup B – IDL | B65: THR support & staf | C65: =E49+E50 -> 24271384 | D65: Tetap | E65: Man-hour
A66: Grup B – IDL | B66: BPJS support & staf | C66: =F49+F50 -> 49426324 | D66: Tetap | E66: Man-hour
A67: Grup C – energi & utilitas | B67: Listrik (5101-006) | C67: =$C$11 -> 56566114 | D67: Variabel | E67: kWh
A68: Grup C – energi & utilitas | B68: Air (5101-007) | C68: =$C$12 -> 79000 | D68: Variabel | E68: kWh
A69: Grup C – energi & utilitas | B69: Utilitas (5101-008) | C69: =$C$13 -> 0 | D69: Variabel | E69: kWh
A70: Grup D – mesin | B70: Pemeliharaan mesin (5101-010) | C70: =$C$15 -> 1.0365535e+08 | D70: Semi-variabel | E70: kWh
A71: Grup D – mesin | B71: Penyusutan mesin Gol 1 (5101-013) | C71: =$C$18 -> 16700889 | D71: Tetap | E71: kWh
A72: Grup D – mesin | B72: Penyusutan mesin Gol 2 (5101-014) | C72: =$C$19 -> 1.3762689e+08 | D72: Tetap | E72: kWh
A73: Grup E – pabrik umum | B73: Rumah tangga pabrik (5101-009) | C73: =$C$14 -> 24213641 | D73: Tetap | E73: Nilai material
A74: Grup E – pabrik umum | B74: Pemeliharaan pabrik (5101-011) | C74: =$C$16 -> 41591502 | D74: Tetap | E74: Nilai material
A75: Grup E – pabrik umum | B75: Pemeliharaan inventaris pabrik (5101-012) | C75: =$C$17 -> 4703135 | D75: Tetap | E75: Nilai material
A76: Grup E – pabrik umum | B76: Pabrikasi & pengiriman (5101-016) | C76: =$C$20 -> 12505355 | D76: Variabel | E76: Nilai material
A77: Grup E – pabrik umum | B77: Penyusutan inventaris pabrik Gol 1 (6500-006) | C77: =$C$21 -> 41008046 | D77: Tetap | E77: Nilai material
A78: Grup E – pabrik umum | B78: Penyusutan inventaris pabrik Gol 2 (6500-007) | C78: =$C$22 -> 14533271 | D78: Tetap | E78: Nilai material
A80: Ringkasan pool | D80: Tetap | E80: Variabel + semi
A81: Grup A – DL operator | C81: =SUMIF($A$56:$A$78,A81,$C$56:$C$78) -> 6.5061603e+08 | D81: =SUMIFS($C$56:$C$78,$A$56:$A$78,A81,$D$56:$D$78,"Tetap") -> 1.1801207e+08 | E81: =C81-D81 -> 532603963
A82: Kupas | C82: =SUMIF($A$56:$A$78,A82,$C$56:$C$78) -> 110021625 | D82: =SUMIFS($C$56:$C$78,$A$56:$A$78,A82,$D$56:$D$78,"Tetap") -> 0 | E82: =C82-D82 -> 110021625
A83: Grup B – IDL | C83: =SUMIF($A$56:$A$78,A83,$C$56:$C$78) -> 3.9283192e+08 | D83: =SUMIFS($C$56:$C$78,$A$56:$A$78,A83,$D$56:$D$78,"Tetap") -> 2.3951142e+08 | E83: =C83-D83 -> 1.533205e+08
A84: Grup C – energi & utilitas | C84: =SUMIF($A$56:$A$78,A84,$C$56:$C$78) -> 56645114 | D84: =SUMIFS($C$56:$C$78,$A$56:$A$78,A84,$D$56:$D$78,"Tetap") -> 0 | E84: =C84-D84 -> 56645114
A85: Grup D – mesin | C85: =SUMIF($A$56:$A$78,A85,$C$56:$C$78) -> 2.5798312e+08 | D85: =SUMIFS($C$56:$C$78,$A$56:$A$78,A85,$D$56:$D$78,"Tetap") -> 1.5432778e+08 | E85: =C85-D85 -> 1.0365535e+08
A86: Grup E – pabrik umum | C86: =SUMIF($A$56:$A$78,A86,$C$56:$C$78) -> 1.3855495e+08 | D86: =SUMIFS($C$56:$C$78,$A$56:$A$78,A86,$D$56:$D$78,"Tetap") -> 1.2604959e+08 | E86: =C86-D86 -> 12505355
A87: Total pool | C87: =SUM(C81:C86) -> 1.6066528e+09 | D87: =SUM(D81:D86) -> 6.3790086e+08 | E87: =SUM(E81:E86) -> 9.687519e+08
A89: 4. Driver alokasi per produk (diambil dari sheet produk)
A90: Driver | B90: Satuan | C90: FCC | D90: Ubi Ungu | E90: Ubi Orange | F90: Lain-lain | G90: Total | H90: Sumber
A91: Man-hour | B91: jam | C91: =FCC!$C$198 -> 24745 | D91: =UU!$C$199 -> 2015 | E91: =UO!$C$200 -> 1071 | F91: ='LAIN-LAIN'!$H$43 -> 1191.3383 | G91: =SUM(C91:F91) -> 29022.338 | H91: Labor!D30:D73 lewat sheet produk
A92: Kg dikupas | B92: kg | C92: =FCC!$C$197 -> 409266 | D92: =UU!$C$198 -> 0 | E92: =UO!$C$199 -> 0 | F92: 0 | G92: =SUM(C92:F92) -> 409266 | H92: Labor!I6 lewat sheet produk
A93: kWh | B93: kWh | C93: =FCC!$C$199 -> 45475.808 | D93: =UU!$C$200 -> 835.37102 | E93: =UO!$C$201 -> 503.00853 | F93: ='LAIN-LAIN'!$I$43 -> 4757.8126 | G93: =SUM(C93:F93) -> 51572 | H93: Overhead Allocation!D6:D48 lewat sheet produk
A94: Nilai material | B94: Rp | C94: =FCC!$G$228 -> 5.9242269e+09 | D94: =UU!$G$218 -> 3.7968621e+08 | E94: =UO!$G$219 -> 1.9324667e+08 | F94: ='LAIN-LAIN'!$G$43 -> 12633600 | G94: =SUM(C94:F94) -> 6.5097933e+09 | H94: Material eksternal di sheet produk
A95: Volume produksi (metode budget) | B95: kg | C95: =FCC!$B$30 -> 338754 | D95: =UU!$B$32 -> 13376 | E95: =UO!$B$32 -> 7403 | F95: 0 | G95: =SUM(C95:F95) -> 359533 | H95: Produksi bulan ini di sheet produk
A96: Porsi
A97: Man-hour | C97: =IF($G$91=0,0,C91/$G$91) -> 0.8526191 | D97: =IF($G$91=0,0,D91/$G$91) -> 0.069429278 | E97: =IF($G$91=0,0,E91/$G$91) -> 0.036902609 | F97: =IF($G$91=0,0,F91/$G$91) -> 0.041049012 | G97: =IF($G$91=0,0,G91/$G$91) -> 1
A98: Kg dikupas | C98: =IF($G$92=0,0,C92/$G$92) -> 1 | D98: =IF($G$92=0,0,D92/$G$92) -> 0 | E98: =IF($G$92=0,0,E92/$G$92) -> 0 | F98: =IF($G$92=0,0,F92/$G$92) -> 0 | G98: =IF($G$92=0,0,G92/$G$92) -> 1
A99: kWh | C99: =IF($G$93=0,0,C93/$G$93) -> 0.8817926 | D99: =IF($G$93=0,0,D93/$G$93) -> 0.016198151 | E99: =IF($G$93=0,0,E93/$G$93) -> 0.00975352 | F99: =IF($G$93=0,0,F93/$G$93) -> 0.092255732 | G99: =IF($G$93=0,0,G93/$G$93) -> 1
A100: Nilai material | C100: =IF($G$94=0,0,C94/$G$94) -> 0.91004838 | D100: =IF($G$94=0,0,D94/$G$94) -> 0.058325386 | E100: =IF($G$94=0,0,E94/$G$94) -> 0.029685531 | F100: =IF($G$94=0,0,F94/$G$94) -> 0.0019407068 | G100: =IF($G$94=0,0,G94/$G$94) -> 1
A101: Volume produksi (metode budget) | C101: =IF($G$95=0,0,C95/$G$95) -> 0.94220558 | D101: =IF($G$95=0,0,D95/$G$95) -> 0.037203817 | E101: =IF($G$95=0,0,E95/$G$95) -> 0.020590599 | F101: =IF($G$95=0,0,F95/$G$95) -> 0 | G101: =IF($G$95=0,0,G95/$G$95) -> 1
A103: 5. Kapasitas tenaga kerja: jam dibayar vs jam yang dipakai produk (PSAK 202: biaya kapasitas menganggur di atas normal adalah beban periode)
A104: Pos | B104: Satuan | C104: Agu-26 | H104: Sumber
A105: Jam kerja operator dibayar (Unit I) | B105: jam | C105: 32036.133 | H105: Labor!D6
A106: Jam yang dicatat ke produk | B106: jam | C106: =G91 -> 29022.338
A107: Jam tidak terpakai untuk produk | B107: jam | C107: =C105-C106 -> 3013.795 | D107: =IF(C105=0,0,C107/C105) -> 0.094074868
A108: Biaya Grup A per jam dibayar | B108: Rp/jam | C108: =IF(C105=0,0,$C$81/C105) -> 20308.819
A109: Biaya jam tidak terpakai | B109: Rp | C109: =C107*C108 -> 61206618
A110: Parameter: bebankan ke periode? (1 = ya, 0 = tetap diserap produk) | C110: 0 | E110: Keputusan kebijakan kapasitas normal; lihat ASUMSI no. 9
A111: Dibebankan ke periode (tidak masuk kartu produk) | C111: =C109*$C$110 -> 0
...

Sheet REKON & KONTROL
A1: REKAP, REKONSILIASI KE GL, DAN KONTROL – Agustus 2026
A2: Semua produk dijumlahkan dan dicocokkan ke GL. Biru = input (lampiran), hijau = tautan antarsheet, hitam = rumus. Ringkasan dalam Rp juta; rincian dalam Rp.
A4: 1. Rekap semua produk (Rp juta)
A5: Pos | B5: FCC | C5: Ubi Ungu | D5: Ubi Orange | E5: Lain-lain | F5: Total | H5: Budget total | I5: Selisih
A6: Produksi (kg) | B6: =FCC!$B$30 -> 338754 | C6: =UU!$B$32 -> 13376 | D6: =UO!$B$32 -> 7403 | E6: ='LAIN-LAIN'!$C$43 -> 17571.48 | F6: =SUM(B6:E6) -> 377104.48
A7: Material eksternal | B7: =FCC!$G$228/10^6 -> 5924.2269 | C7: =UU!$G$218/10^6 -> 379.68621 | D7: =UO!$G$219/10^6 -> 193.24667 | E7: ='LAIN-LAIN'!$D$68/10^6 -> 12.6336 | F7: =SUM(B7:E7) -> 6509.7933
A8: Bahan antarproduk (FCC premium, KW 2) | B8: 0 | C8: 0 | D8: 0 | E8: =('LAIN-LAIN'!$B$68+'LAIN-LAIN'!$C$68)/10^6 -> 270.8207 | F8: =SUM(B8:E8) -> 270.8207
A9: Upah kupas | B9: =FCC!$E$57/10^6 -> 110.02163 | C9: =UU!$E$58/10^6 -> 0 | D9: =UO!$E$58/10^6 -> 0 | E9: 0 | F9: =SUM(B9:E9) -> 110.02163
A10: Direct labour (Grup A) | B10: =FCC!$E$58/10^6 -> 554.72766 | C10: =UU!$E$59/10^6 -> 45.171801 | D10: =UO!$E$59/10^6 -> 24.009429 | E10: ='LAIN-LAIN'!$E$68/10^6 -> 26.707145 | F10: =SUM(B10:E10) -> 650.61603
A11: Factory overhead (Grup B–E) | B11: =FCC!$E$63/10^6 -> 738.46455 | C11: =UU!$E$64/10^6 -> 40.451703 | D11: =UO!$E$64/10^6 -> 21.678333 | E11: ='LAIN-LAIN'!$F$68/10^6 -> 45.420515 | F11: =SUM(B11:E11) -> 846.0151
A12: Total biaya produksi | B12: =SUM(B7:B11) -> 7327.4407 | C12: =SUM(C7:C11) -> 465.30971 | D12: =SUM(D7:D11) -> 238.93443 | E12: =SUM(E7:E11) -> 355.58196 | F12: =SUM(F7:F11) -> 8387.2668
A13: Rp per kg produksi | B13: =IF(B6=0,0,B12*10^6/B6) -> 21630.566 | C13: =IF(C6=0,0,C12*10^6/C6) -> 34786.91 | D13: =IF(D6=0,0,D12*10^6/D6) -> 32275.352 | E13: =IF(E6=0,0,E12*10^6/E6) -> 20236.313 | F13: =IF(F6=0,0,F12*10^6/F6) -> 22241.228
A14: HPP | B14: =FCC!$E$103/10^6 -> 6925.005 | C14: =UU!$E$98/10^6 -> 250.83102 | D14: =UO!$E$98/10^6 -> 238.93443 | E14: ='LAIN-LAIN'!$G$68/10^6 -> 355.58196 | F14: =SUM(B14:E14) -> 7770.3524 | H14: =(FCC!$E$105+UU!$E$100+UO!$E$100+INDEX(BUDGET!$C$199:$R$199,'LAIN-LAIN'!$E$5))/10^6 -> 7618.5801 | I14: =F14-H14 -> 151.77227
A15: Pendapatan (dikelompokkan sejalan dengan biaya) | B15: =FCC!$C$210/10^6 -> 8672.0977 | C15: =UU!$C$207/10^6 -> 349.70925 | D15: =UO!$C$208/10^6 -> 354.6037 | E15: =416714799.61/10^6 -> 416.7148 | F15: =SUM(B15:E15) -> 9793.1255
A16: Margin kotor per produk (%) | B16: =IF(B15=0,0,(B15-B14)/B15) -> 0.20146138 | C16: =IF(C15=0,0,(C15-C14)/C15) -> 0.28274411 | D16: =IF(D15=0,0,(D15-D14)/D15) -> 0.32619307 | E16: =IF(E15=0,0,(E15-E14)/E15) -> 0.14670186 | F16: =IF(F15=0,0,(F15-F14)/F15) -> 0.20655031
A17: Budget HPP memakai bulan yang dipilih di masing-masing sheet dan volume budget. Margin di atas belum termasuk pos di bagian 3 yang tidak dibagi ke produk.
A18: Pendapatan: FCC = premium IFM + KW 2 tawar; Others = retail & maklon + KW 2 berbumbu. Total sama dengan GL. BP baris 10–13 saat ini menghitung KW 2 dua kali (Rp 107,9 jt di Agustus).
A20: 2. Material semua produk vs pemakaian GL, dan varian per akun (Rp juta)
A21: Produk / lini | B21: Material kartu | C21: Porsi | D21: Varian sementara | E21: Akun varian mulai Okt-26
A22: FCC | B22: ='BIAYA BERSAMA'!C94/10^6 -> 5924.2269 | C22: =IF($B$28=0,0,B22/$B$28) -> 0.91004838 | D22: =$B$30*C22 -> 185.40464 | E22: 5101-301 Varian Produksi Singkong
A23: Ubi Ungu IFM | B23: ='BIAYA BERSAMA'!D94/10^6 -> 379.68621 | C23: =IF($B$28=0,0,B23/$B$28) -> 0.058325386 | D23: =$B$30*C23 -> 11.882662 | E23: 5101-302 Varian Produksi Ubi Ungu
A24: Ubi Orange IFM | B24: ='BIAYA BERSAMA'!E94/10^6 -> 193.24667 | C24: =IF($B$28=0,0,B24/$B$28) -> 0.029685531 | D24: =$B$30*C24 -> 6.047849 | E24: 5101-303 Varian Produksi Ubi Orange
A25: Lain-lain lini singkong (termasuk maklon) | B25: =SUMPRODUCT(('LAIN-LAIN'!$B$22:$B$42<>"Ubi Ungu")*('LAIN-LAIN'!$B$22:$B$42<>"Ubi Orange")*('LAIN-LAIN'!$B$22:$B$42<>"Ubi Ungu – cek bahan")*'LAIN-LAIN'!$G$22:$G$42)/10^6 -> 12.6336 | C25: =IF($B$28=0,0,B25/$B$28) -> 0.0019407068 | D25: =$B$30*C25 -> 0.39538124 | E25: 5101-301 Varian Produksi Singkong
A26: Lain-lain lini ubi ungu | B26: =SUMIF('LAIN-LAIN'!$B$22:$B$42,"Ubi Ungu*",'LAIN-LAIN'!$G$22:$G$42)/10^6 -> 0 | C26: =IF($B$28=0,0,B26/$B$28) -> 0 | D26: =$B$30*C26 -> 0 | E26: 5101-302 Varian Produksi Ubi Ungu
A27: Lain-lain lini ubi orange | B27: =SUMIF('LAIN-LAIN'!$B$22:$B$42,"Ubi Orange",'LAIN-LAIN'!$G$22:$G$42)/10^6 -> 0 | C27: =IF($B$28=0,0,B27/$B$28) -> 0 | D27: =$B$30*C27 -> 0 | E27: 5101-303 Varian Produksi Ubi Orange
A28: Total material kartu | B28: =SUM(B22:B27) -> 6509.7933 | D28: =SUM(D22:D27) -> 203.73054
A29: Pemakaian bahan baku menurut GL | B29: 6713.5239 | E29: BP DATA - GL Aktual 2026 J43
A30: Varian material (GL − kartu) | B30: =B29-B28 -> 203.73054
A31: 5101-301 Varian Produksi Singkong | D31: =D22+D25 -> 185.80002
A32: 5101-302 Varian Produksi Ubi Ungu | D32: =D23+D26 -> 11.882662
A33: 5101-303 Varian Produksi Ubi Orange | D33: =D24+D27 -> 6.047849
A34: Pembagian ke lini sementara memakai porsi kartu, karena GL belum memisahkan pemakaian per jenis bahan. Mulai Okt-26 dihitung per jenis bahan (akun 5101-201 s/d 207).
A36: 3. Rekonsiliasi HPP semua produk ke HPP GL (Rp juta)
A37: Total HPP kartu baru, semua produk | C37: =F14 -> 7770.3524
A38: + Varian material (GL − kartu) | C38: =$B$30 -> 203.73054
A39: + Kenaikan persediaan WIP & FG menurut kartu baru (FCC, UU, UO) | C39: =((FCC!$E$78+FCC!$E$91-FCC!$E$71-FCC!$E$85)+(UU!$E$77+UU!$E$89-UU!$E$70-UU!$E$84)+(UO!$E$77+UO!$E$89-UO!$E$70-UO!$E$84))/10^6 -> 325.80393
A40: − Kenaikan persediaan WIP & FG menurut GL (1106-002, 1106-003) | C40: =-((494002781.765743-238973459.696273)+(499690064.502333-276688460.92344))/10^6 -> -478.03093
A41: + Kenaikan persediaan KW 2 pada NRV (tidak dicatat di GL) | C41: =(-FCC!$E$73-'LAIN-LAIN'!$E$43*FCC!$C$208-FCC!$E$102)/10^6 -> 20.289793
A42: + Biaya jam menganggur dibebankan ke periode (BIAYA BERSAMA bagian 5) | C42: ='BIAYA BERSAMA'!$C$111/10^6 -> 0
A43: HPP menurut rekonsiliasi | C43: =SUM(C37:C42) -> 7842.1457
A44: HPP blended menurut GL (BP baris 87) | C44: 7842.1457
A45: Cek: HPP GL − HPP rekonsiliasi (harus nol) | C45: =C44-C43 -> 0
A46: Informasi: selisih kenaikan persediaan kartu baru vs GL | C46: =C39+C40 -> -152.227
A47: Selisih kenaikan persediaan berasal dari dasar penilaian (kartu baru penuh vs Accurate), item tanpa kartu di Accurate, dan residu nilai tanpa kuantitas.
A49: 4. Aliran KW 2 pada NRV – memo produk sampingan (Rp juta)
A50: Pos | C50: Kg | D50: Rp jt
A51: Masuk: KW 2 dari produksi FCC | C51: =FCC!$B$33 -> 13755 | D51: =-FCC!$E$73/10^6 -> 134.48637
A52: Keluar: bahan Lain-lain (koperasi, Maicih keripik) | C52: =-'LAIN-LAIN'!$E$43 -> -5617.8 | D52: =-'LAIN-LAIN'!$E$43*FCC!$C$208/10^6 -> -54.926754
A53: Keluar: KW 2 tawar terjual ke KGS (HPP pada NRV) | C53: =-FCC!$C$207 -> -6062 | D53: =-FCC!$E$102/10^6 -> -59.269818
A54: Kenaikan persediaan KW 2 (hitungan) | C54: =SUM(C51:C53) -> 2075.2 | D54: =SUM(D51:D53) -> 20.289793
A56: 5. Semua kontrol
A57: Cek | C57: Nilai | D57: Status
A58: Konversi di semua kartu = total pool − jam menganggur | C58: =F9+F10+F11-('BIAYA BERSAMA'!$C$87-'BIAYA BERSAMA'!$C$111)/10^6 -> 0 | D58: =IF(ISERROR(C58),"GAGAL",IF(ABS(C58)<=0.001,"LULUS","GAGAL")) -> LULUS
A59: Material kartu + varian = pemakaian GL | C59: =F7+$B$30-B29 -> 0 | D59: =IF(ISERROR(C59),"GAGAL",IF(ABS(C59)<=0.001,"LULUS","GAGAL")) -> LULUS
A60: Rekonsiliasi HPP ke GL | C60: =C45 -> 0 | D60: =IF(ISERROR(C60),"GAGAL",IF(ABS(C60)<=0.001,"LULUS","GAGAL")) -> LULUS
A61: Lini Lain-lain = material eksternal Lain-lain | C61: =B25+B26+B27-'LAIN-LAIN'!$G$43/10^6 -> 0 | D61: =IF(ISERROR(C61),"GAGAL",IF(ABS(C61)<=0.001,"LULUS","GAGAL")) -> LULUS
A62: Pendapatan semua produk = pendapatan GL (Rp 9.793,1 jt) | C62: =F15-9793125452.06/10^6 -> 0 | D62: =IF(ISERROR(C62),"GAGAL",IF(ABS(C62)<=0.001,"LULUS","GAGAL")) -> LULUS
A63: Sheet BIAYA BERSAMA | C63: =IF('BIAYA BERSAMA'!$D$139="LULUS",0,1) -> 0 | D63: =IF(ISERROR(C63),"GAGAL",IF(ABS(C63)<=0.5,"LULUS","GAGAL")) -> LULUS
A64: Sheet FCC | C64: =IF(FCC!$C$6="LULUS",0,1) -> 0 | D64: =IF(ISERROR(C64),"GAGAL",IF(ABS(C64)<=0.5,"LULUS","GAGAL")) -> LULUS
A65: Sheet UU | C65: =IF(UU!$C$6="LULUS",0,1) -> 0 | D65: =IF(ISERROR(C65),"GAGAL",IF(ABS(C65)<=0.5,"LULUS","GAGAL")) -> LULUS
A66: Sheet UO | C66: =IF(UO!$C$6="LULUS",0,1) -> 0 | D66: =IF(ISERROR(C66),"GAGAL",IF(ABS(C66)<=0.5,"LULUS","GAGAL")) -> LULUS
A67: Sheet LAIN-LAIN | C67: =IF('LAIN-LAIN'!$C$6="LULUS",0,1) -> 0 | D67: =IF(ISERROR(C67),"GAGAL",IF(ABS(C67)<=0.5,"LULUS","GAGAL")) -> LULUS
A68: STATUS SEMUA SHEET | D68: =IF(COUNTIF(D58:D67,"GAGAL")=0,"LULUS","GAGAL") -> LULUS

Sheet ASUMSI
A1: DAFTAR ASUMSI DAN SUMBER
A2: Setiap angka yang bukan aktual dari GL/laporan produksi. Status: Aktual / Estimasi / [TBC] = perlu konfirmasi.
A4: No | B4: Asumsi | C4: Nilai | D4: Dasar | E4: Pemilik | F4: Status | G4: Terdokumentasi? | H4: Dipakai di
A5: 1 | B5: Sistem biaya | C5: Biaya aktual, penyerapan penuh | D5: Kartu menyerap seluruh pool pabrik GL; overhead dialokasikan dengan driver aktual bulan berjalan (bukan tarif ditetapkan) | E5: Finance (costing) | F5: Usulan | G5: Belum | H5: Semua sheet produk
A6: 2 | B6: Pembagian 5101-002 per kelompok | C6: Rekap sheet Labor + register payroll staf | D6: Akun payroll per kelompok baru aktif Okt-26 | E6: HR / Finance | F6: Estimasi | G6: Sebagian | H6: BIAYA BERSAMA 2
A7: 3 | B7: Kupas ikut THR & BPJS | C7: 0 (tidak) | D7: THR pabrik 2026 ≈ 1x rata-rata upah Jan–Mar tanpa kupas | E7: HR | F7: [TBC] | G7: Belum | H7: BIAYA BERSAMA 2
A8: 4 | B8: Pembagian THR & BPJS antarkelompok | C8: Pro rata upah/gaji pokok | D8: Akun THR/BPJS belum terpisah per kelompok | E8: Finance | F8: Estimasi | G8: Belum | H8: BIAYA BERSAMA 2
A9: 5 | B9: NRV KW 2 | C9: Rp 9.777,27/kg | D9: Harga KW 2 ke KGS tertimbang Jan–Agu (tawar + berbumbu), tanpa pengurang biaya jual | E9: Commercial / Finance | F9: Estimasi | G9: Sebagian | H9: FCC, LAIN-LAIN
A10: 6 | B10: Konversi CNG | C10: 22,2967 m3 per MMBTU | D10: Uji 12 invoice (catatan proyek CNG) | E10: Purchasing | F10: Estimasi | G10: Ya (catatan) | H10: FCC, UU, UO
A11: 7 | B11: Nilai KW 2 ubi sebagai bahan Lain-lain | C11: Rp 0/kg | D11: UU/UO tidak mencatat KW 2 di kartu; tidak ada kredit NRV | E11: Produksi / Finance | F11: [TBC] | G11: Belum | H11: LAIN-LAIN
A12: 8 | B12: Driver alokasi | C12: A, B: man-hour; C, D: kWh; E: nilai material; kupas: kg dikupas | D12: Data kartu Labor dan Overhead Allocation | E12: Finance (costing) | F12: Usulan | G12: Belum | H12: BIAYA BERSAMA 6
A13: 9 | B13: Kapasitas normal tenaga kerja | C13: Jam dibayar Unit I; jam tak terpakai tetap diserap (parameter 0) | D13: Belum ada penetapan kapasitas normal (PSAK 202) | E13: Produksi / Finance | F13: [TBC] | G13: Belum | H13: BIAYA BERSAMA 5
A14: 10 | B14: Nilai WIP awal FCC Agustus | C14: Nilai kartu lama (penyerapan parsial) | D14: Hanya untuk bulan percontohan; berikutnya WIP akhir kartu baru | E14: Finance | F14: Estimasi | G14: - | H14: FCC 2c
A15: 11 | B15: Harga material | C15: Sheet Average Price WP lama | D15: Target: laporan nilai persediaan Accurate | E15: Finance / Gudang | F15: Estimasi | G15: Sebagian | H15: Lampiran B
A16: 12 | B16: Nilai tanpa kuantitas di Accurate | C16: Tidak ikut rata-rata FG | D16: Residu penilaian; perlu dibersihkan di Accurate | E16: Finance | F16: Aktual | G16: - | H16: UU, UO bagian 3
... A18: 14 | B18: Lini bahan utama produk Maxi, Umbiis, Pellet lainnya | C18: Ditandai "cek bahan" | D18: Belum ada konfirmasi bahan | E18: Produksi | F18: [TBC] | G18: Belum | H18: LAIN-LAIN 2

Sheet BUDGET
A1: BUDGET – ekstrak dari Business Plan v2 (sheet Business Plan - Model Details, kolom R:AG)
A2: Nilai ditempel dari BP, bukan tautan. Dipakai sebagai pembanding di sheet produk (bulan dipilih di masing-masing sheet).
A4: Baris MD | B4: Keterangan | C4: Sep-26 | D4: Okt-26 | E4: Nov-26 | F4: Des-26 | G4: Jan-27 | H4: Feb-27 | I4: Mar-27 | J4: Apr-27 | K4: Mei-27 | L4: Jun-27 | M4: Jul-27 | N4: Agu-27 | O4: Sep-27 | P4: Okt-27 | Q4: Nov-27 | R4: Des-27
A5: Flat Cassava Chips (FCC)
A6: MD411 | B6: Premium / layak jual | C6: 0.92953993 | D6: 0.92797454 | E6: 0.92989808 | F6: 0.92913752 | G6: 0.92900338 | H6: 0.92934632 | I6: 0.92916241 | J6: 0.9291707 | K6: 0.92922648 | L6: 0.92918653 | M6: 0.92919457 | N6: 0.92920253 | O6: 0.92919454 | P6: 0.92919721 | Q6: 0.92919809 | R6: 0.92919662
A7: MD412 | B7: KW 2 | C7: 0.035044382 | D7: 0.036571749 | E7: 0.037721086 | F7: 0.038771452 | G7: 0.038629975 | H7: 0.038727903 | I7: 0.038742466 | J7: 0.038070834 | K7: 0.037784981 | L7: 0.038127556 | M7: 0.038322031 | N7: 0.03839715 | O7: 0.038350362 | P7: 0.03831541 | Q7: 0.038263849 | R7: 0.038204022
A8: MD413 | B8: Keripik waste | C8: 0.035415693 | D8: 0.035453707 | E8: 0.032380835 | F8: 0.032091032 | G8: 0.032366646 | H8: 0.031925772 | I8: 0.032095127 | J8: 0.032758462 | K8: 0.032988541 | L8: 0.032685915 | M8: 0.032483398 | N8: 0.032400324 | O8: 0.032455096 | P8: 0.032487377 | Q8: 0.032538057 | R8: 0.032599362
A9: MD414 | B9: WIP from Premium/Layak Jual | C9: 0 | D9: 0 | E9: 0 | F9: 0 | G9: 0 | H9: 0 | I9: 0 | J9: 0 | K9: 0 | L9: 0 | M9: 0 | N9: 0 | O9: 0 | P9: 0 | Q9: 0 | R9: 0
A10: MD417 | B10: Target Volume Penjualan/Layak Jual | C10: 278373.52 | D10: 278373.52 | E10: 278373.52 | F10: 278373.52 | G10: 278373.52 | H10: 278373.52 | I10: 278373.52 | J10: 278373.52 | K10: 278373.52 | L10: 278373.52 | M10: 278373.52 | N10: 278373.52 | O10: 278373.52 | P10: 278373.52 | Q10: 278373.52 | R10: 278373.52
A11: MD418 | B11: KW 2 | C11: 10494.899 | D11: 10970.782 | E11: 11292.153 | F11: 11616.09 | G11: 11575.374 | H11: 11600.436 | I11: 11607.095 | J11: 11405.775 | K11: 11319.456 | L11: 11422.574 | M11: 11480.737 | N11: 11503.143 | O11: 11489.225 | P11: 11478.721 | Q11: 11463.263 | R11: 11445.358
A12: MD419 | B12: Keripik waste | C12: 10606.097 | D12: 10635.392 | E12: 9693.4997 | F12: 9614.6085 | G12: 9698.5836 | H12: 9562.9468 | I12: 9615.5779 | J12: 9814.2228 | K12: 9882.5596 | L12: 9792.3212 | M12: 9731.5653 | N12: 9706.5945 | O12: 9723.0868 | P12: 9732.7297 | Q12: 9747.9036 | R12: 9766.2851
A13: MD420 | B13: WIP | C13: 0 | D13: 0 | E13: 0 | F13: 0 | G13: 0 | H13: 0 | I13: 0 | J13: 0 | K13: 0 | L13: 0 | M13: 0 | N13: 0 | O13: 0 | P13: 0 | Q13: 0 | R13: 0
A14: MD421 | B14: Target output Produksi | C14: 299474.51 | D14: 299979.69 | E14: 299359.17 | F14: 299604.22 | G14: 299647.47 | H14: 299536.9 | I14: 299596.19 | J14: 299593.51 | K14: 299575.53 | L14: 299588.41 | M14: 299585.82 | N14: 299583.25 | O14: 299585.83 | P14: 299584.97 | Q14: 299584.68 | R14: 299585.16
A15: MD424 | B15: Overall yield singkong to Output | C15: 3.2 | D15: 3.2 | E15: 3.2 | F15: 3.2 | G15: 3.2 | H15: 3.2 | I15: 3.2 | J15: 3.2 | K15: 3.2 | L15: 3.2 | M15: 3.2 | N15: 3.2 | O15: 3.2 | P15: 3.2 | Q15: 3.2 | R15: 3.2
A16: MD425 | B16: Total Kebutuhan equivalent to singkong kulit | C16: 958318.44 | D16: 959935.01 | E16: 957949.34 | F16: 958733.49 | G16: 958871.92 | H16: 958518.08 | I16: 958707.81 | J16: 958699.25 | K16: 958641.7 | L16: 958682.92 | M16: 958674.62 | N16: 958666.41 | O16: 958674.65 | P16: 958671.9 | Q16: 958670.99 | R16: 958672.51
A17: MD427 | B17: Portion | C17: 0.92509938 | D17: 0.92522552 | E17: 0.92507052 | F17: 0.92513181 | G17: 0.92514262 | H17: 0.92511498 | I17: 0.9251298 | J17: 0.92512913 | K17: 0.92512464 | L17: 0.92512786 | M17: 0.92512721 | N17: 0.92512657 | O17: 0.92512721 | P17: 0.925127 | Q17: 0.92512693 | R17: 0.92512705
... A86: MD205 | B86: Ubi Orange | C86: 5620.6313 | D86: 5620.6313 | E86: 5620.6313 | F86: 5620.6313 | G86: 5620.6313 | H86: 5620.6313 | I86: 5620.6313 | J86: 5620.6313 | K86: 5620.6313 | L86: 5620.6313 | M86: 5620.6313 | N86: 5620.6313 | O86: 5620.6313 | P86: 5620.6313 | Q86: 5620.6313 | R86: 5620.6313
B87: Grup A diselaraskan: DL operator + THR 1/12 + BPJS DL, porsi volume | C87: =(C59+C59/12+C64)*IF(C71=0,0,C72/C71) -> 6.3190982e+08 | D87: =(D59+D59/12+D64)*IF(D71=0,0,D72/D71) -> 6.3161259e+08 | E87: =(E59+E59/12+E64)*IF(E71=0,0,E72/E71) -> 6.317616e+08 | F87: =(F59+F59/12+F64)*IF(F71=0,0,F72/F71) -> 6.3176134e+08 | G87: =(G59+G59/12+G64)*IF(G71=0,0,G72/G71) -> 6.3171184e+08 | H87: =(H59+H59/12+H64)*IF(H71=0,0,H72/H71) -> 6.3174493e+08 | I87: =(I59+I59/12+I64)*IF(I71=0,0,I72/I71) -> 6.3173937e+08 | J87: =(J59+J59/12+J64)*IF(J71=0,0,J72/J71) -> 6.3173205e+08 | ... R87: =(R59+R59/12+R64)*IF(R71=0,0,R72/R71) -> 6.3173661e+08
B88: Grup B diselaraskan: support + staf + THR + BPJS IDL, porsi volume | C88: =(C60+C60/12+C61+C63+C65)*IF(C71=0,0,C72/C71) -> 3.9907776e+08 | D88: =(D60+D60/12+D61+D63+D65)*IF(D71=0,0,D72/D71) -> 3.9889005e+08 | E88: =(E60+E60/12+E61+E63+E65)*IF(E71=0,0,E72/E71) -> 3.9898416e+08 | F88: =(F60+F60/12+F61+F63+F65)*IF(F71=0,0,F72/F71) -> 3.9898399e+08 | G88: =(G60+G60/12+G61+G63+G65)*IF(G71=0,0,G72/G71) -> 3.9895273e+08 | H88: =(H60+H60/12+H61+H63+H65)*IF(H71=0,0,H72/H71) -> 3.9897363e+08 | I88: =(I60+I60/12+I61+I63+I65)*IF(I71=0,0,I72/I71) -> 3.9897012e+08 | J88: =(J60+J60/12+J61+J63+J65)*IF(J71=0,0,J72/J71) -> 3.9896549e+08 | ... R88: =(R60+R60/12+R61+R63+R65)*IF(R71=0,0,R72/R71) -> 3.9896837e+08
B89: Cek: A + B diselaraskan − pool A + B budget (harus nol) | C89: =C87+C88-C54-C55 -> 2.3841858e-06 | D89: =D87+D88-D54-D55 -> -1.8775463e-06 | E89: =E87+E88-E54-E55 -> -2.2649765e-06 | F89: =F87+F88-F54-F55 -> -1.4901161e-06 | G89: =G87+G88-G54-G55 -> -1.2516975e-06 | H89: =H87+H88-H54-H55 -> -9.8347664e-07 | I89: =I87+I88-I54-I55 -> 2.1755695e-06 | J89: =J87+J88-J54-J55 -> 1.8179417e-06 | ... R89: =R87+R88-R54-R55 -> 1.0430813e-06
A91: Ubi Ungu IFM (QKSP)
A92: MD572 | B92: Premium / layak jual | C92: 0.99 | D92: 0.99 | E92: 0.99 | F92: 0.99 | G92: 0.99 | H92: 0.99 | I92: 0.99 | J92: 0.99 | K92: 0.99 | L92: 0.99 | M92: 0.99 | N92: 0.99 | O92: 0.99 | P92: 0.99 | Q92: 0.99 | R92: 0.99
A93: MD573 | B93: KW 2 | C93: 0 | D93: 0 | E93: 0 | F93: 0 | G93: 0 | H93: 0 | I93: 0 | J93: 0 | K93: 0 | L93: 0 | M93: 0 | N93: 0 | O93: 0 | P93: 0 | Q93: 0 | R93: 0
A94: MD574 | B94: Keripik waste | C94: 0.01 | D94: 0.01 | E94: 0.01 | F94: 0.01 | G94: 0.01 | H94: 0.01 | I94: 0.01 | J94: 0.01 | K94: 0.01 | L94: 0.01 | M94: 0.01 | N94: 0.01 | O94: 0.01 | P94: 0.01 | Q94: 0.01 | R94: 0.01
A95: MD578 | B95: Target Volume Penjualan/Layak Jual | C95: 6388 | D95: 6388 | E95: 6388 | F95: 6388 | G95: 6388 | H95: 6388 | I95: 6388 | J95: 6388 | K95: 6388 | L95: 6388 | M95: 6388 | N95: 6388 | O95: 6388 | P95: 6388 | Q95: 6388 | R95: 6388
A96: MD579 | B96: KW 2 | C96: 0 | D96: 0 | E96: 0 | F96: 0 | G96: 0 | H96: 0 | I96: 0 | J96: 0 | K96: 0 | L96: 0 | M96: 0 | N96: 0 | O96: 0 | P96: 0 | Q96: 0 | R96: 0
A97: MD580 | B97: Keripik waste | C97: 64.525253 | D97: 64.525253 | E97: 64.525253 | F97: 64.525253 | G97: 64.525253 | H97: 64.525253 | I97: 64.525253 | J97: 64.525253 | K97: 64.525253 | L97: 64.525253 | M97: 64.525253 | N97: 64.525253 | O97: 64.525253 | P97: 64.525253 | Q97: 64.525253 | R97: 64.525253
A98: MD581 | B98: WIP | C98: 0 | D98: 0 | E98: 0 | F98: 0 | G98: 0 | H98: 0 | I98: 0 | J98: 0 | K98: 0 | L98: 0 | M98: 0 | N98: 0 | O98: 0 | P98: 0 | Q98: 0 | R98: 0
A99: MD582 | B99: Target output Produksi | C99: 6452.5253 | D99: 6452.5253 | E99: 6452.5253 | F99: 6452.5253 | G99: 6452.5253 | H99: 6452.5253 | I99: 6452.5253 | J99: 6452.5253 | K99: 6452.5253 | L99: 6452.5253 | M99: 6452.5253 | N99: 6452.5253 | O99: 6452.5253 | P99: 6452.5253 | Q99: 6452.5253 | R99: 6452.5253
A100: MD586 | B100: Yield target | C100: 3.1297847 | D100: 3.1297847 | E100: 3.1297847 | F100: 3.1297847 | G100: 3.1297847 | H100: 3.1297847 | I100: 3.1297847 | J100: 3.1297847 | K100: 3.1297847 | L100: 3.1297847 | M100: 3.1297847 | N100: 3.1297847 | O100: 3.1297847 | P100: 3.1297847 | Q100: 3.1297847 | R100: 3.1297847
A101: MD587 | B101: Raw materials | C101: 20195.015 | D101: 20195.015 | E101: 20195.015 | F101: 20195.015 | G101: 20195.015 | H101: 20195.015 | I101: 20195.015 | J101: 20195.015 | K101: 20195.015 | L101: 20195.015 | M101: 20195.015 | N101: 20195.015 | O101: 20195.015 | P101: 20195.015 | Q101: 20195.015 | R101: 20195.015
A102: MD589 | B102: Total Ubi Ungu | C102: 1.194004e+08 | D102: 1.194004e+08 | E102: 1.194004e+08 | F102: 1.194004e+08 | G102: 1.194004e+08 | H102: 1.194004e+08 | I102: 1.194004e+08 | J102: 1.194004e+08 | K102: 1.194004e+08 | L102: 1.194004e+08 | M102: 1.194004e+08 | N102: 1.194004e+08 | O102: 1.194004e+08 | P102: 1.194004e+08 | Q102: 1.194004e+08 | R102: 1.194004e+08
A103: MD598 | B103: Raw materials | C103: 2561.9104 | D103: 2561.9104 | E103: 2561.9104 | F103: 2561.9104 | G103: 2561.9104 | H103: 2561.9104 | I103: 2561.9104 | J103: 2561.9104 | K103: 2561.9104 | L103: 2561.9104 | M103: 2561.9104 | N103: 2561.9104 | O103: 2561.9104 | P103: 2561.9104 | Q103: 2561.9104 | R103: 2561.9104
... A139: MD205 | B139: Ubi Orange | C139: 5620.6313 | D139: 5620.6313 | E139: 5620.6313 | F139: 5620.6313 | G139: 5620.6313 | H139: 5620.6313 | I139: 5620.6313 | J139: 5620.6313 | K139: 5620.6313 | L139: 5620.6313 | M139: 5620.6313 | N139: 5620.6313 | O139: 5620.6313 | P139: 5620.6313 | Q139: 5620.6313 | R139: 5620.6313
B140: Grup A diselaraskan: DL operator + THR 1/12 + BPJS DL, porsi volume | C140: =(C129+C129/12+C134)*IF(C136=0,0,C138/C136) -> 13615229 | D140: =(D129+D129/12+D134)*IF(D136=0,0,D138/D136) -> 13585907 | E140: =(E129+E129/12+E134)*IF(E136=0,0,E138/E136) -> 13617280 | F140: =(F129+F129/12+F134)*IF(F136=0,0,F138/F136) -> 13606137 | G140: =(G129+G129/12+G134)*IF(G136=0,0,G138/G136) -> 13603107 | H140: =(H129+H129/12+H134)*IF(H136=0,0,H138/H136) -> 13608841 | I140: =(I129+I129/12+I134)*IF(I136=0,0,I138/I136) -> 13606028 | J140: =(J129+J129/12+J134)*IF(J136=0,0,J138/J136) -> 13605992 | ... R140: =(R129+R129/12+R134)*IF(R136=0,0,R138/R136) -> 13606470
B141: Grup B diselaraskan: support + staf + THR + BPJS IDL, porsi volume | C141: =(C130+C130/12+C131+C133+C135)*IF(C136=0,0,C138/C136) -> 8598592.6 | D141: =(D130+D130/12+D131+D133+D135)*IF(D136=0,0,D138/D136) -> 8580074.6 | E141: =(E130+E130/12+E131+E133+E135)*IF(E136=0,0,E138/E136) -> 8599888 | F141: =(F130+F130/12+F131+F133+F135)*IF(F136=0,0,F138/F136) -> 8592850.7 | G141: =(G130+G130/12+G131+G133+G135)*IF(G136=0,0,G138/G136) -> 8590937.1 | H141: =(H130+H130/12+H131+H133+H135)*IF(H136=0,0,H138/H136) -> 8594558.5 | I141: =(I130+I130/12+I131+I133+I135)*IF(I136=0,0,I138/I136) -> 8592782 | J141: =(J130+J130/12+J131+J133+J135)*IF(J136=0,0,J138/J136) -> 8592759.2 | ... R141: =(R130+R130/12+R131+R133+R135)*IF(R136=0,0,R138/R136) -> 8593060.8
B142: Cek: A + B diselaraskan − pool A + B budget (harus nol) | C142: =C140+C141-C120-C121 -> 5.7742e-08 | D142: =D140+D141-D120-D121 -> -1.1175871e-08 | E142: =E140+E141-E120-E121 -> -5.7276338e-08 | F142: =F140+F141-F120-F121 -> -3.0733645e-08 | G142: =G140+G141-G120-G121 -> -1.3504177e-08 | H142: =H140+H141-H120-H121 -> -8.4750354e-08 | I142: =I140+I141-I120-I121 -> -2.5611371e-08 | J142: =J140+J141-J120-J121 -> 2.4680048e-08 | ... R142: =R140+R141-R120-R121 -> 0
A144: Ubi Orange IFM (QKSO)
A145: MD735 | B145: Premium / layak jual | C145: 0.99 | D145: 0.99 | E145: 0.99 | F145: 0.99 | G145: 0.99 | H145: 0.99 | I145: 0.99 | J145: 0.99 | K145: 0.99 | L145: 0.99 | M145: 0.99 | N145: 0.99 | O145: 0.99 | P145: 0.99 | Q145: 0.99 | R145: 0.99
A146: MD736 | B146: KW 2 | C146: 0 | D146: 0 | E146: 0 | F146: 0 | G146: 0 | H146: 0 | I146: 0 | J146: 0 | K146: 0 | L146: 0 | M146: 0 | N146: 0 | O146: 0 | P146: 0 | Q146: 0 | R146: 0
A147: MD737 | B147: Keripik waste | C147: 0.01 | D147: 0.01 | E147: 0.01 | F147: 0.01 | G147: 0.01 | H147: 0.01 | I147: 0.01 | J147: 0.01 | K147: 0.01 | L147: 0.01 | M147: 0.01 | N147: 0.01 | O147: 0.01 | P147: 0.01 | Q147: 0.01 | R147: 0.01
A148: MD741 | B148: Target volume penjualan/Layak Jual | C148: 5564.425 | D148: 5564.425 | E148: 5564.425 | F148: 5564.425 | G148: 5564.425 | H148: 5564.425 | I148: 5564.425 | J148: 5564.425 | K148: 5564.425 | L148: 5564.425 | M148: 5564.425 | N148: 5564.425 | O148: 5564.425 | P148: 5564.425 | Q148: 5564.425 | R148: 5564.425
A149: MD742 | B149: KW 2 | C149: 0 | D149: 0 | E149: 0 | F149: 0 | G149: 0 | H149: 0 | I149: 0 | J149: 0 | K149: 0 | L149: 0 | M149: 0 | N149: 0 | O149: 0 | P149: 0 | Q149: 0 | R149: 0
A150: MD743 | B150: Keripik waste | C150: 56.206313 | D150: 56.206313 | E150: 56.206313 | F150: 56.206313 | G150: 56.206313 | H150: 56.206313 | I150: 56.206313 | J150: 56.206313 | K150: 56.206313 | L150: 56.206313 | M150: 56.206313 | N150: 56.206313 | O150: 56.206313 | P150: 56.206313 | Q150: 56.206313 | R150: 56.206313
A151: MD744 | B151: WIP | C151: 0 | D151: 0 | E151: 0 | F151: 0 | G151: 0 | H151: 0 | I151: 0 | J151: 0 | K151: 0 | L151: 0 | M151: 0 | N151: 0 | O151: 0 | P151: 0 | Q151: 0 | R151: 0
A152: MD745 | B152: Target output Produksi | C152: 5620.6313 | D152: 5620.6313 | E152: 5620.6313 | F152: 5620.6313 | G152: 5620.6313 | H152: 5620.6313 | I152: 5620.6313 | J152: 5620.6313 | K152: 5620.6313 | L152: 5620.6313 | M152: 5620.6313 | N152: 5620.6313 | O152: 5620.6313 | P152: 5620.6313 | Q152: 5620.6313 | R152: 5620.6313
A153: MD750 | B153: Yield target | C153: 3.7290115 | D153: 3.7290115 | E153: 3.7290115 | F153: 3.7290115 | G153: 3.7290115 | H153: 3.7290115 | I153: 3.7290115 | J153: 3.7290115 | K153: 3.7290115 | L153: 3.7290115 | M153: 3.7290115 | N153: 3.7290115 | O153: 3.7290115 | P153: 3.7290115 | Q153: 3.7290115 | R153: 3.7290115
A154: MD751 | B154: Raw materials | C154: 20959.399 | D154: 20959.399 | E154: 20959.399 | F154: 20959.399 | G154: 20959.399 | H154: 20959.399 | I154: 20959.399 | J154: 20959.399 | K154: 20959.399 | L154: 20959.399 | M154: 20959.399 | N154: 20959.399 | O154: 20959.399 | P154: 20959.399 | Q154: 20959.399 | R154: 20959.399
A155: MD753 | B155: Total Ubi Orange | C155: 95564799 | D155: 95564799 | E155: 95564799 | F155: 95564799 | G155: 95564799 | H155: 95564799 | I155: 95564799 | J155: 95564799 | K155: 95564799 | L155: 95564799 | M155: 95564799 | N155: 95564799 | O155: 95564799 | P155: 95564799 | Q155: 95564799 | R155: 95564799
A156: MD762 | B156: Raw materials | C156: 2400.5051 | D156: 2400.5051 | E156: 2400.5051 | F156: 2400.5051 | G156: 2400.5051 | H156: 2400.5051 | I156: 2400.5051 | J156: 2400.5051 | K156: 2400.5051 | L156: 2400.5051 | M156: 2400.5051 | N156: 2400.5051 | O156: 2400.5051 | P156: 2400.5051 | Q156: 2400.5051 | R156: 2400.5051
... A192: MD205 | B192: Ubi Orange | C192: 5620.6313 | D192: 5620.6313 | E192: 5620.6313 | F192: 5620.6313 | G192: 5620.6313 | H192: 5620.6313 | I192: 5620.6313 | J192: 5620.6313 | K192: 5620.6313 | L192: 5620.6313 | M192: 5620.6313 | N192: 5620.6313 | O192: 5620.6313 | P192: 5620.6313 | Q192: 5620.6313 | R192: 5620.6313
B193: Grup A diselaraskan: DL operator + THR 1/12 + BPJS DL, porsi volume | C193: =(C182+C182/12+C187)*IF(C189=0,0,C192/C189) -> 11859881 | D193: =(D182+D182/12+D187)*IF(D189=0,0,D192/D189) -> 11834340 | E193: =(E182+E182/12+E187)*IF(E189=0,0,E192/E189) -> 11861668 | F193: =(F182+F182/12+F187)*IF(F189=0,0,F192/F189) -> 11851961 | G193: =(G182+G182/12+G187)*IF(G189=0,0,G192/G189) -> 11849322 | H193: =(H182+H182/12+H187)*IF(H189=0,0,H192/H189) -> 11854317 | I193: =(I182+I182/12+I187)*IF(I189=0,0,I192/I189) -> 11851867 | J193: =(J182+J182/12+J187)*IF(J189=0,0,J192/J189) -> 11851835 | ... R193: =(R182+R182/12+R187)*IF(R189=0,0,R192/R189) -> 11852251
B194: Grup B diselaraskan: support + staf + THR + BPJS IDL, porsi volume | C194: =(C183+C183/12+C184+C186+C188)*IF(C189=0,0,C192/C189) -> 7490016.2 | D194: =(D183+D183/12+D184+D186+D188)*IF(D189=0,0,D192/D189) -> 7473885.7 | E194: =(E183+E183/12+E184+E186+E188)*IF(E189=0,0,E192/E189) -> 7491144.6 | F194: =(F183+F183/12+F184+F186+F188)*IF(F189=0,0,F192/F189) -> 7485014.6 | G194: =(G183+G183/12+G184+G186+G188)*IF(G189=0,0,G192/G189) -> 7483347.7 | H194: =(H183+H183/12+H184+H186+H188)*IF(H189=0,0,H192/H189) -> 7486502.2 | I194: =(I183+I183/12+I184+I186+I188)*IF(I189=0,0,I192/I189) -> 7484954.8 | J194: =(J183+J183/12+J184+J186+J188)*IF(J189=0,0,J192/J189) -> 7484934.9 | ... R194: =(R183+R183/12+R184+R186+R188)*IF(R189=0,0,R192/R189) -> 7485197.6
B195: Cek: A + B diselaraskan − pool A + B budget (harus nol) | C195: =C193+C194-C173-C174 -> -2.7939677e-08 | D195: =D193+D194-D173-D174 -> -4.33065e-08 | E195: =E193+E194-E173-E174 -> 0 | F195: =F193+F194-F173-F174 -> 0 | G195: =G193+G194-G173-G174 -> -8.8941306e-08 | H195: =H193+H194-H173-H174 -> -7.6368451e-08 | I195: =I193+I194-I173-I174 -> 1.7229468e-08 | J195: =J193+J194-J173-J174 -> 4.703179e-08 | ... R195: =R193+R194-R173-R174 -> -2.8871e-08
A197: Lain-lain
A198: MD949 | B198: Total Cost of Manufacturing | C198: 40912328 | D198: 41069007 | E198: 41125442 | F198: 41046643 | G198: 41045071 | H198: 41031043 | I198: 41034476 | J198: 40677936 | K198: 40672355 | L198: 40654377 | M198: 40645818 | N198: 40623027 | O198: 40622446 | P198: 40618140 | Q198: 40617479 | R198: 40614135
A199: MD955 | B199: COGS | C199: 40912328 | D199: 41069007 | E199: 41125442 | F199: 41046643 | G199: 41045071 | H199: 41031043 | I199: 41034476 | J199: 40677936 | K199: 40672355 | L199: 40654377 | M199: 40645818 | N199: 40623027 | O199: 40622446 | P199: 40618140 | Q199: 40617479 | R199: 40614135
